---- AspectJ Properties ---
AspectJ Compiler 1.6.12 built on Tuesday Oct 18, 2011 at 17:52:06 GMT
---- Dump Properties ---
Dump file: ajcore.20170412.104021.445.txt
Dump reason: abort
Dump on exception: true
Dump at exit condition: abort
---- System Properties ---
java.runtime.name=Java(TM) SE Runtime Environment
sun.boot.library.path=C:\Program Files\Java\jre1.8.0_121\bin
java.vm.version=25.121-b13
java.vm.vendor=Oracle Corporation
java.vendor.url=http://java.oracle.com/
path.separator=;
java.vm.name=Java HotSpot(TM) 64-Bit Server VM
file.encoding.pkg=sun.io
user.country=FR
user.script=
sun.java.launcher=SUN_STANDARD
sun.os.patch.level=
java.vm.specification.name=Java Virtual Machine Specification
user.dir=C:\Users\formation\git\projects\SpringExpl
java.runtime.version=1.8.0_121-b13
java.awt.graphicsenv=sun.awt.Win32GraphicsEnvironment
java.endorsed.dirs=C:\Program Files\Java\jre1.8.0_121\lib\endorsed
os.arch=amd64
java.io.tmpdir=C:\Users\FORMAT~1\AppData\Local\Temp\
line.separator=

java.vm.specification.vendor=Oracle Corporation
user.variant=
os.name=Windows 10
sun.jnu.encoding=Cp1252
java.library.path=C:\Program Files\Java\jre1.8.0_121\bin;C:\windows\Sun\Java\bin;C:\windows\system32;C:\windows;C:/Program Files/Java/jre1.8.0_121/bin/server;C:/Program Files/Java/jre1.8.0_121/bin;C:/Program Files/Java/jre1.8.0_121/lib/amd64;C:\ProgramData\Oracle\Java\javapath;C:\windows\system32;C:\windows;C:\windows\System32\Wbem;C:\windows\System32\WindowsPowerShell\v1.0\;C:\Program Files\Java\jdk1.8.0_101\bin;C:\Outils\apache-maven-3.3.9\bin;C:\Users\formation\AppData\Local\Microsoft\WindowsApps;;C:\Users\formation\Desktop\JRE JDK ECLIPSE\sts-bundle\sts-3.8.3.RELEASE;;.
java.specification.name=Java Platform API Specification
java.class.version=52.0
sun.management.compiler=HotSpot 64-Bit Tiered Compilers
os.version=10.0
user.home=C:\Users\formation
user.timezone=Europe/Paris
java.awt.printerjob=sun.awt.windows.WPrinterJob
file.encoding=UTF-8
java.specification.version=1.8
java.class.path=C:\Users\formation\git\projects\SpringExpl\target\classes;C:\Users\formation\.m2\repository\org\springframework\spring-aspects\4.1.4.RELEASE\spring-aspects-4.1.4.RELEASE.jar;C:\Users\formation\.m2\repository\org\aspectj\aspectjrt\1.6.12\aspectjrt-1.6.12.jar;C:\Users\formation\.m2\repository\org\aspectj\aspectjweaver\1.6.12\aspectjweaver-1.6.12.jar;C:\Users\formation\.m2\repository\org\springframework\spring-core\4.1.6.RELEASE\spring-core-4.1.6.RELEASE.jar;C:\Users\formation\.m2\repository\commons-logging\commons-logging\1.2\commons-logging-1.2.jar;C:\Users\formation\.m2\repository\org\springframework\spring-context\4.1.6.RELEASE\spring-context-4.1.6.RELEASE.jar;C:\Users\formation\.m2\repository\org\springframework\spring-aop\4.1.6.RELEASE\spring-aop-4.1.6.RELEASE.jar;C:\Users\formation\.m2\repository\aopalliance\aopalliance\1.0\aopalliance-1.0.jar;C:\Users\formation\.m2\repository\org\springframework\spring-beans\4.1.6.RELEASE\spring-beans-4.1.6.RELEASE.jar;C:\Users\formation\.m2\repository\org\springframework\spring-expression\4.1.6.RELEASE\spring-expression-4.1.6.RELEASE.jar;C:\Users\formation\Desktop\spring-agent-2.5.6.jar
user.name=formation
java.vm.specification.version=1.8
sun.java.command=com.springExemple.presentation.Presentation2
java.home=C:\Program Files\Java\jre1.8.0_121
sun.arch.data.model=64
user.language=fr
java.specification.vendor=Oracle Corporation
awt.toolkit=sun.awt.windows.WToolkit
java.vm.info=mixed mode
java.version=1.8.0_121
java.ext.dirs=C:\Program Files\Java\jre1.8.0_121\lib\ext;C:\windows\Sun\Java\lib\ext
sun.boot.class.path=C:\Program Files\Java\jre1.8.0_121\lib\resources.jar;C:\Program Files\Java\jre1.8.0_121\lib\rt.jar;C:\Program Files\Java\jre1.8.0_121\lib\sunrsasign.jar;C:\Program Files\Java\jre1.8.0_121\lib\jsse.jar;C:\Program Files\Java\jre1.8.0_121\lib\jce.jar;C:\Program Files\Java\jre1.8.0_121\lib\charsets.jar;C:\Program Files\Java\jre1.8.0_121\lib\jfr.jar;C:\Program Files\Java\jre1.8.0_121\classes
java.vendor=Oracle Corporation
file.separator=\
java.vendor.url.bug=http://bugreport.sun.com/bugreport/
sun.io.unicode.encoding=UnicodeLittle
sun.cpu.endian=little
sun.desktop=windows
sun.cpu.isalist=amd64
---- Command Line ---
Empty
---- Full Classpath ---
Empty
---- Compiler Messages ---
info AspectJ Weaver Version 1.6.12 built on Tuesday Oct 18, 2011 at 17:52:06 GMT
info register classloader sun.misc.Launcher$AppClassLoader@18b4aac2
info using configuration file:/C:/Users/formation/.m2/repository/org/springframework/spring-aspects/4.1.4.RELEASE/spring-aspects-4.1.4.RELEASE.jar!/META-INF/aop.xml
error can't determine annotations of missing type org.springframework.transaction.annotation.Transactional
when weaving type org.springframework.expression.spel.support.StandardTypeLocator
when weaving classes 
when weaving 
 [Xlint:cantFindType]
abort trouble in: 
public class org.springframework.expression.spel.support.StandardTypeLocator extends java.lang.Object implements org.springframework.expression.TypeLocator:
  private final ClassLoader classLoader
  private final java.util.List knownPackagePrefixes [Signature(Ljava/util/List<Ljava/lang/String;>;)]
  public void <init>():
                    ALOAD_0     // Lorg/springframework/expression/spel/support/StandardTypeLocator; this   (line 50)
                    INVOKESTATIC org.springframework.util.ClassUtils.getDefaultClassLoader ()Ljava/lang/ClassLoader;
                    INVOKESPECIAL org.springframework.expression.spel.support.StandardTypeLocator.<init> (Ljava/lang/ClassLoader;)V
    constructor-execution(void org.springframework.expression.spel.support.StandardTypeLocator.<init>())
    |               RETURN   (line 51)
    constructor-execution(void org.springframework.expression.spel.support.StandardTypeLocator.<init>())
  end public void <init>()

  public void <init>(ClassLoader):
                    ALOAD_0     // Lorg/springframework/expression/spel/support/StandardTypeLocator; this   (line 57)
                    INVOKESPECIAL java.lang.Object.<init> ()V
    constructor-execution(void org.springframework.expression.spel.support.StandardTypeLocator.<init>(java.lang.ClassLoader))
    |               ALOAD_0     // Lorg/springframework/expression/spel/support/StandardTypeLocator; this   (line 42)
    |               NEW java.util.LinkedList
    |               DUP
    |               INVOKESPECIAL java.util.LinkedList.<init> ()V
    |               PUTFIELD org.springframework.expression.spel.support.StandardTypeLocator.knownPackagePrefixes Ljava/util/List;
    |               ALOAD_0     // Lorg/springframework/expression/spel/support/StandardTypeLocator; this   (line 58)
    |               ALOAD_1     // Ljava/lang/ClassLoader; classLoader
    |               PUTFIELD org.springframework.expression.spel.support.StandardTypeLocator.classLoader Ljava/lang/ClassLoader;
    |               ALOAD_0     // Lorg/springframework/expression/spel/support/StandardTypeLocator; this   (line 60)
    |               LDC "java.lang"
    |               INVOKEVIRTUAL org.springframework.expression.spel.support.StandardTypeLocator.registerImport (Ljava/lang/String;)V
    |               RETURN   (line 61)
    constructor-execution(void org.springframework.expression.spel.support.StandardTypeLocator.<init>(java.lang.ClassLoader))
  end public void <init>(ClassLoader)

  public void registerImport(String):
                    ALOAD_0     // Lorg/springframework/expression/spel/support/StandardTypeLocator; this   (line 70)
                    GETFIELD org.springframework.expression.spel.support.StandardTypeLocator.knownPackagePrefixes Ljava/util/List;
                    ALOAD_1     // Ljava/lang/String; prefix
                    INVOKEINTERFACE java.util.List.add (Ljava/lang/Object;)Z
                    POP
                    RETURN   (line 71)
  end public void registerImport(String)

  public void removeImport(String):
                    ALOAD_0     // Lorg/springframework/expression/spel/support/StandardTypeLocator; this   (line 78)
                    GETFIELD org.springframework.expression.spel.support.StandardTypeLocator.knownPackagePrefixes Ljava/util/List;
                    ALOAD_1     // Ljava/lang/String; prefix
                    INVOKEINTERFACE java.util.List.remove (Ljava/lang/Object;)Z
                    POP
                    RETURN   (line 79)
  end public void removeImport(String)

  public java.util.List getImportPrefixes():
                    ALOAD_0     // Lorg/springframework/expression/spel/support/StandardTypeLocator; this   (line 86)
                    GETFIELD org.springframework.expression.spel.support.StandardTypeLocator.knownPackagePrefixes Ljava/util/List;
                    INVOKESTATIC java.util.Collections.unmodifiableList (Ljava/util/List;)Ljava/util/List;
                    ARETURN
  end public java.util.List getImportPrefixes()

  public Class findType(String) throws org.springframework.expression.EvaluationException:
                    ALOAD_1     // Ljava/lang/String; typeName   (line 99)
                    ASTORE_2
    catch java.lang.ClassNotFoundException -> E0
    |               ALOAD_2     // Ljava/lang/String; nameToLookup   (line 101)
    |               ALOAD_0     // Lorg/springframework/expression/spel/support/StandardTypeLocator; this
    |               GETFIELD org.springframework.expression.spel.support.StandardTypeLocator.classLoader Ljava/lang/ClassLoader;
    |               INVOKESTATIC org.springframework.util.ClassUtils.forName (Ljava/lang/String;Ljava/lang/ClassLoader;)Ljava/lang/Class;
    catch java.lang.ClassNotFoundException -> E0
                    ARETURN
                E0: ASTORE_3   (line 103)
                    ALOAD_0     // Lorg/springframework/expression/spel/support/StandardTypeLocator; this   (line 106)
                    GETFIELD org.springframework.expression.spel.support.StandardTypeLocator.knownPackagePrefixes Ljava/util/List;
                    INVOKEINTERFACE java.util.List.iterator ()Ljava/util/Iterator;
                    ASTORE_3
                L0: ALOAD_3
                    INVOKEINTERFACE java.util.Iterator.hasNext ()Z
                    IFEQ L1
                    ALOAD_3
                    INVOKEINTERFACE java.util.Iterator.next ()Ljava/lang/Object;
                    CHECKCAST java.lang.String
                    ASTORE 4
    catch java.lang.ClassNotFoundException -> E1
    |               NEW java.lang.StringBuilder   (line 108)
    |               DUP
    |               INVOKESPECIAL java.lang.StringBuilder.<init> ()V
    |               ALOAD 4     // Ljava/lang/String; prefix
    |               INVOKEVIRTUAL java.lang.StringBuilder.append (Ljava/lang/String;)Ljava/lang/StringBuilder;
    |               LDC "."
    |               INVOKEVIRTUAL java.lang.StringBuilder.append (Ljava/lang/String;)Ljava/lang/StringBuilder;
    |               ALOAD_1     // Ljava/lang/String; typeName
    |               INVOKEVIRTUAL java.lang.StringBuilder.append (Ljava/lang/String;)Ljava/lang/StringBuilder;
    |               INVOKEVIRTUAL java.lang.StringBuilder.toString ()Ljava/lang/String;
    |               ASTORE_2     // Ljava/lang/String; nameToLookup
    |               ALOAD_2     // Ljava/lang/String; nameToLookup   (line 109)
    |               ALOAD_0     // Lorg/springframework/expression/spel/support/StandardTypeLocator; this
    |               GETFIELD org.springframework.expression.spel.support.StandardTypeLocator.classLoader Ljava/lang/ClassLoader;
    |               INVOKESTATIC org.springframework.util.ClassUtils.forName (Ljava/lang/String;Ljava/lang/ClassLoader;)Ljava/lang/Class;
    catch java.lang.ClassNotFoundException -> E1
                    ARETURN
                E1: ASTORE 5   (line 111)
                    GOTO L0   (line 114)
                L1: NEW org.springframework.expression.spel.SpelEvaluationException   (line 115)
                    DUP
                    GETSTATIC org.springframework.expression.spel.SpelMessage.TYPE_NOT_FOUND Lorg/springframework/expression/spel/SpelMessage;
                    ICONST_1
                    ANEWARRAY java.lang.Object
                    DUP
                    ICONST_0
                    ALOAD_1     // Ljava/lang/String; typeName
                    AASTORE
                    INVOKESPECIAL org.springframework.expression.spel.SpelEvaluationException.<init> (Lorg/springframework/expression/spel/SpelMessage;[Ljava/lang/Object;)V
                    ATHROW
  end public Class findType(String) throws org.springframework.expression.EvaluationException

end public class org.springframework.expression.spel.support.StandardTypeLocator
 -- (NullPointerException) null
null
java.lang.NullPointerException
	at org.aspectj.weaver.UnresolvedType.forSignature(UnresolvedType.java:384)
	at org.aspectj.weaver.bcel.BcelObjectType.getDeclaredInterfaces(BcelObjectType.java:275)
	at org.aspectj.weaver.ReferenceType.getDeclaredInterfaces(ReferenceType.java:626)
	at org.aspectj.weaver.ResolvedType.getDirectSupertypes(ResolvedType.java:82)
	at org.aspectj.weaver.patterns.TypePattern.matchesSubtypes(TypePattern.java:178)
	at org.aspectj.weaver.patterns.ExactTypePattern.matchesSubtypes(ExactTypePattern.java:74)
	at org.aspectj.weaver.patterns.TypePattern.matchesStatically(TypePattern.java:130)
	at org.aspectj.weaver.patterns.OrTypePattern.matchesStatically(OrTypePattern.java:76)
	at org.aspectj.weaver.patterns.SignaturePattern.matchesExactlyMethod(SignaturePattern.java:505)
	at org.aspectj.weaver.patterns.SignaturePattern.matchesExactly(SignaturePattern.java:360)
	at org.aspectj.weaver.patterns.SignaturePattern.matches(SignaturePattern.java:320)
	at org.aspectj.weaver.patterns.KindedPointcut.matchInternal(KindedPointcut.java:202)
	at org.aspectj.weaver.patterns.Pointcut.match(Pointcut.java:137)
	at org.aspectj.weaver.patterns.AndPointcut.matchInternal(AndPointcut.java:51)
	at org.aspectj.weaver.patterns.Pointcut.match(Pointcut.java:137)
	at org.aspectj.weaver.patterns.OrPointcut.matchInternal(OrPointcut.java:54)
	at org.aspectj.weaver.patterns.Pointcut.match(Pointcut.java:137)
	at org.aspectj.weaver.ShadowMunger.match(ShadowMunger.java:113)
	at org.aspectj.weaver.Advice.match(Advice.java:109)
	at org.aspectj.weaver.bcel.BcelAdvice.match(BcelAdvice.java:149)
	at org.aspectj.weaver.bcel.BcelClassWeaver.match(BcelClassWeaver.java:3173)
	at org.aspectj.weaver.bcel.BcelClassWeaver.match(BcelClassWeaver.java:2565)
	at org.aspectj.weaver.bcel.BcelClassWeaver.weave(BcelClassWeaver.java:480)
	at org.aspectj.weaver.bcel.BcelClassWeaver.weave(BcelClassWeaver.java:99)
	at org.aspectj.weaver.bcel.BcelWeaver.weave(BcelWeaver.java:1694)
	at org.aspectj.weaver.bcel.BcelWeaver.weaveWithoutDump(BcelWeaver.java:1638)
	at org.aspectj.weaver.bcel.BcelWeaver.weaveAndNotify(BcelWeaver.java:1401)
	at org.aspectj.weaver.bcel.BcelWeaver.weave(BcelWeaver.java:1187)
	at org.aspectj.weaver.tools.WeavingAdaptor.getWovenBytes(WeavingAdaptor.java:472)
	at org.aspectj.weaver.tools.WeavingAdaptor.weaveClass(WeavingAdaptor.java:323)
	at org.aspectj.weaver.loadtime.Aj.preProcess(Aj.java:99)
	at org.aspectj.weaver.loadtime.ClassPreProcessorAgentAdapter.transform(ClassPreProcessorAgentAdapter.java:54)
	at org.springframework.context.weaving.AspectJWeavingEnabler$AspectJClassBypassingClassFileTransformer.transform(AspectJWeavingEnabler.java:108)
	at org.springframework.instrument.classloading.InstrumentationLoadTimeWeaver$FilteringClassFileTransformer.transform(InstrumentationLoadTimeWeaver.java:184)
	at sun.instrument.TransformerManager.transform(Unknown Source)
	at sun.instrument.InstrumentationImpl.transform(Unknown Source)
	at java.lang.ClassLoader.defineClass1(Native Method)
	at java.lang.ClassLoader.defineClass(Unknown Source)
	at java.security.SecureClassLoader.defineClass(Unknown Source)
	at java.net.URLClassLoader.defineClass(Unknown Source)
	at java.net.URLClassLoader.access$100(Unknown Source)
	at java.net.URLClassLoader$1.run(Unknown Source)
	at java.net.URLClassLoader$1.run(Unknown Source)
	at java.security.AccessController.doPrivileged(Native Method)
	at java.net.URLClassLoader.findClass(Unknown Source)
	at java.lang.ClassLoader.loadClass(Unknown Source)
	at sun.misc.Launcher$AppClassLoader.loadClass(Unknown Source)
	at java.lang.ClassLoader.loadClass(Unknown Source)
	at org.springframework.context.expression.StandardBeanExpressionResolver.evaluate(StandardBeanExpressionResolver.java:153)
	at org.springframework.beans.factory.support.AbstractBeanFactory.evaluateBeanDefinitionString(AbstractBeanFactory.java:1365)
	at org.springframework.beans.factory.support.BeanDefinitionValueResolver.doEvaluate(BeanDefinitionValueResolver.java:255)
	at org.springframework.beans.factory.support.BeanDefinitionValueResolver.resolveReference(BeanDefinitionValueResolver.java:340)
	at org.springframework.beans.factory.support.BeanDefinitionValueResolver.resolveValueIfNecessary(BeanDefinitionValueResolver.java:108)
	at org.springframework.beans.factory.support.AbstractAutowireCapableBeanFactory.applyPropertyValues(AbstractAutowireCapableBeanFactory.java:1477)
	at org.springframework.beans.factory.support.AbstractAutowireCapableBeanFactory.populateBean(AbstractAutowireCapableBeanFactory.java:1222)
	at org.springframework.beans.factory.support.AbstractAutowireCapableBeanFactory.doCreateBean(AbstractAutowireCapableBeanFactory.java:537)
	at org.springframework.beans.factory.support.AbstractAutowireCapableBeanFactory.createBean(AbstractAutowireCapableBeanFactory.java:476)
	at org.springframework.beans.factory.support.AbstractBeanFactory$1.getObject(AbstractBeanFactory.java:303)
	at org.springframework.beans.factory.support.DefaultSingletonBeanRegistry.getSingleton(DefaultSingletonBeanRegistry.java:230)
	at org.springframework.beans.factory.support.AbstractBeanFactory.doGetBean(AbstractBeanFactory.java:299)
	at org.springframework.beans.factory.support.AbstractBeanFactory.getBean(AbstractBeanFactory.java:194)
	at org.springframework.beans.factory.support.DefaultListableBeanFactory.findAutowireCandidates(DefaultListableBeanFactory.java:1120)
	at org.springframework.beans.factory.support.DefaultListableBeanFactory.doResolveDependency(DefaultListableBeanFactory.java:996)
	at org.springframework.beans.factory.support.DefaultListableBeanFactory.resolveDependency(DefaultListableBeanFactory.java:942)
	at org.springframework.beans.factory.annotation.AutowiredAnnotationBeanPostProcessor$AutowiredFieldElement.inject(AutowiredAnnotationBeanPostProcessor.java:533)
	at org.springframework.beans.factory.annotation.InjectionMetadata.inject(InjectionMetadata.java:88)
	at org.springframework.beans.factory.annotation.AutowiredAnnotationBeanPostProcessor.postProcessPropertyValues(AutowiredAnnotationBeanPostProcessor.java:331)
	at org.springframework.beans.factory.support.AbstractAutowireCapableBeanFactory.populateBean(AbstractAutowireCapableBeanFactory.java:1210)
	at org.springframework.beans.factory.support.AbstractAutowireCapableBeanFactory.doCreateBean(AbstractAutowireCapableBeanFactory.java:537)
	at org.springframework.beans.factory.support.AbstractAutowireCapableBeanFactory.createBean(AbstractAutowireCapableBeanFactory.java:476)
	at org.springframework.beans.factory.support.AbstractBeanFactory$1.getObject(AbstractBeanFactory.java:303)
	at org.springframework.beans.factory.support.DefaultSingletonBeanRegistry.getSingleton(DefaultSingletonBeanRegistry.java:230)
	at org.springframework.beans.factory.support.AbstractBeanFactory.doGetBean(AbstractBeanFactory.java:299)
	at org.springframework.beans.factory.support.AbstractBeanFactory.getBean(AbstractBeanFactory.java:194)
	at org.springframework.beans.factory.support.DefaultListableBeanFactory.preInstantiateSingletons(DefaultListableBeanFactory.java:755)
	at org.springframework.context.support.AbstractApplicationContext.finishBeanFactoryInitialization(AbstractApplicationContext.java:757)
	at org.springframework.context.support.AbstractApplicationContext.refresh(AbstractApplicationContext.java:480)
	at org.springframework.context.support.ClassPathXmlApplicationContext.<init>(ClassPathXmlApplicationContext.java:139)
	at org.springframework.context.support.ClassPathXmlApplicationContext.<init>(ClassPathXmlApplicationContext.java:93)
	at com.springExemple.presentation.Presentation2.main(Presentation2.java:13)

error can't determine annotations of missing type org.springframework.transaction.annotation.Transactional
when weaving type org.springframework.beans.PropertyAccessorUtils
when weaving classes 
when weaving 
 [Xlint:cantFindType]
abort trouble in: 
public abstract class org.springframework.beans.PropertyAccessorUtils extends java.lang.Object:
  public void <init>():
                    ALOAD_0     // Lorg/springframework/beans/PropertyAccessorUtils; this   (line 26)
                    INVOKESPECIAL java.lang.Object.<init> ()V
    constructor-execution(void org.springframework.beans.PropertyAccessorUtils.<init>())
    |               RETURN
    constructor-execution(void org.springframework.beans.PropertyAccessorUtils.<init>())
  end public void <init>()

  public static String getPropertyName(String):
                    ALOAD_0     // Ljava/lang/String; propertyPath   (line 35)
                    LDC "]"
                    INVOKEVIRTUAL java.lang.String.endsWith (Ljava/lang/String;)Z
                    IFEQ L0
                    ALOAD_0     // Ljava/lang/String; propertyPath
                    BIPUSH 91
                    INVOKEVIRTUAL java.lang.String.indexOf (I)I   (line 36)
                    GOTO L1
                L0: ICONST_M1
                L1: ISTORE_1
                    ILOAD_1     // I separatorIndex   (line 37)
                    ICONST_M1
                    IF_ICMPEQ L2
                    ALOAD_0     // Ljava/lang/String; propertyPath
                    ICONST_0
                    ILOAD_1     // I separatorIndex
                    INVOKEVIRTUAL java.lang.String.substring (II)Ljava/lang/String;
                    GOTO L3
                L2: ALOAD_0     // Ljava/lang/String; propertyPath
                L3: ARETURN
  end public static String getPropertyName(String)

  public static boolean isNestedOrIndexedProperty(String):
                    ALOAD_0     // Ljava/lang/String; propertyPath   (line 46)
                    IFNONNULL L0
                    ICONST_0   (line 47)
                    IRETURN
                L0: ICONST_0   (line 49)
                    ISTORE_1
                L1: ILOAD_1     // I i
                    ALOAD_0     // Ljava/lang/String; propertyPath
                    INVOKEVIRTUAL java.lang.String.length ()I
                    IF_ICMPGE L4
                    ALOAD_0     // Ljava/lang/String; propertyPath   (line 50)
                    ILOAD_1     // I i
                    INVOKEVIRTUAL java.lang.String.charAt (I)C
                    ISTORE_2
                    ILOAD_2     // C ch   (line 51)
                    BIPUSH 46
                    IF_ICMPEQ L2
                    ILOAD_2     // C ch
                    BIPUSH 91
                    IF_ICMPNE L3
                L2: ICONST_1   (line 53)
                    IRETURN
                L3: IINC_1 1     // I i   (line 49)
                    GOTO L1
                L4: ICONST_0   (line 56)
                    IRETURN
  end public static boolean isNestedOrIndexedProperty(String)

  public static int getFirstNestedPropertySeparatorIndex(String):
                    ALOAD_0     // Ljava/lang/String; propertyPath   (line 66)
                    ICONST_0
                    INVOKESTATIC org.springframework.beans.PropertyAccessorUtils.getNestedPropertySeparatorIndex (Ljava/lang/String;Z)I
                    IRETURN
  end public static int getFirstNestedPropertySeparatorIndex(String)

  public static int getLastNestedPropertySeparatorIndex(String):
                    ALOAD_0     // Ljava/lang/String; propertyPath   (line 76)
                    ICONST_1
                    INVOKESTATIC org.springframework.beans.PropertyAccessorUtils.getNestedPropertySeparatorIndex (Ljava/lang/String;Z)I
                    IRETURN
  end public static int getLastNestedPropertySeparatorIndex(String)

  private static int getNestedPropertySeparatorIndex(String, boolean):
                    ICONST_0   (line 87)
                    ISTORE_2
                    ALOAD_0     // Ljava/lang/String; propertyPath   (line 88)
                    INVOKEVIRTUAL java.lang.String.length ()I
                    ISTORE_3
                    ILOAD_1     // Z last   (line 89)
                    IFEQ L0
                    ILOAD_3     // I length
                    ICONST_1
                    ISUB
                    GOTO L1
                L0: ICONST_0
                L1: ISTORE 4
                L2: ILOAD_1     // Z last   (line 90)
                    IFEQ L3
                    ILOAD 4     // I i
                    IFLT L11
                    GOTO L4
                L3: ILOAD 4     // I i
                    ILOAD_3     // I length
                    IF_ICMPGE L11
                L4: ALOAD_0     // Ljava/lang/String; propertyPath   (line 91)
                    ILOAD 4     // I i
                    INVOKEVIRTUAL java.lang.String.charAt (I)C
                    LOOKUPSWITCH
                      46: 	L8
                      91: 	L5
                      93: 	L5
                      default: 	L9
                L5: ILOAD_2     // Z inKey   (line 94)
                    IFNE L6
                    ICONST_1
                    GOTO L7
                L6: ICONST_0
                L7: ISTORE_2     // Z inKey
                    GOTO L9   (line 95)
                L8: ILOAD_2     // Z inKey   (line 97)
                    IFNE L9
                    ILOAD 4     // I i   (line 98)
                    IRETURN
                L9: ILOAD_1     // Z last   (line 101)
                    IFEQ L10
                    IINC 4 -1     // I i   (line 102)
                    GOTO L2
               L10: IINC 4 1     // I i   (line 105)
                    GOTO L2
               L11: ICONST_M1   (line 108)
                    IRETURN
  end private static int getNestedPropertySeparatorIndex(String, boolean)

  public static boolean matchesProperty(String, String):
                    ALOAD_0     // Ljava/lang/String; registeredPath   (line 119)
                    ALOAD_1     // Ljava/lang/String; propertyPath
                    INVOKEVIRTUAL java.lang.String.startsWith (Ljava/lang/String;)Z
                    IFNE L0
                    ICONST_0   (line 120)
                    IRETURN
                L0: ALOAD_0     // Ljava/lang/String; registeredPath   (line 122)
                    INVOKEVIRTUAL java.lang.String.length ()I
                    ALOAD_1     // Ljava/lang/String; propertyPath
                    INVOKEVIRTUAL java.lang.String.length ()I
                    IF_ICMPNE L1
                    ICONST_1   (line 123)
                    IRETURN
                L1: ALOAD_0     // Ljava/lang/String; registeredPath   (line 125)
                    ALOAD_1     // Ljava/lang/String; propertyPath
                    INVOKEVIRTUAL java.lang.String.length ()I
                    INVOKEVIRTUAL java.lang.String.charAt (I)C
                    BIPUSH 91
                    IF_ICMPEQ L2
                    ICONST_0   (line 126)
                    IRETURN
                L2: ALOAD_0     // Ljava/lang/String; registeredPath   (line 128)
                    BIPUSH 93
                    ALOAD_1     // Ljava/lang/String; propertyPath
                    INVOKEVIRTUAL java.lang.String.length ()I
                    ICONST_1
                    IADD
                    INVOKEVIRTUAL java.lang.String.indexOf (II)I
                    ALOAD_0     // Ljava/lang/String; registeredPath
                    INVOKEVIRTUAL java.lang.String.length ()I   (line 129)
                    ICONST_1
                    ISUB
                    IF_ICMPNE L3
                    ICONST_1
                    GOTO L4
                L3: ICONST_0
                L4: IRETURN
  end public static boolean matchesProperty(String, String)

  public static String canonicalPropertyName(String):
                    ALOAD_0     // Ljava/lang/String; propertyName   (line 141)
                    IFNONNULL L0
                    LDC ""   (line 142)
                    ARETURN
                L0: NEW java.lang.StringBuilder   (line 145)
                    DUP
                    ALOAD_0     // Ljava/lang/String; propertyName
                    INVOKESPECIAL java.lang.StringBuilder.<init> (Ljava/lang/String;)V
                    ASTORE_1
                    ICONST_0   (line 146)
                    ISTORE_2
                L1: ILOAD_2     // I searchIndex   (line 147)
                    ICONST_M1
                    IF_ICMPEQ L6
                    ALOAD_1     // Ljava/lang/StringBuilder; sb   (line 148)
                    LDC "["
                    ILOAD_2     // I searchIndex
                    INVOKEVIRTUAL java.lang.StringBuilder.indexOf (Ljava/lang/String;I)I
                    ISTORE_3
                    ICONST_M1   (line 149)
                    ISTORE_2     // I searchIndex
                    ILOAD_3     // I keyStart   (line 150)
                    ICONST_M1
                    IF_ICMPEQ L5
                    ALOAD_1     // Ljava/lang/StringBuilder; sb   (line 151)
                    LDC "]"
                    ILOAD_3     // I keyStart
                    LDC "["
                    INVOKEVIRTUAL java.lang.String.length ()I   (line 152)
                    IADD
                    INVOKEVIRTUAL java.lang.StringBuilder.indexOf (Ljava/lang/String;I)I   (line 151)
                    ISTORE 4
                    ILOAD 4     // I keyEnd   (line 153)
                    ICONST_M1
                    IF_ICMPEQ L5
                    ALOAD_1     // Ljava/lang/StringBuilder; sb   (line 154)
                    ILOAD_3     // I keyStart
                    LDC "["
                    INVOKEVIRTUAL java.lang.String.length ()I
                    IADD
                    ILOAD 4     // I keyEnd
                    INVOKEVIRTUAL java.lang.StringBuilder.substring (II)Ljava/lang/String;
                    ASTORE 5
                    ALOAD 5     // Ljava/lang/String; key   (line 155)
                    LDC "'"
                    INVOKEVIRTUAL java.lang.String.startsWith (Ljava/lang/String;)Z
                    IFEQ L2
                    ALOAD 5     // Ljava/lang/String; key
                    LDC "'"
                    INVOKEVIRTUAL java.lang.String.endsWith (Ljava/lang/String;)Z
                    IFNE L3
                L2: ALOAD 5     // Ljava/lang/String; key
                    LDC "\""
                    INVOKEVIRTUAL java.lang.String.startsWith (Ljava/lang/String;)Z
                    IFEQ L4
                    ALOAD 5     // Ljava/lang/String; key
                    LDC "\""
                    INVOKEVIRTUAL java.lang.String.endsWith (Ljava/lang/String;)Z
                    IFEQ L4
                L3: ALOAD_1     // Ljava/lang/StringBuilder; sb   (line 156)
                    ILOAD_3     // I keyStart
                    ICONST_1
                    IADD
                    ILOAD_3     // I keyStart
                    ICONST_2
                    IADD
                    INVOKEVIRTUAL java.lang.StringBuilder.delete (II)Ljava/lang/StringBuilder;
                    POP
                    ALOAD_1     // Ljava/lang/StringBuilder; sb   (line 157)
                    ILOAD 4     // I keyEnd
                    ICONST_2
                    ISUB
                    ILOAD 4     // I keyEnd
                    ICONST_1
                    ISUB
                    INVOKEVIRTUAL java.lang.StringBuilder.delete (II)Ljava/lang/StringBuilder;
                    POP
                    ILOAD 4     // I keyEnd   (line 158)
                    ICONST_2
                    ISUB
                    ISTORE 4     // I keyEnd
                L4: ILOAD 4     // I keyEnd   (line 160)
                    LDC "]"
                    INVOKEVIRTUAL java.lang.String.length ()I
                    IADD
                    ISTORE_2     // I searchIndex
                L5: GOTO L1   (line 163)
                L6: ALOAD_1     // Ljava/lang/StringBuilder; sb   (line 164)
                    INVOKEVIRTUAL java.lang.StringBuilder.toString ()Ljava/lang/String;
                    ARETURN
  end public static String canonicalPropertyName(String)

  public static String[] canonicalPropertyNames(String[]):
                    ALOAD_0     // [Ljava/lang/String; propertyNames   (line 175)
                    IFNONNULL L0
                    ACONST_NULL   (line 176)
                    ARETURN
                L0: ALOAD_0     // [Ljava/lang/String; propertyNames   (line 178)
                    ARRAYLENGTH
                    ANEWARRAY java.lang.String
                    ASTORE_1
                    ICONST_0   (line 179)
                    ISTORE_2
                L1: ILOAD_2     // I i
                    ALOAD_0     // [Ljava/lang/String; propertyNames
                    ARRAYLENGTH
                    IF_ICMPGE L2
                    ALOAD_1     // [Ljava/lang/String; result   (line 180)
                    ILOAD_2     // I i
                    ALOAD_0     // [Ljava/lang/String; propertyNames
                    ILOAD_2     // I i
                    AALOAD
                    INVOKESTATIC org.springframework.beans.PropertyAccessorUtils.canonicalPropertyName (Ljava/lang/String;)Ljava/lang/String;
                    AASTORE
                    IINC_2 1     // I i   (line 179)
                    GOTO L1
                L2: ALOAD_1     // [Ljava/lang/String; result   (line 182)
                    ARETURN
  end public static String[] canonicalPropertyNames(String[])

end public abstract class org.springframework.beans.PropertyAccessorUtils
 -- (NullPointerException) null
null
java.lang.NullPointerException
	at org.aspectj.weaver.UnresolvedType.forSignature(UnresolvedType.java:384)
	at org.aspectj.weaver.bcel.BcelObjectType.getDeclaredInterfaces(BcelObjectType.java:275)
	at org.aspectj.weaver.ReferenceType.getDeclaredInterfaces(ReferenceType.java:626)
	at org.aspectj.weaver.ResolvedType.getDirectSupertypes(ResolvedType.java:82)
	at org.aspectj.weaver.patterns.TypePattern.matchesSubtypes(TypePattern.java:178)
	at org.aspectj.weaver.patterns.ExactTypePattern.matchesSubtypes(ExactTypePattern.java:74)
	at org.aspectj.weaver.patterns.TypePattern.matchesStatically(TypePattern.java:130)
	at org.aspectj.weaver.patterns.OrTypePattern.matchesStatically(OrTypePattern.java:76)
	at org.aspectj.weaver.patterns.SignaturePattern.matchesExactlyMethod(SignaturePattern.java:505)
	at org.aspectj.weaver.patterns.SignaturePattern.matchesExactly(SignaturePattern.java:360)
	at org.aspectj.weaver.patterns.SignaturePattern.matches(SignaturePattern.java:320)
	at org.aspectj.weaver.patterns.KindedPointcut.matchInternal(KindedPointcut.java:202)
	at org.aspectj.weaver.patterns.Pointcut.match(Pointcut.java:137)
	at org.aspectj.weaver.patterns.AndPointcut.matchInternal(AndPointcut.java:51)
	at org.aspectj.weaver.patterns.Pointcut.match(Pointcut.java:137)
	at org.aspectj.weaver.patterns.OrPointcut.matchInternal(OrPointcut.java:54)
	at org.aspectj.weaver.patterns.Pointcut.match(Pointcut.java:137)
	at org.aspectj.weaver.ShadowMunger.match(ShadowMunger.java:113)
	at org.aspectj.weaver.Advice.match(Advice.java:109)
	at org.aspectj.weaver.bcel.BcelAdvice.match(BcelAdvice.java:149)
	at org.aspectj.weaver.bcel.BcelClassWeaver.match(BcelClassWeaver.java:3173)
	at org.aspectj.weaver.bcel.BcelClassWeaver.match(BcelClassWeaver.java:2565)
	at org.aspectj.weaver.bcel.BcelClassWeaver.weave(BcelClassWeaver.java:480)
	at org.aspectj.weaver.bcel.BcelClassWeaver.weave(BcelClassWeaver.java:99)
	at org.aspectj.weaver.bcel.BcelWeaver.weave(BcelWeaver.java:1694)
	at org.aspectj.weaver.bcel.BcelWeaver.weaveWithoutDump(BcelWeaver.java:1638)
	at org.aspectj.weaver.bcel.BcelWeaver.weaveAndNotify(BcelWeaver.java:1401)
	at org.aspectj.weaver.bcel.BcelWeaver.weave(BcelWeaver.java:1187)
	at org.aspectj.weaver.tools.WeavingAdaptor.getWovenBytes(WeavingAdaptor.java:472)
	at org.aspectj.weaver.tools.WeavingAdaptor.weaveClass(WeavingAdaptor.java:323)
	at org.aspectj.weaver.loadtime.Aj.preProcess(Aj.java:99)
	at org.aspectj.weaver.loadtime.ClassPreProcessorAgentAdapter.transform(ClassPreProcessorAgentAdapter.java:54)
	at org.springframework.context.weaving.AspectJWeavingEnabler$AspectJClassBypassingClassFileTransformer.transform(AspectJWeavingEnabler.java:108)
	at org.springframework.instrument.classloading.InstrumentationLoadTimeWeaver$FilteringClassFileTransformer.transform(InstrumentationLoadTimeWeaver.java:184)
	at sun.instrument.TransformerManager.transform(Unknown Source)
	at sun.instrument.InstrumentationImpl.transform(Unknown Source)
	at java.lang.ClassLoader.defineClass1(Native Method)
	at java.lang.ClassLoader.defineClass(Unknown Source)
	at java.security.SecureClassLoader.defineClass(Unknown Source)
	at java.net.URLClassLoader.defineClass(Unknown Source)
	at java.net.URLClassLoader.access$100(Unknown Source)
	at java.net.URLClassLoader$1.run(Unknown Source)
	at java.net.URLClassLoader$1.run(Unknown Source)
	at java.security.AccessController.doPrivileged(Native Method)
	at java.net.URLClassLoader.findClass(Unknown Source)
	at java.lang.ClassLoader.loadClass(Unknown Source)
	at sun.misc.Launcher$AppClassLoader.loadClass(Unknown Source)
	at java.lang.ClassLoader.loadClass(Unknown Source)
	at org.springframework.beans.BeanWrapperImpl.getBeanWrapperForPropertyPath(BeanWrapperImpl.java:544)
	at org.springframework.beans.BeanWrapperImpl.getPropertyDescriptorInternal(BeanWrapperImpl.java:359)
	at org.springframework.beans.BeanWrapperImpl.isWritableProperty(BeanWrapperImpl.java:440)
	at org.springframework.beans.factory.support.AbstractAutowireCapableBeanFactory.applyPropertyValues(AbstractAutowireCapableBeanFactory.java:1479)
	at org.springframework.beans.factory.support.AbstractAutowireCapableBeanFactory.populateBean(AbstractAutowireCapableBeanFactory.java:1222)
	at org.springframework.beans.factory.support.AbstractAutowireCapableBeanFactory.doCreateBean(AbstractAutowireCapableBeanFactory.java:537)
	at org.springframework.beans.factory.support.AbstractAutowireCapableBeanFactory.createBean(AbstractAutowireCapableBeanFactory.java:476)
	at org.springframework.beans.factory.support.AbstractBeanFactory$1.getObject(AbstractBeanFactory.java:303)
	at org.springframework.beans.factory.support.DefaultSingletonBeanRegistry.getSingleton(DefaultSingletonBeanRegistry.java:230)
	at org.springframework.beans.factory.support.AbstractBeanFactory.doGetBean(AbstractBeanFactory.java:299)
	at org.springframework.beans.factory.support.AbstractBeanFactory.getBean(AbstractBeanFactory.java:194)
	at org.springframework.beans.factory.support.DefaultListableBeanFactory.findAutowireCandidates(DefaultListableBeanFactory.java:1120)
	at org.springframework.beans.factory.support.DefaultListableBeanFactory.doResolveDependency(DefaultListableBeanFactory.java:996)
	at org.springframework.beans.factory.support.DefaultListableBeanFactory.resolveDependency(DefaultListableBeanFactory.java:942)
	at org.springframework.beans.factory.annotation.AutowiredAnnotationBeanPostProcessor$AutowiredFieldElement.inject(AutowiredAnnotationBeanPostProcessor.java:533)
	at org.springframework.beans.factory.annotation.InjectionMetadata.inject(InjectionMetadata.java:88)
	at org.springframework.beans.factory.annotation.AutowiredAnnotationBeanPostProcessor.postProcessPropertyValues(AutowiredAnnotationBeanPostProcessor.java:331)
	at org.springframework.beans.factory.support.AbstractAutowireCapableBeanFactory.populateBean(AbstractAutowireCapableBeanFactory.java:1210)
	at org.springframework.beans.factory.support.AbstractAutowireCapableBeanFactory.doCreateBean(AbstractAutowireCapableBeanFactory.java:537)
	at org.springframework.beans.factory.support.AbstractAutowireCapableBeanFactory.createBean(AbstractAutowireCapableBeanFactory.java:476)
	at org.springframework.beans.factory.support.AbstractBeanFactory$1.getObject(AbstractBeanFactory.java:303)
	at org.springframework.beans.factory.support.DefaultSingletonBeanRegistry.getSingleton(DefaultSingletonBeanRegistry.java:230)
	at org.springframework.beans.factory.support.AbstractBeanFactory.doGetBean(AbstractBeanFactory.java:299)
	at org.springframework.beans.factory.support.AbstractBeanFactory.getBean(AbstractBeanFactory.java:194)
	at org.springframework.beans.factory.support.DefaultListableBeanFactory.preInstantiateSingletons(DefaultListableBeanFactory.java:755)
	at org.springframework.context.support.AbstractApplicationContext.finishBeanFactoryInitialization(AbstractApplicationContext.java:757)
	at org.springframework.context.support.AbstractApplicationContext.refresh(AbstractApplicationContext.java:480)
	at org.springframework.context.support.ClassPathXmlApplicationContext.<init>(ClassPathXmlApplicationContext.java:139)
	at org.springframework.context.support.ClassPathXmlApplicationContext.<init>(ClassPathXmlApplicationContext.java:93)
	at com.springExemple.presentation.Presentation2.main(Presentation2.java:13)

error can't determine annotations of missing type org.springframework.transaction.annotation.Transactional
when weaving type org.springframework.core.convert.Property
when weaving classes 
when weaving 
 [Xlint:cantFindType]
abort trouble in: 
public final class org.springframework.core.convert.Property extends java.lang.Object:
  private static java.util.Map annotationCache [Signature(Ljava/util/Map<Lorg/springframework/core/convert/Property;[Ljava/lang/annotation/Annotation;>;)]
  private final Class objectType [Signature(Ljava/lang/Class<*>;)]
  private final java.lang.reflect.Method readMethod
  private final java.lang.reflect.Method writeMethod
  private final String name
  private final org.springframework.core.MethodParameter methodParameter
  private java.lang.annotation.Annotation[] annotations
  public void <init>(Class, java.lang.reflect.Method, java.lang.reflect.Method):
                    ALOAD_0     // Lorg/springframework/core/convert/Property; this   (line 67)
                    ALOAD_1     // Ljava/lang/Class; objectType
                    ALOAD_2     // Ljava/lang/reflect/Method; readMethod
                    ALOAD_3     // Ljava/lang/reflect/Method; writeMethod
                    ACONST_NULL
                    INVOKESPECIAL org.springframework.core.convert.Property.<init> (Ljava/lang/Class;Ljava/lang/reflect/Method;Ljava/lang/reflect/Method;Ljava/lang/String;)V
    constructor-execution(void org.springframework.core.convert.Property.<init>(java.lang.Class, java.lang.reflect.Method, java.lang.reflect.Method))
    |               RETURN   (line 68)
    constructor-execution(void org.springframework.core.convert.Property.<init>(java.lang.Class, java.lang.reflect.Method, java.lang.reflect.Method))
  end public void <init>(Class, java.lang.reflect.Method, java.lang.reflect.Method)

  public void <init>(Class, java.lang.reflect.Method, java.lang.reflect.Method, String):
                    ALOAD_0     // Lorg/springframework/core/convert/Property; this   (line 70)
                    INVOKESPECIAL java.lang.Object.<init> ()V
    constructor-execution(void org.springframework.core.convert.Property.<init>(java.lang.Class, java.lang.reflect.Method, java.lang.reflect.Method, java.lang.String))
    |               ALOAD_0     // Lorg/springframework/core/convert/Property; this   (line 71)
    |               ALOAD_1     // Ljava/lang/Class; objectType
    |               PUTFIELD org.springframework.core.convert.Property.objectType Ljava/lang/Class;
    |               ALOAD_0     // Lorg/springframework/core/convert/Property; this   (line 72)
    |               ALOAD_2     // Ljava/lang/reflect/Method; readMethod
    |               PUTFIELD org.springframework.core.convert.Property.readMethod Ljava/lang/reflect/Method;
    |               ALOAD_0     // Lorg/springframework/core/convert/Property; this   (line 73)
    |               ALOAD_3     // Ljava/lang/reflect/Method; writeMethod
    |               PUTFIELD org.springframework.core.convert.Property.writeMethod Ljava/lang/reflect/Method;
    |               ALOAD_0     // Lorg/springframework/core/convert/Property; this   (line 74)
    |               ALOAD_0     // Lorg/springframework/core/convert/Property; this
    |               INVOKESPECIAL org.springframework.core.convert.Property.resolveMethodParameter ()Lorg/springframework/core/MethodParameter;
    |               PUTFIELD org.springframework.core.convert.Property.methodParameter Lorg/springframework/core/MethodParameter;
    |               ALOAD_0     // Lorg/springframework/core/convert/Property; this   (line 75)
    |               ALOAD 4     // Ljava/lang/String; name
    |               IFNONNULL L0
    |               ALOAD_0     // Lorg/springframework/core/convert/Property; this
    |               INVOKESPECIAL org.springframework.core.convert.Property.resolveName ()Ljava/lang/String;
    |               GOTO L1
    |           L0: ALOAD 4     // Ljava/lang/String; name
    |           L1: PUTFIELD org.springframework.core.convert.Property.name Ljava/lang/String;
    |               RETURN   (line 76)
    constructor-execution(void org.springframework.core.convert.Property.<init>(java.lang.Class, java.lang.reflect.Method, java.lang.reflect.Method, java.lang.String))
  end public void <init>(Class, java.lang.reflect.Method, java.lang.reflect.Method, String)

  public Class getObjectType():
                    ALOAD_0     // Lorg/springframework/core/convert/Property; this   (line 83)
                    GETFIELD org.springframework.core.convert.Property.objectType Ljava/lang/Class;
                    ARETURN
  end public Class getObjectType()

  public String getName():
                    ALOAD_0     // Lorg/springframework/core/convert/Property; this   (line 90)
                    GETFIELD org.springframework.core.convert.Property.name Ljava/lang/String;
                    ARETURN
  end public String getName()

  public Class getType():
                    ALOAD_0     // Lorg/springframework/core/convert/Property; this   (line 97)
                    GETFIELD org.springframework.core.convert.Property.methodParameter Lorg/springframework/core/MethodParameter;
                    INVOKEVIRTUAL org.springframework.core.MethodParameter.getParameterType ()Ljava/lang/Class;
                    ARETURN
  end public Class getType()

  public java.lang.reflect.Method getReadMethod():
                    ALOAD_0     // Lorg/springframework/core/convert/Property; this   (line 104)
                    GETFIELD org.springframework.core.convert.Property.readMethod Ljava/lang/reflect/Method;
                    ARETURN
  end public java.lang.reflect.Method getReadMethod()

  public java.lang.reflect.Method getWriteMethod():
                    ALOAD_0     // Lorg/springframework/core/convert/Property; this   (line 111)
                    GETFIELD org.springframework.core.convert.Property.writeMethod Ljava/lang/reflect/Method;
                    ARETURN
  end public java.lang.reflect.Method getWriteMethod()

  org.springframework.core.MethodParameter getMethodParameter():
                    ALOAD_0     // Lorg/springframework/core/convert/Property; this   (line 118)
                    GETFIELD org.springframework.core.convert.Property.methodParameter Lorg/springframework/core/MethodParameter;
                    ARETURN
  end org.springframework.core.MethodParameter getMethodParameter()

  java.lang.annotation.Annotation[] getAnnotations():
                    ALOAD_0     // Lorg/springframework/core/convert/Property; this   (line 122)
                    GETFIELD org.springframework.core.convert.Property.annotations [Ljava/lang/annotation/Annotation;
                    IFNONNULL L0
                    ALOAD_0     // Lorg/springframework/core/convert/Property; this   (line 123)
                    ALOAD_0     // Lorg/springframework/core/convert/Property; this
                    INVOKESPECIAL org.springframework.core.convert.Property.resolveAnnotations ()[Ljava/lang/annotation/Annotation;
                    PUTFIELD org.springframework.core.convert.Property.annotations [Ljava/lang/annotation/Annotation;
                L0: ALOAD_0     // Lorg/springframework/core/convert/Property; this   (line 125)
                    GETFIELD org.springframework.core.convert.Property.annotations [Ljava/lang/annotation/Annotation;
                    ARETURN
  end java.lang.annotation.Annotation[] getAnnotations()

  private String resolveName():
                    ALOAD_0     // Lorg/springframework/core/convert/Property; this   (line 132)
                    GETFIELD org.springframework.core.convert.Property.readMethod Ljava/lang/reflect/Method;
                    IFNULL L3
                    ALOAD_0     // Lorg/springframework/core/convert/Property; this   (line 133)
                    GETFIELD org.springframework.core.convert.Property.readMethod Ljava/lang/reflect/Method;
                    INVOKEVIRTUAL java.lang.reflect.Method.getName ()Ljava/lang/String;
                    LDC "get"
                    INVOKEVIRTUAL java.lang.String.indexOf (Ljava/lang/String;)I
                    ISTORE_1
                    ILOAD_1     // I index   (line 134)
                    ICONST_M1
                    IF_ICMPEQ L0
                    IINC_1 3     // I index   (line 135)
                    GOTO L2
                L0: ALOAD_0     // Lorg/springframework/core/convert/Property; this   (line 138)
                    GETFIELD org.springframework.core.convert.Property.readMethod Ljava/lang/reflect/Method;
                    INVOKEVIRTUAL java.lang.reflect.Method.getName ()Ljava/lang/String;
                    LDC "is"
                    INVOKEVIRTUAL java.lang.String.indexOf (Ljava/lang/String;)I
                    ISTORE_1     // I index
                    ILOAD_1     // I index   (line 139)
                    ICONST_M1
                    IF_ICMPNE L1
                    NEW java.lang.IllegalArgumentException   (line 140)
                    DUP
                    LDC "Not a getter method"
                    INVOKESPECIAL java.lang.IllegalArgumentException.<init> (Ljava/lang/String;)V
                    ATHROW
                L1: IINC_1 2     // I index   (line 142)
                L2: ALOAD_0     // Lorg/springframework/core/convert/Property; this   (line 144)
                    GETFIELD org.springframework.core.convert.Property.readMethod Ljava/lang/reflect/Method;
                    INVOKEVIRTUAL java.lang.reflect.Method.getName ()Ljava/lang/String;
                    ILOAD_1     // I index
                    INVOKEVIRTUAL java.lang.String.substring (I)Ljava/lang/String;
                    INVOKESTATIC org.springframework.util.StringUtils.uncapitalize (Ljava/lang/String;)Ljava/lang/String;
                    ARETURN
                L3: ALOAD_0     // Lorg/springframework/core/convert/Property; this   (line 147)
                    GETFIELD org.springframework.core.convert.Property.writeMethod Ljava/lang/reflect/Method;
                    INVOKEVIRTUAL java.lang.reflect.Method.getName ()Ljava/lang/String;
                    LDC "set"
                    INVOKEVIRTUAL java.lang.String.indexOf (Ljava/lang/String;)I
                    ICONST_3
                    IADD
                    ISTORE_1
                    ILOAD_1     // I index   (line 148)
                    ICONST_M1
                    IF_ICMPNE L4
                    NEW java.lang.IllegalArgumentException   (line 149)
                    DUP
                    LDC "Not a setter method"
                    INVOKESPECIAL java.lang.IllegalArgumentException.<init> (Ljava/lang/String;)V
                    ATHROW
                L4: ALOAD_0     // Lorg/springframework/core/convert/Property; this   (line 151)
                    GETFIELD org.springframework.core.convert.Property.writeMethod Ljava/lang/reflect/Method;
                    INVOKEVIRTUAL java.lang.reflect.Method.getName ()Ljava/lang/String;
                    ILOAD_1     // I index
                    INVOKEVIRTUAL java.lang.String.substring (I)Ljava/lang/String;
                    INVOKESTATIC org.springframework.util.StringUtils.uncapitalize (Ljava/lang/String;)Ljava/lang/String;
                    ARETURN
  end private String resolveName()

  private org.springframework.core.MethodParameter resolveMethodParameter():
                    ALOAD_0     // Lorg/springframework/core/convert/Property; this   (line 156)
                    INVOKESPECIAL org.springframework.core.convert.Property.resolveReadMethodParameter ()Lorg/springframework/core/MethodParameter;
                    ASTORE_1
                    ALOAD_0     // Lorg/springframework/core/convert/Property; this   (line 157)
                    INVOKESPECIAL org.springframework.core.convert.Property.resolveWriteMethodParameter ()Lorg/springframework/core/MethodParameter;
                    ASTORE_2
                    ALOAD_2     // Lorg/springframework/core/MethodParameter; write   (line 158)
                    IFNONNULL L1
                    ALOAD_1     // Lorg/springframework/core/MethodParameter; read   (line 159)
                    IFNONNULL L0
                    NEW java.lang.IllegalStateException   (line 160)
                    DUP
                    LDC "Property is neither readable nor writeable"
                    INVOKESPECIAL java.lang.IllegalStateException.<init> (Ljava/lang/String;)V
                    ATHROW
                L0: ALOAD_1     // Lorg/springframework/core/MethodParameter; read   (line 162)
                    ARETURN
                L1: ALOAD_1     // Lorg/springframework/core/MethodParameter; read   (line 164)
                    IFNULL L2
                    ALOAD_1     // Lorg/springframework/core/MethodParameter; read   (line 165)
                    INVOKEVIRTUAL org.springframework.core.MethodParameter.getParameterType ()Ljava/lang/Class;
                    ASTORE_3
                    ALOAD_2     // Lorg/springframework/core/MethodParameter; write   (line 166)
                    INVOKEVIRTUAL org.springframework.core.MethodParameter.getParameterType ()Ljava/lang/Class;
                    ASTORE 4
                    ALOAD 4     // Ljava/lang/Class; writeType   (line 167)
                    ALOAD_3     // Ljava/lang/Class; readType
                    INVOKEVIRTUAL java.lang.Object.equals (Ljava/lang/Object;)Z
                    IFNE L2
                    ALOAD 4     // Ljava/lang/Class; writeType
                    ALOAD_3     // Ljava/lang/Class; readType
                    INVOKEVIRTUAL java.lang.Class.isAssignableFrom (Ljava/lang/Class;)Z
                    IFEQ L2
                    ALOAD_1     // Lorg/springframework/core/MethodParameter; read   (line 168)
                    ARETURN
                L2: ALOAD_2     // Lorg/springframework/core/MethodParameter; write   (line 171)
                    ARETURN
  end private org.springframework.core.MethodParameter resolveMethodParameter()

  private org.springframework.core.MethodParameter resolveReadMethodParameter():
                    ALOAD_0     // Lorg/springframework/core/convert/Property; this   (line 175)
                    INVOKEVIRTUAL org.springframework.core.convert.Property.getReadMethod ()Ljava/lang/reflect/Method;
                    IFNONNULL L0
                    ACONST_NULL   (line 176)
                    ARETURN
                L0: ALOAD_0     // Lorg/springframework/core/convert/Property; this   (line 178)
                    NEW org.springframework.core.MethodParameter
                    DUP
                    ALOAD_0     // Lorg/springframework/core/convert/Property; this
                    INVOKEVIRTUAL org.springframework.core.convert.Property.getReadMethod ()Ljava/lang/reflect/Method;
                    ICONST_M1
                    INVOKESPECIAL org.springframework.core.MethodParameter.<init> (Ljava/lang/reflect/Method;I)V
                    INVOKESPECIAL org.springframework.core.convert.Property.resolveParameterType (Lorg/springframework/core/MethodParameter;)Lorg/springframework/core/MethodParameter;
                    ARETURN
  end private org.springframework.core.MethodParameter resolveReadMethodParameter()

  private org.springframework.core.MethodParameter resolveWriteMethodParameter():
                    ALOAD_0     // Lorg/springframework/core/convert/Property; this   (line 182)
                    INVOKEVIRTUAL org.springframework.core.convert.Property.getWriteMethod ()Ljava/lang/reflect/Method;
                    IFNONNULL L0
                    ACONST_NULL   (line 183)
                    ARETURN
                L0: ALOAD_0     // Lorg/springframework/core/convert/Property; this   (line 185)
                    NEW org.springframework.core.MethodParameter
                    DUP
                    ALOAD_0     // Lorg/springframework/core/convert/Property; this
                    INVOKEVIRTUAL org.springframework.core.convert.Property.getWriteMethod ()Ljava/lang/reflect/Method;
                    ICONST_0
                    INVOKESPECIAL org.springframework.core.MethodParameter.<init> (Ljava/lang/reflect/Method;I)V
                    INVOKESPECIAL org.springframework.core.convert.Property.resolveParameterType (Lorg/springframework/core/MethodParameter;)Lorg/springframework/core/MethodParameter;
                    ARETURN
  end private org.springframework.core.MethodParameter resolveWriteMethodParameter()

  private org.springframework.core.MethodParameter resolveParameterType(org.springframework.core.MethodParameter):
                    ALOAD_1     // Lorg/springframework/core/MethodParameter; parameter   (line 190)
                    ALOAD_0     // Lorg/springframework/core/convert/Property; this
                    INVOKEVIRTUAL org.springframework.core.convert.Property.getObjectType ()Ljava/lang/Class;
                    INVOKESTATIC org.springframework.core.GenericTypeResolver.resolveParameterType (Lorg/springframework/core/MethodParameter;Ljava/lang/Class;)Ljava/lang/Class;
                    POP
                    ALOAD_1     // Lorg/springframework/core/MethodParameter; parameter   (line 191)
                    ARETURN
  end private org.springframework.core.MethodParameter resolveParameterType(org.springframework.core.MethodParameter)

  private java.lang.annotation.Annotation[] resolveAnnotations():
                    GETSTATIC org.springframework.core.convert.Property.annotationCache Ljava/util/Map;   (line 195)
                    ALOAD_0     // Lorg/springframework/core/convert/Property; this
                    INVOKEINTERFACE java.util.Map.get (Ljava/lang/Object;)Ljava/lang/Object;
                    CHECKCAST [Ljava.lang.annotation.Annotation;
                    ASTORE_1
                    ALOAD_1     // [Ljava/lang/annotation/Annotation; annotations   (line 196)
                    IFNONNULL L0
                    NEW java.util.LinkedHashMap   (line 197)
                    DUP
                    INVOKESPECIAL java.util.LinkedHashMap.<init> ()V
                    ASTORE_2
                    ALOAD_0     // Lorg/springframework/core/convert/Property; this   (line 198)
                    ALOAD_2     // Ljava/util/Map; annotationMap
                    ALOAD_0     // Lorg/springframework/core/convert/Property; this
                    INVOKEVIRTUAL org.springframework.core.convert.Property.getReadMethod ()Ljava/lang/reflect/Method;
                    INVOKESPECIAL org.springframework.core.convert.Property.addAnnotationsToMap (Ljava/util/Map;Ljava/lang/reflect/AnnotatedElement;)V
                    ALOAD_0     // Lorg/springframework/core/convert/Property; this   (line 199)
                    ALOAD_2     // Ljava/util/Map; annotationMap
                    ALOAD_0     // Lorg/springframework/core/convert/Property; this
                    INVOKEVIRTUAL org.springframework.core.convert.Property.getWriteMethod ()Ljava/lang/reflect/Method;
                    INVOKESPECIAL org.springframework.core.convert.Property.addAnnotationsToMap (Ljava/util/Map;Ljava/lang/reflect/AnnotatedElement;)V
                    ALOAD_0     // Lorg/springframework/core/convert/Property; this   (line 200)
                    ALOAD_2     // Ljava/util/Map; annotationMap
                    ALOAD_0     // Lorg/springframework/core/convert/Property; this
                    INVOKESPECIAL org.springframework.core.convert.Property.getField ()Ljava/lang/reflect/Field;
                    INVOKESPECIAL org.springframework.core.convert.Property.addAnnotationsToMap (Ljava/util/Map;Ljava/lang/reflect/AnnotatedElement;)V
                    ALOAD_2     // Ljava/util/Map; annotationMap   (line 201)
                    INVOKEINTERFACE java.util.Map.values ()Ljava/util/Collection;
                    ALOAD_2     // Ljava/util/Map; annotationMap
                    INVOKEINTERFACE java.util.Map.size ()I
                    ANEWARRAY java.lang.annotation.Annotation
                    INVOKEINTERFACE java.util.Collection.toArray ([Ljava/lang/Object;)[Ljava/lang/Object;
                    CHECKCAST [Ljava.lang.annotation.Annotation;
                    ASTORE_1     // [Ljava/lang/annotation/Annotation; annotations
                    GETSTATIC org.springframework.core.convert.Property.annotationCache Ljava/util/Map;   (line 202)
                    ALOAD_0     // Lorg/springframework/core/convert/Property; this
                    ALOAD_1     // [Ljava/lang/annotation/Annotation; annotations
                    INVOKEINTERFACE java.util.Map.put (Ljava/lang/Object;Ljava/lang/Object;)Ljava/lang/Object;
                    POP
                L0: ALOAD_1     // [Ljava/lang/annotation/Annotation; annotations   (line 204)
                    ARETURN
  end private java.lang.annotation.Annotation[] resolveAnnotations()

  private void addAnnotationsToMap(java.util.Map, java.lang.reflect.AnnotatedElement):
                    ALOAD_2     // Ljava/lang/reflect/AnnotatedElement; object   (line 210)
                    IFNULL L1
                    ALOAD_2     // Ljava/lang/reflect/AnnotatedElement; object   (line 211)
                    INVOKEINTERFACE java.lang.reflect.AnnotatedElement.getAnnotations ()[Ljava/lang/annotation/Annotation;
                    ASTORE_3
                    ALOAD_3
                    ARRAYLENGTH
                    ISTORE 4
                    ICONST_0
                    ISTORE 5
                L0: ILOAD 5
                    ILOAD 4
                    IF_ICMPGE L1
                    ALOAD_3
                    ILOAD 5
                    AALOAD
                    ASTORE 6
                    ALOAD_1     // Ljava/util/Map; annotationMap   (line 212)
                    ALOAD 6     // Ljava/lang/annotation/Annotation; annotation
                    INVOKEINTERFACE java.lang.annotation.Annotation.annotationType ()Ljava/lang/Class;
                    ALOAD 6     // Ljava/lang/annotation/Annotation; annotation
                    INVOKEINTERFACE java.util.Map.put (Ljava/lang/Object;Ljava/lang/Object;)Ljava/lang/Object;
                    POP
                    IINC 5 1   (line 211)
                    GOTO L0
                L1: RETURN   (line 215)
  end private void addAnnotationsToMap(java.util.Map, java.lang.reflect.AnnotatedElement)

  private java.lang.reflect.Field getField():
                    ALOAD_0     // Lorg/springframework/core/convert/Property; this   (line 218)
                    INVOKEVIRTUAL org.springframework.core.convert.Property.getName ()Ljava/lang/String;
                    ASTORE_1
                    ALOAD_1     // Ljava/lang/String; name   (line 219)
                    INVOKESTATIC org.springframework.util.StringUtils.hasLength (Ljava/lang/String;)Z
                    IFNE L0
                    ACONST_NULL   (line 220)
                    ARETURN
                L0: ALOAD_0     // Lorg/springframework/core/convert/Property; this   (line 222)
                    INVOKESPECIAL org.springframework.core.convert.Property.declaringClass ()Ljava/lang/Class;
                    ASTORE_2
                    ALOAD_2     // Ljava/lang/Class; declaringClass   (line 223)
                    ALOAD_1     // Ljava/lang/String; name
                    INVOKESTATIC org.springframework.util.ReflectionUtils.findField (Ljava/lang/Class;Ljava/lang/String;)Ljava/lang/reflect/Field;
                    ASTORE_3
                    ALOAD_3     // Ljava/lang/reflect/Field; field   (line 224)
                    IFNONNULL L1
                    ALOAD_2     // Ljava/lang/Class; declaringClass   (line 226)
                    NEW java.lang.StringBuilder
                    DUP
                    INVOKESPECIAL java.lang.StringBuilder.<init> ()V
                    ALOAD_1     // Ljava/lang/String; name
                    ICONST_0
                    ICONST_1
                    INVOKEVIRTUAL java.lang.String.substring (II)Ljava/lang/String;   (line 227)
                    INVOKEVIRTUAL java.lang.String.toLowerCase ()Ljava/lang/String;
                    INVOKEVIRTUAL java.lang.StringBuilder.append (Ljava/lang/String;)Ljava/lang/StringBuilder;
                    ALOAD_1     // Ljava/lang/String; name
                    ICONST_1
                    INVOKEVIRTUAL java.lang.String.substring (I)Ljava/lang/String;
                    INVOKEVIRTUAL java.lang.StringBuilder.append (Ljava/lang/String;)Ljava/lang/StringBuilder;
                    INVOKEVIRTUAL java.lang.StringBuilder.toString ()Ljava/lang/String;
                    INVOKESTATIC org.springframework.util.ReflectionUtils.findField (Ljava/lang/Class;Ljava/lang/String;)Ljava/lang/reflect/Field;   (line 226)
                    ASTORE_3     // Ljava/lang/reflect/Field; field
                    ALOAD_3     // Ljava/lang/reflect/Field; field   (line 228)
                    IFNONNULL L1
                    ALOAD_2     // Ljava/lang/Class; declaringClass   (line 229)
                    NEW java.lang.StringBuilder
                    DUP
                    INVOKESPECIAL java.lang.StringBuilder.<init> ()V
                    ALOAD_1     // Ljava/lang/String; name
                    ICONST_0
                    ICONST_1
                    INVOKEVIRTUAL java.lang.String.substring (II)Ljava/lang/String;   (line 230)
                    INVOKEVIRTUAL java.lang.String.toUpperCase ()Ljava/lang/String;
                    INVOKEVIRTUAL java.lang.StringBuilder.append (Ljava/lang/String;)Ljava/lang/StringBuilder;
                    ALOAD_1     // Ljava/lang/String; name
                    ICONST_1
                    INVOKEVIRTUAL java.lang.String.substring (I)Ljava/lang/String;
                    INVOKEVIRTUAL java.lang.StringBuilder.append (Ljava/lang/String;)Ljava/lang/StringBuilder;
                    INVOKEVIRTUAL java.lang.StringBuilder.toString ()Ljava/lang/String;
                    INVOKESTATIC org.springframework.util.ReflectionUtils.findField (Ljava/lang/Class;Ljava/lang/String;)Ljava/lang/reflect/Field;   (line 229)
                    ASTORE_3     // Ljava/lang/reflect/Field; field
                L1: ALOAD_3     // Ljava/lang/reflect/Field; field   (line 233)
                    ARETURN
  end private java.lang.reflect.Field getField()

  private Class declaringClass():
                    ALOAD_0     // Lorg/springframework/core/convert/Property; this   (line 237)
                    INVOKEVIRTUAL org.springframework.core.convert.Property.getReadMethod ()Ljava/lang/reflect/Method;
                    IFNULL L0
                    ALOAD_0     // Lorg/springframework/core/convert/Property; this   (line 238)
                    INVOKEVIRTUAL org.springframework.core.convert.Property.getReadMethod ()Ljava/lang/reflect/Method;
                    INVOKEVIRTUAL java.lang.reflect.Method.getDeclaringClass ()Ljava/lang/Class;
                    ARETURN
                L0: ALOAD_0     // Lorg/springframework/core/convert/Property; this   (line 241)
                    INVOKEVIRTUAL org.springframework.core.convert.Property.getWriteMethod ()Ljava/lang/reflect/Method;
                    INVOKEVIRTUAL java.lang.reflect.Method.getDeclaringClass ()Ljava/lang/Class;
                    ARETURN
  end private Class declaringClass()

  public boolean equals(Object):
                    ALOAD_0     // Lorg/springframework/core/convert/Property; this   (line 248)
                    ALOAD_1     // Ljava/lang/Object; other
                    IF_ACMPNE L0
                    ICONST_1   (line 249)
                    IRETURN
                L0: ALOAD_1     // Ljava/lang/Object; other   (line 251)
                    INSTANCEOF org.springframework.core.convert.Property
                    IFNE L1
                    ICONST_0   (line 252)
                    IRETURN
                L1: ALOAD_1     // Ljava/lang/Object; other   (line 254)
                    CHECKCAST org.springframework.core.convert.Property
                    ASTORE_2
                    ALOAD_0     // Lorg/springframework/core/convert/Property; this   (line 255)
                    GETFIELD org.springframework.core.convert.Property.objectType Ljava/lang/Class;
                    ALOAD_2     // Lorg/springframework/core/convert/Property; otherProperty
                    GETFIELD org.springframework.core.convert.Property.objectType Ljava/lang/Class;
                    INVOKESTATIC org.springframework.util.ObjectUtils.nullSafeEquals (Ljava/lang/Object;Ljava/lang/Object;)Z
                    IFEQ L2
                    ALOAD_0     // Lorg/springframework/core/convert/Property; this
                    GETFIELD org.springframework.core.convert.Property.name Ljava/lang/String;
                    ALOAD_2     // Lorg/springframework/core/convert/Property; otherProperty
                    GETFIELD org.springframework.core.convert.Property.name Ljava/lang/String;
                    INVOKESTATIC org.springframework.util.ObjectUtils.nullSafeEquals (Ljava/lang/Object;Ljava/lang/Object;)Z   (line 256)
                    IFEQ L2
                    ALOAD_0     // Lorg/springframework/core/convert/Property; this
                    GETFIELD org.springframework.core.convert.Property.readMethod Ljava/lang/reflect/Method;
                    ALOAD_2     // Lorg/springframework/core/convert/Property; otherProperty
                    GETFIELD org.springframework.core.convert.Property.readMethod Ljava/lang/reflect/Method;
                    INVOKESTATIC org.springframework.util.ObjectUtils.nullSafeEquals (Ljava/lang/Object;Ljava/lang/Object;)Z   (line 257)
                    IFEQ L2
                    ALOAD_0     // Lorg/springframework/core/convert/Property; this
                    GETFIELD org.springframework.core.convert.Property.writeMethod Ljava/lang/reflect/Method;
                    ALOAD_2     // Lorg/springframework/core/convert/Property; otherProperty
                    GETFIELD org.springframework.core.convert.Property.writeMethod Ljava/lang/reflect/Method;
                    INVOKESTATIC org.springframework.util.ObjectUtils.nullSafeEquals (Ljava/lang/Object;Ljava/lang/Object;)Z   (line 258)
                    IFEQ L2
                    ICONST_1
                    GOTO L3
                L2: ICONST_0
                L3: IRETURN
  end public boolean equals(Object)

  public int hashCode():
                    ALOAD_0     // Lorg/springframework/core/convert/Property; this   (line 263)
                    GETFIELD org.springframework.core.convert.Property.objectType Ljava/lang/Class;
                    INVOKESTATIC org.springframework.util.ObjectUtils.nullSafeHashCode (Ljava/lang/Object;)I
                    BIPUSH 31
                    IMUL
                    ALOAD_0     // Lorg/springframework/core/convert/Property; this
                    GETFIELD org.springframework.core.convert.Property.name Ljava/lang/String;
                    INVOKESTATIC org.springframework.util.ObjectUtils.nullSafeHashCode (Ljava/lang/Object;)I
                    IADD
                    IRETURN
  end public int hashCode()

  static void <clinit>():
                    NEW org.springframework.util.ConcurrentReferenceHashMap   (line 50)
                    DUP
                    INVOKESPECIAL org.springframework.util.ConcurrentReferenceHashMap.<init> ()V
                    PUTSTATIC org.springframework.core.convert.Property.annotationCache Ljava/util/Map;
                    RETURN
  end static void <clinit>()
end public final class org.springframework.core.convert.Property
 -- (NullPointerException) null
null
java.lang.NullPointerException
	at org.aspectj.weaver.UnresolvedType.forSignature(UnresolvedType.java:384)
	at org.aspectj.weaver.bcel.BcelObjectType.getDeclaredInterfaces(BcelObjectType.java:275)
	at org.aspectj.weaver.ReferenceType.getDeclaredInterfaces(ReferenceType.java:626)
	at org.aspectj.weaver.ResolvedType.getDirectSupertypes(ResolvedType.java:82)
	at org.aspectj.weaver.patterns.TypePattern.matchesSubtypes(TypePattern.java:178)
	at org.aspectj.weaver.patterns.ExactTypePattern.matchesSubtypes(ExactTypePattern.java:74)
	at org.aspectj.weaver.patterns.TypePattern.matchesStatically(TypePattern.java:130)
	at org.aspectj.weaver.patterns.OrTypePattern.matchesStatically(OrTypePattern.java:76)
	at org.aspectj.weaver.patterns.SignaturePattern.matchesExactlyMethod(SignaturePattern.java:505)
	at org.aspectj.weaver.patterns.SignaturePattern.matchesExactly(SignaturePattern.java:360)
	at org.aspectj.weaver.patterns.SignaturePattern.matches(SignaturePattern.java:320)
	at org.aspectj.weaver.patterns.KindedPointcut.matchInternal(KindedPointcut.java:202)
	at org.aspectj.weaver.patterns.Pointcut.match(Pointcut.java:137)
	at org.aspectj.weaver.patterns.AndPointcut.matchInternal(AndPointcut.java:51)
	at org.aspectj.weaver.patterns.Pointcut.match(Pointcut.java:137)
	at org.aspectj.weaver.patterns.OrPointcut.matchInternal(OrPointcut.java:54)
	at org.aspectj.weaver.patterns.Pointcut.match(Pointcut.java:137)
	at org.aspectj.weaver.ShadowMunger.match(ShadowMunger.java:113)
	at org.aspectj.weaver.Advice.match(Advice.java:109)
	at org.aspectj.weaver.bcel.BcelAdvice.match(BcelAdvice.java:149)
	at org.aspectj.weaver.bcel.BcelClassWeaver.match(BcelClassWeaver.java:3173)
	at org.aspectj.weaver.bcel.BcelClassWeaver.match(BcelClassWeaver.java:2565)
	at org.aspectj.weaver.bcel.BcelClassWeaver.weave(BcelClassWeaver.java:480)
	at org.aspectj.weaver.bcel.BcelClassWeaver.weave(BcelClassWeaver.java:99)
	at org.aspectj.weaver.bcel.BcelWeaver.weave(BcelWeaver.java:1694)
	at org.aspectj.weaver.bcel.BcelWeaver.weaveWithoutDump(BcelWeaver.java:1638)
	at org.aspectj.weaver.bcel.BcelWeaver.weaveAndNotify(BcelWeaver.java:1401)
	at org.aspectj.weaver.bcel.BcelWeaver.weave(BcelWeaver.java:1187)
	at org.aspectj.weaver.tools.WeavingAdaptor.getWovenBytes(WeavingAdaptor.java:472)
	at org.aspectj.weaver.tools.WeavingAdaptor.weaveClass(WeavingAdaptor.java:323)
	at org.aspectj.weaver.loadtime.Aj.preProcess(Aj.java:99)
	at org.aspectj.weaver.loadtime.ClassPreProcessorAgentAdapter.transform(ClassPreProcessorAgentAdapter.java:54)
	at org.springframework.context.weaving.AspectJWeavingEnabler$AspectJClassBypassingClassFileTransformer.transform(AspectJWeavingEnabler.java:108)
	at org.springframework.instrument.classloading.InstrumentationLoadTimeWeaver$FilteringClassFileTransformer.transform(InstrumentationLoadTimeWeaver.java:184)
	at sun.instrument.TransformerManager.transform(Unknown Source)
	at sun.instrument.InstrumentationImpl.transform(Unknown Source)
	at java.lang.ClassLoader.defineClass1(Native Method)
	at java.lang.ClassLoader.defineClass(Unknown Source)
	at java.security.SecureClassLoader.defineClass(Unknown Source)
	at java.net.URLClassLoader.defineClass(Unknown Source)
	at java.net.URLClassLoader.access$100(Unknown Source)
	at java.net.URLClassLoader$1.run(Unknown Source)
	at java.net.URLClassLoader$1.run(Unknown Source)
	at java.security.AccessController.doPrivileged(Native Method)
	at java.net.URLClassLoader.findClass(Unknown Source)
	at java.lang.ClassLoader.loadClass(Unknown Source)
	at sun.misc.Launcher$AppClassLoader.loadClass(Unknown Source)
	at java.lang.ClassLoader.loadClass(Unknown Source)
	at org.springframework.beans.BeanWrapperImpl.property(BeanWrapperImpl.java:517)
	at org.springframework.beans.BeanWrapperImpl.convertForProperty(BeanWrapperImpl.java:504)
	at org.springframework.beans.factory.support.AbstractAutowireCapableBeanFactory.convertForProperty(AbstractAutowireCapableBeanFactory.java:1523)
	at org.springframework.beans.factory.support.AbstractAutowireCapableBeanFactory.applyPropertyValues(AbstractAutowireCapableBeanFactory.java:1482)
	at org.springframework.beans.factory.support.AbstractAutowireCapableBeanFactory.populateBean(AbstractAutowireCapableBeanFactory.java:1222)
	at org.springframework.beans.factory.support.AbstractAutowireCapableBeanFactory.doCreateBean(AbstractAutowireCapableBeanFactory.java:537)
	at org.springframework.beans.factory.support.AbstractAutowireCapableBeanFactory.createBean(AbstractAutowireCapableBeanFactory.java:476)
	at org.springframework.beans.factory.support.AbstractBeanFactory$1.getObject(AbstractBeanFactory.java:303)
	at org.springframework.beans.factory.support.DefaultSingletonBeanRegistry.getSingleton(DefaultSingletonBeanRegistry.java:230)
	at org.springframework.beans.factory.support.AbstractBeanFactory.doGetBean(AbstractBeanFactory.java:299)
	at org.springframework.beans.factory.support.AbstractBeanFactory.getBean(AbstractBeanFactory.java:194)
	at org.springframework.beans.factory.support.DefaultListableBeanFactory.findAutowireCandidates(DefaultListableBeanFactory.java:1120)
	at org.springframework.beans.factory.support.DefaultListableBeanFactory.doResolveDependency(DefaultListableBeanFactory.java:996)
	at org.springframework.beans.factory.support.DefaultListableBeanFactory.resolveDependency(DefaultListableBeanFactory.java:942)
	at org.springframework.beans.factory.annotation.AutowiredAnnotationBeanPostProcessor$AutowiredFieldElement.inject(AutowiredAnnotationBeanPostProcessor.java:533)
	at org.springframework.beans.factory.annotation.InjectionMetadata.inject(InjectionMetadata.java:88)
	at org.springframework.beans.factory.annotation.AutowiredAnnotationBeanPostProcessor.postProcessPropertyValues(AutowiredAnnotationBeanPostProcessor.java:331)
	at org.springframework.beans.factory.support.AbstractAutowireCapableBeanFactory.populateBean(AbstractAutowireCapableBeanFactory.java:1210)
	at org.springframework.beans.factory.support.AbstractAutowireCapableBeanFactory.doCreateBean(AbstractAutowireCapableBeanFactory.java:537)
	at org.springframework.beans.factory.support.AbstractAutowireCapableBeanFactory.createBean(AbstractAutowireCapableBeanFactory.java:476)
	at org.springframework.beans.factory.support.AbstractBeanFactory$1.getObject(AbstractBeanFactory.java:303)
	at org.springframework.beans.factory.support.DefaultSingletonBeanRegistry.getSingleton(DefaultSingletonBeanRegistry.java:230)
	at org.springframework.beans.factory.support.AbstractBeanFactory.doGetBean(AbstractBeanFactory.java:299)
	at org.springframework.beans.factory.support.AbstractBeanFactory.getBean(AbstractBeanFactory.java:194)
	at org.springframework.beans.factory.support.DefaultListableBeanFactory.preInstantiateSingletons(DefaultListableBeanFactory.java:755)
	at org.springframework.context.support.AbstractApplicationContext.finishBeanFactoryInitialization(AbstractApplicationContext.java:757)
	at org.springframework.context.support.AbstractApplicationContext.refresh(AbstractApplicationContext.java:480)
	at org.springframework.context.support.ClassPathXmlApplicationContext.<init>(ClassPathXmlApplicationContext.java:139)
	at org.springframework.context.support.ClassPathXmlApplicationContext.<init>(ClassPathXmlApplicationContext.java:93)
	at com.springExemple.presentation.Presentation2.main(Presentation2.java:13)

error can't determine annotations of missing type org.springframework.transaction.annotation.Transactional
when weaving type org.springframework.beans.factory.config.TypedStringValue
when weaving classes 
when weaving 
 [Xlint:cantFindType]
abort trouble in: 
public class org.springframework.beans.factory.config.TypedStringValue extends java.lang.Object implements org.springframework.beans.BeanMetadataElement:
  private String value
  private volatile Object targetType
  private Object source
  private String specifiedTypeName
  private volatile boolean dynamic
  public void <init>(String):
                    ALOAD_0     // Lorg/springframework/beans/factory/config/TypedStringValue; this   (line 54)
                    INVOKESPECIAL java.lang.Object.<init> ()V
    constructor-execution(void org.springframework.beans.factory.config.TypedStringValue.<init>(java.lang.String))
    |               ALOAD_0     // Lorg/springframework/beans/factory/config/TypedStringValue; this   (line 55)
    |               ALOAD_1     // Ljava/lang/String; value
    |               INVOKEVIRTUAL org.springframework.beans.factory.config.TypedStringValue.setValue (Ljava/lang/String;)V
    |               RETURN   (line 56)
    constructor-execution(void org.springframework.beans.factory.config.TypedStringValue.<init>(java.lang.String))
  end public void <init>(String)

  public void <init>(String, Class):
                    ALOAD_0     // Lorg/springframework/beans/factory/config/TypedStringValue; this   (line 64)
                    INVOKESPECIAL java.lang.Object.<init> ()V
    constructor-execution(void org.springframework.beans.factory.config.TypedStringValue.<init>(java.lang.String, java.lang.Class))
    |               ALOAD_0     // Lorg/springframework/beans/factory/config/TypedStringValue; this   (line 65)
    |               ALOAD_1     // Ljava/lang/String; value
    |               INVOKEVIRTUAL org.springframework.beans.factory.config.TypedStringValue.setValue (Ljava/lang/String;)V
    |               ALOAD_0     // Lorg/springframework/beans/factory/config/TypedStringValue; this   (line 66)
    |               ALOAD_2     // Ljava/lang/Class; targetType
    |               INVOKEVIRTUAL org.springframework.beans.factory.config.TypedStringValue.setTargetType (Ljava/lang/Class;)V
    |               RETURN   (line 67)
    constructor-execution(void org.springframework.beans.factory.config.TypedStringValue.<init>(java.lang.String, java.lang.Class))
  end public void <init>(String, Class)

  public void <init>(String, String):
                    ALOAD_0     // Lorg/springframework/beans/factory/config/TypedStringValue; this   (line 75)
                    INVOKESPECIAL java.lang.Object.<init> ()V
    constructor-execution(void org.springframework.beans.factory.config.TypedStringValue.<init>(java.lang.String, java.lang.String))
    |               ALOAD_0     // Lorg/springframework/beans/factory/config/TypedStringValue; this   (line 76)
    |               ALOAD_1     // Ljava/lang/String; value
    |               INVOKEVIRTUAL org.springframework.beans.factory.config.TypedStringValue.setValue (Ljava/lang/String;)V
    |               ALOAD_0     // Lorg/springframework/beans/factory/config/TypedStringValue; this   (line 77)
    |               ALOAD_2     // Ljava/lang/String; targetTypeName
    |               INVOKEVIRTUAL org.springframework.beans.factory.config.TypedStringValue.setTargetTypeName (Ljava/lang/String;)V
    |               RETURN   (line 78)
    constructor-execution(void org.springframework.beans.factory.config.TypedStringValue.<init>(java.lang.String, java.lang.String))
  end public void <init>(String, String)

  public void setValue(String):
                    ALOAD_0     // Lorg/springframework/beans/factory/config/TypedStringValue; this   (line 88)
                    ALOAD_1     // Ljava/lang/String; value
                    PUTFIELD org.springframework.beans.factory.config.TypedStringValue.value Ljava/lang/String;
                    RETURN   (line 89)
  end public void setValue(String)

  public String getValue():
                    ALOAD_0     // Lorg/springframework/beans/factory/config/TypedStringValue; this   (line 95)
                    GETFIELD org.springframework.beans.factory.config.TypedStringValue.value Ljava/lang/String;
                    ARETURN
  end public String getValue()

  public void setTargetType(Class):
                    ALOAD_1     // Ljava/lang/Class; targetType   (line 105)
                    LDC "'targetType' must not be null"
                    INVOKESTATIC org.springframework.util.Assert.notNull (Ljava/lang/Object;Ljava/lang/String;)V
                    ALOAD_0     // Lorg/springframework/beans/factory/config/TypedStringValue; this   (line 106)
                    ALOAD_1     // Ljava/lang/Class; targetType
                    PUTFIELD org.springframework.beans.factory.config.TypedStringValue.targetType Ljava/lang/Object;
                    RETURN   (line 107)
  end public void setTargetType(Class)

  public Class getTargetType():
                    ALOAD_0     // Lorg/springframework/beans/factory/config/TypedStringValue; this   (line 113)
                    GETFIELD org.springframework.beans.factory.config.TypedStringValue.targetType Ljava/lang/Object;
                    ASTORE_1
                    ALOAD_1     // Ljava/lang/Object; targetTypeValue   (line 114)
                    INSTANCEOF java.lang.Class
                    IFNE L0
                    NEW java.lang.IllegalStateException   (line 115)
                    DUP
                    LDC "Typed String value does not carry a resolved target type"
                    INVOKESPECIAL java.lang.IllegalStateException.<init> (Ljava/lang/String;)V
                    ATHROW
                L0: ALOAD_1     // Ljava/lang/Object; targetTypeValue   (line 117)
                    CHECKCAST java.lang.Class
                    ARETURN
  end public Class getTargetType()

  public void setTargetTypeName(String):
                    ALOAD_1     // Ljava/lang/String; targetTypeName   (line 124)
                    LDC "'targetTypeName' must not be null"
                    INVOKESTATIC org.springframework.util.Assert.notNull (Ljava/lang/Object;Ljava/lang/String;)V
                    ALOAD_0     // Lorg/springframework/beans/factory/config/TypedStringValue; this   (line 125)
                    ALOAD_1     // Ljava/lang/String; targetTypeName
                    PUTFIELD org.springframework.beans.factory.config.TypedStringValue.targetType Ljava/lang/Object;
                    RETURN   (line 126)
  end public void setTargetTypeName(String)

  public String getTargetTypeName():
                    ALOAD_0     // Lorg/springframework/beans/factory/config/TypedStringValue; this   (line 132)
                    GETFIELD org.springframework.beans.factory.config.TypedStringValue.targetType Ljava/lang/Object;
                    ASTORE_1
                    ALOAD_1     // Ljava/lang/Object; targetTypeValue   (line 133)
                    INSTANCEOF java.lang.Class
                    IFEQ L0
                    ALOAD_1     // Ljava/lang/Object; targetTypeValue   (line 134)
                    CHECKCAST java.lang.Class
                    INVOKEVIRTUAL java.lang.Class.getName ()Ljava/lang/String;
                    ARETURN
                L0: ALOAD_1     // Ljava/lang/Object; targetTypeValue   (line 137)
                    CHECKCAST java.lang.String
                    ARETURN
  end public String getTargetTypeName()

  public boolean hasTargetType():
                    ALOAD_0     // Lorg/springframework/beans/factory/config/TypedStringValue; this   (line 145)
                    GETFIELD org.springframework.beans.factory.config.TypedStringValue.targetType Ljava/lang/Object;
                    INSTANCEOF java.lang.Class
                    IRETURN
  end public boolean hasTargetType()

  public Class resolveTargetType(ClassLoader) throws java.lang.ClassNotFoundException:
                    ALOAD_0     // Lorg/springframework/beans/factory/config/TypedStringValue; this   (line 157)
                    GETFIELD org.springframework.beans.factory.config.TypedStringValue.targetType Ljava/lang/Object;
                    IFNONNULL L0
                    ACONST_NULL   (line 158)
                    ARETURN
                L0: ALOAD_0     // Lorg/springframework/beans/factory/config/TypedStringValue; this   (line 160)
                    INVOKEVIRTUAL org.springframework.beans.factory.config.TypedStringValue.getTargetTypeName ()Ljava/lang/String;
                    ALOAD_1     // Ljava/lang/ClassLoader; classLoader
                    INVOKESTATIC org.springframework.util.ClassUtils.forName (Ljava/lang/String;Ljava/lang/ClassLoader;)Ljava/lang/Class;
                    ASTORE_2
                    ALOAD_0     // Lorg/springframework/beans/factory/config/TypedStringValue; this   (line 161)
                    ALOAD_2     // Ljava/lang/Class; resolvedClass
                    PUTFIELD org.springframework.beans.factory.config.TypedStringValue.targetType Ljava/lang/Object;
                    ALOAD_2     // Ljava/lang/Class; resolvedClass   (line 162)
                    ARETURN
  end public Class resolveTargetType(ClassLoader) throws java.lang.ClassNotFoundException

  public void setSource(Object):
                    ALOAD_0     // Lorg/springframework/beans/factory/config/TypedStringValue; this   (line 171)
                    ALOAD_1     // Ljava/lang/Object; source
                    PUTFIELD org.springframework.beans.factory.config.TypedStringValue.source Ljava/lang/Object;
                    RETURN   (line 172)
  end public void setSource(Object)

  public Object getSource():
                    ALOAD_0     // Lorg/springframework/beans/factory/config/TypedStringValue; this   (line 176)
                    GETFIELD org.springframework.beans.factory.config.TypedStringValue.source Ljava/lang/Object;
                    ARETURN
  end public Object getSource()

  public void setSpecifiedTypeName(String):
                    ALOAD_0     // Lorg/springframework/beans/factory/config/TypedStringValue; this   (line 183)
                    ALOAD_1     // Ljava/lang/String; specifiedTypeName
                    PUTFIELD org.springframework.beans.factory.config.TypedStringValue.specifiedTypeName Ljava/lang/String;
                    RETURN   (line 184)
  end public void setSpecifiedTypeName(String)

  public String getSpecifiedTypeName():
                    ALOAD_0     // Lorg/springframework/beans/factory/config/TypedStringValue; this   (line 190)
                    GETFIELD org.springframework.beans.factory.config.TypedStringValue.specifiedTypeName Ljava/lang/String;
                    ARETURN
  end public String getSpecifiedTypeName()

  public void setDynamic():
                    ALOAD_0     // Lorg/springframework/beans/factory/config/TypedStringValue; this   (line 198)
                    ICONST_1
                    PUTFIELD org.springframework.beans.factory.config.TypedStringValue.dynamic Z
                    RETURN   (line 199)
  end public void setDynamic()

  public boolean isDynamic():
                    ALOAD_0     // Lorg/springframework/beans/factory/config/TypedStringValue; this   (line 205)
                    GETFIELD org.springframework.beans.factory.config.TypedStringValue.dynamic Z
                    IRETURN
  end public boolean isDynamic()

  public boolean equals(Object):
                    ALOAD_0     // Lorg/springframework/beans/factory/config/TypedStringValue; this   (line 211)
                    ALOAD_1     // Ljava/lang/Object; other
                    IF_ACMPNE L0
                    ICONST_1   (line 212)
                    IRETURN
                L0: ALOAD_1     // Ljava/lang/Object; other   (line 214)
                    INSTANCEOF org.springframework.beans.factory.config.TypedStringValue
                    IFNE L1
                    ICONST_0   (line 215)
                    IRETURN
                L1: ALOAD_1     // Ljava/lang/Object; other   (line 217)
                    CHECKCAST org.springframework.beans.factory.config.TypedStringValue
                    ASTORE_2
                    ALOAD_0     // Lorg/springframework/beans/factory/config/TypedStringValue; this   (line 218)
                    GETFIELD org.springframework.beans.factory.config.TypedStringValue.value Ljava/lang/String;
                    ALOAD_2     // Lorg/springframework/beans/factory/config/TypedStringValue; otherValue
                    GETFIELD org.springframework.beans.factory.config.TypedStringValue.value Ljava/lang/String;
                    INVOKESTATIC org.springframework.util.ObjectUtils.nullSafeEquals (Ljava/lang/Object;Ljava/lang/Object;)Z
                    IFEQ L2
                    ALOAD_0     // Lorg/springframework/beans/factory/config/TypedStringValue; this
                    GETFIELD org.springframework.beans.factory.config.TypedStringValue.targetType Ljava/lang/Object;
                    ALOAD_2     // Lorg/springframework/beans/factory/config/TypedStringValue; otherValue
                    GETFIELD org.springframework.beans.factory.config.TypedStringValue.targetType Ljava/lang/Object;
                    INVOKESTATIC org.springframework.util.ObjectUtils.nullSafeEquals (Ljava/lang/Object;Ljava/lang/Object;)Z   (line 219)
                    IFEQ L2
                    ICONST_1
                    GOTO L3
                L2: ICONST_0
                L3: IRETURN
  end public boolean equals(Object)

  public int hashCode():
                    ALOAD_0     // Lorg/springframework/beans/factory/config/TypedStringValue; this   (line 224)
                    GETFIELD org.springframework.beans.factory.config.TypedStringValue.value Ljava/lang/String;
                    INVOKESTATIC org.springframework.util.ObjectUtils.nullSafeHashCode (Ljava/lang/Object;)I
                    BIPUSH 29
                    IMUL
                    ALOAD_0     // Lorg/springframework/beans/factory/config/TypedStringValue; this
                    GETFIELD org.springframework.beans.factory.config.TypedStringValue.targetType Ljava/lang/Object;
                    INVOKESTATIC org.springframework.util.ObjectUtils.nullSafeHashCode (Ljava/lang/Object;)I
                    IADD
                    IRETURN
  end public int hashCode()

  public String toString():
                    NEW java.lang.StringBuilder   (line 229)
                    DUP
                    INVOKESPECIAL java.lang.StringBuilder.<init> ()V
                    LDC "TypedStringValue: value ["
                    INVOKEVIRTUAL java.lang.StringBuilder.append (Ljava/lang/String;)Ljava/lang/StringBuilder;
                    ALOAD_0     // Lorg/springframework/beans/factory/config/TypedStringValue; this
                    GETFIELD org.springframework.beans.factory.config.TypedStringValue.value Ljava/lang/String;
                    INVOKEVIRTUAL java.lang.StringBuilder.append (Ljava/lang/String;)Ljava/lang/StringBuilder;
                    LDC "], target type ["
                    INVOKEVIRTUAL java.lang.StringBuilder.append (Ljava/lang/String;)Ljava/lang/StringBuilder;
                    ALOAD_0     // Lorg/springframework/beans/factory/config/TypedStringValue; this
                    GETFIELD org.springframework.beans.factory.config.TypedStringValue.targetType Ljava/lang/Object;
                    INVOKEVIRTUAL java.lang.StringBuilder.append (Ljava/lang/Object;)Ljava/lang/StringBuilder;
                    LDC "]"
                    INVOKEVIRTUAL java.lang.StringBuilder.append (Ljava/lang/String;)Ljava/lang/StringBuilder;
                    INVOKEVIRTUAL java.lang.StringBuilder.toString ()Ljava/lang/String;
                    ARETURN
  end public String toString()

end public class org.springframework.beans.factory.config.TypedStringValue
 -- (NullPointerException) null
null
java.lang.NullPointerException
	at org.aspectj.weaver.UnresolvedType.forSignature(UnresolvedType.java:384)
	at org.aspectj.weaver.bcel.BcelObjectType.getDeclaredInterfaces(BcelObjectType.java:275)
	at org.aspectj.weaver.ReferenceType.getDeclaredInterfaces(ReferenceType.java:626)
	at org.aspectj.weaver.ResolvedType.getDirectSupertypes(ResolvedType.java:82)
	at org.aspectj.weaver.patterns.TypePattern.matchesSubtypes(TypePattern.java:178)
	at org.aspectj.weaver.patterns.ExactTypePattern.matchesSubtypes(ExactTypePattern.java:74)
	at org.aspectj.weaver.patterns.TypePattern.matchesStatically(TypePattern.java:130)
	at org.aspectj.weaver.patterns.OrTypePattern.matchesStatically(OrTypePattern.java:76)
	at org.aspectj.weaver.patterns.SignaturePattern.matchesExactlyMethod(SignaturePattern.java:505)
	at org.aspectj.weaver.patterns.SignaturePattern.matchesExactly(SignaturePattern.java:360)
	at org.aspectj.weaver.patterns.SignaturePattern.matches(SignaturePattern.java:320)
	at org.aspectj.weaver.patterns.KindedPointcut.matchInternal(KindedPointcut.java:202)
	at org.aspectj.weaver.patterns.Pointcut.match(Pointcut.java:137)
	at org.aspectj.weaver.patterns.AndPointcut.matchInternal(AndPointcut.java:51)
	at org.aspectj.weaver.patterns.Pointcut.match(Pointcut.java:137)
	at org.aspectj.weaver.patterns.OrPointcut.matchInternal(OrPointcut.java:54)
	at org.aspectj.weaver.patterns.Pointcut.match(Pointcut.java:137)
	at org.aspectj.weaver.ShadowMunger.match(ShadowMunger.java:113)
	at org.aspectj.weaver.Advice.match(Advice.java:109)
	at org.aspectj.weaver.bcel.BcelAdvice.match(BcelAdvice.java:149)
	at org.aspectj.weaver.bcel.BcelClassWeaver.match(BcelClassWeaver.java:3173)
	at org.aspectj.weaver.bcel.BcelClassWeaver.match(BcelClassWeaver.java:2565)
	at org.aspectj.weaver.bcel.BcelClassWeaver.weave(BcelClassWeaver.java:480)
	at org.aspectj.weaver.bcel.BcelClassWeaver.weave(BcelClassWeaver.java:99)
	at org.aspectj.weaver.bcel.BcelWeaver.weave(BcelWeaver.java:1694)
	at org.aspectj.weaver.bcel.BcelWeaver.weaveWithoutDump(BcelWeaver.java:1638)
	at org.aspectj.weaver.bcel.BcelWeaver.weaveAndNotify(BcelWeaver.java:1401)
	at org.aspectj.weaver.bcel.BcelWeaver.weave(BcelWeaver.java:1187)
	at org.aspectj.weaver.tools.WeavingAdaptor.getWovenBytes(WeavingAdaptor.java:472)
	at org.aspectj.weaver.tools.WeavingAdaptor.weaveClass(WeavingAdaptor.java:323)
	at org.aspectj.weaver.loadtime.Aj.preProcess(Aj.java:99)
	at org.aspectj.weaver.loadtime.ClassPreProcessorAgentAdapter.transform(ClassPreProcessorAgentAdapter.java:54)
	at org.springframework.context.weaving.AspectJWeavingEnabler$AspectJClassBypassingClassFileTransformer.transform(AspectJWeavingEnabler.java:108)
	at org.springframework.instrument.classloading.InstrumentationLoadTimeWeaver$FilteringClassFileTransformer.transform(InstrumentationLoadTimeWeaver.java:184)
	at sun.instrument.TransformerManager.transform(Unknown Source)
	at sun.instrument.InstrumentationImpl.transform(Unknown Source)
	at java.lang.ClassLoader.defineClass1(Native Method)
	at java.lang.ClassLoader.defineClass(Unknown Source)
	at java.security.SecureClassLoader.defineClass(Unknown Source)
	at java.net.URLClassLoader.defineClass(Unknown Source)
	at java.net.URLClassLoader.access$100(Unknown Source)
	at java.net.URLClassLoader$1.run(Unknown Source)
	at java.net.URLClassLoader$1.run(Unknown Source)
	at java.security.AccessController.doPrivileged(Native Method)
	at java.net.URLClassLoader.findClass(Unknown Source)
	at java.lang.ClassLoader.loadClass(Unknown Source)
	at sun.misc.Launcher$AppClassLoader.loadClass(Unknown Source)
	at java.lang.ClassLoader.loadClass(Unknown Source)
	at org.springframework.beans.factory.support.AbstractAutowireCapableBeanFactory.applyPropertyValues(AbstractAutowireCapableBeanFactory.java:1492)
	at org.springframework.beans.factory.support.AbstractAutowireCapableBeanFactory.populateBean(AbstractAutowireCapableBeanFactory.java:1222)
	at org.springframework.beans.factory.support.AbstractAutowireCapableBeanFactory.doCreateBean(AbstractAutowireCapableBeanFactory.java:537)
	at org.springframework.beans.factory.support.AbstractAutowireCapableBeanFactory.createBean(AbstractAutowireCapableBeanFactory.java:476)
	at org.springframework.beans.factory.support.AbstractBeanFactory$1.getObject(AbstractBeanFactory.java:303)
	at org.springframework.beans.factory.support.DefaultSingletonBeanRegistry.getSingleton(DefaultSingletonBeanRegistry.java:230)
	at org.springframework.beans.factory.support.AbstractBeanFactory.doGetBean(AbstractBeanFactory.java:299)
	at org.springframework.beans.factory.support.AbstractBeanFactory.getBean(AbstractBeanFactory.java:194)
	at org.springframework.beans.factory.support.DefaultListableBeanFactory.findAutowireCandidates(DefaultListableBeanFactory.java:1120)
	at org.springframework.beans.factory.support.DefaultListableBeanFactory.doResolveDependency(DefaultListableBeanFactory.java:996)
	at org.springframework.beans.factory.support.DefaultListableBeanFactory.resolveDependency(DefaultListableBeanFactory.java:942)
	at org.springframework.beans.factory.annotation.AutowiredAnnotationBeanPostProcessor$AutowiredFieldElement.inject(AutowiredAnnotationBeanPostProcessor.java:533)
	at org.springframework.beans.factory.annotation.InjectionMetadata.inject(InjectionMetadata.java:88)
	at org.springframework.beans.factory.annotation.AutowiredAnnotationBeanPostProcessor.postProcessPropertyValues(AutowiredAnnotationBeanPostProcessor.java:331)
	at org.springframework.beans.factory.support.AbstractAutowireCapableBeanFactory.populateBean(AbstractAutowireCapableBeanFactory.java:1210)
	at org.springframework.beans.factory.support.AbstractAutowireCapableBeanFactory.doCreateBean(AbstractAutowireCapableBeanFactory.java:537)
	at org.springframework.beans.factory.support.AbstractAutowireCapableBeanFactory.createBean(AbstractAutowireCapableBeanFactory.java:476)
	at org.springframework.beans.factory.support.AbstractBeanFactory$1.getObject(AbstractBeanFactory.java:303)
	at org.springframework.beans.factory.support.DefaultSingletonBeanRegistry.getSingleton(DefaultSingletonBeanRegistry.java:230)
	at org.springframework.beans.factory.support.AbstractBeanFactory.doGetBean(AbstractBeanFactory.java:299)
	at org.springframework.beans.factory.support.AbstractBeanFactory.getBean(AbstractBeanFactory.java:194)
	at org.springframework.beans.factory.support.DefaultListableBeanFactory.preInstantiateSingletons(DefaultListableBeanFactory.java:755)
	at org.springframework.context.support.AbstractApplicationContext.finishBeanFactoryInitialization(AbstractApplicationContext.java:757)
	at org.springframework.context.support.AbstractApplicationContext.refresh(AbstractApplicationContext.java:480)
	at org.springframework.context.support.ClassPathXmlApplicationContext.<init>(ClassPathXmlApplicationContext.java:139)
	at org.springframework.context.support.ClassPathXmlApplicationContext.<init>(ClassPathXmlApplicationContext.java:93)
	at com.springExemple.presentation.Presentation2.main(Presentation2.java:13)

error can't determine annotations of missing type org.springframework.transaction.annotation.Transactional
when weaving type org.springframework.beans.BeanWrapperImpl$PropertyTokenHolder
when weaving classes 
when weaving 
 [Xlint:cantFindType]
