---- AspectJ Properties ---
AspectJ Compiler 1.6.12 built on Tuesday Oct 18, 2011 at 17:52:06 GMT
---- Dump Properties ---
Dump file: ajcore.20170412.103728.915.txt
Dump reason: abort
Dump on exception: true
Dump at exit condition: abort
---- System Properties ---
java.runtime.name=Java(TM) SE Runtime Environment
sun.boot.library.path=C:\Program Files\Java\jre1.8.0_121\bin
java.vm.version=25.121-b13
java.vm.vendor=Oracle Corporation
java.vendor.url=http://java.oracle.com/
path.separator=;
java.vm.name=Java HotSpot(TM) 64-Bit Server VM
file.encoding.pkg=sun.io
user.country=FR
user.script=
sun.java.launcher=SUN_STANDARD
sun.os.patch.level=
java.vm.specification.name=Java Virtual Machine Specification
user.dir=C:\Users\formation\git\projects\SpringExpl
java.runtime.version=1.8.0_121-b13
java.awt.graphicsenv=sun.awt.Win32GraphicsEnvironment
java.endorsed.dirs=C:\Program Files\Java\jre1.8.0_121\lib\endorsed
os.arch=amd64
java.io.tmpdir=C:\Users\FORMAT~1\AppData\Local\Temp\
line.separator=

java.vm.specification.vendor=Oracle Corporation
user.variant=
os.name=Windows 10
sun.jnu.encoding=Cp1252
java.library.path=C:\Program Files\Java\jre1.8.0_121\bin;C:\windows\Sun\Java\bin;C:\windows\system32;C:\windows;C:/Program Files/Java/jre1.8.0_121/bin/server;C:/Program Files/Java/jre1.8.0_121/bin;C:/Program Files/Java/jre1.8.0_121/lib/amd64;C:\ProgramData\Oracle\Java\javapath;C:\windows\system32;C:\windows;C:\windows\System32\Wbem;C:\windows\System32\WindowsPowerShell\v1.0\;C:\Program Files\Java\jdk1.8.0_101\bin;C:\Outils\apache-maven-3.3.9\bin;C:\Users\formation\AppData\Local\Microsoft\WindowsApps;;C:\Users\formation\Desktop\JRE JDK ECLIPSE\sts-bundle\sts-3.8.3.RELEASE;;.
java.specification.name=Java Platform API Specification
java.class.version=52.0
sun.management.compiler=HotSpot 64-Bit Tiered Compilers
os.version=10.0
user.home=C:\Users\formation
user.timezone=Europe/Paris
java.awt.printerjob=sun.awt.windows.WPrinterJob
file.encoding=UTF-8
java.specification.version=1.8
java.class.path=C:\Users\formation\git\projects\SpringExpl\target\classes;C:\Users\formation\.m2\repository\org\springframework\spring-aspects\4.1.4.RELEASE\spring-aspects-4.1.4.RELEASE.jar;C:\Users\formation\.m2\repository\org\aspectj\aspectjrt\1.6.12\aspectjrt-1.6.12.jar;C:\Users\formation\.m2\repository\org\aspectj\aspectjweaver\1.6.12\aspectjweaver-1.6.12.jar;C:\Users\formation\.m2\repository\org\springframework\spring-core\4.1.6.RELEASE\spring-core-4.1.6.RELEASE.jar;C:\Users\formation\.m2\repository\commons-logging\commons-logging\1.2\commons-logging-1.2.jar;C:\Users\formation\.m2\repository\org\springframework\spring-context\4.1.6.RELEASE\spring-context-4.1.6.RELEASE.jar;C:\Users\formation\.m2\repository\org\springframework\spring-aop\4.1.6.RELEASE\spring-aop-4.1.6.RELEASE.jar;C:\Users\formation\.m2\repository\aopalliance\aopalliance\1.0\aopalliance-1.0.jar;C:\Users\formation\.m2\repository\org\springframework\spring-beans\4.1.6.RELEASE\spring-beans-4.1.6.RELEASE.jar;C:\Users\formation\.m2\repository\org\springframework\spring-expression\4.1.6.RELEASE\spring-expression-4.1.6.RELEASE.jar;C:\Users\formation\Desktop\spring-agent-2.5.6.jar
user.name=formation
java.vm.specification.version=1.8
sun.java.command=com.springExemple.presentation.Presentation2
java.home=C:\Program Files\Java\jre1.8.0_121
sun.arch.data.model=64
user.language=fr
java.specification.vendor=Oracle Corporation
awt.toolkit=sun.awt.windows.WToolkit
java.vm.info=mixed mode
java.version=1.8.0_121
java.ext.dirs=C:\Program Files\Java\jre1.8.0_121\lib\ext;C:\windows\Sun\Java\lib\ext
sun.boot.class.path=C:\Program Files\Java\jre1.8.0_121\lib\resources.jar;C:\Program Files\Java\jre1.8.0_121\lib\rt.jar;C:\Program Files\Java\jre1.8.0_121\lib\sunrsasign.jar;C:\Program Files\Java\jre1.8.0_121\lib\jsse.jar;C:\Program Files\Java\jre1.8.0_121\lib\jce.jar;C:\Program Files\Java\jre1.8.0_121\lib\charsets.jar;C:\Program Files\Java\jre1.8.0_121\lib\jfr.jar;C:\Program Files\Java\jre1.8.0_121\classes
java.vendor=Oracle Corporation
file.separator=\
java.vendor.url.bug=http://bugreport.sun.com/bugreport/
sun.io.unicode.encoding=UnicodeLittle
sun.cpu.endian=little
sun.desktop=windows
sun.cpu.isalist=amd64
---- Command Line ---
Empty
---- Full Classpath ---
Empty
---- Compiler Messages ---
info AspectJ Weaver Version 1.6.12 built on Tuesday Oct 18, 2011 at 17:52:06 GMT
info register classloader sun.misc.Launcher$AppClassLoader@18b4aac2
info using configuration file:/C:/Users/formation/.m2/repository/org/springframework/spring-aspects/4.1.4.RELEASE/spring-aspects-4.1.4.RELEASE.jar!/META-INF/aop.xml
error can't determine annotations of missing type org.springframework.transaction.annotation.Transactional
when weaving type org.springframework.beans.ExtendedBeanInfo
when weaving classes 
when weaving 
 [Xlint:cantFindType]
abort trouble in: 
 class org.springframework.beans.ExtendedBeanInfo extends java.lang.Object implements java.beans.BeanInfo:
  private static final org.apache.commons.logging.Log logger
  private final java.beans.BeanInfo delegate
  private final java.util.Set propertyDescriptors [Signature(Ljava/util/Set<Ljava/beans/PropertyDescriptor;>;)]
  public void <init>(java.beans.BeanInfo) throws java.beans.IntrospectionException:
                    ALOAD_0     // Lorg/springframework/beans/ExtendedBeanInfo; this   (line 98)
                    INVOKESPECIAL java.lang.Object.<init> ()V
    constructor-execution(void org.springframework.beans.ExtendedBeanInfo.<init>(java.beans.BeanInfo))
    |               ALOAD_0     // Lorg/springframework/beans/ExtendedBeanInfo; this   (line 82)
    |               NEW java.util.TreeSet
    |               DUP
    |               NEW org.springframework.beans.ExtendedBeanInfo$PropertyDescriptorComparator
    |               DUP
    |               INVOKESPECIAL org.springframework.beans.ExtendedBeanInfo$PropertyDescriptorComparator.<init> ()V
    |               INVOKESPECIAL java.util.TreeSet.<init> (Ljava/util/Comparator;)V
    |               PUTFIELD org.springframework.beans.ExtendedBeanInfo.propertyDescriptors Ljava/util/Set;
    |               ALOAD_0     // Lorg/springframework/beans/ExtendedBeanInfo; this   (line 99)
    |               ALOAD_1     // Ljava/beans/BeanInfo; delegate
    |               PUTFIELD org.springframework.beans.ExtendedBeanInfo.delegate Ljava/beans/BeanInfo;
    |               ALOAD_1     // Ljava/beans/BeanInfo; delegate   (line 100)
    |               INVOKEINTERFACE java.beans.BeanInfo.getPropertyDescriptors ()[Ljava/beans/PropertyDescriptor;
    |               ASTORE_2
    |               ALOAD_2
    |               ARRAYLENGTH
    |               ISTORE_3
    |               ICONST_0
    |               ISTORE 4
    |           L0: ILOAD 4
    |               ILOAD_3
    |               IF_ICMPGE L4
    |               ALOAD_2
    |               ILOAD 4
    |               AALOAD
    |               ASTORE 5
    | catch java.beans.IntrospectionException -> E0
    | |             ALOAD_0     // Lorg/springframework/beans/ExtendedBeanInfo; this   (line 102)
    | |             GETFIELD org.springframework.beans.ExtendedBeanInfo.propertyDescriptors Ljava/util/Set;
    | |             ALOAD 5     // Ljava/beans/PropertyDescriptor; pd
    | |             INSTANCEOF java.beans.IndexedPropertyDescriptor
    | |             IFEQ L1
    | |             NEW org.springframework.beans.ExtendedBeanInfo$SimpleIndexedPropertyDescriptor
    | |             DUP
    | |             ALOAD 5     // Ljava/beans/PropertyDescriptor; pd
    | |             CHECKCAST java.beans.IndexedPropertyDescriptor
    | |             INVOKESPECIAL org.springframework.beans.ExtendedBeanInfo$SimpleIndexedPropertyDescriptor.<init> (Ljava/beans/IndexedPropertyDescriptor;)V
    | |             GOTO L2
    | |         L1: NEW org.springframework.beans.ExtendedBeanInfo$SimplePropertyDescriptor
    | |             DUP
    | |             ALOAD 5     // Ljava/beans/PropertyDescriptor; pd
    | |             INVOKESPECIAL org.springframework.beans.ExtendedBeanInfo$SimplePropertyDescriptor.<init> (Ljava/beans/PropertyDescriptor;)V
    | |         L2: INVOKEINTERFACE java.util.Set.add (Ljava/lang/Object;)Z
    | |             POP
    | catch java.beans.IntrospectionException -> E0
    |               GOTO L3   (line 111)
    |           E0: ASTORE 6   (line 106)
    |               GETSTATIC org.springframework.beans.ExtendedBeanInfo.logger Lorg/apache/commons/logging/Log;   (line 108)
    |               INVOKEINTERFACE org.apache.commons.logging.Log.isDebugEnabled ()Z
    |               IFEQ L3
    |               GETSTATIC org.springframework.beans.ExtendedBeanInfo.logger Lorg/apache/commons/logging/Log;   (line 109)
    |               NEW java.lang.StringBuilder
    |               DUP
    |               INVOKESPECIAL java.lang.StringBuilder.<init> ()V
    |               LDC "Ignoring invalid bean property '"
    |               INVOKEVIRTUAL java.lang.StringBuilder.append (Ljava/lang/String;)Ljava/lang/StringBuilder;
    |               ALOAD 5     // Ljava/beans/PropertyDescriptor; pd
    |               INVOKEVIRTUAL java.beans.PropertyDescriptor.getName ()Ljava/lang/String;
    |               INVOKEVIRTUAL java.lang.StringBuilder.append (Ljava/lang/String;)Ljava/lang/StringBuilder;
    |               LDC "': "
    |               INVOKEVIRTUAL java.lang.StringBuilder.append (Ljava/lang/String;)Ljava/lang/StringBuilder;
    |               ALOAD 6     // Ljava/beans/IntrospectionException; ex
    |               INVOKEVIRTUAL java.beans.IntrospectionException.getMessage ()Ljava/lang/String;
    |               INVOKEVIRTUAL java.lang.StringBuilder.append (Ljava/lang/String;)Ljava/lang/StringBuilder;
    |               INVOKEVIRTUAL java.lang.StringBuilder.toString ()Ljava/lang/String;
    |               INVOKEINTERFACE org.apache.commons.logging.Log.debug (Ljava/lang/Object;)V
    |           L3: IINC 4 1   (line 100)
    |               GOTO L0
    |           L4: ALOAD_1     // Ljava/beans/BeanInfo; delegate   (line 113)
    |               INVOKEINTERFACE java.beans.BeanInfo.getMethodDescriptors ()[Ljava/beans/MethodDescriptor;
    |               ASTORE_2
    |               ALOAD_2     // [Ljava/beans/MethodDescriptor; methodDescriptors   (line 114)
    |               IFNULL L7
    |               ALOAD_0     // Lorg/springframework/beans/ExtendedBeanInfo; this   (line 115)
    |               ALOAD_2     // [Ljava/beans/MethodDescriptor; methodDescriptors
    |               INVOKESPECIAL org.springframework.beans.ExtendedBeanInfo.findCandidateWriteMethods ([Ljava/beans/MethodDescriptor;)Ljava/util/List;
    |               INVOKEINTERFACE java.util.List.iterator ()Ljava/util/Iterator;
    |               ASTORE_3
    |           L5: ALOAD_3
    |               INVOKEINTERFACE java.util.Iterator.hasNext ()Z
    |               IFEQ L7
    |               ALOAD_3
    |               INVOKEINTERFACE java.util.Iterator.next ()Ljava/lang/Object;
    |               CHECKCAST java.lang.reflect.Method
    |               ASTORE 4
    | catch java.beans.IntrospectionException -> E1
    | |             ALOAD_0     // Lorg/springframework/beans/ExtendedBeanInfo; this   (line 117)
    | |             ALOAD 4     // Ljava/lang/reflect/Method; method
    | |             INVOKESPECIAL org.springframework.beans.ExtendedBeanInfo.handleCandidateWriteMethod (Ljava/lang/reflect/Method;)V
    | catch java.beans.IntrospectionException -> E1
    |               GOTO L6   (line 124)
    |           E1: ASTORE 5   (line 119)
    |               GETSTATIC org.springframework.beans.ExtendedBeanInfo.logger Lorg/apache/commons/logging/Log;   (line 121)
    |               INVOKEINTERFACE org.apache.commons.logging.Log.isDebugEnabled ()Z
    |               IFEQ L6
    |               GETSTATIC org.springframework.beans.ExtendedBeanInfo.logger Lorg/apache/commons/logging/Log;   (line 122)
    |               NEW java.lang.StringBuilder
    |               DUP
    |               INVOKESPECIAL java.lang.StringBuilder.<init> ()V
    |               LDC "Ignoring candidate write method ["
    |               INVOKEVIRTUAL java.lang.StringBuilder.append (Ljava/lang/String;)Ljava/lang/StringBuilder;
    |               ALOAD 4     // Ljava/lang/reflect/Method; method
    |               INVOKEVIRTUAL java.lang.StringBuilder.append (Ljava/lang/Object;)Ljava/lang/StringBuilder;
    |               LDC "]: "
    |               INVOKEVIRTUAL java.lang.StringBuilder.append (Ljava/lang/String;)Ljava/lang/StringBuilder;
    |               ALOAD 5     // Ljava/beans/IntrospectionException; ex
    |               INVOKEVIRTUAL java.beans.IntrospectionException.getMessage ()Ljava/lang/String;
    |               INVOKEVIRTUAL java.lang.StringBuilder.append (Ljava/lang/String;)Ljava/lang/StringBuilder;
    |               INVOKEVIRTUAL java.lang.StringBuilder.toString ()Ljava/lang/String;
    |               INVOKEINTERFACE org.apache.commons.logging.Log.debug (Ljava/lang/Object;)V
    |           L6: GOTO L5   (line 125)
    |           L7: RETURN   (line 127)
    constructor-execution(void org.springframework.beans.ExtendedBeanInfo.<init>(java.beans.BeanInfo))
  end public void <init>(java.beans.BeanInfo) throws java.beans.IntrospectionException

  private java.util.List findCandidateWriteMethods(java.beans.MethodDescriptor[]):
                    NEW java.util.ArrayList   (line 131)
                    DUP
                    INVOKESPECIAL java.util.ArrayList.<init> ()V
                    ASTORE_2
                    ALOAD_1     // [Ljava/beans/MethodDescriptor; methodDescriptors   (line 132)
                    ASTORE_3
                    ALOAD_3
                    ARRAYLENGTH
                    ISTORE 4
                    ICONST_0
                    ISTORE 5
                L0: ILOAD 5
                    ILOAD 4
                    IF_ICMPGE L2
                    ALOAD_3
                    ILOAD 5
                    AALOAD
                    ASTORE 6
                    ALOAD 6     // Ljava/beans/MethodDescriptor; methodDescriptor   (line 133)
                    INVOKEVIRTUAL java.beans.MethodDescriptor.getMethod ()Ljava/lang/reflect/Method;
                    ASTORE 7
                    ALOAD 7     // Ljava/lang/reflect/Method; method   (line 134)
                    INVOKESTATIC org.springframework.beans.ExtendedBeanInfo.isCandidateWriteMethod (Ljava/lang/reflect/Method;)Z
                    IFEQ L1
                    ALOAD_2     // Ljava/util/List; matches   (line 135)
                    ALOAD 7     // Ljava/lang/reflect/Method; method
                    INVOKEINTERFACE java.util.List.add (Ljava/lang/Object;)Z
                    POP
                L1: IINC 5 1   (line 132)
                    GOTO L0
                L2: ALOAD_2     // Ljava/util/List; matches   (line 141)
                    NEW org.springframework.beans.ExtendedBeanInfo$1
                    DUP
                    ALOAD_0     // Lorg/springframework/beans/ExtendedBeanInfo; this
                    INVOKESPECIAL org.springframework.beans.ExtendedBeanInfo$1.<init> (Lorg/springframework/beans/ExtendedBeanInfo;)V
                    INVOKESTATIC java.util.Collections.sort (Ljava/util/List;Ljava/util/Comparator;)V
                    ALOAD_2     // Ljava/util/List; matches   (line 147)
                    ARETURN
  end private java.util.List findCandidateWriteMethods(java.beans.MethodDescriptor[])

  public static boolean isCandidateWriteMethod(java.lang.reflect.Method):
                    ALOAD_0     // Ljava/lang/reflect/Method; method   (line 151)
                    INVOKEVIRTUAL java.lang.reflect.Method.getName ()Ljava/lang/String;
                    ASTORE_1
                    ALOAD_0     // Ljava/lang/reflect/Method; method   (line 152)
                    INVOKEVIRTUAL java.lang.reflect.Method.getParameterTypes ()[Ljava/lang/Class;
                    ASTORE_2
                    ALOAD_2     // [Ljava/lang/Class; parameterTypes   (line 153)
                    ARRAYLENGTH
                    ISTORE_3
                    ALOAD_1     // Ljava/lang/String; methodName   (line 154)
                    INVOKEVIRTUAL java.lang.String.length ()I
                    ICONST_3
                    IF_ICMPLE L2
                    ALOAD_1     // Ljava/lang/String; methodName
                    LDC "set"
                    INVOKEVIRTUAL java.lang.String.startsWith (Ljava/lang/String;)Z
                    IFEQ L2
                    ALOAD_0     // Ljava/lang/reflect/Method; method
                    INVOKEVIRTUAL java.lang.reflect.Method.getModifiers ()I
                    INVOKESTATIC java.lang.reflect.Modifier.isPublic (I)Z
                    IFEQ L2
                    GETSTATIC java.lang.Void.TYPE Ljava/lang/Class;
                    ALOAD_0     // Ljava/lang/reflect/Method; method
                    INVOKEVIRTUAL java.lang.reflect.Method.getReturnType ()Ljava/lang/Class;   (line 155)
                    INVOKEVIRTUAL java.lang.Class.isAssignableFrom (Ljava/lang/Class;)Z
                    IFEQ L0
                    ALOAD_0     // Ljava/lang/reflect/Method; method
                    INVOKEVIRTUAL java.lang.reflect.Method.getModifiers ()I
                    INVOKESTATIC java.lang.reflect.Modifier.isStatic (I)Z
                    IFEQ L2
                L0: ILOAD_3     // I nParams
                    ICONST_1
                    IF_ICMPEQ L1
                    ILOAD_3     // I nParams
                    ICONST_2
                    IF_ICMPNE L2
                    ALOAD_2     // [Ljava/lang/Class; parameterTypes
                    ICONST_0
                    AALOAD
                    GETSTATIC java.lang.Integer.TYPE Ljava/lang/Class;
                    INVOKEVIRTUAL java.lang.Object.equals (Ljava/lang/Object;)Z   (line 156)
                    IFEQ L2
                L1: ICONST_1
                    GOTO L3
                L2: ICONST_0
                L3: IRETURN
  end public static boolean isCandidateWriteMethod(java.lang.reflect.Method)

  private void handleCandidateWriteMethod(java.lang.reflect.Method) throws java.beans.IntrospectionException:
                    ALOAD_1     // Ljava/lang/reflect/Method; method   (line 160)
                    INVOKEVIRTUAL java.lang.reflect.Method.getParameterTypes ()[Ljava/lang/Class;
                    ARRAYLENGTH
                    ISTORE_2
                    ALOAD_0     // Lorg/springframework/beans/ExtendedBeanInfo; this   (line 161)
                    ALOAD_1     // Ljava/lang/reflect/Method; method
                    INVOKESPECIAL org.springframework.beans.ExtendedBeanInfo.propertyNameFor (Ljava/lang/reflect/Method;)Ljava/lang/String;
                    ASTORE_3
                    ALOAD_1     // Ljava/lang/reflect/Method; method   (line 162)
                    INVOKEVIRTUAL java.lang.reflect.Method.getParameterTypes ()[Ljava/lang/Class;
                    ILOAD_2     // I nParams
                    ICONST_1
                    ISUB
                    AALOAD
                    ASTORE 4
                    ALOAD_0     // Lorg/springframework/beans/ExtendedBeanInfo; this   (line 163)
                    ALOAD_3     // Ljava/lang/String; propertyName
                    ALOAD 4     // Ljava/lang/Class; propertyType
                    INVOKESPECIAL org.springframework.beans.ExtendedBeanInfo.findExistingPropertyDescriptor (Ljava/lang/String;Ljava/lang/Class;)Ljava/beans/PropertyDescriptor;
                    ASTORE 5
                    ILOAD_2     // I nParams   (line 164)
                    ICONST_1
                    IF_ICMPNE L1
                    ALOAD 5     // Ljava/beans/PropertyDescriptor; existingPd   (line 165)
                    IFNONNULL L0
                    ALOAD_0     // Lorg/springframework/beans/ExtendedBeanInfo; this   (line 166)
                    GETFIELD org.springframework.beans.ExtendedBeanInfo.propertyDescriptors Ljava/util/Set;
                    NEW org.springframework.beans.ExtendedBeanInfo$SimplePropertyDescriptor
                    DUP
                    ALOAD_3     // Ljava/lang/String; propertyName
                    ACONST_NULL
                    ALOAD_1     // Ljava/lang/reflect/Method; method
                    INVOKESPECIAL org.springframework.beans.ExtendedBeanInfo$SimplePropertyDescriptor.<init> (Ljava/lang/String;Ljava/lang/reflect/Method;Ljava/lang/reflect/Method;)V
                    INVOKEINTERFACE java.util.Set.add (Ljava/lang/Object;)Z
                    POP
                    GOTO L5
                L0: ALOAD 5     // Ljava/beans/PropertyDescriptor; existingPd   (line 169)
                    ALOAD_1     // Ljava/lang/reflect/Method; method
                    INVOKEVIRTUAL java.beans.PropertyDescriptor.setWriteMethod (Ljava/lang/reflect/Method;)V
                    GOTO L5
                L1: ILOAD_2     // I nParams   (line 172)
                    ICONST_2
                    IF_ICMPNE L4
                    ALOAD 5     // Ljava/beans/PropertyDescriptor; existingPd   (line 173)
                    IFNONNULL L2
                    ALOAD_0     // Lorg/springframework/beans/ExtendedBeanInfo; this   (line 174)
                    GETFIELD org.springframework.beans.ExtendedBeanInfo.propertyDescriptors Ljava/util/Set;
                    NEW org.springframework.beans.ExtendedBeanInfo$SimpleIndexedPropertyDescriptor
                    DUP
                    ALOAD_3     // Ljava/lang/String; propertyName
                    ACONST_NULL
                    ACONST_NULL
                    ACONST_NULL
                    ALOAD_1     // Ljava/lang/reflect/Method; method
                    INVOKESPECIAL org.springframework.beans.ExtendedBeanInfo$SimpleIndexedPropertyDescriptor.<init> (Ljava/lang/String;Ljava/lang/reflect/Method;Ljava/lang/reflect/Method;Ljava/lang/reflect/Method;Ljava/lang/reflect/Method;)V
                    INVOKEINTERFACE java.util.Set.add (Ljava/lang/Object;)Z
                    POP
                    GOTO L5
                L2: ALOAD 5     // Ljava/beans/PropertyDescriptor; existingPd   (line 177)
                    INSTANCEOF java.beans.IndexedPropertyDescriptor
                    IFEQ L3
                    ALOAD 5     // Ljava/beans/PropertyDescriptor; existingPd   (line 178)
                    CHECKCAST java.beans.IndexedPropertyDescriptor
                    ALOAD_1     // Ljava/lang/reflect/Method; method
                    INVOKEVIRTUAL java.beans.IndexedPropertyDescriptor.setIndexedWriteMethod (Ljava/lang/reflect/Method;)V
                    GOTO L5
                L3: ALOAD_0     // Lorg/springframework/beans/ExtendedBeanInfo; this   (line 181)
                    GETFIELD org.springframework.beans.ExtendedBeanInfo.propertyDescriptors Ljava/util/Set;
                    ALOAD 5     // Ljava/beans/PropertyDescriptor; existingPd
                    INVOKEINTERFACE java.util.Set.remove (Ljava/lang/Object;)Z
                    POP
                    ALOAD_0     // Lorg/springframework/beans/ExtendedBeanInfo; this   (line 182)
                    GETFIELD org.springframework.beans.ExtendedBeanInfo.propertyDescriptors Ljava/util/Set;
                    NEW org.springframework.beans.ExtendedBeanInfo$SimpleIndexedPropertyDescriptor
                    DUP
                    ALOAD_3     // Ljava/lang/String; propertyName
                    ALOAD 5     // Ljava/beans/PropertyDescriptor; existingPd
                    INVOKEVIRTUAL java.beans.PropertyDescriptor.getReadMethod ()Ljava/lang/reflect/Method;   (line 183)
                    ALOAD 5     // Ljava/beans/PropertyDescriptor; existingPd
                    INVOKEVIRTUAL java.beans.PropertyDescriptor.getWriteMethod ()Ljava/lang/reflect/Method;
                    ACONST_NULL
                    ALOAD_1     // Ljava/lang/reflect/Method; method
                    INVOKESPECIAL org.springframework.beans.ExtendedBeanInfo$SimpleIndexedPropertyDescriptor.<init> (Ljava/lang/String;Ljava/lang/reflect/Method;Ljava/lang/reflect/Method;Ljava/lang/reflect/Method;Ljava/lang/reflect/Method;)V
                    INVOKEINTERFACE java.util.Set.add (Ljava/lang/Object;)Z   (line 182)
                    POP
                    GOTO L5
                L4: NEW java.lang.IllegalArgumentException   (line 187)
                    DUP
                    NEW java.lang.StringBuilder
                    DUP
                    INVOKESPECIAL java.lang.StringBuilder.<init> ()V
                    LDC "Write method must have exactly 1 or 2 parameters: "
                    INVOKEVIRTUAL java.lang.StringBuilder.append (Ljava/lang/String;)Ljava/lang/StringBuilder;
                    ALOAD_1     // Ljava/lang/reflect/Method; method
                    INVOKEVIRTUAL java.lang.StringBuilder.append (Ljava/lang/Object;)Ljava/lang/StringBuilder;
                    INVOKEVIRTUAL java.lang.StringBuilder.toString ()Ljava/lang/String;
                    INVOKESPECIAL java.lang.IllegalArgumentException.<init> (Ljava/lang/String;)V
                    ATHROW
                L5: RETURN   (line 189)
  end private void handleCandidateWriteMethod(java.lang.reflect.Method) throws java.beans.IntrospectionException

  private java.beans.PropertyDescriptor findExistingPropertyDescriptor(String, Class):
                    ALOAD_0     // Lorg/springframework/beans/ExtendedBeanInfo; this   (line 192)
                    GETFIELD org.springframework.beans.ExtendedBeanInfo.propertyDescriptors Ljava/util/Set;
                    INVOKEINTERFACE java.util.Set.iterator ()Ljava/util/Iterator;
                    ASTORE_3
                L0: ALOAD_3
                    INVOKEINTERFACE java.util.Iterator.hasNext ()Z
                    IFEQ L6
                    ALOAD_3
                    INVOKEINTERFACE java.util.Iterator.next ()Ljava/lang/Object;
                    CHECKCAST java.beans.PropertyDescriptor
                    ASTORE 4
                    ALOAD 4     // Ljava/beans/PropertyDescriptor; pd   (line 194)
                    INVOKEVIRTUAL java.beans.PropertyDescriptor.getName ()Ljava/lang/String;
                    ASTORE 6
                    ALOAD 4     // Ljava/beans/PropertyDescriptor; pd   (line 195)
                    INSTANCEOF java.beans.IndexedPropertyDescriptor
                    IFEQ L3
                    ALOAD 4     // Ljava/beans/PropertyDescriptor; pd   (line 196)
                    CHECKCAST java.beans.IndexedPropertyDescriptor
                    ASTORE 7
                    ALOAD 7     // Ljava/beans/IndexedPropertyDescriptor; ipd   (line 197)
                    INVOKEVIRTUAL java.beans.IndexedPropertyDescriptor.getIndexedPropertyType ()Ljava/lang/Class;
                    ASTORE 5
                    ALOAD 6     // Ljava/lang/String; candidateName   (line 198)
                    ALOAD_1     // Ljava/lang/String; propertyName
                    INVOKEVIRTUAL java.lang.String.equals (Ljava/lang/Object;)Z
                    IFEQ L2
                    ALOAD 5     // Ljava/lang/Class; candidateType
                    ALOAD_2     // Ljava/lang/Class; propertyType
                    INVOKEVIRTUAL java.lang.Object.equals (Ljava/lang/Object;)Z   (line 199)
                    IFNE L1
                    ALOAD 5     // Ljava/lang/Class; candidateType
                    ALOAD_2     // Ljava/lang/Class; propertyType
                    INVOKEVIRTUAL java.lang.Class.getComponentType ()Ljava/lang/Class;
                    INVOKEVIRTUAL java.lang.Object.equals (Ljava/lang/Object;)Z
                    IFEQ L2
                L1: ALOAD 4     // Ljava/beans/PropertyDescriptor; pd   (line 200)
                    ARETURN
                L2: GOTO L5   (line 202)
                L3: ALOAD 4     // Ljava/beans/PropertyDescriptor; pd   (line 204)
                    INVOKEVIRTUAL java.beans.PropertyDescriptor.getPropertyType ()Ljava/lang/Class;
                    ASTORE 5
                    ALOAD 6     // Ljava/lang/String; candidateName   (line 205)
                    ALOAD_1     // Ljava/lang/String; propertyName
                    INVOKEVIRTUAL java.lang.String.equals (Ljava/lang/Object;)Z
                    IFEQ L5
                    ALOAD 5     // Ljava/lang/Class; candidateType
                    ALOAD_2     // Ljava/lang/Class; propertyType
                    INVOKEVIRTUAL java.lang.Object.equals (Ljava/lang/Object;)Z   (line 206)
                    IFNE L4
                    ALOAD_2     // Ljava/lang/Class; propertyType
                    ALOAD 5     // Ljava/lang/Class; candidateType
                    INVOKEVIRTUAL java.lang.Class.getComponentType ()Ljava/lang/Class;
                    INVOKEVIRTUAL java.lang.Object.equals (Ljava/lang/Object;)Z
                    IFEQ L5
                L4: ALOAD 4     // Ljava/beans/PropertyDescriptor; pd   (line 207)
                    ARETURN
                L5: GOTO L0   (line 210)
                L6: ACONST_NULL   (line 211)
                    ARETURN
  end private java.beans.PropertyDescriptor findExistingPropertyDescriptor(String, Class)

  private String propertyNameFor(java.lang.reflect.Method):
                    ALOAD_1     // Ljava/lang/reflect/Method; method   (line 215)
                    INVOKEVIRTUAL java.lang.reflect.Method.getName ()Ljava/lang/String;
                    ICONST_3
                    ALOAD_1     // Ljava/lang/reflect/Method; method
                    INVOKEVIRTUAL java.lang.reflect.Method.getName ()Ljava/lang/String;
                    INVOKEVIRTUAL java.lang.String.length ()I
                    INVOKEVIRTUAL java.lang.String.substring (II)Ljava/lang/String;
                    INVOKESTATIC java.beans.Introspector.decapitalize (Ljava/lang/String;)Ljava/lang/String;
                    ARETURN
  end private String propertyNameFor(java.lang.reflect.Method)

  public java.beans.PropertyDescriptor[] getPropertyDescriptors():
                    ALOAD_0     // Lorg/springframework/beans/ExtendedBeanInfo; this   (line 227)
                    GETFIELD org.springframework.beans.ExtendedBeanInfo.propertyDescriptors Ljava/util/Set;
                    ALOAD_0     // Lorg/springframework/beans/ExtendedBeanInfo; this
                    GETFIELD org.springframework.beans.ExtendedBeanInfo.propertyDescriptors Ljava/util/Set;
                    INVOKEINTERFACE java.util.Set.size ()I
                    ANEWARRAY java.beans.PropertyDescriptor
                    INVOKEINTERFACE java.util.Set.toArray ([Ljava/lang/Object;)[Ljava/lang/Object;
                    CHECKCAST [Ljava.beans.PropertyDescriptor;
                    ARETURN
  end public java.beans.PropertyDescriptor[] getPropertyDescriptors()

  public java.beans.BeanInfo[] getAdditionalBeanInfo():
                    ALOAD_0     // Lorg/springframework/beans/ExtendedBeanInfo; this   (line 232)
                    GETFIELD org.springframework.beans.ExtendedBeanInfo.delegate Ljava/beans/BeanInfo;
                    INVOKEINTERFACE java.beans.BeanInfo.getAdditionalBeanInfo ()[Ljava/beans/BeanInfo;
                    ARETURN
  end public java.beans.BeanInfo[] getAdditionalBeanInfo()

  public java.beans.BeanDescriptor getBeanDescriptor():
                    ALOAD_0     // Lorg/springframework/beans/ExtendedBeanInfo; this   (line 237)
                    GETFIELD org.springframework.beans.ExtendedBeanInfo.delegate Ljava/beans/BeanInfo;
                    INVOKEINTERFACE java.beans.BeanInfo.getBeanDescriptor ()Ljava/beans/BeanDescriptor;
                    ARETURN
  end public java.beans.BeanDescriptor getBeanDescriptor()

  public int getDefaultEventIndex():
                    ALOAD_0     // Lorg/springframework/beans/ExtendedBeanInfo; this   (line 242)
                    GETFIELD org.springframework.beans.ExtendedBeanInfo.delegate Ljava/beans/BeanInfo;
                    INVOKEINTERFACE java.beans.BeanInfo.getDefaultEventIndex ()I
                    IRETURN
  end public int getDefaultEventIndex()

  public int getDefaultPropertyIndex():
                    ALOAD_0     // Lorg/springframework/beans/ExtendedBeanInfo; this   (line 247)
                    GETFIELD org.springframework.beans.ExtendedBeanInfo.delegate Ljava/beans/BeanInfo;
                    INVOKEINTERFACE java.beans.BeanInfo.getDefaultPropertyIndex ()I
                    IRETURN
  end public int getDefaultPropertyIndex()

  public java.beans.EventSetDescriptor[] getEventSetDescriptors():
                    ALOAD_0     // Lorg/springframework/beans/ExtendedBeanInfo; this   (line 252)
                    GETFIELD org.springframework.beans.ExtendedBeanInfo.delegate Ljava/beans/BeanInfo;
                    INVOKEINTERFACE java.beans.BeanInfo.getEventSetDescriptors ()[Ljava/beans/EventSetDescriptor;
                    ARETURN
  end public java.beans.EventSetDescriptor[] getEventSetDescriptors()

  public java.awt.Image getIcon(int):
                    ALOAD_0     // Lorg/springframework/beans/ExtendedBeanInfo; this   (line 257)
                    GETFIELD org.springframework.beans.ExtendedBeanInfo.delegate Ljava/beans/BeanInfo;
                    ILOAD_1     // I iconKind
                    INVOKEINTERFACE java.beans.BeanInfo.getIcon (I)Ljava/awt/Image;
                    ARETURN
  end public java.awt.Image getIcon(int)

  public java.beans.MethodDescriptor[] getMethodDescriptors():
                    ALOAD_0     // Lorg/springframework/beans/ExtendedBeanInfo; this   (line 262)
                    GETFIELD org.springframework.beans.ExtendedBeanInfo.delegate Ljava/beans/BeanInfo;
                    INVOKEINTERFACE java.beans.BeanInfo.getMethodDescriptors ()[Ljava/beans/MethodDescriptor;
                    ARETURN
  end public java.beans.MethodDescriptor[] getMethodDescriptors()

  static void <clinit>():
                    LDC org.springframework.beans.ExtendedBeanInfo   (line 78)
                    INVOKESTATIC org.apache.commons.logging.LogFactory.getLog (Ljava/lang/Class;)Lorg/apache/commons/logging/Log;
                    PUTSTATIC org.springframework.beans.ExtendedBeanInfo.logger Lorg/apache/commons/logging/Log;
                    RETURN
  end static void <clinit>()
end  class org.springframework.beans.ExtendedBeanInfo
 -- (NullPointerException) null
null
java.lang.NullPointerException
	at org.aspectj.weaver.UnresolvedType.forSignature(UnresolvedType.java:384)
	at org.aspectj.weaver.bcel.BcelObjectType.getDeclaredInterfaces(BcelObjectType.java:275)
	at org.aspectj.weaver.ReferenceType.getDeclaredInterfaces(ReferenceType.java:626)
	at org.aspectj.weaver.ResolvedType.getDirectSupertypes(ResolvedType.java:82)
	at org.aspectj.weaver.patterns.TypePattern.matchesSubtypes(TypePattern.java:178)
	at org.aspectj.weaver.patterns.ExactTypePattern.matchesSubtypes(ExactTypePattern.java:74)
	at org.aspectj.weaver.patterns.TypePattern.matchesStatically(TypePattern.java:130)
	at org.aspectj.weaver.patterns.OrTypePattern.matchesStatically(OrTypePattern.java:76)
	at org.aspectj.weaver.patterns.SignaturePattern.matchesExactlyMethod(SignaturePattern.java:505)
	at org.aspectj.weaver.patterns.SignaturePattern.matchesExactly(SignaturePattern.java:360)
	at org.aspectj.weaver.patterns.SignaturePattern.matches(SignaturePattern.java:320)
	at org.aspectj.weaver.patterns.KindedPointcut.matchInternal(KindedPointcut.java:202)
	at org.aspectj.weaver.patterns.Pointcut.match(Pointcut.java:137)
	at org.aspectj.weaver.patterns.AndPointcut.matchInternal(AndPointcut.java:51)
	at org.aspectj.weaver.patterns.Pointcut.match(Pointcut.java:137)
	at org.aspectj.weaver.patterns.OrPointcut.matchInternal(OrPointcut.java:54)
	at org.aspectj.weaver.patterns.Pointcut.match(Pointcut.java:137)
	at org.aspectj.weaver.ShadowMunger.match(ShadowMunger.java:113)
	at org.aspectj.weaver.Advice.match(Advice.java:109)
	at org.aspectj.weaver.bcel.BcelAdvice.match(BcelAdvice.java:149)
	at org.aspectj.weaver.bcel.BcelClassWeaver.match(BcelClassWeaver.java:3173)
	at org.aspectj.weaver.bcel.BcelClassWeaver.match(BcelClassWeaver.java:2565)
	at org.aspectj.weaver.bcel.BcelClassWeaver.weave(BcelClassWeaver.java:480)
	at org.aspectj.weaver.bcel.BcelClassWeaver.weave(BcelClassWeaver.java:99)
	at org.aspectj.weaver.bcel.BcelWeaver.weave(BcelWeaver.java:1694)
	at org.aspectj.weaver.bcel.BcelWeaver.weaveWithoutDump(BcelWeaver.java:1638)
	at org.aspectj.weaver.bcel.BcelWeaver.weaveAndNotify(BcelWeaver.java:1401)
	at org.aspectj.weaver.bcel.BcelWeaver.weave(BcelWeaver.java:1187)
	at org.aspectj.weaver.tools.WeavingAdaptor.getWovenBytes(WeavingAdaptor.java:472)
	at org.aspectj.weaver.tools.WeavingAdaptor.weaveClass(WeavingAdaptor.java:323)
	at org.aspectj.weaver.loadtime.Aj.preProcess(Aj.java:99)
	at org.aspectj.weaver.loadtime.ClassPreProcessorAgentAdapter.transform(ClassPreProcessorAgentAdapter.java:54)
	at org.springframework.context.weaving.AspectJWeavingEnabler$AspectJClassBypassingClassFileTransformer.transform(AspectJWeavingEnabler.java:108)
	at org.springframework.instrument.classloading.InstrumentationLoadTimeWeaver$FilteringClassFileTransformer.transform(InstrumentationLoadTimeWeaver.java:184)
	at sun.instrument.TransformerManager.transform(Unknown Source)
	at sun.instrument.InstrumentationImpl.transform(Unknown Source)
	at java.lang.ClassLoader.defineClass1(Native Method)
	at java.lang.ClassLoader.defineClass(Unknown Source)
	at java.security.SecureClassLoader.defineClass(Unknown Source)
	at java.net.URLClassLoader.defineClass(Unknown Source)
	at java.net.URLClassLoader.access$100(Unknown Source)
	at java.net.URLClassLoader$1.run(Unknown Source)
	at java.net.URLClassLoader$1.run(Unknown Source)
	at java.security.AccessController.doPrivileged(Native Method)
	at java.net.URLClassLoader.findClass(Unknown Source)
	at java.lang.ClassLoader.loadClass(Unknown Source)
	at sun.misc.Launcher$AppClassLoader.loadClass(Unknown Source)
	at java.lang.ClassLoader.loadClass(Unknown Source)
	at org.springframework.beans.ExtendedBeanInfoFactory.supports(ExtendedBeanInfoFactory.java:55)
	at org.springframework.beans.ExtendedBeanInfoFactory.getBeanInfo(ExtendedBeanInfoFactory.java:46)
	at org.springframework.beans.CachedIntrospectionResults.<init>(CachedIntrospectionResults.java:270)
	at org.springframework.beans.CachedIntrospectionResults.forClass(CachedIntrospectionResults.java:189)
	at org.springframework.beans.BeanWrapperImpl.getCachedIntrospectionResults(BeanWrapperImpl.java:328)
	at org.springframework.beans.BeanWrapperImpl.getPropertyDescriptors(BeanWrapperImpl.java:336)
	at org.springframework.beans.factory.support.AbstractAutowireCapableBeanFactory.filterPropertyDescriptorsForDependencyCheck(AbstractAutowireCapableBeanFactory.java:1364)
	at org.springframework.beans.factory.support.AbstractAutowireCapableBeanFactory.filterPropertyDescriptorsForDependencyCheck(AbstractAutowireCapableBeanFactory.java:1343)
	at org.springframework.beans.factory.support.AbstractAutowireCapableBeanFactory.populateBean(AbstractAutowireCapableBeanFactory.java:1205)
	at org.springframework.beans.factory.support.AbstractAutowireCapableBeanFactory.doCreateBean(AbstractAutowireCapableBeanFactory.java:537)
	at org.springframework.beans.factory.support.AbstractAutowireCapableBeanFactory.createBean(AbstractAutowireCapableBeanFactory.java:476)
	at org.springframework.beans.factory.support.AbstractBeanFactory$1.getObject(AbstractBeanFactory.java:303)
	at org.springframework.beans.factory.support.DefaultSingletonBeanRegistry.getSingleton(DefaultSingletonBeanRegistry.java:230)
	at org.springframework.beans.factory.support.AbstractBeanFactory.doGetBean(AbstractBeanFactory.java:299)
	at org.springframework.beans.factory.support.AbstractBeanFactory.getBean(AbstractBeanFactory.java:194)
	at org.springframework.beans.factory.support.DefaultListableBeanFactory.preInstantiateSingletons(DefaultListableBeanFactory.java:755)
	at org.springframework.context.support.AbstractApplicationContext.finishBeanFactoryInitialization(AbstractApplicationContext.java:757)
	at org.springframework.context.support.AbstractApplicationContext.refresh(AbstractApplicationContext.java:480)
	at org.springframework.context.support.ClassPathXmlApplicationContext.<init>(ClassPathXmlApplicationContext.java:139)
	at org.springframework.context.support.ClassPathXmlApplicationContext.<init>(ClassPathXmlApplicationContext.java:93)
	at com.springExemple.presentation.Presentation2.main(Presentation2.java:13)

error can't determine annotations of missing type org.springframework.transaction.annotation.Transactional
when weaving type org.springframework.beans.ExtendedBeanInfo$SimpleIndexedPropertyDescriptor
when weaving classes 
when weaving 
 [Xlint:cantFindType]
abort trouble in: 
 class org.springframework.beans.ExtendedBeanInfo$SimpleIndexedPropertyDescriptor extends java.beans.IndexedPropertyDescriptor:
  private java.lang.reflect.Method readMethod
  private java.lang.reflect.Method writeMethod
  private Class propertyType [Signature(Ljava/lang/Class<*>;)]
  private java.lang.reflect.Method indexedReadMethod
  private java.lang.reflect.Method indexedWriteMethod
  private Class indexedPropertyType [Signature(Ljava/lang/Class<*>;)]
  private Class propertyEditorClass [Signature(Ljava/lang/Class<*>;)]
  public void <init>(java.beans.IndexedPropertyDescriptor) throws java.beans.IntrospectionException:
                    ALOAD_0     // Lorg/springframework/beans/ExtendedBeanInfo$SimpleIndexedPropertyDescriptor; this   (line 367)
                    ALOAD_1     // Ljava/beans/IndexedPropertyDescriptor; original
                    INVOKEVIRTUAL java.beans.IndexedPropertyDescriptor.getName ()Ljava/lang/String;
                    ALOAD_1     // Ljava/beans/IndexedPropertyDescriptor; original
                    INVOKEVIRTUAL java.beans.IndexedPropertyDescriptor.getReadMethod ()Ljava/lang/reflect/Method;
                    ALOAD_1     // Ljava/beans/IndexedPropertyDescriptor; original
                    INVOKEVIRTUAL java.beans.IndexedPropertyDescriptor.getWriteMethod ()Ljava/lang/reflect/Method;
                    ALOAD_1     // Ljava/beans/IndexedPropertyDescriptor; original
                    INVOKEVIRTUAL java.beans.IndexedPropertyDescriptor.getIndexedReadMethod ()Ljava/lang/reflect/Method;   (line 368)
                    ALOAD_1     // Ljava/beans/IndexedPropertyDescriptor; original
                    INVOKEVIRTUAL java.beans.IndexedPropertyDescriptor.getIndexedWriteMethod ()Ljava/lang/reflect/Method;
                    INVOKESPECIAL org.springframework.beans.ExtendedBeanInfo$SimpleIndexedPropertyDescriptor.<init> (Ljava/lang/String;Ljava/lang/reflect/Method;Ljava/lang/reflect/Method;Ljava/lang/reflect/Method;Ljava/lang/reflect/Method;)V   (line 367)
    constructor-execution(void org.springframework.beans.ExtendedBeanInfo$SimpleIndexedPropertyDescriptor.<init>(java.beans.IndexedPropertyDescriptor))
    |               ALOAD_1     // Ljava/beans/IndexedPropertyDescriptor; original   (line 369)
    |               ALOAD_0     // Lorg/springframework/beans/ExtendedBeanInfo$SimpleIndexedPropertyDescriptor; this
    |               INVOKESTATIC org.springframework.beans.PropertyDescriptorUtils.copyNonMethodProperties (Ljava/beans/PropertyDescriptor;Ljava/beans/PropertyDescriptor;)V
    |               RETURN   (line 370)
    constructor-execution(void org.springframework.beans.ExtendedBeanInfo$SimpleIndexedPropertyDescriptor.<init>(java.beans.IndexedPropertyDescriptor))
  end public void <init>(java.beans.IndexedPropertyDescriptor) throws java.beans.IntrospectionException

  public void <init>(String, java.lang.reflect.Method, java.lang.reflect.Method, java.lang.reflect.Method, java.lang.reflect.Method) throws java.beans.IntrospectionException:
                    ALOAD_0     // Lorg/springframework/beans/ExtendedBeanInfo$SimpleIndexedPropertyDescriptor; this   (line 375)
                    ALOAD_1     // Ljava/lang/String; propertyName
                    ACONST_NULL
                    ACONST_NULL
                    ACONST_NULL
                    ACONST_NULL
                    INVOKESPECIAL java.beans.IndexedPropertyDescriptor.<init> (Ljava/lang/String;Ljava/lang/reflect/Method;Ljava/lang/reflect/Method;Ljava/lang/reflect/Method;Ljava/lang/reflect/Method;)V
    constructor-execution(void org.springframework.beans.ExtendedBeanInfo$SimpleIndexedPropertyDescriptor.<init>(java.lang.String, java.lang.reflect.Method, java.lang.reflect.Method, java.lang.reflect.Method, java.lang.reflect.Method))
    |               ALOAD_0     // Lorg/springframework/beans/ExtendedBeanInfo$SimpleIndexedPropertyDescriptor; this   (line 376)
    |               ALOAD_2     // Ljava/lang/reflect/Method; readMethod
    |               PUTFIELD org.springframework.beans.ExtendedBeanInfo$SimpleIndexedPropertyDescriptor.readMethod Ljava/lang/reflect/Method;
    |               ALOAD_0     // Lorg/springframework/beans/ExtendedBeanInfo$SimpleIndexedPropertyDescriptor; this   (line 377)
    |               ALOAD_3     // Ljava/lang/reflect/Method; writeMethod
    |               PUTFIELD org.springframework.beans.ExtendedBeanInfo$SimpleIndexedPropertyDescriptor.writeMethod Ljava/lang/reflect/Method;
    |               ALOAD_0     // Lorg/springframework/beans/ExtendedBeanInfo$SimpleIndexedPropertyDescriptor; this   (line 378)
    |               ALOAD_2     // Ljava/lang/reflect/Method; readMethod
    |               ALOAD_3     // Ljava/lang/reflect/Method; writeMethod
    |               INVOKESTATIC org.springframework.beans.PropertyDescriptorUtils.findPropertyType (Ljava/lang/reflect/Method;Ljava/lang/reflect/Method;)Ljava/lang/Class;
    |               PUTFIELD org.springframework.beans.ExtendedBeanInfo$SimpleIndexedPropertyDescriptor.propertyType Ljava/lang/Class;
    |               ALOAD_0     // Lorg/springframework/beans/ExtendedBeanInfo$SimpleIndexedPropertyDescriptor; this   (line 379)
    |               ALOAD 4     // Ljava/lang/reflect/Method; indexedReadMethod
    |               PUTFIELD org.springframework.beans.ExtendedBeanInfo$SimpleIndexedPropertyDescriptor.indexedReadMethod Ljava/lang/reflect/Method;
    |               ALOAD_0     // Lorg/springframework/beans/ExtendedBeanInfo$SimpleIndexedPropertyDescriptor; this   (line 380)
    |               ALOAD 5     // Ljava/lang/reflect/Method; indexedWriteMethod
    |               PUTFIELD org.springframework.beans.ExtendedBeanInfo$SimpleIndexedPropertyDescriptor.indexedWriteMethod Ljava/lang/reflect/Method;
    |               ALOAD_0     // Lorg/springframework/beans/ExtendedBeanInfo$SimpleIndexedPropertyDescriptor; this   (line 381)
    |               ALOAD_1     // Ljava/lang/String; propertyName
    |               ALOAD_0     // Lorg/springframework/beans/ExtendedBeanInfo$SimpleIndexedPropertyDescriptor; this
    |               GETFIELD org.springframework.beans.ExtendedBeanInfo$SimpleIndexedPropertyDescriptor.propertyType Ljava/lang/Class;
    |               ALOAD 4     // Ljava/lang/reflect/Method; indexedReadMethod
    |               ALOAD 5     // Ljava/lang/reflect/Method; indexedWriteMethod
    |               INVOKESTATIC org.springframework.beans.PropertyDescriptorUtils.findIndexedPropertyType (Ljava/lang/String;Ljava/lang/Class;Ljava/lang/reflect/Method;Ljava/lang/reflect/Method;)Ljava/lang/Class;
    |               PUTFIELD org.springframework.beans.ExtendedBeanInfo$SimpleIndexedPropertyDescriptor.indexedPropertyType Ljava/lang/Class;
    |               RETURN   (line 383)
    constructor-execution(void org.springframework.beans.ExtendedBeanInfo$SimpleIndexedPropertyDescriptor.<init>(java.lang.String, java.lang.reflect.Method, java.lang.reflect.Method, java.lang.reflect.Method, java.lang.reflect.Method))
  end public void <init>(String, java.lang.reflect.Method, java.lang.reflect.Method, java.lang.reflect.Method, java.lang.reflect.Method) throws java.beans.IntrospectionException

  public java.lang.reflect.Method getReadMethod():
                    ALOAD_0     // Lorg/springframework/beans/ExtendedBeanInfo$SimpleIndexedPropertyDescriptor; this   (line 387)
                    GETFIELD org.springframework.beans.ExtendedBeanInfo$SimpleIndexedPropertyDescriptor.readMethod Ljava/lang/reflect/Method;
                    ARETURN
  end public java.lang.reflect.Method getReadMethod()

  public void setReadMethod(java.lang.reflect.Method):
                    ALOAD_0     // Lorg/springframework/beans/ExtendedBeanInfo$SimpleIndexedPropertyDescriptor; this   (line 392)
                    ALOAD_1     // Ljava/lang/reflect/Method; readMethod
                    PUTFIELD org.springframework.beans.ExtendedBeanInfo$SimpleIndexedPropertyDescriptor.readMethod Ljava/lang/reflect/Method;
                    RETURN   (line 393)
  end public void setReadMethod(java.lang.reflect.Method)

  public java.lang.reflect.Method getWriteMethod():
                    ALOAD_0     // Lorg/springframework/beans/ExtendedBeanInfo$SimpleIndexedPropertyDescriptor; this   (line 397)
                    GETFIELD org.springframework.beans.ExtendedBeanInfo$SimpleIndexedPropertyDescriptor.writeMethod Ljava/lang/reflect/Method;
                    ARETURN
  end public java.lang.reflect.Method getWriteMethod()

  public void setWriteMethod(java.lang.reflect.Method):
                    ALOAD_0     // Lorg/springframework/beans/ExtendedBeanInfo$SimpleIndexedPropertyDescriptor; this   (line 402)
                    ALOAD_1     // Ljava/lang/reflect/Method; writeMethod
                    PUTFIELD org.springframework.beans.ExtendedBeanInfo$SimpleIndexedPropertyDescriptor.writeMethod Ljava/lang/reflect/Method;
                    RETURN   (line 403)
  end public void setWriteMethod(java.lang.reflect.Method)

  public Class getPropertyType():
                    ALOAD_0     // Lorg/springframework/beans/ExtendedBeanInfo$SimpleIndexedPropertyDescriptor; this   (line 407)
                    GETFIELD org.springframework.beans.ExtendedBeanInfo$SimpleIndexedPropertyDescriptor.propertyType Ljava/lang/Class;
                    IFNONNULL L0
    catch java.beans.IntrospectionException -> E0
    |               ALOAD_0     // Lorg/springframework/beans/ExtendedBeanInfo$SimpleIndexedPropertyDescriptor; this   (line 409)
    |               ALOAD_0     // Lorg/springframework/beans/ExtendedBeanInfo$SimpleIndexedPropertyDescriptor; this
    |               GETFIELD org.springframework.beans.ExtendedBeanInfo$SimpleIndexedPropertyDescriptor.readMethod Ljava/lang/reflect/Method;
    |               ALOAD_0     // Lorg/springframework/beans/ExtendedBeanInfo$SimpleIndexedPropertyDescriptor; this
    |               GETFIELD org.springframework.beans.ExtendedBeanInfo$SimpleIndexedPropertyDescriptor.writeMethod Ljava/lang/reflect/Method;
    |               INVOKESTATIC org.springframework.beans.PropertyDescriptorUtils.findPropertyType (Ljava/lang/reflect/Method;Ljava/lang/reflect/Method;)Ljava/lang/Class;
    |               PUTFIELD org.springframework.beans.ExtendedBeanInfo$SimpleIndexedPropertyDescriptor.propertyType Ljava/lang/Class;
    catch java.beans.IntrospectionException -> E0
                    GOTO L0   (line 413)
                E0: ASTORE_1   (line 411)
                L0: ALOAD_0     // Lorg/springframework/beans/ExtendedBeanInfo$SimpleIndexedPropertyDescriptor; this   (line 415)
                    GETFIELD org.springframework.beans.ExtendedBeanInfo$SimpleIndexedPropertyDescriptor.propertyType Ljava/lang/Class;
                    ARETURN
  end public Class getPropertyType()

  public java.lang.reflect.Method getIndexedReadMethod():
                    ALOAD_0     // Lorg/springframework/beans/ExtendedBeanInfo$SimpleIndexedPropertyDescriptor; this   (line 420)
                    GETFIELD org.springframework.beans.ExtendedBeanInfo$SimpleIndexedPropertyDescriptor.indexedReadMethod Ljava/lang/reflect/Method;
                    ARETURN
  end public java.lang.reflect.Method getIndexedReadMethod()

  public void setIndexedReadMethod(java.lang.reflect.Method) throws java.beans.IntrospectionException:
                    ALOAD_0     // Lorg/springframework/beans/ExtendedBeanInfo$SimpleIndexedPropertyDescriptor; this   (line 425)
                    ALOAD_1     // Ljava/lang/reflect/Method; indexedReadMethod
                    PUTFIELD org.springframework.beans.ExtendedBeanInfo$SimpleIndexedPropertyDescriptor.indexedReadMethod Ljava/lang/reflect/Method;
                    RETURN   (line 426)
  end public void setIndexedReadMethod(java.lang.reflect.Method) throws java.beans.IntrospectionException

  public java.lang.reflect.Method getIndexedWriteMethod():
                    ALOAD_0     // Lorg/springframework/beans/ExtendedBeanInfo$SimpleIndexedPropertyDescriptor; this   (line 430)
                    GETFIELD org.springframework.beans.ExtendedBeanInfo$SimpleIndexedPropertyDescriptor.indexedWriteMethod Ljava/lang/reflect/Method;
                    ARETURN
  end public java.lang.reflect.Method getIndexedWriteMethod()

  public void setIndexedWriteMethod(java.lang.reflect.Method) throws java.beans.IntrospectionException:
                    ALOAD_0     // Lorg/springframework/beans/ExtendedBeanInfo$SimpleIndexedPropertyDescriptor; this   (line 435)
                    ALOAD_1     // Ljava/lang/reflect/Method; indexedWriteMethod
                    PUTFIELD org.springframework.beans.ExtendedBeanInfo$SimpleIndexedPropertyDescriptor.indexedWriteMethod Ljava/lang/reflect/Method;
                    RETURN   (line 436)
  end public void setIndexedWriteMethod(java.lang.reflect.Method) throws java.beans.IntrospectionException

  public Class getIndexedPropertyType():
                    ALOAD_0     // Lorg/springframework/beans/ExtendedBeanInfo$SimpleIndexedPropertyDescriptor; this   (line 440)
                    GETFIELD org.springframework.beans.ExtendedBeanInfo$SimpleIndexedPropertyDescriptor.indexedPropertyType Ljava/lang/Class;
                    IFNONNULL L0
    catch java.beans.IntrospectionException -> E0
    |               ALOAD_0     // Lorg/springframework/beans/ExtendedBeanInfo$SimpleIndexedPropertyDescriptor; this   (line 442)
    |               ALOAD_0     // Lorg/springframework/beans/ExtendedBeanInfo$SimpleIndexedPropertyDescriptor; this
    |               INVOKEVIRTUAL org.springframework.beans.ExtendedBeanInfo$SimpleIndexedPropertyDescriptor.getName ()Ljava/lang/String;   (line 443)
    |               ALOAD_0     // Lorg/springframework/beans/ExtendedBeanInfo$SimpleIndexedPropertyDescriptor; this
    |               INVOKEVIRTUAL org.springframework.beans.ExtendedBeanInfo$SimpleIndexedPropertyDescriptor.getPropertyType ()Ljava/lang/Class;
    |               ALOAD_0     // Lorg/springframework/beans/ExtendedBeanInfo$SimpleIndexedPropertyDescriptor; this
    |               GETFIELD org.springframework.beans.ExtendedBeanInfo$SimpleIndexedPropertyDescriptor.indexedReadMethod Ljava/lang/reflect/Method;
    |               ALOAD_0     // Lorg/springframework/beans/ExtendedBeanInfo$SimpleIndexedPropertyDescriptor; this
    |               GETFIELD org.springframework.beans.ExtendedBeanInfo$SimpleIndexedPropertyDescriptor.indexedWriteMethod Ljava/lang/reflect/Method;
    |               INVOKESTATIC org.springframework.beans.PropertyDescriptorUtils.findIndexedPropertyType (Ljava/lang/String;Ljava/lang/Class;Ljava/lang/reflect/Method;Ljava/lang/reflect/Method;)Ljava/lang/Class;   (line 442)
    |               PUTFIELD org.springframework.beans.ExtendedBeanInfo$SimpleIndexedPropertyDescriptor.indexedPropertyType Ljava/lang/Class;
    catch java.beans.IntrospectionException -> E0
                    GOTO L0   (line 447)
                E0: ASTORE_1   (line 445)
                L0: ALOAD_0     // Lorg/springframework/beans/ExtendedBeanInfo$SimpleIndexedPropertyDescriptor; this   (line 449)
                    GETFIELD org.springframework.beans.ExtendedBeanInfo$SimpleIndexedPropertyDescriptor.indexedPropertyType Ljava/lang/Class;
                    ARETURN
  end public Class getIndexedPropertyType()

  public Class getPropertyEditorClass():
                    ALOAD_0     // Lorg/springframework/beans/ExtendedBeanInfo$SimpleIndexedPropertyDescriptor; this   (line 454)
                    GETFIELD org.springframework.beans.ExtendedBeanInfo$SimpleIndexedPropertyDescriptor.propertyEditorClass Ljava/lang/Class;
                    ARETURN
  end public Class getPropertyEditorClass()

  public void setPropertyEditorClass(Class):
                    ALOAD_0     // Lorg/springframework/beans/ExtendedBeanInfo$SimpleIndexedPropertyDescriptor; this   (line 459)
                    ALOAD_1     // Ljava/lang/Class; propertyEditorClass
                    PUTFIELD org.springframework.beans.ExtendedBeanInfo$SimpleIndexedPropertyDescriptor.propertyEditorClass Ljava/lang/Class;
                    RETURN   (line 460)
  end public void setPropertyEditorClass(Class)

  public boolean equals(Object):
                    ALOAD_0     // Lorg/springframework/beans/ExtendedBeanInfo$SimpleIndexedPropertyDescriptor; this   (line 467)
                    ALOAD_1     // Ljava/lang/Object; other
                    IF_ACMPNE L0
                    ICONST_1   (line 468)
                    IRETURN
                L0: ALOAD_1     // Ljava/lang/Object; other   (line 470)
                    INSTANCEOF java.beans.IndexedPropertyDescriptor
                    IFNE L1
                    ICONST_0   (line 471)
                    IRETURN
                L1: ALOAD_1     // Ljava/lang/Object; other   (line 473)
                    CHECKCAST java.beans.IndexedPropertyDescriptor
                    ASTORE_2
                    ALOAD_0     // Lorg/springframework/beans/ExtendedBeanInfo$SimpleIndexedPropertyDescriptor; this   (line 474)
                    INVOKEVIRTUAL org.springframework.beans.ExtendedBeanInfo$SimpleIndexedPropertyDescriptor.getIndexedReadMethod ()Ljava/lang/reflect/Method;
                    ALOAD_2     // Ljava/beans/IndexedPropertyDescriptor; otherPd
                    INVOKEVIRTUAL java.beans.IndexedPropertyDescriptor.getIndexedReadMethod ()Ljava/lang/reflect/Method;
                    INVOKESTATIC org.springframework.util.ObjectUtils.nullSafeEquals (Ljava/lang/Object;Ljava/lang/Object;)Z
                    IFEQ L2
                    ALOAD_0     // Lorg/springframework/beans/ExtendedBeanInfo$SimpleIndexedPropertyDescriptor; this
                    INVOKEVIRTUAL org.springframework.beans.ExtendedBeanInfo$SimpleIndexedPropertyDescriptor.getIndexedWriteMethod ()Ljava/lang/reflect/Method;   (line 475)
                    ALOAD_2     // Ljava/beans/IndexedPropertyDescriptor; otherPd
                    INVOKEVIRTUAL java.beans.IndexedPropertyDescriptor.getIndexedWriteMethod ()Ljava/lang/reflect/Method;
                    INVOKESTATIC org.springframework.util.ObjectUtils.nullSafeEquals (Ljava/lang/Object;Ljava/lang/Object;)Z
                    IFEQ L2
                    ALOAD_0     // Lorg/springframework/beans/ExtendedBeanInfo$SimpleIndexedPropertyDescriptor; this
                    INVOKEVIRTUAL org.springframework.beans.ExtendedBeanInfo$SimpleIndexedPropertyDescriptor.getIndexedPropertyType ()Ljava/lang/Class;   (line 476)
                    ALOAD_2     // Ljava/beans/IndexedPropertyDescriptor; otherPd
                    INVOKEVIRTUAL java.beans.IndexedPropertyDescriptor.getIndexedPropertyType ()Ljava/lang/Class;
                    INVOKESTATIC org.springframework.util.ObjectUtils.nullSafeEquals (Ljava/lang/Object;Ljava/lang/Object;)Z
                    IFEQ L2
                    ALOAD_0     // Lorg/springframework/beans/ExtendedBeanInfo$SimpleIndexedPropertyDescriptor; this
                    ALOAD_2     // Ljava/beans/IndexedPropertyDescriptor; otherPd
                    INVOKESTATIC org.springframework.beans.PropertyDescriptorUtils.equals (Ljava/beans/PropertyDescriptor;Ljava/beans/PropertyDescriptor;)Z   (line 477)
                    IFEQ L2
                    ICONST_1
                    GOTO L3
                L2: ICONST_0
                L3: IRETURN
  end public boolean equals(Object)

  public int hashCode():
                    ALOAD_0     // Lorg/springframework/beans/ExtendedBeanInfo$SimpleIndexedPropertyDescriptor; this   (line 482)
                    INVOKEVIRTUAL org.springframework.beans.ExtendedBeanInfo$SimpleIndexedPropertyDescriptor.getReadMethod ()Ljava/lang/reflect/Method;
                    INVOKESTATIC org.springframework.util.ObjectUtils.nullSafeHashCode (Ljava/lang/Object;)I
                    ISTORE_1
                    BIPUSH 29   (line 483)
                    ILOAD_1     // I hashCode
                    IMUL
                    ALOAD_0     // Lorg/springframework/beans/ExtendedBeanInfo$SimpleIndexedPropertyDescriptor; this
                    INVOKEVIRTUAL org.springframework.beans.ExtendedBeanInfo$SimpleIndexedPropertyDescriptor.getWriteMethod ()Ljava/lang/reflect/Method;
                    INVOKESTATIC org.springframework.util.ObjectUtils.nullSafeHashCode (Ljava/lang/Object;)I
                    IADD
                    ISTORE_1     // I hashCode
                    BIPUSH 29   (line 484)
                    ILOAD_1     // I hashCode
                    IMUL
                    ALOAD_0     // Lorg/springframework/beans/ExtendedBeanInfo$SimpleIndexedPropertyDescriptor; this
                    INVOKEVIRTUAL org.springframework.beans.ExtendedBeanInfo$SimpleIndexedPropertyDescriptor.getIndexedReadMethod ()Ljava/lang/reflect/Method;
                    INVOKESTATIC org.springframework.util.ObjectUtils.nullSafeHashCode (Ljava/lang/Object;)I
                    IADD
                    ISTORE_1     // I hashCode
                    BIPUSH 29   (line 485)
                    ILOAD_1     // I hashCode
                    IMUL
                    ALOAD_0     // Lorg/springframework/beans/ExtendedBeanInfo$SimpleIndexedPropertyDescriptor; this
                    INVOKEVIRTUAL org.springframework.beans.ExtendedBeanInfo$SimpleIndexedPropertyDescriptor.getIndexedWriteMethod ()Ljava/lang/reflect/Method;
                    INVOKESTATIC org.springframework.util.ObjectUtils.nullSafeHashCode (Ljava/lang/Object;)I
                    IADD
                    ISTORE_1     // I hashCode
                    ILOAD_1     // I hashCode   (line 486)
                    IRETURN
  end public int hashCode()

  public String toString():
                    LDC "%s[name=%s, propertyType=%s, indexedPropertyType=%s, readMethod=%s, writeMethod=%s, indexedReadMethod=%s, indexedWriteMethod=%s]"   (line 491)
                    BIPUSH 8
                    ANEWARRAY java.lang.Object
                    DUP
                    ICONST_0
                    ALOAD_0     // Lorg/springframework/beans/ExtendedBeanInfo$SimpleIndexedPropertyDescriptor; this
                    INVOKEVIRTUAL java.lang.Object.getClass ()Ljava/lang/Class;   (line 493)
                    INVOKEVIRTUAL java.lang.Class.getSimpleName ()Ljava/lang/String;
                    AASTORE
                    DUP
                    ICONST_1
                    ALOAD_0     // Lorg/springframework/beans/ExtendedBeanInfo$SimpleIndexedPropertyDescriptor; this
                    INVOKEVIRTUAL org.springframework.beans.ExtendedBeanInfo$SimpleIndexedPropertyDescriptor.getName ()Ljava/lang/String;
                    AASTORE
                    DUP
                    ICONST_2
                    ALOAD_0     // Lorg/springframework/beans/ExtendedBeanInfo$SimpleIndexedPropertyDescriptor; this
                    INVOKEVIRTUAL org.springframework.beans.ExtendedBeanInfo$SimpleIndexedPropertyDescriptor.getPropertyType ()Ljava/lang/Class;
                    AASTORE
                    DUP
                    ICONST_3
                    ALOAD_0     // Lorg/springframework/beans/ExtendedBeanInfo$SimpleIndexedPropertyDescriptor; this
                    INVOKEVIRTUAL org.springframework.beans.ExtendedBeanInfo$SimpleIndexedPropertyDescriptor.getIndexedPropertyType ()Ljava/lang/Class;
                    AASTORE
                    DUP
                    ICONST_4
                    ALOAD_0     // Lorg/springframework/beans/ExtendedBeanInfo$SimpleIndexedPropertyDescriptor; this
                    GETFIELD org.springframework.beans.ExtendedBeanInfo$SimpleIndexedPropertyDescriptor.readMethod Ljava/lang/reflect/Method;
                    AASTORE
                    DUP
                    ICONST_5
                    ALOAD_0     // Lorg/springframework/beans/ExtendedBeanInfo$SimpleIndexedPropertyDescriptor; this
                    GETFIELD org.springframework.beans.ExtendedBeanInfo$SimpleIndexedPropertyDescriptor.writeMethod Ljava/lang/reflect/Method;
                    AASTORE
                    DUP
                    BIPUSH 6
                    ALOAD_0     // Lorg/springframework/beans/ExtendedBeanInfo$SimpleIndexedPropertyDescriptor; this
                    GETFIELD org.springframework.beans.ExtendedBeanInfo$SimpleIndexedPropertyDescriptor.indexedReadMethod Ljava/lang/reflect/Method;
                    AASTORE
                    DUP
                    BIPUSH 7
                    ALOAD_0     // Lorg/springframework/beans/ExtendedBeanInfo$SimpleIndexedPropertyDescriptor; this
                    GETFIELD org.springframework.beans.ExtendedBeanInfo$SimpleIndexedPropertyDescriptor.indexedWriteMethod Ljava/lang/reflect/Method;
                    AASTORE
                    INVOKESTATIC java.lang.String.format (Ljava/lang/String;[Ljava/lang/Object;)Ljava/lang/String;   (line 491)
                    ARETURN
  end public String toString()

end  class org.springframework.beans.ExtendedBeanInfo$SimpleIndexedPropertyDescriptor
 -- (NullPointerException) null
null
java.lang.NullPointerException
	at org.aspectj.weaver.UnresolvedType.forSignature(UnresolvedType.java:384)
	at org.aspectj.weaver.bcel.BcelObjectType.getDeclaredInterfaces(BcelObjectType.java:275)
	at org.aspectj.weaver.ReferenceType.getDeclaredInterfaces(ReferenceType.java:626)
	at org.aspectj.weaver.ResolvedType.getDirectSupertypes(ResolvedType.java:82)
	at org.aspectj.weaver.patterns.TypePattern.matchesSubtypes(TypePattern.java:201)
	at org.aspectj.weaver.patterns.TypePattern.matchesSubtypes(TypePattern.java:203)
	at org.aspectj.weaver.patterns.TypePattern.matchesSubtypes(TypePattern.java:183)
	at org.aspectj.weaver.patterns.ExactTypePattern.matchesSubtypes(ExactTypePattern.java:74)
	at org.aspectj.weaver.patterns.TypePattern.matchesStatically(TypePattern.java:130)
	at org.aspectj.weaver.patterns.OrTypePattern.matchesStatically(OrTypePattern.java:76)
	at org.aspectj.weaver.patterns.SignaturePattern.matchesExactlyMethod(SignaturePattern.java:505)
	at org.aspectj.weaver.patterns.SignaturePattern.matchesExactly(SignaturePattern.java:360)
	at org.aspectj.weaver.patterns.SignaturePattern.matches(SignaturePattern.java:320)
	at org.aspectj.weaver.patterns.KindedPointcut.matchInternal(KindedPointcut.java:202)
	at org.aspectj.weaver.patterns.Pointcut.match(Pointcut.java:137)
	at org.aspectj.weaver.patterns.AndPointcut.matchInternal(AndPointcut.java:51)
	at org.aspectj.weaver.patterns.Pointcut.match(Pointcut.java:137)
	at org.aspectj.weaver.patterns.OrPointcut.matchInternal(OrPointcut.java:54)
	at org.aspectj.weaver.patterns.Pointcut.match(Pointcut.java:137)
	at org.aspectj.weaver.ShadowMunger.match(ShadowMunger.java:113)
	at org.aspectj.weaver.Advice.match(Advice.java:109)
	at org.aspectj.weaver.bcel.BcelAdvice.match(BcelAdvice.java:149)
	at org.aspectj.weaver.bcel.BcelClassWeaver.match(BcelClassWeaver.java:3173)
	at org.aspectj.weaver.bcel.BcelClassWeaver.match(BcelClassWeaver.java:2565)
	at org.aspectj.weaver.bcel.BcelClassWeaver.weave(BcelClassWeaver.java:480)
	at org.aspectj.weaver.bcel.BcelClassWeaver.weave(BcelClassWeaver.java:99)
	at org.aspectj.weaver.bcel.BcelWeaver.weave(BcelWeaver.java:1694)
	at org.aspectj.weaver.bcel.BcelWeaver.weaveWithoutDump(BcelWeaver.java:1638)
	at org.aspectj.weaver.bcel.BcelWeaver.weaveAndNotify(BcelWeaver.java:1401)
	at org.aspectj.weaver.bcel.BcelWeaver.weave(BcelWeaver.java:1187)
	at org.aspectj.weaver.tools.WeavingAdaptor.getWovenBytes(WeavingAdaptor.java:472)
	at org.aspectj.weaver.tools.WeavingAdaptor.weaveClass(WeavingAdaptor.java:323)
	at org.aspectj.weaver.loadtime.Aj.preProcess(Aj.java:99)
	at org.aspectj.weaver.loadtime.ClassPreProcessorAgentAdapter.transform(ClassPreProcessorAgentAdapter.java:54)
	at org.springframework.context.weaving.AspectJWeavingEnabler$AspectJClassBypassingClassFileTransformer.transform(AspectJWeavingEnabler.java:108)
	at org.springframework.instrument.classloading.InstrumentationLoadTimeWeaver$FilteringClassFileTransformer.transform(InstrumentationLoadTimeWeaver.java:184)
	at sun.instrument.TransformerManager.transform(Unknown Source)
	at sun.instrument.InstrumentationImpl.transform(Unknown Source)
	at java.lang.ClassLoader.defineClass1(Native Method)
	at java.lang.ClassLoader.defineClass(Unknown Source)
	at java.security.SecureClassLoader.defineClass(Unknown Source)
	at java.net.URLClassLoader.defineClass(Unknown Source)
	at java.net.URLClassLoader.access$100(Unknown Source)
	at java.net.URLClassLoader$1.run(Unknown Source)
	at java.net.URLClassLoader$1.run(Unknown Source)
	at java.security.AccessController.doPrivileged(Native Method)
	at java.net.URLClassLoader.findClass(Unknown Source)
	at java.lang.ClassLoader.loadClass(Unknown Source)
	at sun.misc.Launcher$AppClassLoader.loadClass(Unknown Source)
	at java.lang.ClassLoader.loadClass(Unknown Source)
	at org.springframework.beans.ExtendedBeanInfoFactory.supports(ExtendedBeanInfoFactory.java:55)
	at org.springframework.beans.ExtendedBeanInfoFactory.getBeanInfo(ExtendedBeanInfoFactory.java:46)
	at org.springframework.beans.CachedIntrospectionResults.<init>(CachedIntrospectionResults.java:270)
	at org.springframework.beans.CachedIntrospectionResults.forClass(CachedIntrospectionResults.java:189)
	at org.springframework.beans.BeanWrapperImpl.getCachedIntrospectionResults(BeanWrapperImpl.java:328)
	at org.springframework.beans.BeanWrapperImpl.getPropertyDescriptors(BeanWrapperImpl.java:336)
	at org.springframework.beans.factory.support.AbstractAutowireCapableBeanFactory.filterPropertyDescriptorsForDependencyCheck(AbstractAutowireCapableBeanFactory.java:1364)
	at org.springframework.beans.factory.support.AbstractAutowireCapableBeanFactory.filterPropertyDescriptorsForDependencyCheck(AbstractAutowireCapableBeanFactory.java:1343)
	at org.springframework.beans.factory.support.AbstractAutowireCapableBeanFactory.populateBean(AbstractAutowireCapableBeanFactory.java:1205)
	at org.springframework.beans.factory.support.AbstractAutowireCapableBeanFactory.doCreateBean(AbstractAutowireCapableBeanFactory.java:537)
	at org.springframework.beans.factory.support.AbstractAutowireCapableBeanFactory.createBean(AbstractAutowireCapableBeanFactory.java:476)
	at org.springframework.beans.factory.support.AbstractBeanFactory$1.getObject(AbstractBeanFactory.java:303)
	at org.springframework.beans.factory.support.DefaultSingletonBeanRegistry.getSingleton(DefaultSingletonBeanRegistry.java:230)
	at org.springframework.beans.factory.support.AbstractBeanFactory.doGetBean(AbstractBeanFactory.java:299)
	at org.springframework.beans.factory.support.AbstractBeanFactory.getBean(AbstractBeanFactory.java:194)
	at org.springframework.beans.factory.support.DefaultListableBeanFactory.preInstantiateSingletons(DefaultListableBeanFactory.java:755)
	at org.springframework.context.support.AbstractApplicationContext.finishBeanFactoryInitialization(AbstractApplicationContext.java:757)
	at org.springframework.context.support.AbstractApplicationContext.refresh(AbstractApplicationContext.java:480)
	at org.springframework.context.support.ClassPathXmlApplicationContext.<init>(ClassPathXmlApplicationContext.java:139)
	at org.springframework.context.support.ClassPathXmlApplicationContext.<init>(ClassPathXmlApplicationContext.java:93)
	at com.springExemple.presentation.Presentation2.main(Presentation2.java:13)

error can't determine annotations of missing type org.springframework.transaction.annotation.Transactional
when weaving type org.springframework.beans.ExtendedBeanInfo$SimplePropertyDescriptor
when weaving classes 
when weaving 
 [Xlint:cantFindType]
abort trouble in: 
 class org.springframework.beans.ExtendedBeanInfo$SimplePropertyDescriptor extends java.beans.PropertyDescriptor:
  private java.lang.reflect.Method readMethod
  private java.lang.reflect.Method writeMethod
  private Class propertyType [Signature(Ljava/lang/Class<*>;)]
  private Class propertyEditorClass [Signature(Ljava/lang/Class<*>;)]
  public void <init>(java.beans.PropertyDescriptor) throws java.beans.IntrospectionException:
                    ALOAD_0     // Lorg/springframework/beans/ExtendedBeanInfo$SimplePropertyDescriptor; this   (line 277)
                    ALOAD_1     // Ljava/beans/PropertyDescriptor; original
                    INVOKEVIRTUAL java.beans.PropertyDescriptor.getName ()Ljava/lang/String;
                    ALOAD_1     // Ljava/beans/PropertyDescriptor; original
                    INVOKEVIRTUAL java.beans.PropertyDescriptor.getReadMethod ()Ljava/lang/reflect/Method;
                    ALOAD_1     // Ljava/beans/PropertyDescriptor; original
                    INVOKEVIRTUAL java.beans.PropertyDescriptor.getWriteMethod ()Ljava/lang/reflect/Method;
                    INVOKESPECIAL org.springframework.beans.ExtendedBeanInfo$SimplePropertyDescriptor.<init> (Ljava/lang/String;Ljava/lang/reflect/Method;Ljava/lang/reflect/Method;)V
    constructor-execution(void org.springframework.beans.ExtendedBeanInfo$SimplePropertyDescriptor.<init>(java.beans.PropertyDescriptor))
    |               ALOAD_1     // Ljava/beans/PropertyDescriptor; original   (line 278)
    |               ALOAD_0     // Lorg/springframework/beans/ExtendedBeanInfo$SimplePropertyDescriptor; this
    |               INVOKESTATIC org.springframework.beans.PropertyDescriptorUtils.copyNonMethodProperties (Ljava/beans/PropertyDescriptor;Ljava/beans/PropertyDescriptor;)V
    |               RETURN   (line 279)
    constructor-execution(void org.springframework.beans.ExtendedBeanInfo$SimplePropertyDescriptor.<init>(java.beans.PropertyDescriptor))
  end public void <init>(java.beans.PropertyDescriptor) throws java.beans.IntrospectionException

  public void <init>(String, java.lang.reflect.Method, java.lang.reflect.Method) throws java.beans.IntrospectionException:
                    ALOAD_0     // Lorg/springframework/beans/ExtendedBeanInfo$SimplePropertyDescriptor; this   (line 282)
                    ALOAD_1     // Ljava/lang/String; propertyName
                    ACONST_NULL
                    ACONST_NULL
                    INVOKESPECIAL java.beans.PropertyDescriptor.<init> (Ljava/lang/String;Ljava/lang/reflect/Method;Ljava/lang/reflect/Method;)V
    constructor-execution(void org.springframework.beans.ExtendedBeanInfo$SimplePropertyDescriptor.<init>(java.lang.String, java.lang.reflect.Method, java.lang.reflect.Method))
    |               ALOAD_0     // Lorg/springframework/beans/ExtendedBeanInfo$SimplePropertyDescriptor; this   (line 283)
    |               ALOAD_2     // Ljava/lang/reflect/Method; readMethod
    |               PUTFIELD org.springframework.beans.ExtendedBeanInfo$SimplePropertyDescriptor.readMethod Ljava/lang/reflect/Method;
    |               ALOAD_0     // Lorg/springframework/beans/ExtendedBeanInfo$SimplePropertyDescriptor; this   (line 284)
    |               ALOAD_3     // Ljava/lang/reflect/Method; writeMethod
    |               PUTFIELD org.springframework.beans.ExtendedBeanInfo$SimplePropertyDescriptor.writeMethod Ljava/lang/reflect/Method;
    |               ALOAD_0     // Lorg/springframework/beans/ExtendedBeanInfo$SimplePropertyDescriptor; this   (line 285)
    |               ALOAD_2     // Ljava/lang/reflect/Method; readMethod
    |               ALOAD_3     // Ljava/lang/reflect/Method; writeMethod
    |               INVOKESTATIC org.springframework.beans.PropertyDescriptorUtils.findPropertyType (Ljava/lang/reflect/Method;Ljava/lang/reflect/Method;)Ljava/lang/Class;
    |               PUTFIELD org.springframework.beans.ExtendedBeanInfo$SimplePropertyDescriptor.propertyType Ljava/lang/Class;
    |               RETURN   (line 286)
    constructor-execution(void org.springframework.beans.ExtendedBeanInfo$SimplePropertyDescriptor.<init>(java.lang.String, java.lang.reflect.Method, java.lang.reflect.Method))
  end public void <init>(String, java.lang.reflect.Method, java.lang.reflect.Method) throws java.beans.IntrospectionException

  public java.lang.reflect.Method getReadMethod():
                    ALOAD_0     // Lorg/springframework/beans/ExtendedBeanInfo$SimplePropertyDescriptor; this   (line 290)
                    GETFIELD org.springframework.beans.ExtendedBeanInfo$SimplePropertyDescriptor.readMethod Ljava/lang/reflect/Method;
                    ARETURN
  end public java.lang.reflect.Method getReadMethod()

  public void setReadMethod(java.lang.reflect.Method):
                    ALOAD_0     // Lorg/springframework/beans/ExtendedBeanInfo$SimplePropertyDescriptor; this   (line 295)
                    ALOAD_1     // Ljava/lang/reflect/Method; readMethod
                    PUTFIELD org.springframework.beans.ExtendedBeanInfo$SimplePropertyDescriptor.readMethod Ljava/lang/reflect/Method;
                    RETURN   (line 296)
  end public void setReadMethod(java.lang.reflect.Method)

  public java.lang.reflect.Method getWriteMethod():
                    ALOAD_0     // Lorg/springframework/beans/ExtendedBeanInfo$SimplePropertyDescriptor; this   (line 300)
                    GETFIELD org.springframework.beans.ExtendedBeanInfo$SimplePropertyDescriptor.writeMethod Ljava/lang/reflect/Method;
                    ARETURN
  end public java.lang.reflect.Method getWriteMethod()

  public void setWriteMethod(java.lang.reflect.Method):
                    ALOAD_0     // Lorg/springframework/beans/ExtendedBeanInfo$SimplePropertyDescriptor; this   (line 305)
                    ALOAD_1     // Ljava/lang/reflect/Method; writeMethod
                    PUTFIELD org.springframework.beans.ExtendedBeanInfo$SimplePropertyDescriptor.writeMethod Ljava/lang/reflect/Method;
                    RETURN   (line 306)
  end public void setWriteMethod(java.lang.reflect.Method)

  public Class getPropertyType():
                    ALOAD_0     // Lorg/springframework/beans/ExtendedBeanInfo$SimplePropertyDescriptor; this   (line 310)
                    GETFIELD org.springframework.beans.ExtendedBeanInfo$SimplePropertyDescriptor.propertyType Ljava/lang/Class;
                    IFNONNULL L0
    catch java.beans.IntrospectionException -> E0
    |               ALOAD_0     // Lorg/springframework/beans/ExtendedBeanInfo$SimplePropertyDescriptor; this   (line 312)
    |               ALOAD_0     // Lorg/springframework/beans/ExtendedBeanInfo$SimplePropertyDescriptor; this
    |               GETFIELD org.springframework.beans.ExtendedBeanInfo$SimplePropertyDescriptor.readMethod Ljava/lang/reflect/Method;
    |               ALOAD_0     // Lorg/springframework/beans/ExtendedBeanInfo$SimplePropertyDescriptor; this
    |               GETFIELD org.springframework.beans.ExtendedBeanInfo$SimplePropertyDescriptor.writeMethod Ljava/lang/reflect/Method;
    |               INVOKESTATIC org.springframework.beans.PropertyDescriptorUtils.findPropertyType (Ljava/lang/reflect/Method;Ljava/lang/reflect/Method;)Ljava/lang/Class;
    |               PUTFIELD org.springframework.beans.ExtendedBeanInfo$SimplePropertyDescriptor.propertyType Ljava/lang/Class;
    catch java.beans.IntrospectionException -> E0
                    GOTO L0   (line 316)
                E0: ASTORE_1   (line 314)
                L0: ALOAD_0     // Lorg/springframework/beans/ExtendedBeanInfo$SimplePropertyDescriptor; this   (line 318)
                    GETFIELD org.springframework.beans.ExtendedBeanInfo$SimplePropertyDescriptor.propertyType Ljava/lang/Class;
                    ARETURN
  end public Class getPropertyType()

  public Class getPropertyEditorClass():
                    ALOAD_0     // Lorg/springframework/beans/ExtendedBeanInfo$SimplePropertyDescriptor; this   (line 323)
                    GETFIELD org.springframework.beans.ExtendedBeanInfo$SimplePropertyDescriptor.propertyEditorClass Ljava/lang/Class;
                    ARETURN
  end public Class getPropertyEditorClass()

  public void setPropertyEditorClass(Class):
                    ALOAD_0     // Lorg/springframework/beans/ExtendedBeanInfo$SimplePropertyDescriptor; this   (line 328)
                    ALOAD_1     // Ljava/lang/Class; propertyEditorClass
                    PUTFIELD org.springframework.beans.ExtendedBeanInfo$SimplePropertyDescriptor.propertyEditorClass Ljava/lang/Class;
                    RETURN   (line 329)
  end public void setPropertyEditorClass(Class)

  public boolean equals(Object):
                    ALOAD_0     // Lorg/springframework/beans/ExtendedBeanInfo$SimplePropertyDescriptor; this   (line 333)
                    ALOAD_1     // Ljava/lang/Object; other
                    IF_ACMPEQ L0
                    ALOAD_1     // Ljava/lang/Object; other
                    INSTANCEOF java.beans.PropertyDescriptor
                    IFEQ L1
                    ALOAD_0     // Lorg/springframework/beans/ExtendedBeanInfo$SimplePropertyDescriptor; this
                    ALOAD_1     // Ljava/lang/Object; other
                    CHECKCAST java.beans.PropertyDescriptor
                    INVOKESTATIC org.springframework.beans.PropertyDescriptorUtils.equals (Ljava/beans/PropertyDescriptor;Ljava/beans/PropertyDescriptor;)Z   (line 334)
                    IFEQ L1
                L0: ICONST_1
                    GOTO L2
                L1: ICONST_0
                L2: IRETURN
  end public boolean equals(Object)

  public int hashCode():
                    ALOAD_0     // Lorg/springframework/beans/ExtendedBeanInfo$SimplePropertyDescriptor; this   (line 339)
                    INVOKEVIRTUAL org.springframework.beans.ExtendedBeanInfo$SimplePropertyDescriptor.getReadMethod ()Ljava/lang/reflect/Method;
                    INVOKESTATIC org.springframework.util.ObjectUtils.nullSafeHashCode (Ljava/lang/Object;)I
                    BIPUSH 29
                    IMUL
                    ALOAD_0     // Lorg/springframework/beans/ExtendedBeanInfo$SimplePropertyDescriptor; this
                    INVOKEVIRTUAL org.springframework.beans.ExtendedBeanInfo$SimplePropertyDescriptor.getWriteMethod ()Ljava/lang/reflect/Method;
                    INVOKESTATIC org.springframework.util.ObjectUtils.nullSafeHashCode (Ljava/lang/Object;)I
                    IADD
                    IRETURN
  end public int hashCode()

  public String toString():
                    LDC "%s[name=%s, propertyType=%s, readMethod=%s, writeMethod=%s]"   (line 344)
                    ICONST_5
                    ANEWARRAY java.lang.Object
                    DUP
                    ICONST_0
                    ALOAD_0     // Lorg/springframework/beans/ExtendedBeanInfo$SimplePropertyDescriptor; this
                    INVOKEVIRTUAL java.lang.Object.getClass ()Ljava/lang/Class;   (line 345)
                    INVOKEVIRTUAL java.lang.Class.getSimpleName ()Ljava/lang/String;
                    AASTORE
                    DUP
                    ICONST_1
                    ALOAD_0     // Lorg/springframework/beans/ExtendedBeanInfo$SimplePropertyDescriptor; this
                    INVOKEVIRTUAL org.springframework.beans.ExtendedBeanInfo$SimplePropertyDescriptor.getName ()Ljava/lang/String;
                    AASTORE
                    DUP
                    ICONST_2
                    ALOAD_0     // Lorg/springframework/beans/ExtendedBeanInfo$SimplePropertyDescriptor; this
                    INVOKEVIRTUAL org.springframework.beans.ExtendedBeanInfo$SimplePropertyDescriptor.getPropertyType ()Ljava/lang/Class;
                    AASTORE
                    DUP
                    ICONST_3
                    ALOAD_0     // Lorg/springframework/beans/ExtendedBeanInfo$SimplePropertyDescriptor; this
                    GETFIELD org.springframework.beans.ExtendedBeanInfo$SimplePropertyDescriptor.readMethod Ljava/lang/reflect/Method;
                    AASTORE
                    DUP
                    ICONST_4
                    ALOAD_0     // Lorg/springframework/beans/ExtendedBeanInfo$SimplePropertyDescriptor; this
                    GETFIELD org.springframework.beans.ExtendedBeanInfo$SimplePropertyDescriptor.writeMethod Ljava/lang/reflect/Method;
                    AASTORE
                    INVOKESTATIC java.lang.String.format (Ljava/lang/String;[Ljava/lang/Object;)Ljava/lang/String;   (line 344)
                    ARETURN
  end public String toString()

end  class org.springframework.beans.ExtendedBeanInfo$SimplePropertyDescriptor
 -- (NullPointerException) null
null
java.lang.NullPointerException
	at org.aspectj.weaver.UnresolvedType.forSignature(UnresolvedType.java:384)
	at org.aspectj.weaver.bcel.BcelObjectType.getDeclaredInterfaces(BcelObjectType.java:275)
	at org.aspectj.weaver.ReferenceType.getDeclaredInterfaces(ReferenceType.java:626)
	at org.aspectj.weaver.ResolvedType.getDirectSupertypes(ResolvedType.java:82)
	at org.aspectj.weaver.patterns.TypePattern.matchesSubtypes(TypePattern.java:201)
	at org.aspectj.weaver.patterns.TypePattern.matchesSubtypes(TypePattern.java:203)
	at org.aspectj.weaver.patterns.TypePattern.matchesSubtypes(TypePattern.java:183)
	at org.aspectj.weaver.patterns.ExactTypePattern.matchesSubtypes(ExactTypePattern.java:74)
	at org.aspectj.weaver.patterns.TypePattern.matchesStatically(TypePattern.java:130)
	at org.aspectj.weaver.patterns.OrTypePattern.matchesStatically(OrTypePattern.java:76)
	at org.aspectj.weaver.patterns.SignaturePattern.matchesExactlyMethod(SignaturePattern.java:505)
	at org.aspectj.weaver.patterns.SignaturePattern.matchesExactly(SignaturePattern.java:360)
	at org.aspectj.weaver.patterns.SignaturePattern.matches(SignaturePattern.java:320)
	at org.aspectj.weaver.patterns.KindedPointcut.matchInternal(KindedPointcut.java:202)
	at org.aspectj.weaver.patterns.Pointcut.match(Pointcut.java:137)
	at org.aspectj.weaver.patterns.AndPointcut.matchInternal(AndPointcut.java:51)
	at org.aspectj.weaver.patterns.Pointcut.match(Pointcut.java:137)
	at org.aspectj.weaver.patterns.OrPointcut.matchInternal(OrPointcut.java:54)
	at org.aspectj.weaver.patterns.Pointcut.match(Pointcut.java:137)
	at org.aspectj.weaver.ShadowMunger.match(ShadowMunger.java:113)
	at org.aspectj.weaver.Advice.match(Advice.java:109)
	at org.aspectj.weaver.bcel.BcelAdvice.match(BcelAdvice.java:149)
	at org.aspectj.weaver.bcel.BcelClassWeaver.match(BcelClassWeaver.java:3173)
	at org.aspectj.weaver.bcel.BcelClassWeaver.match(BcelClassWeaver.java:2565)
	at org.aspectj.weaver.bcel.BcelClassWeaver.weave(BcelClassWeaver.java:480)
	at org.aspectj.weaver.bcel.BcelClassWeaver.weave(BcelClassWeaver.java:99)
	at org.aspectj.weaver.bcel.BcelWeaver.weave(BcelWeaver.java:1694)
	at org.aspectj.weaver.bcel.BcelWeaver.weaveWithoutDump(BcelWeaver.java:1638)
	at org.aspectj.weaver.bcel.BcelWeaver.weaveAndNotify(BcelWeaver.java:1401)
	at org.aspectj.weaver.bcel.BcelWeaver.weave(BcelWeaver.java:1187)
	at org.aspectj.weaver.tools.WeavingAdaptor.getWovenBytes(WeavingAdaptor.java:472)
	at org.aspectj.weaver.tools.WeavingAdaptor.weaveClass(WeavingAdaptor.java:323)
	at org.aspectj.weaver.loadtime.Aj.preProcess(Aj.java:99)
	at org.aspectj.weaver.loadtime.ClassPreProcessorAgentAdapter.transform(ClassPreProcessorAgentAdapter.java:54)
	at org.springframework.context.weaving.AspectJWeavingEnabler$AspectJClassBypassingClassFileTransformer.transform(AspectJWeavingEnabler.java:108)
	at org.springframework.instrument.classloading.InstrumentationLoadTimeWeaver$FilteringClassFileTransformer.transform(InstrumentationLoadTimeWeaver.java:184)
	at sun.instrument.TransformerManager.transform(Unknown Source)
	at sun.instrument.InstrumentationImpl.transform(Unknown Source)
	at java.lang.ClassLoader.defineClass1(Native Method)
	at java.lang.ClassLoader.defineClass(Unknown Source)
	at java.security.SecureClassLoader.defineClass(Unknown Source)
	at java.net.URLClassLoader.defineClass(Unknown Source)
	at java.net.URLClassLoader.access$100(Unknown Source)
	at java.net.URLClassLoader$1.run(Unknown Source)
	at java.net.URLClassLoader$1.run(Unknown Source)
	at java.security.AccessController.doPrivileged(Native Method)
	at java.net.URLClassLoader.findClass(Unknown Source)
	at java.lang.ClassLoader.loadClass(Unknown Source)
	at sun.misc.Launcher$AppClassLoader.loadClass(Unknown Source)
	at java.lang.ClassLoader.loadClass(Unknown Source)
	at org.springframework.beans.ExtendedBeanInfoFactory.supports(ExtendedBeanInfoFactory.java:55)
	at org.springframework.beans.ExtendedBeanInfoFactory.getBeanInfo(ExtendedBeanInfoFactory.java:46)
	at org.springframework.beans.CachedIntrospectionResults.<init>(CachedIntrospectionResults.java:270)
	at org.springframework.beans.CachedIntrospectionResults.forClass(CachedIntrospectionResults.java:189)
	at org.springframework.beans.BeanWrapperImpl.getCachedIntrospectionResults(BeanWrapperImpl.java:328)
	at org.springframework.beans.BeanWrapperImpl.getPropertyDescriptors(BeanWrapperImpl.java:336)
	at org.springframework.beans.factory.support.AbstractAutowireCapableBeanFactory.filterPropertyDescriptorsForDependencyCheck(AbstractAutowireCapableBeanFactory.java:1364)
	at org.springframework.beans.factory.support.AbstractAutowireCapableBeanFactory.filterPropertyDescriptorsForDependencyCheck(AbstractAutowireCapableBeanFactory.java:1343)
	at org.springframework.beans.factory.support.AbstractAutowireCapableBeanFactory.populateBean(AbstractAutowireCapableBeanFactory.java:1205)
	at org.springframework.beans.factory.support.AbstractAutowireCapableBeanFactory.doCreateBean(AbstractAutowireCapableBeanFactory.java:537)
	at org.springframework.beans.factory.support.AbstractAutowireCapableBeanFactory.createBean(AbstractAutowireCapableBeanFactory.java:476)
	at org.springframework.beans.factory.support.AbstractBeanFactory$1.getObject(AbstractBeanFactory.java:303)
	at org.springframework.beans.factory.support.DefaultSingletonBeanRegistry.getSingleton(DefaultSingletonBeanRegistry.java:230)
	at org.springframework.beans.factory.support.AbstractBeanFactory.doGetBean(AbstractBeanFactory.java:299)
	at org.springframework.beans.factory.support.AbstractBeanFactory.getBean(AbstractBeanFactory.java:194)
	at org.springframework.beans.factory.support.DefaultListableBeanFactory.preInstantiateSingletons(DefaultListableBeanFactory.java:755)
	at org.springframework.context.support.AbstractApplicationContext.finishBeanFactoryInitialization(AbstractApplicationContext.java:757)
	at org.springframework.context.support.AbstractApplicationContext.refresh(AbstractApplicationContext.java:480)
	at org.springframework.context.support.ClassPathXmlApplicationContext.<init>(ClassPathXmlApplicationContext.java:139)
	at org.springframework.context.support.ClassPathXmlApplicationContext.<init>(ClassPathXmlApplicationContext.java:93)
	at com.springExemple.presentation.Presentation2.main(Presentation2.java:13)

error can't determine annotations of missing type org.springframework.transaction.annotation.Transactional
when weaving type org.springframework.core.MethodParameter
when weaving classes 
when weaving 
 [Xlint:cantFindType]
abort trouble in: 
public class org.springframework.core.MethodParameter extends java.lang.Object:
  private final java.lang.reflect.Method method
  private final java.lang.reflect.Constructor constructor [Signature(Ljava/lang/reflect/Constructor<*>;)]
  private final int parameterIndex
  private int nestingLevel
  java.util.Map typeIndexesPerLevel [Signature(Ljava/util/Map<Ljava/lang/Integer;Ljava/lang/Integer;>;)]
  private volatile Class containingClass [Signature(Ljava/lang/Class<*>;)]
  private volatile Class parameterType [Signature(Ljava/lang/Class<*>;)]
  private volatile java.lang.reflect.Type genericParameterType
  private volatile java.lang.annotation.Annotation[] parameterAnnotations
  private volatile org.springframework.core.ParameterNameDiscoverer parameterNameDiscoverer
  private volatile String parameterName
  public void <init>(java.lang.reflect.Method, int):
                    ALOAD_0     // Lorg/springframework/core/MethodParameter; this   (line 74)
                    ALOAD_1     // Ljava/lang/reflect/Method; method
                    ILOAD_2     // I parameterIndex
                    ICONST_1
                    INVOKESPECIAL org.springframework.core.MethodParameter.<init> (Ljava/lang/reflect/Method;II)V
    constructor-execution(void org.springframework.core.MethodParameter.<init>(java.lang.reflect.Method, int))
    |               RETURN   (line 75)
    constructor-execution(void org.springframework.core.MethodParameter.<init>(java.lang.reflect.Method, int))
  end public void <init>(java.lang.reflect.Method, int)

  public void <init>(java.lang.reflect.Method, int, int):
                    ALOAD_0     // Lorg/springframework/core/MethodParameter; this   (line 87)
                    INVOKESPECIAL java.lang.Object.<init> ()V
    constructor-execution(void org.springframework.core.MethodParameter.<init>(java.lang.reflect.Method, int, int))
    |               ALOAD_0     // Lorg/springframework/core/MethodParameter; this   (line 50)
    |               ICONST_1
    |               PUTFIELD org.springframework.core.MethodParameter.nestingLevel I
    |               ALOAD_1     // Ljava/lang/reflect/Method; method   (line 88)
    |               LDC "Method must not be null"
    |               INVOKESTATIC org.springframework.util.Assert.notNull (Ljava/lang/Object;Ljava/lang/String;)V
    |               ALOAD_0     // Lorg/springframework/core/MethodParameter; this   (line 89)
    |               ALOAD_1     // Ljava/lang/reflect/Method; method
    |               PUTFIELD org.springframework.core.MethodParameter.method Ljava/lang/reflect/Method;
    |               ALOAD_0     // Lorg/springframework/core/MethodParameter; this   (line 90)
    |               ILOAD_2     // I parameterIndex
    |               PUTFIELD org.springframework.core.MethodParameter.parameterIndex I
    |               ALOAD_0     // Lorg/springframework/core/MethodParameter; this   (line 91)
    |               ILOAD_3     // I nestingLevel
    |               PUTFIELD org.springframework.core.MethodParameter.nestingLevel I
    |               ALOAD_0     // Lorg/springframework/core/MethodParameter; this   (line 92)
    |               ACONST_NULL
    |               PUTFIELD org.springframework.core.MethodParameter.constructor Ljava/lang/reflect/Constructor;
    |               RETURN   (line 93)
    constructor-execution(void org.springframework.core.MethodParameter.<init>(java.lang.reflect.Method, int, int))
  end public void <init>(java.lang.reflect.Method, int, int)

  public void <init>(java.lang.reflect.Constructor, int):
                    ALOAD_0     // Lorg/springframework/core/MethodParameter; this   (line 101)
                    ALOAD_1     // Ljava/lang/reflect/Constructor; constructor
                    ILOAD_2     // I parameterIndex
                    ICONST_1
                    INVOKESPECIAL org.springframework.core.MethodParameter.<init> (Ljava/lang/reflect/Constructor;II)V
    constructor-execution(void org.springframework.core.MethodParameter.<init>(java.lang.reflect.Constructor, int))
    |               RETURN   (line 102)
    constructor-execution(void org.springframework.core.MethodParameter.<init>(java.lang.reflect.Constructor, int))
  end public void <init>(java.lang.reflect.Constructor, int)

  public void <init>(java.lang.reflect.Constructor, int, int):
                    ALOAD_0     // Lorg/springframework/core/MethodParameter; this   (line 112)
                    INVOKESPECIAL java.lang.Object.<init> ()V
    constructor-execution(void org.springframework.core.MethodParameter.<init>(java.lang.reflect.Constructor, int, int))
    |               ALOAD_0     // Lorg/springframework/core/MethodParameter; this   (line 50)
    |               ICONST_1
    |               PUTFIELD org.springframework.core.MethodParameter.nestingLevel I
    |               ALOAD_1     // Ljava/lang/reflect/Constructor; constructor   (line 113)
    |               LDC "Constructor must not be null"
    |               INVOKESTATIC org.springframework.util.Assert.notNull (Ljava/lang/Object;Ljava/lang/String;)V
    |               ALOAD_0     // Lorg/springframework/core/MethodParameter; this   (line 114)
    |               ALOAD_1     // Ljava/lang/reflect/Constructor; constructor
    |               PUTFIELD org.springframework.core.MethodParameter.constructor Ljava/lang/reflect/Constructor;
    |               ALOAD_0     // Lorg/springframework/core/MethodParameter; this   (line 115)
    |               ILOAD_2     // I parameterIndex
    |               PUTFIELD org.springframework.core.MethodParameter.parameterIndex I
    |               ALOAD_0     // Lorg/springframework/core/MethodParameter; this   (line 116)
    |               ILOAD_3     // I nestingLevel
    |               PUTFIELD org.springframework.core.MethodParameter.nestingLevel I
    |               ALOAD_0     // Lorg/springframework/core/MethodParameter; this   (line 117)
    |               ACONST_NULL
    |               PUTFIELD org.springframework.core.MethodParameter.method Ljava/lang/reflect/Method;
    |               RETURN   (line 118)
    constructor-execution(void org.springframework.core.MethodParameter.<init>(java.lang.reflect.Constructor, int, int))
  end public void <init>(java.lang.reflect.Constructor, int, int)

  public void <init>(org.springframework.core.MethodParameter):
                    ALOAD_0     // Lorg/springframework/core/MethodParameter; this   (line 125)
                    INVOKESPECIAL java.lang.Object.<init> ()V
    constructor-execution(void org.springframework.core.MethodParameter.<init>(org.springframework.core.MethodParameter))
    |               ALOAD_0     // Lorg/springframework/core/MethodParameter; this   (line 50)
    |               ICONST_1
    |               PUTFIELD org.springframework.core.MethodParameter.nestingLevel I
    |               ALOAD_1     // Lorg/springframework/core/MethodParameter; original   (line 126)
    |               LDC "Original must not be null"
    |               INVOKESTATIC org.springframework.util.Assert.notNull (Ljava/lang/Object;Ljava/lang/String;)V
    |               ALOAD_0     // Lorg/springframework/core/MethodParameter; this   (line 127)
    |               ALOAD_1     // Lorg/springframework/core/MethodParameter; original
    |               GETFIELD org.springframework.core.MethodParameter.method Ljava/lang/reflect/Method;
    |               PUTFIELD org.springframework.core.MethodParameter.method Ljava/lang/reflect/Method;
    |               ALOAD_0     // Lorg/springframework/core/MethodParameter; this   (line 128)
    |               ALOAD_1     // Lorg/springframework/core/MethodParameter; original
    |               GETFIELD org.springframework.core.MethodParameter.constructor Ljava/lang/reflect/Constructor;
    |               PUTFIELD org.springframework.core.MethodParameter.constructor Ljava/lang/reflect/Constructor;
    |               ALOAD_0     // Lorg/springframework/core/MethodParameter; this   (line 129)
    |               ALOAD_1     // Lorg/springframework/core/MethodParameter; original
    |               GETFIELD org.springframework.core.MethodParameter.parameterIndex I
    |               PUTFIELD org.springframework.core.MethodParameter.parameterIndex I
    |               ALOAD_0     // Lorg/springframework/core/MethodParameter; this   (line 130)
    |               ALOAD_1     // Lorg/springframework/core/MethodParameter; original
    |               GETFIELD org.springframework.core.MethodParameter.nestingLevel I
    |               PUTFIELD org.springframework.core.MethodParameter.nestingLevel I
    |               ALOAD_0     // Lorg/springframework/core/MethodParameter; this   (line 131)
    |               ALOAD_1     // Lorg/springframework/core/MethodParameter; original
    |               GETFIELD org.springframework.core.MethodParameter.typeIndexesPerLevel Ljava/util/Map;
    |               PUTFIELD org.springframework.core.MethodParameter.typeIndexesPerLevel Ljava/util/Map;
    |               ALOAD_0     // Lorg/springframework/core/MethodParameter; this   (line 132)
    |               ALOAD_1     // Lorg/springframework/core/MethodParameter; original
    |               GETFIELD org.springframework.core.MethodParameter.containingClass Ljava/lang/Class;
    |               PUTFIELD org.springframework.core.MethodParameter.containingClass Ljava/lang/Class;
    |               ALOAD_0     // Lorg/springframework/core/MethodParameter; this   (line 133)
    |               ALOAD_1     // Lorg/springframework/core/MethodParameter; original
    |               GETFIELD org.springframework.core.MethodParameter.parameterType Ljava/lang/Class;
    |               PUTFIELD org.springframework.core.MethodParameter.parameterType Ljava/lang/Class;
    |               ALOAD_0     // Lorg/springframework/core/MethodParameter; this   (line 134)
    |               ALOAD_1     // Lorg/springframework/core/MethodParameter; original
    |               GETFIELD org.springframework.core.MethodParameter.genericParameterType Ljava/lang/reflect/Type;
    |               PUTFIELD org.springframework.core.MethodParameter.genericParameterType Ljava/lang/reflect/Type;
    |               ALOAD_0     // Lorg/springframework/core/MethodParameter; this   (line 135)
    |               ALOAD_1     // Lorg/springframework/core/MethodParameter; original
    |               GETFIELD org.springframework.core.MethodParameter.parameterAnnotations [Ljava/lang/annotation/Annotation;
    |               PUTFIELD org.springframework.core.MethodParameter.parameterAnnotations [Ljava/lang/annotation/Annotation;
    |               ALOAD_0     // Lorg/springframework/core/MethodParameter; this   (line 136)
    |               ALOAD_1     // Lorg/springframework/core/MethodParameter; original
    |               GETFIELD org.springframework.core.MethodParameter.parameterNameDiscoverer Lorg/springframework/core/ParameterNameDiscoverer;
    |               PUTFIELD org.springframework.core.MethodParameter.parameterNameDiscoverer Lorg/springframework/core/ParameterNameDiscoverer;
    |               ALOAD_0     // Lorg/springframework/core/MethodParameter; this   (line 137)
    |               ALOAD_1     // Lorg/springframework/core/MethodParameter; original
    |               GETFIELD org.springframework.core.MethodParameter.parameterName Ljava/lang/String;
    |               PUTFIELD org.springframework.core.MethodParameter.parameterName Ljava/lang/String;
    |               RETURN   (line 138)
    constructor-execution(void org.springframework.core.MethodParameter.<init>(org.springframework.core.MethodParameter))
  end public void <init>(org.springframework.core.MethodParameter)

  public java.lang.reflect.Method getMethod():
                    ALOAD_0     // Lorg/springframework/core/MethodParameter; this   (line 147)
                    GETFIELD org.springframework.core.MethodParameter.method Ljava/lang/reflect/Method;
                    ARETURN
  end public java.lang.reflect.Method getMethod()

  public java.lang.reflect.Constructor getConstructor():
                    ALOAD_0     // Lorg/springframework/core/MethodParameter; this   (line 156)
                    GETFIELD org.springframework.core.MethodParameter.constructor Ljava/lang/reflect/Constructor;
                    ARETURN
  end public java.lang.reflect.Constructor getConstructor()

  public java.lang.reflect.Member getMember():
                    ALOAD_0     // Lorg/springframework/core/MethodParameter; this   (line 167)
                    GETFIELD org.springframework.core.MethodParameter.method Ljava/lang/reflect/Method;
                    IFNULL L0
                    ALOAD_0     // Lorg/springframework/core/MethodParameter; this   (line 168)
                    GETFIELD org.springframework.core.MethodParameter.method Ljava/lang/reflect/Method;
                    ARETURN
                L0: ALOAD_0     // Lorg/springframework/core/MethodParameter; this   (line 171)
                    GETFIELD org.springframework.core.MethodParameter.constructor Ljava/lang/reflect/Constructor;
                    ARETURN
  end public java.lang.reflect.Member getMember()

  public java.lang.reflect.AnnotatedElement getAnnotatedElement():
                    ALOAD_0     // Lorg/springframework/core/MethodParameter; this   (line 183)
                    GETFIELD org.springframework.core.MethodParameter.method Ljava/lang/reflect/Method;
                    IFNULL L0
                    ALOAD_0     // Lorg/springframework/core/MethodParameter; this   (line 184)
                    GETFIELD org.springframework.core.MethodParameter.method Ljava/lang/reflect/Method;
                    ARETURN
                L0: ALOAD_0     // Lorg/springframework/core/MethodParameter; this   (line 187)
                    GETFIELD org.springframework.core.MethodParameter.constructor Ljava/lang/reflect/Constructor;
                    ARETURN
  end public java.lang.reflect.AnnotatedElement getAnnotatedElement()

  public Class getDeclaringClass():
                    ALOAD_0     // Lorg/springframework/core/MethodParameter; this   (line 195)
                    INVOKEVIRTUAL org.springframework.core.MethodParameter.getMember ()Ljava/lang/reflect/Member;
                    INVOKEINTERFACE java.lang.reflect.Member.getDeclaringClass ()Ljava/lang/Class;
                    ARETURN
  end public Class getDeclaringClass()

  public int getParameterIndex():
                    ALOAD_0     // Lorg/springframework/core/MethodParameter; this   (line 203)
                    GETFIELD org.springframework.core.MethodParameter.parameterIndex I
                    IRETURN
  end public int getParameterIndex()

  public void increaseNestingLevel():
                    ALOAD_0     // Lorg/springframework/core/MethodParameter; this   (line 211)
                    DUP
                    GETFIELD org.springframework.core.MethodParameter.nestingLevel I
                    ICONST_1
                    IADD
                    PUTFIELD org.springframework.core.MethodParameter.nestingLevel I
                    RETURN   (line 212)
  end public void increaseNestingLevel()

  public void decreaseNestingLevel():
                    ALOAD_0     // Lorg/springframework/core/MethodParameter; this   (line 219)
                    INVOKESPECIAL org.springframework.core.MethodParameter.getTypeIndexesPerLevel ()Ljava/util/Map;
                    ALOAD_0     // Lorg/springframework/core/MethodParameter; this
                    GETFIELD org.springframework.core.MethodParameter.nestingLevel I
                    INVOKESTATIC java.lang.Integer.valueOf (I)Ljava/lang/Integer;
                    INVOKEINTERFACE java.util.Map.remove (Ljava/lang/Object;)Ljava/lang/Object;
                    POP
                    ALOAD_0     // Lorg/springframework/core/MethodParameter; this   (line 220)
                    DUP
                    GETFIELD org.springframework.core.MethodParameter.nestingLevel I
                    ICONST_1
                    ISUB
                    PUTFIELD org.springframework.core.MethodParameter.nestingLevel I
                    RETURN   (line 221)
  end public void decreaseNestingLevel()

  public int getNestingLevel():
                    ALOAD_0     // Lorg/springframework/core/MethodParameter; this   (line 229)
                    GETFIELD org.springframework.core.MethodParameter.nestingLevel I
                    IRETURN
  end public int getNestingLevel()

  public void setTypeIndexForCurrentLevel(int):
                    ALOAD_0     // Lorg/springframework/core/MethodParameter; this   (line 239)
                    INVOKESPECIAL org.springframework.core.MethodParameter.getTypeIndexesPerLevel ()Ljava/util/Map;
                    ALOAD_0     // Lorg/springframework/core/MethodParameter; this
                    GETFIELD org.springframework.core.MethodParameter.nestingLevel I
                    INVOKESTATIC java.lang.Integer.valueOf (I)Ljava/lang/Integer;
                    ILOAD_1     // I typeIndex
                    INVOKESTATIC java.lang.Integer.valueOf (I)Ljava/lang/Integer;
                    INVOKEINTERFACE java.util.Map.put (Ljava/lang/Object;Ljava/lang/Object;)Ljava/lang/Object;
                    POP
                    RETURN   (line 240)
  end public void setTypeIndexForCurrentLevel(int)

  public Integer getTypeIndexForCurrentLevel():
                    ALOAD_0     // Lorg/springframework/core/MethodParameter; this   (line 249)
                    ALOAD_0     // Lorg/springframework/core/MethodParameter; this
                    GETFIELD org.springframework.core.MethodParameter.nestingLevel I
                    INVOKEVIRTUAL org.springframework.core.MethodParameter.getTypeIndexForLevel (I)Ljava/lang/Integer;
                    ARETURN
  end public Integer getTypeIndexForCurrentLevel()

  public Integer getTypeIndexForLevel(int):
                    ALOAD_0     // Lorg/springframework/core/MethodParameter; this   (line 259)
                    INVOKESPECIAL org.springframework.core.MethodParameter.getTypeIndexesPerLevel ()Ljava/util/Map;
                    ILOAD_1     // I nestingLevel
                    INVOKESTATIC java.lang.Integer.valueOf (I)Ljava/lang/Integer;
                    INVOKEINTERFACE java.util.Map.get (Ljava/lang/Object;)Ljava/lang/Object;
                    CHECKCAST java.lang.Integer
                    ARETURN
  end public Integer getTypeIndexForLevel(int)

  private java.util.Map getTypeIndexesPerLevel():
                    ALOAD_0     // Lorg/springframework/core/MethodParameter; this   (line 266)
                    GETFIELD org.springframework.core.MethodParameter.typeIndexesPerLevel Ljava/util/Map;
                    IFNONNULL L0
                    ALOAD_0     // Lorg/springframework/core/MethodParameter; this   (line 267)
                    NEW java.util.HashMap
                    DUP
                    ICONST_4
                    INVOKESPECIAL java.util.HashMap.<init> (I)V
                    PUTFIELD org.springframework.core.MethodParameter.typeIndexesPerLevel Ljava/util/Map;
                L0: ALOAD_0     // Lorg/springframework/core/MethodParameter; this   (line 269)
                    GETFIELD org.springframework.core.MethodParameter.typeIndexesPerLevel Ljava/util/Map;
                    ARETURN
  end private java.util.Map getTypeIndexesPerLevel()

  void setContainingClass(Class):
                    ALOAD_0     // Lorg/springframework/core/MethodParameter; this   (line 277)
                    ALOAD_1     // Ljava/lang/Class; containingClass
                    PUTFIELD org.springframework.core.MethodParameter.containingClass Ljava/lang/Class;
                    RETURN   (line 278)
  end void setContainingClass(Class)

  public Class getContainingClass():
                    ALOAD_0     // Lorg/springframework/core/MethodParameter; this   (line 281)
                    GETFIELD org.springframework.core.MethodParameter.containingClass Ljava/lang/Class;
                    IFNULL L0
                    ALOAD_0     // Lorg/springframework/core/MethodParameter; this
                    GETFIELD org.springframework.core.MethodParameter.containingClass Ljava/lang/Class;
                    GOTO L1
                L0: ALOAD_0     // Lorg/springframework/core/MethodParameter; this
                    INVOKEVIRTUAL org.springframework.core.MethodParameter.getDeclaringClass ()Ljava/lang/Class;
                L1: ARETURN
  end public Class getContainingClass()

  void setParameterType(Class):
                    ALOAD_0     // Lorg/springframework/core/MethodParameter; this   (line 288)
                    ALOAD_1     // Ljava/lang/Class; parameterType
                    PUTFIELD org.springframework.core.MethodParameter.parameterType Ljava/lang/Class;
                    RETURN   (line 289)
  end void setParameterType(Class)

  public Class getParameterType():
                    ALOAD_0     // Lorg/springframework/core/MethodParameter; this   (line 296)
                    GETFIELD org.springframework.core.MethodParameter.parameterType Ljava/lang/Class;
                    IFNONNULL L5
                    ALOAD_0     // Lorg/springframework/core/MethodParameter; this   (line 297)
                    GETFIELD org.springframework.core.MethodParameter.parameterIndex I
                    IFGE L2
                    ALOAD_0     // Lorg/springframework/core/MethodParameter; this   (line 298)
                    ALOAD_0     // Lorg/springframework/core/MethodParameter; this
                    GETFIELD org.springframework.core.MethodParameter.method Ljava/lang/reflect/Method;
                    IFNULL L0
                    ALOAD_0     // Lorg/springframework/core/MethodParameter; this
                    GETFIELD org.springframework.core.MethodParameter.method Ljava/lang/reflect/Method;
                    INVOKEVIRTUAL java.lang.reflect.Method.getReturnType ()Ljava/lang/Class;
                    GOTO L1
                L0: ACONST_NULL
                L1: PUTFIELD org.springframework.core.MethodParameter.parameterType Ljava/lang/Class;
                    GOTO L5
                L2: ALOAD_0     // Lorg/springframework/core/MethodParameter; this   (line 301)
                    ALOAD_0     // Lorg/springframework/core/MethodParameter; this
                    GETFIELD org.springframework.core.MethodParameter.method Ljava/lang/reflect/Method;
                    IFNULL L3
                    ALOAD_0     // Lorg/springframework/core/MethodParameter; this
                    GETFIELD org.springframework.core.MethodParameter.method Ljava/lang/reflect/Method;
                    INVOKEVIRTUAL java.lang.reflect.Method.getParameterTypes ()[Ljava/lang/Class;   (line 302)
                    ALOAD_0     // Lorg/springframework/core/MethodParameter; this
                    GETFIELD org.springframework.core.MethodParameter.parameterIndex I
                    AALOAD
                    GOTO L4
                L3: ALOAD_0     // Lorg/springframework/core/MethodParameter; this
                    GETFIELD org.springframework.core.MethodParameter.constructor Ljava/lang/reflect/Constructor;
                    INVOKEVIRTUAL java.lang.reflect.Constructor.getParameterTypes ()[Ljava/lang/Class;   (line 303)
                    ALOAD_0     // Lorg/springframework/core/MethodParameter; this
                    GETFIELD org.springframework.core.MethodParameter.parameterIndex I
                    AALOAD
                L4: PUTFIELD org.springframework.core.MethodParameter.parameterType Ljava/lang/Class;
                L5: ALOAD_0     // Lorg/springframework/core/MethodParameter; this   (line 306)
                    GETFIELD org.springframework.core.MethodParameter.parameterType Ljava/lang/Class;
                    ARETURN
  end public Class getParameterType()

  public java.lang.reflect.Type getGenericParameterType():
                    ALOAD_0     // Lorg/springframework/core/MethodParameter; this   (line 315)
                    GETFIELD org.springframework.core.MethodParameter.genericParameterType Ljava/lang/reflect/Type;
                    IFNONNULL L5
                    ALOAD_0     // Lorg/springframework/core/MethodParameter; this   (line 316)
                    GETFIELD org.springframework.core.MethodParameter.parameterIndex I
                    IFGE L2
                    ALOAD_0     // Lorg/springframework/core/MethodParameter; this   (line 317)
                    ALOAD_0     // Lorg/springframework/core/MethodParameter; this
                    GETFIELD org.springframework.core.MethodParameter.method Ljava/lang/reflect/Method;
                    IFNULL L0
                    ALOAD_0     // Lorg/springframework/core/MethodParameter; this
                    GETFIELD org.springframework.core.MethodParameter.method Ljava/lang/reflect/Method;
                    INVOKEVIRTUAL java.lang.reflect.Method.getGenericReturnType ()Ljava/lang/reflect/Type;
                    GOTO L1
                L0: ACONST_NULL
                L1: PUTFIELD org.springframework.core.MethodParameter.genericParameterType Ljava/lang/reflect/Type;
                    GOTO L5
                L2: ALOAD_0     // Lorg/springframework/core/MethodParameter; this   (line 320)
                    ALOAD_0     // Lorg/springframework/core/MethodParameter; this
                    GETFIELD org.springframework.core.MethodParameter.method Ljava/lang/reflect/Method;
                    IFNULL L3
                    ALOAD_0     // Lorg/springframework/core/MethodParameter; this
                    GETFIELD org.springframework.core.MethodParameter.method Ljava/lang/reflect/Method;
                    INVOKEVIRTUAL java.lang.reflect.Method.getGenericParameterTypes ()[Ljava/lang/reflect/Type;   (line 321)
                    ALOAD_0     // Lorg/springframework/core/MethodParameter; this
                    GETFIELD org.springframework.core.MethodParameter.parameterIndex I
                    AALOAD
                    GOTO L4
                L3: ALOAD_0     // Lorg/springframework/core/MethodParameter; this
                    GETFIELD org.springframework.core.MethodParameter.constructor Ljava/lang/reflect/Constructor;
                    INVOKEVIRTUAL java.lang.reflect.Constructor.getGenericParameterTypes ()[Ljava/lang/reflect/Type;   (line 322)
                    ALOAD_0     // Lorg/springframework/core/MethodParameter; this
                    GETFIELD org.springframework.core.MethodParameter.parameterIndex I
                    AALOAD
                L4: PUTFIELD org.springframework.core.MethodParameter.genericParameterType Ljava/lang/reflect/Type;
                L5: ALOAD_0     // Lorg/springframework/core/MethodParameter; this   (line 325)
                    GETFIELD org.springframework.core.MethodParameter.genericParameterType Ljava/lang/reflect/Type;
                    ARETURN
  end public java.lang.reflect.Type getGenericParameterType()

  public Class getNestedParameterType():
                    ALOAD_0     // Lorg/springframework/core/MethodParameter; this   (line 335)
                    GETFIELD org.springframework.core.MethodParameter.nestingLevel I
                    ICONST_1
                    IF_ICMPLE L7
                    ALOAD_0     // Lorg/springframework/core/MethodParameter; this   (line 336)
                    INVOKEVIRTUAL org.springframework.core.MethodParameter.getGenericParameterType ()Ljava/lang/reflect/Type;
                    ASTORE_1
                    ICONST_2   (line 337)
                    ISTORE_2
                L0: ILOAD_2     // I i
                    ALOAD_0     // Lorg/springframework/core/MethodParameter; this
                    GETFIELD org.springframework.core.MethodParameter.nestingLevel I
                    IF_ICMPGT L4
                    ALOAD_1     // Ljava/lang/reflect/Type; type   (line 338)
                    INSTANCEOF java.lang.reflect.ParameterizedType
                    IFEQ L3
                    ALOAD_1     // Ljava/lang/reflect/Type; type   (line 339)
                    CHECKCAST java.lang.reflect.ParameterizedType
                    INVOKEINTERFACE java.lang.reflect.ParameterizedType.getActualTypeArguments ()[Ljava/lang/reflect/Type;
                    ASTORE_3
                    ALOAD_0     // Lorg/springframework/core/MethodParameter; this   (line 340)
                    ILOAD_2     // I i
                    INVOKEVIRTUAL org.springframework.core.MethodParameter.getTypeIndexForLevel (I)Ljava/lang/Integer;
                    ASTORE 4
                    ALOAD_3     // [Ljava/lang/reflect/Type; args   (line 341)
                    ALOAD 4     // Ljava/lang/Integer; index
                    IFNULL L1
                    ALOAD 4     // Ljava/lang/Integer; index
                    INVOKEVIRTUAL java.lang.Integer.intValue ()I
                    GOTO L2
                L1: ALOAD_3     // [Ljava/lang/reflect/Type; args
                    ARRAYLENGTH
                    ICONST_1
                    ISUB
                L2: AALOAD
                    ASTORE_1     // Ljava/lang/reflect/Type; type
                L3: IINC_2 1     // I i   (line 337)
                    GOTO L0
                L4: ALOAD_1     // Ljava/lang/reflect/Type; type   (line 344)
                    INSTANCEOF java.lang.Class
                    IFEQ L5
                    ALOAD_1     // Ljava/lang/reflect/Type; type   (line 345)
                    CHECKCAST java.lang.Class
                    ARETURN
                L5: ALOAD_1     // Ljava/lang/reflect/Type; type   (line 347)
                    INSTANCEOF java.lang.reflect.ParameterizedType
                    IFEQ L6
                    ALOAD_1     // Ljava/lang/reflect/Type; type   (line 348)
                    CHECKCAST java.lang.reflect.ParameterizedType
                    INVOKEINTERFACE java.lang.reflect.ParameterizedType.getRawType ()Ljava/lang/reflect/Type;
                    ASTORE_2
                    ALOAD_2     // Ljava/lang/reflect/Type; arg   (line 349)
                    INSTANCEOF java.lang.Class
                    IFEQ L6
                    ALOAD_2     // Ljava/lang/reflect/Type; arg   (line 350)
                    CHECKCAST java.lang.Class
                    ARETURN
                L6: LDC java.lang.Object   (line 353)
                    ARETURN
                L7: ALOAD_0     // Lorg/springframework/core/MethodParameter; this   (line 356)
                    INVOKEVIRTUAL org.springframework.core.MethodParameter.getParameterType ()Ljava/lang/Class;
                    ARETURN
  end public Class getNestedParameterType()

  public java.lang.annotation.Annotation[] getMethodAnnotations():
                    ALOAD_0     // Lorg/springframework/core/MethodParameter; this   (line 364)
                    INVOKEVIRTUAL org.springframework.core.MethodParameter.getAnnotatedElement ()Ljava/lang/reflect/AnnotatedElement;
                    INVOKEINTERFACE java.lang.reflect.AnnotatedElement.getAnnotations ()[Ljava/lang/annotation/Annotation;
                    ARETURN
  end public java.lang.annotation.Annotation[] getMethodAnnotations()

  public java.lang.annotation.Annotation getMethodAnnotation(Class):
                    ALOAD_0     // Lorg/springframework/core/MethodParameter; this   (line 373)
                    INVOKEVIRTUAL org.springframework.core.MethodParameter.getAnnotatedElement ()Ljava/lang/reflect/AnnotatedElement;
                    ALOAD_1     // Ljava/lang/Class; annotationType
                    INVOKEINTERFACE java.lang.reflect.AnnotatedElement.getAnnotation (Ljava/lang/Class;)Ljava/lang/annotation/Annotation;
                    ARETURN
  end public java.lang.annotation.Annotation getMethodAnnotation(Class)

  public java.lang.annotation.Annotation[] getParameterAnnotations():
                    ALOAD_0     // Lorg/springframework/core/MethodParameter; this   (line 380)
                    GETFIELD org.springframework.core.MethodParameter.parameterAnnotations [Ljava/lang/annotation/Annotation;
                    IFNONNULL L3
                    ALOAD_0     // Lorg/springframework/core/MethodParameter; this   (line 381)
                    GETFIELD org.springframework.core.MethodParameter.method Ljava/lang/reflect/Method;
                    IFNULL L0
                    ALOAD_0     // Lorg/springframework/core/MethodParameter; this
                    GETFIELD org.springframework.core.MethodParameter.method Ljava/lang/reflect/Method;
                    INVOKEVIRTUAL java.lang.reflect.Method.getParameterAnnotations ()[[Ljava/lang/annotation/Annotation;   (line 382)
                    GOTO L1
                L0: ALOAD_0     // Lorg/springframework/core/MethodParameter; this
                    GETFIELD org.springframework.core.MethodParameter.constructor Ljava/lang/reflect/Constructor;
                    INVOKEVIRTUAL java.lang.reflect.Constructor.getParameterAnnotations ()[[Ljava/lang/annotation/Annotation;
                L1: ASTORE_1
                    ALOAD_0     // Lorg/springframework/core/MethodParameter; this   (line 383)
                    GETFIELD org.springframework.core.MethodParameter.parameterIndex I
                    IFLT L2
                    ALOAD_0     // Lorg/springframework/core/MethodParameter; this
                    GETFIELD org.springframework.core.MethodParameter.parameterIndex I
                    ALOAD_1     // [[Ljava/lang/annotation/Annotation; annotationArray
                    ARRAYLENGTH
                    IF_ICMPGE L2
                    ALOAD_0     // Lorg/springframework/core/MethodParameter; this   (line 384)
                    ALOAD_1     // [[Ljava/lang/annotation/Annotation; annotationArray
                    ALOAD_0     // Lorg/springframework/core/MethodParameter; this
                    GETFIELD org.springframework.core.MethodParameter.parameterIndex I
                    AALOAD
                    PUTFIELD org.springframework.core.MethodParameter.parameterAnnotations [Ljava/lang/annotation/Annotation;
                    GOTO L3
                L2: ALOAD_0     // Lorg/springframework/core/MethodParameter; this   (line 387)
                    ICONST_0
                    ANEWARRAY java.lang.annotation.Annotation
                    PUTFIELD org.springframework.core.MethodParameter.parameterAnnotations [Ljava/lang/annotation/Annotation;
                L3: ALOAD_0     // Lorg/springframework/core/MethodParameter; this   (line 390)
                    GETFIELD org.springframework.core.MethodParameter.parameterAnnotations [Ljava/lang/annotation/Annotation;
                    ARETURN
  end public java.lang.annotation.Annotation[] getParameterAnnotations()

  public java.lang.annotation.Annotation getParameterAnnotation(Class):
                    ALOAD_0     // Lorg/springframework/core/MethodParameter; this   (line 400)
                    INVOKEVIRTUAL org.springframework.core.MethodParameter.getParameterAnnotations ()[Ljava/lang/annotation/Annotation;
                    ASTORE_2
                    ALOAD_2     // [Ljava/lang/annotation/Annotation; anns   (line 401)
                    ASTORE_3
                    ALOAD_3
                    ARRAYLENGTH
                    ISTORE 4
                    ICONST_0
                    ISTORE 5
                L0: ILOAD 5
                    ILOAD 4
                    IF_ICMPGE L2
                    ALOAD_3
                    ILOAD 5
                    AALOAD
                    ASTORE 6
                    ALOAD_1     // Ljava/lang/Class; annotationType   (line 402)
                    ALOAD 6     // Ljava/lang/annotation/Annotation; ann
                    INVOKEVIRTUAL java.lang.Class.isInstance (Ljava/lang/Object;)Z
                    IFEQ L1
                    ALOAD 6     // Ljava/lang/annotation/Annotation; ann   (line 403)
                    ARETURN
                L1: IINC 5 1   (line 401)
                    GOTO L0
                L2: ACONST_NULL   (line 406)
                    ARETURN
  end public java.lang.annotation.Annotation getParameterAnnotation(Class)

  public boolean hasParameterAnnotations():
                    ALOAD_0     // Lorg/springframework/core/MethodParameter; this   (line 413)
                    INVOKEVIRTUAL org.springframework.core.MethodParameter.getParameterAnnotations ()[Ljava/lang/annotation/Annotation;
                    ARRAYLENGTH
                    IFEQ L0
                    ICONST_1
                    GOTO L1
                L0: ICONST_0
                L1: IRETURN
  end public boolean hasParameterAnnotations()

  public boolean hasParameterAnnotation(Class):
                    ALOAD_0     // Lorg/springframework/core/MethodParameter; this   (line 420)
                    ALOAD_1     // Ljava/lang/Class; annotationType
                    INVOKEVIRTUAL org.springframework.core.MethodParameter.getParameterAnnotation (Ljava/lang/Class;)Ljava/lang/annotation/Annotation;
                    IFNULL L0
                    ICONST_1
                    GOTO L1
                L0: ICONST_0
                L1: IRETURN
  end public boolean hasParameterAnnotation(Class)

  public void initParameterNameDiscovery(org.springframework.core.ParameterNameDiscoverer):
                    ALOAD_0     // Lorg/springframework/core/MethodParameter; this   (line 430)
                    ALOAD_1     // Lorg/springframework/core/ParameterNameDiscoverer; parameterNameDiscoverer
                    PUTFIELD org.springframework.core.MethodParameter.parameterNameDiscoverer Lorg/springframework/core/ParameterNameDiscoverer;
                    RETURN   (line 431)
  end public void initParameterNameDiscovery(org.springframework.core.ParameterNameDiscoverer)

  public String getParameterName():
                    ALOAD_0     // Lorg/springframework/core/MethodParameter; this   (line 441)
                    GETFIELD org.springframework.core.MethodParameter.parameterNameDiscoverer Lorg/springframework/core/ParameterNameDiscoverer;
                    ASTORE_1
                    ALOAD_1     // Lorg/springframework/core/ParameterNameDiscoverer; discoverer   (line 442)
                    IFNULL L3
                    ALOAD_0     // Lorg/springframework/core/MethodParameter; this   (line 443)
                    GETFIELD org.springframework.core.MethodParameter.method Ljava/lang/reflect/Method;
                    IFNULL L0
                    ALOAD_1     // Lorg/springframework/core/ParameterNameDiscoverer; discoverer
                    ALOAD_0     // Lorg/springframework/core/MethodParameter; this
                    GETFIELD org.springframework.core.MethodParameter.method Ljava/lang/reflect/Method;
                    INVOKEINTERFACE org.springframework.core.ParameterNameDiscoverer.getParameterNames (Ljava/lang/reflect/Method;)[Ljava/lang/String;   (line 444)
                    GOTO L1
                L0: ALOAD_1     // Lorg/springframework/core/ParameterNameDiscoverer; discoverer
                    ALOAD_0     // Lorg/springframework/core/MethodParameter; this
                    GETFIELD org.springframework.core.MethodParameter.constructor Ljava/lang/reflect/Constructor;
                    INVOKEINTERFACE org.springframework.core.ParameterNameDiscoverer.getParameterNames (Ljava/lang/reflect/Constructor;)[Ljava/lang/String;
                L1: ASTORE_2
                    ALOAD_2     // [Ljava/lang/String; parameterNames   (line 445)
                    IFNULL L2
                    ALOAD_0     // Lorg/springframework/core/MethodParameter; this   (line 446)
                    ALOAD_2     // [Ljava/lang/String; parameterNames
                    ALOAD_0     // Lorg/springframework/core/MethodParameter; this
                    GETFIELD org.springframework.core.MethodParameter.parameterIndex I
                    AALOAD
                    PUTFIELD org.springframework.core.MethodParameter.parameterName Ljava/lang/String;
                L2: ALOAD_0     // Lorg/springframework/core/MethodParameter; this   (line 448)
                    ACONST_NULL
                    PUTFIELD org.springframework.core.MethodParameter.parameterNameDiscoverer Lorg/springframework/core/ParameterNameDiscoverer;
                L3: ALOAD_0     // Lorg/springframework/core/MethodParameter; this   (line 450)
                    GETFIELD org.springframework.core.MethodParameter.parameterName Ljava/lang/String;
                    ARETURN
  end public String getParameterName()

  public boolean equals(Object):
                    ALOAD_0     // Lorg/springframework/core/MethodParameter; this   (line 456)
                    ALOAD_1     // Ljava/lang/Object; other
                    IF_ACMPNE L0
                    ICONST_1   (line 457)
                    IRETURN
                L0: ALOAD_1     // Ljava/lang/Object; other   (line 459)
                    INSTANCEOF org.springframework.core.MethodParameter
                    IFNE L1
                    ICONST_0   (line 460)
                    IRETURN
                L1: ALOAD_1     // Ljava/lang/Object; other   (line 462)
                    CHECKCAST org.springframework.core.MethodParameter
                    ASTORE_2
                    ALOAD_0     // Lorg/springframework/core/MethodParameter; this   (line 463)
                    GETFIELD org.springframework.core.MethodParameter.parameterIndex I
                    ALOAD_2     // Lorg/springframework/core/MethodParameter; otherParam
                    GETFIELD org.springframework.core.MethodParameter.parameterIndex I
                    IF_ICMPNE L2
                    ALOAD_0     // Lorg/springframework/core/MethodParameter; this
                    INVOKEVIRTUAL org.springframework.core.MethodParameter.getMember ()Ljava/lang/reflect/Member;
                    ALOAD_2     // Lorg/springframework/core/MethodParameter; otherParam
                    INVOKEVIRTUAL org.springframework.core.MethodParameter.getMember ()Ljava/lang/reflect/Member;
                    INVOKEVIRTUAL java.lang.Object.equals (Ljava/lang/Object;)Z
                    IFEQ L2
                    ICONST_1
                    GOTO L3
                L2: ICONST_0
                L3: IRETURN
  end public boolean equals(Object)

  public int hashCode():
                    ALOAD_0     // Lorg/springframework/core/MethodParameter; this   (line 468)
                    INVOKEVIRTUAL org.springframework.core.MethodParameter.getMember ()Ljava/lang/reflect/Member;
                    INVOKEVIRTUAL java.lang.Object.hashCode ()I
                    BIPUSH 31
                    IMUL
                    ALOAD_0     // Lorg/springframework/core/MethodParameter; this
                    GETFIELD org.springframework.core.MethodParameter.parameterIndex I
                    IADD
                    IRETURN
  end public int hashCode()

  public static org.springframework.core.MethodParameter forMethodOrConstructor(Object, int):
                    ALOAD_0     // Ljava/lang/Object; methodOrConstructor   (line 481)
                    INSTANCEOF java.lang.reflect.Method
                    IFEQ L0
                    NEW org.springframework.core.MethodParameter   (line 482)
                    DUP
                    ALOAD_0     // Ljava/lang/Object; methodOrConstructor
                    CHECKCAST java.lang.reflect.Method
                    ILOAD_1     // I parameterIndex
                    INVOKESPECIAL org.springframework.core.MethodParameter.<init> (Ljava/lang/reflect/Method;I)V
                    ARETURN
                L0: ALOAD_0     // Ljava/lang/Object; methodOrConstructor   (line 484)
                    INSTANCEOF java.lang.reflect.Constructor
                    IFEQ L1
                    NEW org.springframework.core.MethodParameter   (line 485)
                    DUP
                    ALOAD_0     // Ljava/lang/Object; methodOrConstructor
                    CHECKCAST java.lang.reflect.Constructor
                    ILOAD_1     // I parameterIndex
                    INVOKESPECIAL org.springframework.core.MethodParameter.<init> (Ljava/lang/reflect/Constructor;I)V
                    ARETURN
                L1: NEW java.lang.IllegalArgumentException   (line 488)
                    DUP
                    NEW java.lang.StringBuilder
                    DUP
                    INVOKESPECIAL java.lang.StringBuilder.<init> ()V
                    LDC "Given object ["
                    INVOKEVIRTUAL java.lang.StringBuilder.append (Ljava/lang/String;)Ljava/lang/StringBuilder;
                    ALOAD_0     // Ljava/lang/Object; methodOrConstructor
                    INVOKEVIRTUAL java.lang.StringBuilder.append (Ljava/lang/Object;)Ljava/lang/StringBuilder;
                    LDC "] is neither a Method nor a Constructor"
                    INVOKEVIRTUAL java.lang.StringBuilder.append (Ljava/lang/String;)Ljava/lang/StringBuilder;
                    INVOKEVIRTUAL java.lang.StringBuilder.toString ()Ljava/lang/String;
                    INVOKESPECIAL java.lang.IllegalArgumentException.<init> (Ljava/lang/String;)V
                    ATHROW
  end public static org.springframework.core.MethodParameter forMethodOrConstructor(Object, int)

end public class org.springframework.core.MethodParameter
 -- (NullPointerException) null
null
java.lang.NullPointerException
	at org.aspectj.weaver.UnresolvedType.forSignature(UnresolvedType.java:384)
	at org.aspectj.weaver.bcel.BcelObjectType.getDeclaredInterfaces(BcelObjectType.java:275)
	at org.aspectj.weaver.ReferenceType.getDeclaredInterfaces(ReferenceType.java:626)
	at org.aspectj.weaver.ResolvedType.getDirectSupertypes(ResolvedType.java:82)
	at org.aspectj.weaver.patterns.TypePattern.matchesSubtypes(TypePattern.java:201)
	at org.aspectj.weaver.patterns.TypePattern.matchesSubtypes(TypePattern.java:203)
	at org.aspectj.weaver.patterns.TypePattern.matchesSubtypes(TypePattern.java:183)
	at org.aspectj.weaver.patterns.ExactTypePattern.matchesSubtypes(ExactTypePattern.java:74)
	at org.aspectj.weaver.patterns.TypePattern.matchesStatically(TypePattern.java:130)
	at org.aspectj.weaver.patterns.OrTypePattern.matchesStatically(OrTypePattern.java:76)
	at org.aspectj.weaver.patterns.SignaturePattern.matchesExactlyMethod(SignaturePattern.java:505)
	at org.aspectj.weaver.patterns.SignaturePattern.matchesExactly(SignaturePattern.java:360)
	at org.aspectj.weaver.patterns.SignaturePattern.matches(SignaturePattern.java:320)
	at org.aspectj.weaver.patterns.KindedPointcut.matchInternal(KindedPointcut.java:202)
	at org.aspectj.weaver.patterns.Pointcut.match(Pointcut.java:137)
	at org.aspectj.weaver.patterns.AndPointcut.matchInternal(AndPointcut.java:51)
	at org.aspectj.weaver.patterns.Pointcut.match(Pointcut.java:137)
	at org.aspectj.weaver.patterns.OrPointcut.matchInternal(OrPointcut.java:54)
	at org.aspectj.weaver.patterns.Pointcut.match(Pointcut.java:137)
	at org.aspectj.weaver.ShadowMunger.match(ShadowMunger.java:113)
	at org.aspectj.weaver.Advice.match(Advice.java:109)
	at org.aspectj.weaver.bcel.BcelAdvice.match(BcelAdvice.java:149)
	at org.aspectj.weaver.bcel.BcelClassWeaver.match(BcelClassWeaver.java:3173)
	at org.aspectj.weaver.bcel.BcelClassWeaver.match(BcelClassWeaver.java:2565)
	at org.aspectj.weaver.bcel.BcelClassWeaver.weave(BcelClassWeaver.java:480)
	at org.aspectj.weaver.bcel.BcelClassWeaver.weave(BcelClassWeaver.java:99)
	at org.aspectj.weaver.bcel.BcelWeaver.weave(BcelWeaver.java:1694)
	at org.aspectj.weaver.bcel.BcelWeaver.weaveWithoutDump(BcelWeaver.java:1638)
	at org.aspectj.weaver.bcel.BcelWeaver.weaveAndNotify(BcelWeaver.java:1401)
	at org.aspectj.weaver.bcel.BcelWeaver.weave(BcelWeaver.java:1187)
	at org.aspectj.weaver.tools.WeavingAdaptor.getWovenBytes(WeavingAdaptor.java:472)
	at org.aspectj.weaver.tools.WeavingAdaptor.weaveClass(WeavingAdaptor.java:323)
	at org.aspectj.weaver.loadtime.Aj.preProcess(Aj.java:99)
	at org.aspectj.weaver.loadtime.ClassPreProcessorAgentAdapter.transform(ClassPreProcessorAgentAdapter.java:54)
	at org.springframework.context.weaving.AspectJWeavingEnabler$AspectJClassBypassingClassFileTransformer.transform(AspectJWeavingEnabler.java:108)
	at org.springframework.instrument.classloading.InstrumentationLoadTimeWeaver$FilteringClassFileTransformer.transform(InstrumentationLoadTimeWeaver.java:184)
	at sun.instrument.TransformerManager.transform(Unknown Source)
	at sun.instrument.InstrumentationImpl.transform(Unknown Source)
	at java.lang.ClassLoader.defineClass1(Native Method)
	at java.lang.ClassLoader.defineClass(Unknown Source)
	at java.security.SecureClassLoader.defineClass(Unknown Source)
	at java.net.URLClassLoader.defineClass(Unknown Source)
	at java.net.URLClassLoader.access$100(Unknown Source)
	at java.net.URLClassLoader$1.run(Unknown Source)
	at java.net.URLClassLoader$1.run(Unknown Source)
	at java.security.AccessController.doPrivileged(Native Method)
	at java.net.URLClassLoader.findClass(Unknown Source)
	at java.lang.ClassLoader.loadClass(Unknown Source)
	at sun.misc.Launcher$AppClassLoader.loadClass(Unknown Source)
	at java.lang.ClassLoader.loadClass(Unknown Source)
	at org.springframework.beans.GenericTypeAwarePropertyDescriptor.<init>(GenericTypeAwarePropertyDescriptor.java:101)
	at org.springframework.beans.CachedIntrospectionResults.buildGenericTypeAwarePropertyDescriptor(CachedIntrospectionResults.java:348)
	at org.springframework.beans.CachedIntrospectionResults.<init>(CachedIntrospectionResults.java:302)
	at org.springframework.beans.CachedIntrospectionResults.forClass(CachedIntrospectionResults.java:189)
	at org.springframework.beans.BeanWrapperImpl.getCachedIntrospectionResults(BeanWrapperImpl.java:328)
	at org.springframework.beans.BeanWrapperImpl.getPropertyDescriptors(BeanWrapperImpl.java:336)
	at org.springframework.beans.factory.support.AbstractAutowireCapableBeanFactory.filterPropertyDescriptorsForDependencyCheck(AbstractAutowireCapableBeanFactory.java:1364)
	at org.springframework.beans.factory.support.AbstractAutowireCapableBeanFactory.filterPropertyDescriptorsForDependencyCheck(AbstractAutowireCapableBeanFactory.java:1343)
	at org.springframework.beans.factory.support.AbstractAutowireCapableBeanFactory.populateBean(AbstractAutowireCapableBeanFactory.java:1205)
	at org.springframework.beans.factory.support.AbstractAutowireCapableBeanFactory.doCreateBean(AbstractAutowireCapableBeanFactory.java:537)
	at org.springframework.beans.factory.support.AbstractAutowireCapableBeanFactory.createBean(AbstractAutowireCapableBeanFactory.java:476)
	at org.springframework.beans.factory.support.AbstractBeanFactory$1.getObject(AbstractBeanFactory.java:303)
	at org.springframework.beans.factory.support.DefaultSingletonBeanRegistry.getSingleton(DefaultSingletonBeanRegistry.java:230)
	at org.springframework.beans.factory.support.AbstractBeanFactory.doGetBean(AbstractBeanFactory.java:299)
	at org.springframework.beans.factory.support.AbstractBeanFactory.getBean(AbstractBeanFactory.java:194)
	at org.springframework.beans.factory.support.DefaultListableBeanFactory.preInstantiateSingletons(DefaultListableBeanFactory.java:755)
	at org.springframework.context.support.AbstractApplicationContext.finishBeanFactoryInitialization(AbstractApplicationContext.java:757)
	at org.springframework.context.support.AbstractApplicationContext.refresh(AbstractApplicationContext.java:480)
	at org.springframework.context.support.ClassPathXmlApplicationContext.<init>(ClassPathXmlApplicationContext.java:139)
	at org.springframework.context.support.ClassPathXmlApplicationContext.<init>(ClassPathXmlApplicationContext.java:93)
	at com.springExemple.presentation.Presentation2.main(Presentation2.java:13)

error can't determine annotations of missing type org.springframework.transaction.annotation.Transactional
when weaving type org.springframework.core.GenericTypeResolver
when weaving classes 
when weaving 
 [Xlint:cantFindType]
abort trouble in: 
public abstract class org.springframework.core.GenericTypeResolver extends java.lang.Object:
  private static final java.util.Map typeVariableCache [Signature(Ljava/util/Map<Ljava/lang/Class<*>;Ljava/util/Map<Ljava/lang/reflect/TypeVariable;Ljava/lang/reflect/Type;>;>;)]
  public void <init>():
                    ALOAD_0     // Lorg/springframework/core/GenericTypeResolver; this   (line 44)
                    INVOKESPECIAL java.lang.Object.<init> ()V
    constructor-execution(void org.springframework.core.GenericTypeResolver.<init>())
    |               RETURN   (line 309)
    constructor-execution(void org.springframework.core.GenericTypeResolver.<init>())
  end public void <init>()

  public static java.lang.reflect.Type getTargetType(org.springframework.core.MethodParameter):
                    ALOAD_0     // Lorg/springframework/core/MethodParameter; methodParam   (line 60)
                    LDC "MethodParameter must not be null"
                    INVOKESTATIC org.springframework.util.Assert.notNull (Ljava/lang/Object;Ljava/lang/String;)V
                    ALOAD_0     // Lorg/springframework/core/MethodParameter; methodParam   (line 61)
                    INVOKEVIRTUAL org.springframework.core.MethodParameter.getGenericParameterType ()Ljava/lang/reflect/Type;
                    ARETURN
  end public static java.lang.reflect.Type getTargetType(org.springframework.core.MethodParameter)

  public static Class resolveParameterType(org.springframework.core.MethodParameter, Class):
                    ALOAD_0     // Lorg/springframework/core/MethodParameter; methodParam   (line 71)
                    LDC "MethodParameter must not be null"
                    INVOKESTATIC org.springframework.util.Assert.notNull (Ljava/lang/Object;Ljava/lang/String;)V
                    ALOAD_1     // Ljava/lang/Class; clazz   (line 72)
                    LDC "Class must not be null"
                    INVOKESTATIC org.springframework.util.Assert.notNull (Ljava/lang/Object;Ljava/lang/String;)V
                    ALOAD_0     // Lorg/springframework/core/MethodParameter; methodParam   (line 73)
                    ALOAD_1     // Ljava/lang/Class; clazz
                    INVOKEVIRTUAL org.springframework.core.MethodParameter.setContainingClass (Ljava/lang/Class;)V
                    ALOAD_0     // Lorg/springframework/core/MethodParameter; methodParam   (line 74)
                    ALOAD_0     // Lorg/springframework/core/MethodParameter; methodParam
                    INVOKESTATIC org.springframework.core.ResolvableType.forMethodParameter (Lorg/springframework/core/MethodParameter;)Lorg/springframework/core/ResolvableType;
                    INVOKEVIRTUAL org.springframework.core.ResolvableType.resolve ()Ljava/lang/Class;
                    INVOKEVIRTUAL org.springframework.core.MethodParameter.setParameterType (Ljava/lang/Class;)V
                    ALOAD_0     // Lorg/springframework/core/MethodParameter; methodParam   (line 75)
                    INVOKEVIRTUAL org.springframework.core.MethodParameter.getParameterType ()Ljava/lang/Class;
                    ARETURN
  end public static Class resolveParameterType(org.springframework.core.MethodParameter, Class)

  public static Class resolveReturnType(java.lang.reflect.Method, Class):
                    ALOAD_0     // Ljava/lang/reflect/Method; method   (line 87)
                    LDC "Method must not be null"
                    INVOKESTATIC org.springframework.util.Assert.notNull (Ljava/lang/Object;Ljava/lang/String;)V
                    ALOAD_1     // Ljava/lang/Class; clazz   (line 88)
                    LDC "Class must not be null"
                    INVOKESTATIC org.springframework.util.Assert.notNull (Ljava/lang/Object;Ljava/lang/String;)V
                    ALOAD_0     // Ljava/lang/reflect/Method; method   (line 89)
                    ALOAD_1     // Ljava/lang/Class; clazz
                    INVOKESTATIC org.springframework.core.ResolvableType.forMethodReturnType (Ljava/lang/reflect/Method;Ljava/lang/Class;)Lorg/springframework/core/ResolvableType;
                    ALOAD_0     // Ljava/lang/reflect/Method; method
                    INVOKEVIRTUAL java.lang.reflect.Method.getReturnType ()Ljava/lang/Class;
                    INVOKEVIRTUAL org.springframework.core.ResolvableType.resolve (Ljava/lang/Class;)Ljava/lang/Class;
                    ARETURN
  end public static Class resolveReturnType(java.lang.reflect.Method, Class)

  public static Class resolveReturnTypeForGenericMethod(java.lang.reflect.Method, Object[], ClassLoader):
                    ALOAD_0     // Ljava/lang/reflect/Method; method   (line 125)
                    LDC "Method must not be null"
                    INVOKESTATIC org.springframework.util.Assert.notNull (Ljava/lang/Object;Ljava/lang/String;)V
                    ALOAD_1     // [Ljava/lang/Object; args   (line 126)
                    LDC "Argument array must not be null"
                    INVOKESTATIC org.springframework.util.Assert.notNull (Ljava/lang/Object;Ljava/lang/String;)V
                    ALOAD_0     // Ljava/lang/reflect/Method; method   (line 128)
                    INVOKEVIRTUAL java.lang.reflect.Method.getTypeParameters ()[Ljava/lang/reflect/TypeVariable;
                    ASTORE_3
                    ALOAD_0     // Ljava/lang/reflect/Method; method   (line 129)
                    INVOKEVIRTUAL java.lang.reflect.Method.getGenericReturnType ()Ljava/lang/reflect/Type;
                    ASTORE 4
                    ALOAD_0     // Ljava/lang/reflect/Method; method   (line 130)
                    INVOKEVIRTUAL java.lang.reflect.Method.getGenericParameterTypes ()[Ljava/lang/reflect/Type;
                    ASTORE 5
                    ALOAD_3     // [Ljava/lang/reflect/TypeVariable; declaredTypeVariables   (line 133)
                    ARRAYLENGTH
                    IFNE L0
                    ALOAD_0     // Ljava/lang/reflect/Method; method   (line 134)
                    INVOKEVIRTUAL java.lang.reflect.Method.getReturnType ()Ljava/lang/Class;
                    ARETURN
                L0: ALOAD_1     // [Ljava/lang/Object; args   (line 139)
                    ARRAYLENGTH
                    ALOAD 5     // [Ljava/lang/reflect/Type; methodArgumentTypes
                    ARRAYLENGTH
                    IF_ICMPGE L1
                    ACONST_NULL   (line 140)
                    ARETURN
                L1: ICONST_0   (line 145)
                    ISTORE 6
                    ALOAD_3     // [Ljava/lang/reflect/TypeVariable; declaredTypeVariables   (line 146)
                    ASTORE 7
                    ALOAD 7
                    ARRAYLENGTH
                    ISTORE 8
                    ICONST_0
                    ISTORE 9
                L2: ILOAD 9
                    ILOAD 8
                    IF_ICMPGE L4
                    ALOAD 7
                    ILOAD 9
                    AALOAD
                    ASTORE 10
                    ALOAD 10     // Ljava/lang/reflect/TypeVariable; currentTypeVariable   (line 147)
                    ALOAD 4     // Ljava/lang/reflect/Type; genericReturnType
                    INVOKEVIRTUAL java.lang.Object.equals (Ljava/lang/Object;)Z
                    IFEQ L3
                    ICONST_1   (line 148)
                    ISTORE 6     // Z locallyDeclaredTypeVariableMatchesReturnType
                    GOTO L4   (line 149)
                L3: IINC 9 1   (line 146)
                    GOTO L2
                L4: ILOAD 6     // Z locallyDeclaredTypeVariableMatchesReturnType   (line 153)
                    IFEQ L12
                    ICONST_0   (line 154)
                    ISTORE 7
                L5: ILOAD 7     // I i
                    ALOAD 5     // [Ljava/lang/reflect/Type; methodArgumentTypes
                    ARRAYLENGTH
                    IF_ICMPGE L12
                    ALOAD 5     // [Ljava/lang/reflect/Type; methodArgumentTypes   (line 155)
                    ILOAD 7     // I i
                    AALOAD
                    ASTORE 8
                    ALOAD 8     // Ljava/lang/reflect/Type; currentMethodArgumentType   (line 156)
                    ALOAD 4     // Ljava/lang/reflect/Type; genericReturnType
                    INVOKEVIRTUAL java.lang.Object.equals (Ljava/lang/Object;)Z
                    IFEQ L6
                    ALOAD_1     // [Ljava/lang/Object; args   (line 157)
                    ILOAD 7     // I i
                    AALOAD
                    INVOKEVIRTUAL java.lang.Object.getClass ()Ljava/lang/Class;
                    ARETURN
                L6: ALOAD 8     // Ljava/lang/reflect/Type; currentMethodArgumentType   (line 159)
                    INSTANCEOF java.lang.reflect.ParameterizedType
                    IFEQ L11
                    ALOAD 8     // Ljava/lang/reflect/Type; currentMethodArgumentType   (line 160)
                    CHECKCAST java.lang.reflect.ParameterizedType
                    ASTORE 9
                    ALOAD 9     // Ljava/lang/reflect/ParameterizedType; parameterizedType   (line 161)
                    INVOKEINTERFACE java.lang.reflect.ParameterizedType.getActualTypeArguments ()[Ljava/lang/reflect/Type;
                    ASTORE 10
                    ALOAD 10     // [Ljava/lang/reflect/Type; actualTypeArguments   (line 162)
                    ASTORE 11
                    ALOAD 11
                    ARRAYLENGTH
                    ISTORE 12
                    ICONST_0
                    ISTORE 13
                L7: ILOAD 13
                    ILOAD 12
                    IF_ICMPGE L11
                    ALOAD 11
                    ILOAD 13
                    AALOAD
                    ASTORE 14
                    ALOAD 14     // Ljava/lang/reflect/Type; typeArg   (line 163)
                    ALOAD 4     // Ljava/lang/reflect/Type; genericReturnType
                    INVOKEVIRTUAL java.lang.Object.equals (Ljava/lang/Object;)Z
                    IFEQ L10
                    ALOAD_1     // [Ljava/lang/Object; args   (line 164)
                    ILOAD 7     // I i
                    AALOAD
                    ASTORE 15
                    ALOAD 15     // Ljava/lang/Object; arg   (line 165)
                    INSTANCEOF java.lang.Class
                    IFEQ L8
                    ALOAD 15     // Ljava/lang/Object; arg   (line 166)
                    CHECKCAST java.lang.Class
                    ARETURN
                L8: ALOAD 15     // Ljava/lang/Object; arg   (line 168)
                    INSTANCEOF java.lang.String
                    IFEQ L9
                    ALOAD_2     // Ljava/lang/ClassLoader; classLoader
                    IFNULL L9
    catch java.lang.ClassNotFoundException -> E0
    |               ALOAD_2     // Ljava/lang/ClassLoader; classLoader   (line 170)
    |               ALOAD 15     // Ljava/lang/Object; arg
    |               CHECKCAST java.lang.String
    |               INVOKEVIRTUAL java.lang.ClassLoader.loadClass (Ljava/lang/String;)Ljava/lang/Class;
    catch java.lang.ClassNotFoundException -> E0
                    ARETURN
                E0: ASTORE 16   (line 172)
                    NEW java.lang.IllegalStateException   (line 173)
                    DUP
                    NEW java.lang.StringBuilder
                    DUP
                    INVOKESPECIAL java.lang.StringBuilder.<init> ()V
                    LDC "Could not resolve specific class name argument ["
                    INVOKEVIRTUAL java.lang.StringBuilder.append (Ljava/lang/String;)Ljava/lang/StringBuilder;
                    ALOAD 15     // Ljava/lang/Object; arg
                    INVOKEVIRTUAL java.lang.StringBuilder.append (Ljava/lang/Object;)Ljava/lang/StringBuilder;
                    LDC "]"
                    INVOKEVIRTUAL java.lang.StringBuilder.append (Ljava/lang/String;)Ljava/lang/StringBuilder;
                    INVOKEVIRTUAL java.lang.StringBuilder.toString ()Ljava/lang/String;
                    ALOAD 16     // Ljava/lang/ClassNotFoundException; ex
                    INVOKESPECIAL java.lang.IllegalStateException.<init> (Ljava/lang/String;Ljava/lang/Throwable;)V
                    ATHROW
                L9: ALOAD_0     // Ljava/lang/reflect/Method; method   (line 180)
                    INVOKEVIRTUAL java.lang.reflect.Method.getReturnType ()Ljava/lang/Class;
                    ARETURN
               L10: IINC 13 1   (line 162)
                    GOTO L7
               L11: IINC 7 1     // I i   (line 154)
                    GOTO L5
               L12: ALOAD_0     // Ljava/lang/reflect/Method; method   (line 189)
                    INVOKEVIRTUAL java.lang.reflect.Method.getReturnType ()Ljava/lang/Class;
                    ARETURN
  end public static Class resolveReturnTypeForGenericMethod(java.lang.reflect.Method, Object[], ClassLoader)

  public static Class resolveReturnTypeArgument(java.lang.reflect.Method, Class):
                    ALOAD_0     // Ljava/lang/reflect/Method; method   (line 202)
                    LDC "method must not be null"
                    INVOKESTATIC org.springframework.util.Assert.notNull (Ljava/lang/Object;Ljava/lang/String;)V
                    ALOAD_0     // Ljava/lang/reflect/Method; method   (line 203)
                    INVOKESTATIC org.springframework.core.ResolvableType.forMethodReturnType (Ljava/lang/reflect/Method;)Lorg/springframework/core/ResolvableType;
                    ALOAD_1     // Ljava/lang/Class; genericIfc
                    INVOKEVIRTUAL org.springframework.core.ResolvableType.as (Ljava/lang/Class;)Lorg/springframework/core/ResolvableType;
                    ASTORE_2
                    ALOAD_2     // Lorg/springframework/core/ResolvableType; resolvableType   (line 204)
                    INVOKEVIRTUAL org.springframework.core.ResolvableType.hasGenerics ()Z
                    IFEQ L0
                    ALOAD_2     // Lorg/springframework/core/ResolvableType; resolvableType
                    INVOKEVIRTUAL org.springframework.core.ResolvableType.getType ()Ljava/lang/reflect/Type;
                    INSTANCEOF java.lang.reflect.WildcardType
                    IFEQ L1
                L0: ACONST_NULL   (line 205)
                    ARETURN
                L1: ALOAD_2     // Lorg/springframework/core/ResolvableType; resolvableType   (line 207)
                    INVOKESTATIC org.springframework.core.GenericTypeResolver.getSingleGeneric (Lorg/springframework/core/ResolvableType;)Ljava/lang/Class;
                    ARETURN
  end public static Class resolveReturnTypeArgument(java.lang.reflect.Method, Class)

  public static Class resolveTypeArgument(Class, Class):
                    ALOAD_0     // Ljava/lang/Class; clazz   (line 219)
                    INVOKESTATIC org.springframework.core.ResolvableType.forClass (Ljava/lang/Class;)Lorg/springframework/core/ResolvableType;
                    ALOAD_1     // Ljava/lang/Class; genericIfc
                    INVOKEVIRTUAL org.springframework.core.ResolvableType.as (Ljava/lang/Class;)Lorg/springframework/core/ResolvableType;
                    ASTORE_2
                    ALOAD_2     // Lorg/springframework/core/ResolvableType; resolvableType   (line 220)
                    INVOKEVIRTUAL org.springframework.core.ResolvableType.hasGenerics ()Z
                    IFNE L0
                    ACONST_NULL   (line 221)
                    ARETURN
                L0: ALOAD_2     // Lorg/springframework/core/ResolvableType; resolvableType   (line 223)
                    INVOKESTATIC org.springframework.core.GenericTypeResolver.getSingleGeneric (Lorg/springframework/core/ResolvableType;)Ljava/lang/Class;
                    ARETURN
  end public static Class resolveTypeArgument(Class, Class)

  private static Class getSingleGeneric(org.springframework.core.ResolvableType):
                    ALOAD_0     // Lorg/springframework/core/ResolvableType; resolvableType   (line 227)
                    INVOKEVIRTUAL org.springframework.core.ResolvableType.getGenerics ()[Lorg/springframework/core/ResolvableType;
                    ARRAYLENGTH
                    ICONST_1
                    IF_ICMPLE L0
                    NEW java.lang.IllegalArgumentException   (line 228)
                    DUP
                    NEW java.lang.StringBuilder
                    DUP
                    INVOKESPECIAL java.lang.StringBuilder.<init> ()V
                    LDC "Expected 1 type argument on generic interface ["
                    INVOKEVIRTUAL java.lang.StringBuilder.append (Ljava/lang/String;)Ljava/lang/StringBuilder;
                    ALOAD_0     // Lorg/springframework/core/ResolvableType; resolvableType
                    INVOKEVIRTUAL java.lang.StringBuilder.append (Ljava/lang/Object;)Ljava/lang/StringBuilder;
                    LDC "] but found "
                    INVOKEVIRTUAL java.lang.StringBuilder.append (Ljava/lang/String;)Ljava/lang/StringBuilder;
                    ALOAD_0     // Lorg/springframework/core/ResolvableType; resolvableType
                    INVOKEVIRTUAL org.springframework.core.ResolvableType.getGenerics ()[Lorg/springframework/core/ResolvableType;   (line 229)
                    ARRAYLENGTH
                    INVOKEVIRTUAL java.lang.StringBuilder.append (I)Ljava/lang/StringBuilder;
                    INVOKEVIRTUAL java.lang.StringBuilder.toString ()Ljava/lang/String;
                    INVOKESPECIAL java.lang.IllegalArgumentException.<init> (Ljava/lang/String;)V
                    ATHROW
                L0: ALOAD_0     // Lorg/springframework/core/ResolvableType; resolvableType   (line 231)
                    ICONST_0
                    NEWARRAY 10
                    INVOKEVIRTUAL org.springframework.core.ResolvableType.getGeneric ([I)Lorg/springframework/core/ResolvableType;
                    INVOKEVIRTUAL org.springframework.core.ResolvableType.resolve ()Ljava/lang/Class;
                    ARETURN
  end private static Class getSingleGeneric(org.springframework.core.ResolvableType)

  public static Class[] resolveTypeArguments(Class, Class):
                    ALOAD_0     // Ljava/lang/Class; clazz   (line 245)
                    INVOKESTATIC org.springframework.core.ResolvableType.forClass (Ljava/lang/Class;)Lorg/springframework/core/ResolvableType;
                    ALOAD_1     // Ljava/lang/Class; genericIfc
                    INVOKEVIRTUAL org.springframework.core.ResolvableType.as (Ljava/lang/Class;)Lorg/springframework/core/ResolvableType;
                    ASTORE_2
                    ALOAD_2     // Lorg/springframework/core/ResolvableType; type   (line 246)
                    INVOKEVIRTUAL org.springframework.core.ResolvableType.hasGenerics ()Z
                    IFEQ L0
                    ALOAD_2     // Lorg/springframework/core/ResolvableType; type
                    INVOKEVIRTUAL org.springframework.core.ResolvableType.isEntirelyUnresolvable ()Z
                    IFEQ L1
                L0: ACONST_NULL   (line 247)
                    ARETURN
                L1: ALOAD_2     // Lorg/springframework/core/ResolvableType; type   (line 249)
                    LDC java.lang.Object
                    INVOKEVIRTUAL org.springframework.core.ResolvableType.resolveGenerics (Ljava/lang/Class;)[Ljava/lang/Class;
                    ARETURN
  end public static Class[] resolveTypeArguments(Class, Class)

  public static Class resolveType(java.lang.reflect.Type, java.util.Map):
                    ALOAD_0     // Ljava/lang/reflect/Type; genericType   (line 262)
                    NEW org.springframework.core.GenericTypeResolver$TypeVariableMapVariableResolver
                    DUP
                    ALOAD_1     // Ljava/util/Map; map
                    INVOKESPECIAL org.springframework.core.GenericTypeResolver$TypeVariableMapVariableResolver.<init> (Ljava/util/Map;)V
                    INVOKESTATIC org.springframework.core.ResolvableType.forType (Ljava/lang/reflect/Type;Lorg/springframework/core/ResolvableType$VariableResolver;)Lorg/springframework/core/ResolvableType;
                    LDC java.lang.Object
                    INVOKEVIRTUAL org.springframework.core.ResolvableType.resolve (Ljava/lang/Class;)Ljava/lang/Class;
                    ARETURN
  end public static Class resolveType(java.lang.reflect.Type, java.util.Map)

  public static java.util.Map getTypeVariableMap(Class):
                    GETSTATIC org.springframework.core.GenericTypeResolver.typeVariableCache Ljava/util/Map;   (line 274)
                    ALOAD_0     // Ljava/lang/Class; clazz
                    INVOKEINTERFACE java.util.Map.get (Ljava/lang/Object;)Ljava/lang/Object;
                    CHECKCAST java.util.Map
                    ASTORE_1
                    ALOAD_1     // Ljava/util/Map; typeVariableMap   (line 275)
                    IFNONNULL L0
                    NEW java.util.HashMap   (line 276)
                    DUP
                    INVOKESPECIAL java.util.HashMap.<init> ()V
                    ASTORE_1     // Ljava/util/Map; typeVariableMap
                    ALOAD_0     // Ljava/lang/Class; clazz   (line 277)
                    INVOKESTATIC org.springframework.core.ResolvableType.forClass (Ljava/lang/Class;)Lorg/springframework/core/ResolvableType;
                    ALOAD_1     // Ljava/util/Map; typeVariableMap
                    INVOKESTATIC org.springframework.core.GenericTypeResolver.buildTypeVariableMap (Lorg/springframework/core/ResolvableType;Ljava/util/Map;)V
                    GETSTATIC org.springframework.core.GenericTypeResolver.typeVariableCache Ljava/util/Map;   (line 278)
                    ALOAD_0     // Ljava/lang/Class; clazz
                    ALOAD_1     // Ljava/util/Map; typeVariableMap
                    INVOKESTATIC java.util.Collections.unmodifiableMap (Ljava/util/Map;)Ljava/util/Map;
                    INVOKEINTERFACE java.util.Map.put (Ljava/lang/Object;Ljava/lang/Object;)Ljava/lang/Object;
                    POP
                L0: ALOAD_1     // Ljava/util/Map; typeVariableMap   (line 280)
                    ARETURN
  end public static java.util.Map getTypeVariableMap(Class)

  private static void buildTypeVariableMap(org.springframework.core.ResolvableType, java.util.Map):
                    ALOAD_0     // Lorg/springframework/core/ResolvableType; type   (line 285)
                    GETSTATIC org.springframework.core.ResolvableType.NONE Lorg/springframework/core/ResolvableType;
                    IF_ACMPEQ L7
                    ALOAD_0     // Lorg/springframework/core/ResolvableType; type   (line 286)
                    INVOKEVIRTUAL org.springframework.core.ResolvableType.getType ()Ljava/lang/reflect/Type;
                    INSTANCEOF java.lang.reflect.ParameterizedType
                    IFEQ L4
                    ALOAD_0     // Lorg/springframework/core/ResolvableType; type   (line 287)
                    INVOKEVIRTUAL org.springframework.core.ResolvableType.resolve ()Ljava/lang/Class;
                    INVOKEVIRTUAL java.lang.Class.getTypeParameters ()[Ljava/lang/reflect/TypeVariable;
                    ASTORE_2
                    ICONST_0   (line 288)
                    ISTORE_3
                L0: ILOAD_3     // I i
                    ALOAD_2     // [Ljava/lang/reflect/TypeVariable; variables
                    ARRAYLENGTH
                    IF_ICMPGE L4
                    ALOAD_0     // Lorg/springframework/core/ResolvableType; type   (line 289)
                    ICONST_1
                    NEWARRAY 10
                    DUP
                    ICONST_0
                    ILOAD_3     // I i
                    IASTORE
                    INVOKEVIRTUAL org.springframework.core.ResolvableType.getGeneric ([I)Lorg/springframework/core/ResolvableType;
                    ASTORE 4
                L1: ALOAD 4     // Lorg/springframework/core/ResolvableType; generic   (line 290)
                    INVOKEVIRTUAL org.springframework.core.ResolvableType.getType ()Ljava/lang/reflect/Type;
                    INSTANCEOF java.lang.reflect.TypeVariable
                    IFEQ L2
                    ALOAD 4     // Lorg/springframework/core/ResolvableType; generic   (line 291)
                    INVOKEVIRTUAL org.springframework.core.ResolvableType.resolveType ()Lorg/springframework/core/ResolvableType;
                    ASTORE 4     // Lorg/springframework/core/ResolvableType; generic
                    GOTO L1
                L2: ALOAD 4     // Lorg/springframework/core/ResolvableType; generic   (line 293)
                    GETSTATIC org.springframework.core.ResolvableType.NONE Lorg/springframework/core/ResolvableType;
                    IF_ACMPEQ L3
                    ALOAD_1     // Ljava/util/Map; typeVariableMap   (line 294)
                    ALOAD_2     // [Ljava/lang/reflect/TypeVariable; variables
                    ILOAD_3     // I i
                    AALOAD
                    ALOAD 4     // Lorg/springframework/core/ResolvableType; generic
                    INVOKEVIRTUAL org.springframework.core.ResolvableType.getType ()Ljava/lang/reflect/Type;
                    INVOKEINTERFACE java.util.Map.put (Ljava/lang/Object;Ljava/lang/Object;)Ljava/lang/Object;
                    POP
                L3: IINC_3 1     // I i   (line 288)
                    GOTO L0
                L4: ALOAD_0     // Lorg/springframework/core/ResolvableType; type   (line 298)
                    INVOKEVIRTUAL org.springframework.core.ResolvableType.getSuperType ()Lorg/springframework/core/ResolvableType;
                    ALOAD_1     // Ljava/util/Map; typeVariableMap
                    INVOKESTATIC org.springframework.core.GenericTypeResolver.buildTypeVariableMap (Lorg/springframework/core/ResolvableType;Ljava/util/Map;)V
                    ALOAD_0     // Lorg/springframework/core/ResolvableType; type   (line 299)
                    INVOKEVIRTUAL org.springframework.core.ResolvableType.getInterfaces ()[Lorg/springframework/core/ResolvableType;
                    ASTORE_2
                    ALOAD_2
                    ARRAYLENGTH
                    ISTORE_3
                    ICONST_0
                    ISTORE 4
                L5: ILOAD 4
                    ILOAD_3
                    IF_ICMPGE L6
                    ALOAD_2
                    ILOAD 4
                    AALOAD
                    ASTORE 5
                    ALOAD 5     // Lorg/springframework/core/ResolvableType; interfaceType   (line 300)
                    ALOAD_1     // Ljava/util/Map; typeVariableMap
                    INVOKESTATIC org.springframework.core.GenericTypeResolver.buildTypeVariableMap (Lorg/springframework/core/ResolvableType;Ljava/util/Map;)V
                    IINC 4 1   (line 299)
                    GOTO L5
                L6: ALOAD_0     // Lorg/springframework/core/ResolvableType; type   (line 302)
                    INVOKEVIRTUAL org.springframework.core.ResolvableType.resolve ()Ljava/lang/Class;
                    INVOKEVIRTUAL java.lang.Class.isMemberClass ()Z
                    IFEQ L7
                    ALOAD_0     // Lorg/springframework/core/ResolvableType; type   (line 303)
                    INVOKEVIRTUAL org.springframework.core.ResolvableType.resolve ()Ljava/lang/Class;
                    INVOKEVIRTUAL java.lang.Class.getEnclosingClass ()Ljava/lang/Class;
                    INVOKESTATIC org.springframework.core.ResolvableType.forClass (Ljava/lang/Class;)Lorg/springframework/core/ResolvableType;
                    ALOAD_1     // Ljava/util/Map; typeVariableMap
                    INVOKESTATIC org.springframework.core.GenericTypeResolver.buildTypeVariableMap (Lorg/springframework/core/ResolvableType;Ljava/util/Map;)V
                L7: RETURN   (line 306)
  end private static void buildTypeVariableMap(org.springframework.core.ResolvableType, java.util.Map)

  static void <clinit>():
                    NEW org.springframework.util.ConcurrentReferenceHashMap   (line 48)
                    DUP
                    INVOKESPECIAL org.springframework.util.ConcurrentReferenceHashMap.<init> ()V
                    PUTSTATIC org.springframework.core.GenericTypeResolver.typeVariableCache Ljava/util/Map;
                    RETURN
  end static void <clinit>()
end public abstract class org.springframework.core.GenericTypeResolver
 -- (NullPointerException) null
null
java.lang.NullPointerException
	at org.aspectj.weaver.UnresolvedType.forSignature(UnresolvedType.java:384)
	at org.aspectj.weaver.bcel.BcelObjectType.getDeclaredInterfaces(BcelObjectType.java:275)
	at org.aspectj.weaver.ReferenceType.getDeclaredInterfaces(ReferenceType.java:626)
	at org.aspectj.weaver.ResolvedType.getDirectSupertypes(ResolvedType.java:82)
	at org.aspectj.weaver.patterns.TypePattern.matchesSubtypes(TypePattern.java:178)
	at org.aspectj.weaver.patterns.ExactTypePattern.matchesSubtypes(ExactTypePattern.java:74)
	at org.aspectj.weaver.patterns.TypePattern.matchesStatically(TypePattern.java:130)
	at org.aspectj.weaver.patterns.OrTypePattern.matchesStatically(OrTypePattern.java:76)
	at org.aspectj.weaver.patterns.SignaturePattern.matchesExactlyMethod(SignaturePattern.java:505)
	at org.aspectj.weaver.patterns.SignaturePattern.matchesExactly(SignaturePattern.java:360)
	at org.aspectj.weaver.patterns.SignaturePattern.matches(SignaturePattern.java:320)
	at org.aspectj.weaver.patterns.KindedPointcut.matchInternal(KindedPointcut.java:202)
	at org.aspectj.weaver.patterns.Pointcut.match(Pointcut.java:137)
	at org.aspectj.weaver.patterns.AndPointcut.matchInternal(AndPointcut.java:51)
	at org.aspectj.weaver.patterns.Pointcut.match(Pointcut.java:137)
	at org.aspectj.weaver.patterns.OrPointcut.matchInternal(OrPointcut.java:54)
	at org.aspectj.weaver.patterns.Pointcut.match(Pointcut.java:137)
	at org.aspectj.weaver.ShadowMunger.match(ShadowMunger.java:113)
	at org.aspectj.weaver.Advice.match(Advice.java:109)
	at org.aspectj.weaver.bcel.BcelAdvice.match(BcelAdvice.java:149)
	at org.aspectj.weaver.bcel.BcelClassWeaver.match(BcelClassWeaver.java:3173)
	at org.aspectj.weaver.bcel.BcelClassWeaver.match(BcelClassWeaver.java:2565)
	at org.aspectj.weaver.bcel.BcelClassWeaver.weave(BcelClassWeaver.java:480)
	at org.aspectj.weaver.bcel.BcelClassWeaver.weave(BcelClassWeaver.java:99)
	at org.aspectj.weaver.bcel.BcelWeaver.weave(BcelWeaver.java:1694)
	at org.aspectj.weaver.bcel.BcelWeaver.weaveWithoutDump(BcelWeaver.java:1638)
	at org.aspectj.weaver.bcel.BcelWeaver.weaveAndNotify(BcelWeaver.java:1401)
	at org.aspectj.weaver.bcel.BcelWeaver.weave(BcelWeaver.java:1187)
	at org.aspectj.weaver.tools.WeavingAdaptor.getWovenBytes(WeavingAdaptor.java:472)
	at org.aspectj.weaver.tools.WeavingAdaptor.weaveClass(WeavingAdaptor.java:323)
	at org.aspectj.weaver.loadtime.Aj.preProcess(Aj.java:99)
	at org.aspectj.weaver.loadtime.ClassPreProcessorAgentAdapter.transform(ClassPreProcessorAgentAdapter.java:54)
	at org.springframework.context.weaving.AspectJWeavingEnabler$AspectJClassBypassingClassFileTransformer.transform(AspectJWeavingEnabler.java:108)
	at org.springframework.instrument.classloading.InstrumentationLoadTimeWeaver$FilteringClassFileTransformer.transform(InstrumentationLoadTimeWeaver.java:184)
	at sun.instrument.TransformerManager.transform(Unknown Source)
	at sun.instrument.InstrumentationImpl.transform(Unknown Source)
	at java.lang.ClassLoader.defineClass1(Native Method)
	at java.lang.ClassLoader.defineClass(Unknown Source)
	at java.security.SecureClassLoader.defineClass(Unknown Source)
	at java.net.URLClassLoader.defineClass(Unknown Source)
	at java.net.URLClassLoader.access$100(Unknown Source)
	at java.net.URLClassLoader$1.run(Unknown Source)
	at java.net.URLClassLoader$1.run(Unknown Source)
	at java.security.AccessController.doPrivileged(Native Method)
	at java.net.URLClassLoader.findClass(Unknown Source)
	at java.lang.ClassLoader.loadClass(Unknown Source)
	at sun.misc.Launcher$AppClassLoader.loadClass(Unknown Source)
	at java.lang.ClassLoader.loadClass(Unknown Source)
	at org.springframework.beans.GenericTypeAwarePropertyDescriptor.<init>(GenericTypeAwarePropertyDescriptor.java:102)
	at org.springframework.beans.CachedIntrospectionResults.buildGenericTypeAwarePropertyDescriptor(CachedIntrospectionResults.java:348)
	at org.springframework.beans.CachedIntrospectionResults.<init>(CachedIntrospectionResults.java:302)
	at org.springframework.beans.CachedIntrospectionResults.forClass(CachedIntrospectionResults.java:189)
	at org.springframework.beans.BeanWrapperImpl.getCachedIntrospectionResults(BeanWrapperImpl.java:328)
	at org.springframework.beans.BeanWrapperImpl.getPropertyDescriptors(BeanWrapperImpl.java:336)
	at org.springframework.beans.factory.support.AbstractAutowireCapableBeanFactory.filterPropertyDescriptorsForDependencyCheck(AbstractAutowireCapableBeanFactory.java:1364)
	at org.springframework.beans.factory.support.AbstractAutowireCapableBeanFactory.filterPropertyDescriptorsForDependencyCheck(AbstractAutowireCapableBeanFactory.java:1343)
	at org.springframework.beans.factory.support.AbstractAutowireCapableBeanFactory.populateBean(AbstractAutowireCapableBeanFactory.java:1205)
	at org.springframework.beans.factory.support.AbstractAutowireCapableBeanFactory.doCreateBean(AbstractAutowireCapableBeanFactory.java:537)
	at org.springframework.beans.factory.support.AbstractAutowireCapableBeanFactory.createBean(AbstractAutowireCapableBeanFactory.java:476)
	at org.springframework.beans.factory.support.AbstractBeanFactory$1.getObject(AbstractBeanFactory.java:303)
	at org.springframework.beans.factory.support.DefaultSingletonBeanRegistry.getSingleton(DefaultSingletonBeanRegistry.java:230)
	at org.springframework.beans.factory.support.AbstractBeanFactory.doGetBean(AbstractBeanFactory.java:299)
	at org.springframework.beans.factory.support.AbstractBeanFactory.getBean(AbstractBeanFactory.java:194)
	at org.springframework.beans.factory.support.DefaultListableBeanFactory.preInstantiateSingletons(DefaultListableBeanFactory.java:755)
	at org.springframework.context.support.AbstractApplicationContext.finishBeanFactoryInitialization(AbstractApplicationContext.java:757)
	at org.springframework.context.support.AbstractApplicationContext.refresh(AbstractApplicationContext.java:480)
	at org.springframework.context.support.ClassPathXmlApplicationContext.<init>(ClassPathXmlApplicationContext.java:139)
	at org.springframework.context.support.ClassPathXmlApplicationContext.<init>(ClassPathXmlApplicationContext.java:93)
	at com.springExemple.presentation.Presentation2.main(Presentation2.java:13)

error can't determine annotations of missing type org.springframework.transaction.annotation.Transactional
when weaving type org.springframework.core.SerializableTypeWrapper$MethodParameterTypeProvider
when weaving classes 
when weaving 
 [Xlint:cantFindType]
