---- AspectJ Properties ---
AspectJ Compiler 1.6.12 built on Tuesday Oct 18, 2011 at 17:52:06 GMT
---- Dump Properties ---
Dump file: ajcore.20170412.104001.920.txt
Dump reason: org.aspectj.bridge.AbortException
Dump on exception: true
Dump at exit condition: abort
---- Exception Information ---
Message: abort trouble in: 
public abstract class org.springframework.beans.PropertyAccessorUtils extends java.lang.Object:
  public void <init>():
                    ALOAD_0     // Lorg/springframework/beans/PropertyAccessorUtils; this   (line 26)
                    INVOKESPECIAL java.lang.Object.<init> ()V
    constructor-execution(void org.springframework.beans.PropertyAccessorUtils.<init>())
    |               RETURN
    constructor-execution(void org.springframework.beans.PropertyAccessorUtils.<init>())
  end public void <init>()

  public static String getPropertyName(String):
                    ALOAD_0     // Ljava/lang/String; propertyPath   (line 35)
                    LDC "]"
                    INVOKEVIRTUAL java.lang.String.endsWith (Ljava/lang/String;)Z
                    IFEQ L0
                    ALOAD_0     // Ljava/lang/String; propertyPath
                    BIPUSH 91
                    INVOKEVIRTUAL java.lang.String.indexOf (I)I   (line 36)
                    GOTO L1
                L0: ICONST_M1
                L1: ISTORE_1
                    ILOAD_1     // I separatorIndex   (line 37)
                    ICONST_M1
                    IF_ICMPEQ L2
                    ALOAD_0     // Ljava/lang/String; propertyPath
                    ICONST_0
                    ILOAD_1     // I separatorIndex
                    INVOKEVIRTUAL java.lang.String.substring (II)Ljava/lang/String;
                    GOTO L3
                L2: ALOAD_0     // Ljava/lang/String; propertyPath
                L3: ARETURN
  end public static String getPropertyName(String)

  public static boolean isNestedOrIndexedProperty(String):
                    ALOAD_0     // Ljava/lang/String; propertyPath   (line 46)
                    IFNONNULL L0
                    ICONST_0   (line 47)
                    IRETURN
                L0: ICONST_0   (line 49)
                    ISTORE_1
                L1: ILOAD_1     // I i
                    ALOAD_0     // Ljava/lang/String; propertyPath
                    INVOKEVIRTUAL java.lang.String.length ()I
                    IF_ICMPGE L4
                    ALOAD_0     // Ljava/lang/String; propertyPath   (line 50)
                    ILOAD_1     // I i
                    INVOKEVIRTUAL java.lang.String.charAt (I)C
                    ISTORE_2
                    ILOAD_2     // C ch   (line 51)
                    BIPUSH 46
                    IF_ICMPEQ L2
                    ILOAD_2     // C ch
                    BIPUSH 91
                    IF_ICMPNE L3
                L2: ICONST_1   (line 53)
                    IRETURN
                L3: IINC_1 1     // I i   (line 49)
                    GOTO L1
                L4: ICONST_0   (line 56)
                    IRETURN
  end public static boolean isNestedOrIndexedProperty(String)

  public static int getFirstNestedPropertySeparatorIndex(String):
                    ALOAD_0     // Ljava/lang/String; propertyPath   (line 66)
                    ICONST_0
                    INVOKESTATIC org.springframework.beans.PropertyAccessorUtils.getNestedPropertySeparatorIndex (Ljava/lang/String;Z)I
                    IRETURN
  end public static int getFirstNestedPropertySeparatorIndex(String)

  public static int getLastNestedPropertySeparatorIndex(String):
                    ALOAD_0     // Ljava/lang/String; propertyPath   (line 76)
                    ICONST_1
                    INVOKESTATIC org.springframework.beans.PropertyAccessorUtils.getNestedPropertySeparatorIndex (Ljava/lang/String;Z)I
                    IRETURN
  end public static int getLastNestedPropertySeparatorIndex(String)

  private static int getNestedPropertySeparatorIndex(String, boolean):
                    ICONST_0   (line 87)
                    ISTORE_2
                    ALOAD_0     // Ljava/lang/String; propertyPath   (line 88)
                    INVOKEVIRTUAL java.lang.String.length ()I
                    ISTORE_3
                    ILOAD_1     // Z last   (line 89)
                    IFEQ L0
                    ILOAD_3     // I length
                    ICONST_1
                    ISUB
                    GOTO L1
                L0: ICONST_0
                L1: ISTORE 4
                L2: ILOAD_1     // Z last   (line 90)
                    IFEQ L3
                    ILOAD 4     // I i
                    IFLT L11
                    GOTO L4
                L3: ILOAD 4     // I i
                    ILOAD_3     // I length
                    IF_ICMPGE L11
                L4: ALOAD_0     // Ljava/lang/String; propertyPath   (line 91)
                    ILOAD 4     // I i
                    INVOKEVIRTUAL java.lang.String.charAt (I)C
                    LOOKUPSWITCH
                      46: 	L8
                      91: 	L5
                      93: 	L5
                      default: 	L9
                L5: ILOAD_2     // Z inKey   (line 94)
                    IFNE L6
                    ICONST_1
                    GOTO L7
                L6: ICONST_0
                L7: ISTORE_2     // Z inKey
                    GOTO L9   (line 95)
                L8: ILOAD_2     // Z inKey   (line 97)
                    IFNE L9
                    ILOAD 4     // I i   (line 98)
                    IRETURN
                L9: ILOAD_1     // Z last   (line 101)
                    IFEQ L10
                    IINC 4 -1     // I i   (line 102)
                    GOTO L2
               L10: IINC 4 1     // I i   (line 105)
                    GOTO L2
               L11: ICONST_M1   (line 108)
                    IRETURN
  end private static int getNestedPropertySeparatorIndex(String, boolean)

  public static boolean matchesProperty(String, String):
                    ALOAD_0     // Ljava/lang/String; registeredPath   (line 119)
                    ALOAD_1     // Ljava/lang/String; propertyPath
                    INVOKEVIRTUAL java.lang.String.startsWith (Ljava/lang/String;)Z
                    IFNE L0
                    ICONST_0   (line 120)
                    IRETURN
                L0: ALOAD_0     // Ljava/lang/String; registeredPath   (line 122)
                    INVOKEVIRTUAL java.lang.String.length ()I
                    ALOAD_1     // Ljava/lang/String; propertyPath
                    INVOKEVIRTUAL java.lang.String.length ()I
                    IF_ICMPNE L1
                    ICONST_1   (line 123)
                    IRETURN
                L1: ALOAD_0     // Ljava/lang/String; registeredPath   (line 125)
                    ALOAD_1     // Ljava/lang/String; propertyPath
                    INVOKEVIRTUAL java.lang.String.length ()I
                    INVOKEVIRTUAL java.lang.String.charAt (I)C
                    BIPUSH 91
                    IF_ICMPEQ L2
                    ICONST_0   (line 126)
                    IRETURN
                L2: ALOAD_0     // Ljava/lang/String; registeredPath   (line 128)
                    BIPUSH 93
                    ALOAD_1     // Ljava/lang/String; propertyPath
                    INVOKEVIRTUAL java.lang.String.length ()I
                    ICONST_1
                    IADD
                    INVOKEVIRTUAL java.lang.String.indexOf (II)I
                    ALOAD_0     // Ljava/lang/String; registeredPath
                    INVOKEVIRTUAL java.lang.String.length ()I   (line 129)
                    ICONST_1
                    ISUB
                    IF_ICMPNE L3
                    ICONST_1
                    GOTO L4
                L3: ICONST_0
                L4: IRETURN
  end public static boolean matchesProperty(String, String)

  public static String canonicalPropertyName(String):
                    ALOAD_0     // Ljava/lang/String; propertyName   (line 141)
                    IFNONNULL L0
                    LDC ""   (line 142)
                    ARETURN
                L0: NEW java.lang.StringBuilder   (line 145)
                    DUP
                    ALOAD_0     // Ljava/lang/String; propertyName
                    INVOKESPECIAL java.lang.StringBuilder.<init> (Ljava/lang/String;)V
                    ASTORE_1
                    ICONST_0   (line 146)
                    ISTORE_2
                L1: ILOAD_2     // I searchIndex   (line 147)
                    ICONST_M1
                    IF_ICMPEQ L6
                    ALOAD_1     // Ljava/lang/StringBuilder; sb   (line 148)
                    LDC "["
                    ILOAD_2     // I searchIndex
                    INVOKEVIRTUAL java.lang.StringBuilder.indexOf (Ljava/lang/String;I)I
                    ISTORE_3
                    ICONST_M1   (line 149)
                    ISTORE_2     // I searchIndex
                    ILOAD_3     // I keyStart   (line 150)
                    ICONST_M1
                    IF_ICMPEQ L5
                    ALOAD_1     // Ljava/lang/StringBuilder; sb   (line 151)
                    LDC "]"
                    ILOAD_3     // I keyStart
                    LDC "["
                    INVOKEVIRTUAL java.lang.String.length ()I   (line 152)
                    IADD
                    INVOKEVIRTUAL java.lang.StringBuilder.indexOf (Ljava/lang/String;I)I   (line 151)
                    ISTORE 4
                    ILOAD 4     // I keyEnd   (line 153)
                    ICONST_M1
                    IF_ICMPEQ L5
                    ALOAD_1     // Ljava/lang/StringBuilder; sb   (line 154)
                    ILOAD_3     // I keyStart
                    LDC "["
                    INVOKEVIRTUAL java.lang.String.length ()I
                    IADD
                    ILOAD 4     // I keyEnd
                    INVOKEVIRTUAL java.lang.StringBuilder.substring (II)Ljava/lang/String;
                    ASTORE 5
                    ALOAD 5     // Ljava/lang/String; key   (line 155)
                    LDC "'"
                    INVOKEVIRTUAL java.lang.String.startsWith (Ljava/lang/String;)Z
                    IFEQ L2
                    ALOAD 5     // Ljava/lang/String; key
                    LDC "'"
                    INVOKEVIRTUAL java.lang.String.endsWith (Ljava/lang/String;)Z
                    IFNE L3
                L2: ALOAD 5     // Ljava/lang/String; key
                    LDC "\""
                    INVOKEVIRTUAL java.lang.String.startsWith (Ljava/lang/String;)Z
                    IFEQ L4
                    ALOAD 5     // Ljava/lang/String; key
                    LDC "\""
                    INVOKEVIRTUAL java.lang.String.endsWith (Ljava/lang/String;)Z
                    IFEQ L4
                L3: ALOAD_1     // Ljava/lang/StringBuilder; sb   (line 156)
                    ILOAD_3     // I keyStart
                    ICONST_1
                    IADD
                    ILOAD_3     // I keyStart
                    ICONST_2
                    IADD
                    INVOKEVIRTUAL java.lang.StringBuilder.delete (II)Ljava/lang/StringBuilder;
                    POP
                    ALOAD_1     // Ljava/lang/StringBuilder; sb   (line 157)
                    ILOAD 4     // I keyEnd
                    ICONST_2
                    ISUB
                    ILOAD 4     // I keyEnd
                    ICONST_1
                    ISUB
                    INVOKEVIRTUAL java.lang.StringBuilder.delete (II)Ljava/lang/StringBuilder;
                    POP
                    ILOAD 4     // I keyEnd   (line 158)
                    ICONST_2
                    ISUB
                    ISTORE 4     // I keyEnd
                L4: ILOAD 4     // I keyEnd   (line 160)
                    LDC "]"
                    INVOKEVIRTUAL java.lang.String.length ()I
                    IADD
                    ISTORE_2     // I searchIndex
                L5: GOTO L1   (line 163)
                L6: ALOAD_1     // Ljava/lang/StringBuilder; sb   (line 164)
                    INVOKEVIRTUAL java.lang.StringBuilder.toString ()Ljava/lang/String;
                    ARETURN
  end public static String canonicalPropertyName(String)

  public static String[] canonicalPropertyNames(String[]):
                    ALOAD_0     // [Ljava/lang/String; propertyNames   (line 175)
                    IFNONNULL L0
                    ACONST_NULL   (line 176)
                    ARETURN
                L0: ALOAD_0     // [Ljava/lang/String; propertyNames   (line 178)
                    ARRAYLENGTH
                    ANEWARRAY java.lang.String
                    ASTORE_1
                    ICONST_0   (line 179)
                    ISTORE_2
                L1: ILOAD_2     // I i
                    ALOAD_0     // [Ljava/lang/String; propertyNames
                    ARRAYLENGTH
                    IF_ICMPGE L2
                    ALOAD_1     // [Ljava/lang/String; result   (line 180)
                    ILOAD_2     // I i
                    ALOAD_0     // [Ljava/lang/String; propertyNames
                    ILOAD_2     // I i
                    AALOAD
                    INVOKESTATIC org.springframework.beans.PropertyAccessorUtils.canonicalPropertyName (Ljava/lang/String;)Ljava/lang/String;
                    AASTORE
                    IINC_2 1     // I i   (line 179)
                    GOTO L1
                L2: ALOAD_1     // [Ljava/lang/String; result   (line 182)
                    ARETURN
  end public static String[] canonicalPropertyNames(String[])

end public abstract class org.springframework.beans.PropertyAccessorUtils
 -- (NullPointerException) null
null
java.lang.NullPointerException
	at org.aspectj.weaver.UnresolvedType.forSignature(UnresolvedType.java:384)
	at org.aspectj.weaver.bcel.BcelObjectType.getDeclaredInterfaces(BcelObjectType.java:275)
	at org.aspectj.weaver.ReferenceType.getDeclaredInterfaces(ReferenceType.java:626)
	at org.aspectj.weaver.ResolvedType.getDirectSupertypes(ResolvedType.java:82)
	at org.aspectj.weaver.patterns.TypePattern.matchesSubtypes(TypePattern.java:178)
	at org.aspectj.weaver.patterns.ExactTypePattern.matchesSubtypes(ExactTypePattern.java:74)
	at org.aspectj.weaver.patterns.TypePattern.matchesStatically(TypePattern.java:130)
	at org.aspectj.weaver.patterns.OrTypePattern.matchesStatically(OrTypePattern.java:76)
	at org.aspectj.weaver.patterns.SignaturePattern.matchesExactlyMethod(SignaturePattern.java:505)
	at org.aspectj.weaver.patterns.SignaturePattern.matchesExactly(SignaturePattern.java:360)
	at org.aspectj.weaver.patterns.SignaturePattern.matches(SignaturePattern.java:320)
	at org.aspectj.weaver.patterns.KindedPointcut.matchInternal(KindedPointcut.java:202)
	at org.aspectj.weaver.patterns.Pointcut.match(Pointcut.java:137)
	at org.aspectj.weaver.patterns.AndPointcut.matchInternal(AndPointcut.java:51)
	at org.aspectj.weaver.patterns.Pointcut.match(Pointcut.java:137)
	at org.aspectj.weaver.patterns.OrPointcut.matchInternal(OrPointcut.java:54)
	at org.aspectj.weaver.patterns.Pointcut.match(Pointcut.java:137)
	at org.aspectj.weaver.ShadowMunger.match(ShadowMunger.java:113)
	at org.aspectj.weaver.Advice.match(Advice.java:109)
	at org.aspectj.weaver.bcel.BcelAdvice.match(BcelAdvice.java:149)
	at org.aspectj.weaver.bcel.BcelClassWeaver.match(BcelClassWeaver.java:3173)
	at org.aspectj.weaver.bcel.BcelClassWeaver.match(BcelClassWeaver.java:2565)
	at org.aspectj.weaver.bcel.BcelClassWeaver.weave(BcelClassWeaver.java:480)
	at org.aspectj.weaver.bcel.BcelClassWeaver.weave(BcelClassWeaver.java:99)
	at org.aspectj.weaver.bcel.BcelWeaver.weave(BcelWeaver.java:1694)
	at org.aspectj.weaver.bcel.BcelWeaver.weaveWithoutDump(BcelWeaver.java:1638)
	at org.aspectj.weaver.bcel.BcelWeaver.weaveAndNotify(BcelWeaver.java:1401)
	at org.aspectj.weaver.bcel.BcelWeaver.weave(BcelWeaver.java:1187)
	at org.aspectj.weaver.tools.WeavingAdaptor.getWovenBytes(WeavingAdaptor.java:472)
	at org.aspectj.weaver.tools.WeavingAdaptor.weaveClass(WeavingAdaptor.java:323)
	at org.aspectj.weaver.loadtime.Aj.preProcess(Aj.java:99)
	at org.aspectj.weaver.loadtime.ClassPreProcessorAgentAdapter.transform(ClassPreProcessorAgentAdapter.java:54)
	at org.springframework.context.weaving.AspectJWeavingEnabler$AspectJClassBypassingClassFileTransformer.transform(AspectJWeavingEnabler.java:108)
	at org.springframework.instrument.classloading.InstrumentationLoadTimeWeaver$FilteringClassFileTransformer.transform(InstrumentationLoadTimeWeaver.java:184)
	at sun.instrument.TransformerManager.transform(Unknown Source)
	at sun.instrument.InstrumentationImpl.transform(Unknown Source)
	at java.lang.ClassLoader.defineClass1(Native Method)
	at java.lang.ClassLoader.defineClass(Unknown Source)
	at java.security.SecureClassLoader.defineClass(Unknown Source)
	at java.net.URLClassLoader.defineClass(Unknown Source)
	at java.net.URLClassLoader.access$100(Unknown Source)
	at java.net.URLClassLoader$1.run(Unknown Source)
	at java.net.URLClassLoader$1.run(Unknown Source)
	at java.security.AccessController.doPrivileged(Native Method)
	at java.net.URLClassLoader.findClass(Unknown Source)
	at java.lang.ClassLoader.loadClass(Unknown Source)
	at sun.misc.Launcher$AppClassLoader.loadClass(Unknown Source)
	at java.lang.ClassLoader.loadClass(Unknown Source)
	at org.springframework.beans.BeanWrapperImpl.getBeanWrapperForPropertyPath(BeanWrapperImpl.java:544)
	at org.springframework.beans.BeanWrapperImpl.getPropertyDescriptorInternal(BeanWrapperImpl.java:359)
	at org.springframework.beans.BeanWrapperImpl.isWritableProperty(BeanWrapperImpl.java:440)
	at org.springframework.beans.factory.support.AbstractAutowireCapableBeanFactory.applyPropertyValues(AbstractAutowireCapableBeanFactory.java:1479)
	at org.springframework.beans.factory.support.AbstractAutowireCapableBeanFactory.populateBean(AbstractAutowireCapableBeanFactory.java:1222)
	at org.springframework.beans.factory.support.AbstractAutowireCapableBeanFactory.doCreateBean(AbstractAutowireCapableBeanFactory.java:537)
	at org.springframework.beans.factory.support.AbstractAutowireCapableBeanFactory.createBean(AbstractAutowireCapableBeanFactory.java:476)
	at org.springframework.beans.factory.support.AbstractBeanFactory$1.getObject(AbstractBeanFactory.java:303)
	at org.springframework.beans.factory.support.DefaultSingletonBeanRegistry.getSingleton(DefaultSingletonBeanRegistry.java:230)
	at org.springframework.beans.factory.support.AbstractBeanFactory.doGetBean(AbstractBeanFactory.java:299)
	at org.springframework.beans.factory.support.AbstractBeanFactory.getBean(AbstractBeanFactory.java:194)
	at org.springframework.beans.factory.support.DefaultListableBeanFactory.findAutowireCandidates(DefaultListableBeanFactory.java:1120)
	at org.springframework.beans.factory.support.DefaultListableBeanFactory.doResolveDependency(DefaultListableBeanFactory.java:996)
	at org.springframework.beans.factory.support.DefaultListableBeanFactory.resolveDependency(DefaultListableBeanFactory.java:942)
	at org.springframework.beans.factory.annotation.AutowiredAnnotationBeanPostProcessor$AutowiredFieldElement.inject(AutowiredAnnotationBeanPostProcessor.java:533)
	at org.springframework.beans.factory.annotation.InjectionMetadata.inject(InjectionMetadata.java:88)
	at org.springframework.beans.factory.annotation.AutowiredAnnotationBeanPostProcessor.postProcessPropertyValues(AutowiredAnnotationBeanPostProcessor.java:331)
	at org.springframework.beans.factory.support.AbstractAutowireCapableBeanFactory.populateBean(AbstractAutowireCapableBeanFactory.java:1210)
	at org.springframework.beans.factory.support.AbstractAutowireCapableBeanFactory.doCreateBean(AbstractAutowireCapableBeanFactory.java:537)
	at org.springframework.beans.factory.support.AbstractAutowireCapableBeanFactory.createBean(AbstractAutowireCapableBeanFactory.java:476)
	at org.springframework.beans.factory.support.AbstractBeanFactory$1.getObject(AbstractBeanFactory.java:303)
	at org.springframework.beans.factory.support.DefaultSingletonBeanRegistry.getSingleton(DefaultSingletonBeanRegistry.java:230)
	at org.springframework.beans.factory.support.AbstractBeanFactory.doGetBean(AbstractBeanFactory.java:299)
	at org.springframework.beans.factory.support.AbstractBeanFactory.getBean(AbstractBeanFactory.java:194)
	at org.springframework.beans.factory.support.DefaultListableBeanFactory.preInstantiateSingletons(DefaultListableBeanFactory.java:755)
	at org.springframework.context.support.AbstractApplicationContext.finishBeanFactoryInitialization(AbstractApplicationContext.java:757)
	at org.springframework.context.support.AbstractApplicationContext.refresh(AbstractApplicationContext.java:480)
	at org.springframework.context.support.ClassPathXmlApplicationContext.<init>(ClassPathXmlApplicationContext.java:139)
	at org.springframework.context.support.ClassPathXmlApplicationContext.<init>(ClassPathXmlApplicationContext.java:93)
	at com.springExemple.presentation.Presentation2.main(Presentation2.java:13)

org.aspectj.bridge.AbortException: trouble in: 
public abstract class org.springframework.beans.PropertyAccessorUtils extends java.lang.Object:
  public void <init>():
                    ALOAD_0     // Lorg/springframework/beans/PropertyAccessorUtils; this   (line 26)
                    INVOKESPECIAL java.lang.Object.<init> ()V
    constructor-execution(void org.springframework.beans.PropertyAccessorUtils.<init>())
    |               RETURN
    constructor-execution(void org.springframework.beans.PropertyAccessorUtils.<init>())
  end public void <init>()

  public static String getPropertyName(String):
                    ALOAD_0     // Ljava/lang/String; propertyPath   (line 35)
                    LDC "]"
                    INVOKEVIRTUAL java.lang.String.endsWith (Ljava/lang/String;)Z
                    IFEQ L0
                    ALOAD_0     // Ljava/lang/String; propertyPath
                    BIPUSH 91
                    INVOKEVIRTUAL java.lang.String.indexOf (I)I   (line 36)
                    GOTO L1
                L0: ICONST_M1
                L1: ISTORE_1
                    ILOAD_1     // I separatorIndex   (line 37)
                    ICONST_M1
                    IF_ICMPEQ L2
                    ALOAD_0     // Ljava/lang/String; propertyPath
                    ICONST_0
                    ILOAD_1     // I separatorIndex
                    INVOKEVIRTUAL java.lang.String.substring (II)Ljava/lang/String;
                    GOTO L3
                L2: ALOAD_0     // Ljava/lang/String; propertyPath
                L3: ARETURN
  end public static String getPropertyName(String)

  public static boolean isNestedOrIndexedProperty(String):
                    ALOAD_0     // Ljava/lang/String; propertyPath   (line 46)
                    IFNONNULL L0
                    ICONST_0   (line 47)
                    IRETURN
                L0: ICONST_0   (line 49)
                    ISTORE_1
                L1: ILOAD_1     // I i
                    ALOAD_0     // Ljava/lang/String; propertyPath
                    INVOKEVIRTUAL java.lang.String.length ()I
                    IF_ICMPGE L4
                    ALOAD_0     // Ljava/lang/String; propertyPath   (line 50)
                    ILOAD_1     // I i
                    INVOKEVIRTUAL java.lang.String.charAt (I)C
                    ISTORE_2
                    ILOAD_2     // C ch   (line 51)
                    BIPUSH 46
                    IF_ICMPEQ L2
                    ILOAD_2     // C ch
                    BIPUSH 91
                    IF_ICMPNE L3
                L2: ICONST_1   (line 53)
                    IRETURN
                L3: IINC_1 1     // I i   (line 49)
                    GOTO L1
                L4: ICONST_0   (line 56)
                    IRETURN
  end public static boolean isNestedOrIndexedProperty(String)

  public static int getFirstNestedPropertySeparatorIndex(String):
                    ALOAD_0     // Ljava/lang/String; propertyPath   (line 66)
                    ICONST_0
                    INVOKESTATIC org.springframework.beans.PropertyAccessorUtils.getNestedPropertySeparatorIndex (Ljava/lang/String;Z)I
                    IRETURN
  end public static int getFirstNestedPropertySeparatorIndex(String)

  public static int getLastNestedPropertySeparatorIndex(String):
                    ALOAD_0     // Ljava/lang/String; propertyPath   (line 76)
                    ICONST_1
                    INVOKESTATIC org.springframework.beans.PropertyAccessorUtils.getNestedPropertySeparatorIndex (Ljava/lang/String;Z)I
                    IRETURN
  end public static int getLastNestedPropertySeparatorIndex(String)

  private static int getNestedPropertySeparatorIndex(String, boolean):
                    ICONST_0   (line 87)
                    ISTORE_2
                    ALOAD_0     // Ljava/lang/String; propertyPath   (line 88)
                    INVOKEVIRTUAL java.lang.String.length ()I
                    ISTORE_3
                    ILOAD_1     // Z last   (line 89)
                    IFEQ L0
                    ILOAD_3     // I length
                    ICONST_1
                    ISUB
                    GOTO L1
                L0: ICONST_0
                L1: ISTORE 4
                L2: ILOAD_1     // Z last   (line 90)
                    IFEQ L3
                    ILOAD 4     // I i
                    IFLT L11
                    GOTO L4
                L3: ILOAD 4     // I i
                    ILOAD_3     // I length
                    IF_ICMPGE L11
                L4: ALOAD_0     // Ljava/lang/String; propertyPath   (line 91)
                    ILOAD 4     // I i
                    INVOKEVIRTUAL java.lang.String.charAt (I)C
                    LOOKUPSWITCH
                      46: 	L8
                      91: 	L5
                      93: 	L5
                      default: 	L9
                L5: ILOAD_2     // Z inKey   (line 94)
                    IFNE L6
                    ICONST_1
                    GOTO L7
                L6: ICONST_0
                L7: ISTORE_2     // Z inKey
                    GOTO L9   (line 95)
                L8: ILOAD_2     // Z inKey   (line 97)
                    IFNE L9
                    ILOAD 4     // I i   (line 98)
                    IRETURN
                L9: ILOAD_1     // Z last   (line 101)
                    IFEQ L10
                    IINC 4 -1     // I i   (line 102)
                    GOTO L2
               L10: IINC 4 1     // I i   (line 105)
                    GOTO L2
               L11: ICONST_M1   (line 108)
                    IRETURN
  end private static int getNestedPropertySeparatorIndex(String, boolean)

  public static boolean matchesProperty(String, String):
                    ALOAD_0     // Ljava/lang/String; registeredPath   (line 119)
                    ALOAD_1     // Ljava/lang/String; propertyPath
                    INVOKEVIRTUAL java.lang.String.startsWith (Ljava/lang/String;)Z
                    IFNE L0
                    ICONST_0   (line 120)
                    IRETURN
                L0: ALOAD_0     // Ljava/lang/String; registeredPath   (line 122)
                    INVOKEVIRTUAL java.lang.String.length ()I
                    ALOAD_1     // Ljava/lang/String; propertyPath
                    INVOKEVIRTUAL java.lang.String.length ()I
                    IF_ICMPNE L1
                    ICONST_1   (line 123)
                    IRETURN
                L1: ALOAD_0     // Ljava/lang/String; registeredPath   (line 125)
                    ALOAD_1     // Ljava/lang/String; propertyPath
                    INVOKEVIRTUAL java.lang.String.length ()I
                    INVOKEVIRTUAL java.lang.String.charAt (I)C
                    BIPUSH 91
                    IF_ICMPEQ L2
                    ICONST_0   (line 126)
                    IRETURN
                L2: ALOAD_0     // Ljava/lang/String; registeredPath   (line 128)
                    BIPUSH 93
                    ALOAD_1     // Ljava/lang/String; propertyPath
                    INVOKEVIRTUAL java.lang.String.length ()I
                    ICONST_1
                    IADD
                    INVOKEVIRTUAL java.lang.String.indexOf (II)I
                    ALOAD_0     // Ljava/lang/String; registeredPath
                    INVOKEVIRTUAL java.lang.String.length ()I   (line 129)
                    ICONST_1
                    ISUB
                    IF_ICMPNE L3
                    ICONST_1
                    GOTO L4
                L3: ICONST_0
                L4: IRETURN
  end public static boolean matchesProperty(String, String)

  public static String canonicalPropertyName(String):
                    ALOAD_0     // Ljava/lang/String; propertyName   (line 141)
                    IFNONNULL L0
                    LDC ""   (line 142)
                    ARETURN
                L0: NEW java.lang.StringBuilder   (line 145)
                    DUP
                    ALOAD_0     // Ljava/lang/String; propertyName
                    INVOKESPECIAL java.lang.StringBuilder.<init> (Ljava/lang/String;)V
                    ASTORE_1
                    ICONST_0   (line 146)
                    ISTORE_2
                L1: ILOAD_2     // I searchIndex   (line 147)
                    ICONST_M1
                    IF_ICMPEQ L6
                    ALOAD_1     // Ljava/lang/StringBuilder; sb   (line 148)
                    LDC "["
                    ILOAD_2     // I searchIndex
                    INVOKEVIRTUAL java.lang.StringBuilder.indexOf (Ljava/lang/String;I)I
                    ISTORE_3
                    ICONST_M1   (line 149)
                    ISTORE_2     // I searchIndex
                    ILOAD_3     // I keyStart   (line 150)
                    ICONST_M1
                    IF_ICMPEQ L5
                    ALOAD_1     // Ljava/lang/StringBuilder; sb   (line 151)
                    LDC "]"
                    ILOAD_3     // I keyStart
                    LDC "["
                    INVOKEVIRTUAL java.lang.String.length ()I   (line 152)
                    IADD
                    INVOKEVIRTUAL java.lang.StringBuilder.indexOf (Ljava/lang/String;I)I   (line 151)
                    ISTORE 4
                    ILOAD 4     // I keyEnd   (line 153)
                    ICONST_M1
                    IF_ICMPEQ L5
                    ALOAD_1     // Ljava/lang/StringBuilder; sb   (line 154)
                    ILOAD_3     // I keyStart
                    LDC "["
                    INVOKEVIRTUAL java.lang.String.length ()I
                    IADD
                    ILOAD 4     // I keyEnd
                    INVOKEVIRTUAL java.lang.StringBuilder.substring (II)Ljava/lang/String;
                    ASTORE 5
                    ALOAD 5     // Ljava/lang/String; key   (line 155)
                    LDC "'"
                    INVOKEVIRTUAL java.lang.String.startsWith (Ljava/lang/String;)Z
                    IFEQ L2
                    ALOAD 5     // Ljava/lang/String; key
                    LDC "'"
                    INVOKEVIRTUAL java.lang.String.endsWith (Ljava/lang/String;)Z
                    IFNE L3
                L2: ALOAD 5     // Ljava/lang/String; key
                    LDC "\""
                    INVOKEVIRTUAL java.lang.String.startsWith (Ljava/lang/String;)Z
                    IFEQ L4
                    ALOAD 5     // Ljava/lang/String; key
                    LDC "\""
                    INVOKEVIRTUAL java.lang.String.endsWith (Ljava/lang/String;)Z
                    IFEQ L4
                L3: ALOAD_1     // Ljava/lang/StringBuilder; sb   (line 156)
                    ILOAD_3     // I keyStart
                    ICONST_1
                    IADD
                    ILOAD_3     // I keyStart
                    ICONST_2
                    IADD
                    INVOKEVIRTUAL java.lang.StringBuilder.delete (II)Ljava/lang/StringBuilder;
                    POP
                    ALOAD_1     // Ljava/lang/StringBuilder; sb   (line 157)
                    ILOAD 4     // I keyEnd
                    ICONST_2
                    ISUB
                    ILOAD 4     // I keyEnd
                    ICONST_1
                    ISUB
                    INVOKEVIRTUAL java.lang.StringBuilder.delete (II)Ljava/lang/StringBuilder;
                    POP
                    ILOAD 4     // I keyEnd   (line 158)
                    ICONST_2
                    ISUB
                    ISTORE 4     // I keyEnd
                L4: ILOAD 4     // I keyEnd   (line 160)
                    LDC "]"
                    INVOKEVIRTUAL java.lang.String.length ()I
                    IADD
                    ISTORE_2     // I searchIndex
                L5: GOTO L1   (line 163)
                L6: ALOAD_1     // Ljava/lang/StringBuilder; sb   (line 164)
                    INVOKEVIRTUAL java.lang.StringBuilder.toString ()Ljava/lang/String;
                    ARETURN
  end public static String canonicalPropertyName(String)

  public static String[] canonicalPropertyNames(String[]):
                    ALOAD_0     // [Ljava/lang/String; propertyNames   (line 175)
                    IFNONNULL L0
                    ACONST_NULL   (line 176)
                    ARETURN
                L0: ALOAD_0     // [Ljava/lang/String; propertyNames   (line 178)
                    ARRAYLENGTH
                    ANEWARRAY java.lang.String
                    ASTORE_1
                    ICONST_0   (line 179)
                    ISTORE_2
                L1: ILOAD_2     // I i
                    ALOAD_0     // [Ljava/lang/String; propertyNames
                    ARRAYLENGTH
                    IF_ICMPGE L2
                    ALOAD_1     // [Ljava/lang/String; result   (line 180)
                    ILOAD_2     // I i
                    ALOAD_0     // [Ljava/lang/String; propertyNames
                    ILOAD_2     // I i
                    AALOAD
                    INVOKESTATIC org.springframework.beans.PropertyAccessorUtils.canonicalPropertyName (Ljava/lang/String;)Ljava/lang/String;
                    AASTORE
                    IINC_2 1     // I i   (line 179)
                    GOTO L1
                L2: ALOAD_1     // [Ljava/lang/String; result   (line 182)
                    ARETURN
  end public static String[] canonicalPropertyNames(String[])

end public abstract class org.springframework.beans.PropertyAccessorUtils

	at org.aspectj.bridge.MessageWriter.handleMessage(MessageWriter.java:47)
	at org.aspectj.weaver.tools.WeavingAdaptor$WeavingAdaptorMessageWriter.handleMessage(WeavingAdaptor.java:742)
	at org.aspectj.weaver.tools.WeavingAdaptor$WeavingAdaptorMessageHolder.handleMessage(WeavingAdaptor.java:687)
	at org.aspectj.weaver.bcel.BcelWeaver.weave(BcelWeaver.java:1720)
	at org.aspectj.weaver.bcel.BcelWeaver.weaveWithoutDump(BcelWeaver.java:1638)
	at org.aspectj.weaver.bcel.BcelWeaver.weaveAndNotify(BcelWeaver.java:1401)
	at org.aspectj.weaver.bcel.BcelWeaver.weave(BcelWeaver.java:1187)
	at org.aspectj.weaver.tools.WeavingAdaptor.getWovenBytes(WeavingAdaptor.java:472)
	at org.aspectj.weaver.tools.WeavingAdaptor.weaveClass(WeavingAdaptor.java:323)
	at org.aspectj.weaver.loadtime.Aj.preProcess(Aj.java:99)
	at org.aspectj.weaver.loadtime.ClassPreProcessorAgentAdapter.transform(ClassPreProcessorAgentAdapter.java:54)
	at org.springframework.context.weaving.AspectJWeavingEnabler$AspectJClassBypassingClassFileTransformer.transform(AspectJWeavingEnabler.java:108)
	at org.springframework.instrument.classloading.InstrumentationLoadTimeWeaver$FilteringClassFileTransformer.transform(InstrumentationLoadTimeWeaver.java:184)
	at sun.instrument.TransformerManager.transform(Unknown Source)
	at sun.instrument.InstrumentationImpl.transform(Unknown Source)
	at java.lang.ClassLoader.defineClass1(Native Method)
	at java.lang.ClassLoader.defineClass(Unknown Source)
	at java.security.SecureClassLoader.defineClass(Unknown Source)
	at java.net.URLClassLoader.defineClass(Unknown Source)
	at java.net.URLClassLoader.access$100(Unknown Source)
	at java.net.URLClassLoader$1.run(Unknown Source)
	at java.net.URLClassLoader$1.run(Unknown Source)
	at java.security.AccessController.doPrivileged(Native Method)
	at java.net.URLClassLoader.findClass(Unknown Source)
	at java.lang.ClassLoader.loadClass(Unknown Source)
	at sun.misc.Launcher$AppClassLoader.loadClass(Unknown Source)
	at java.lang.ClassLoader.loadClass(Unknown Source)
	at org.springframework.beans.BeanWrapperImpl.getBeanWrapperForPropertyPath(BeanWrapperImpl.java:544)
	at org.springframework.beans.BeanWrapperImpl.getPropertyDescriptorInternal(BeanWrapperImpl.java:359)
	at org.springframework.beans.BeanWrapperImpl.isWritableProperty(BeanWrapperImpl.java:440)
	at org.springframework.beans.factory.support.AbstractAutowireCapableBeanFactory.applyPropertyValues(AbstractAutowireCapableBeanFactory.java:1479)
	at org.springframework.beans.factory.support.AbstractAutowireCapableBeanFactory.populateBean(AbstractAutowireCapableBeanFactory.java:1222)
	at org.springframework.beans.factory.support.AbstractAutowireCapableBeanFactory.doCreateBean(AbstractAutowireCapableBeanFactory.java:537)
	at org.springframework.beans.factory.support.AbstractAutowireCapableBeanFactory.createBean(AbstractAutowireCapableBeanFactory.java:476)
	at org.springframework.beans.factory.support.AbstractBeanFactory$1.getObject(AbstractBeanFactory.java:303)
	at org.springframework.beans.factory.support.DefaultSingletonBeanRegistry.getSingleton(DefaultSingletonBeanRegistry.java:230)
	at org.springframework.beans.factory.support.AbstractBeanFactory.doGetBean(AbstractBeanFactory.java:299)
	at org.springframework.beans.factory.support.AbstractBeanFactory.getBean(AbstractBeanFactory.java:194)
	at org.springframework.beans.factory.support.DefaultListableBeanFactory.findAutowireCandidates(DefaultListableBeanFactory.java:1120)
	at org.springframework.beans.factory.support.DefaultListableBeanFactory.doResolveDependency(DefaultListableBeanFactory.java:996)
	at org.springframework.beans.factory.support.DefaultListableBeanFactory.resolveDependency(DefaultListableBeanFactory.java:942)
	at org.springframework.beans.factory.annotation.AutowiredAnnotationBeanPostProcessor$AutowiredFieldElement.inject(AutowiredAnnotationBeanPostProcessor.java:533)
	at org.springframework.beans.factory.annotation.InjectionMetadata.inject(InjectionMetadata.java:88)
	at org.springframework.beans.factory.annotation.AutowiredAnnotationBeanPostProcessor.postProcessPropertyValues(AutowiredAnnotationBeanPostProcessor.java:331)
	at org.springframework.beans.factory.support.AbstractAutowireCapableBeanFactory.populateBean(AbstractAutowireCapableBeanFactory.java:1210)
	at org.springframework.beans.factory.support.AbstractAutowireCapableBeanFactory.doCreateBean(AbstractAutowireCapableBeanFactory.java:537)
	at org.springframework.beans.factory.support.AbstractAutowireCapableBeanFactory.createBean(AbstractAutowireCapableBeanFactory.java:476)
	at org.springframework.beans.factory.support.AbstractBeanFactory$1.getObject(AbstractBeanFactory.java:303)
	at org.springframework.beans.factory.support.DefaultSingletonBeanRegistry.getSingleton(DefaultSingletonBeanRegistry.java:230)
	at org.springframework.beans.factory.support.AbstractBeanFactory.doGetBean(AbstractBeanFactory.java:299)
	at org.springframework.beans.factory.support.AbstractBeanFactory.getBean(AbstractBeanFactory.java:194)
	at org.springframework.beans.factory.support.DefaultListableBeanFactory.preInstantiateSingletons(DefaultListableBeanFactory.java:755)
	at org.springframework.context.support.AbstractApplicationContext.finishBeanFactoryInitialization(AbstractApplicationContext.java:757)
	at org.springframework.context.support.AbstractApplicationContext.refresh(AbstractApplicationContext.java:480)
	at org.springframework.context.support.ClassPathXmlApplicationContext.<init>(ClassPathXmlApplicationContext.java:139)
	at org.springframework.context.support.ClassPathXmlApplicationContext.<init>(ClassPathXmlApplicationContext.java:93)
	at com.springExemple.presentation.Presentation2.main(Presentation2.java:13)
---- System Properties ---
java.runtime.name=Java(TM) SE Runtime Environment
sun.boot.library.path=C:\Program Files\Java\jre1.8.0_121\bin
java.vm.version=25.121-b13
java.vm.vendor=Oracle Corporation
java.vendor.url=http://java.oracle.com/
path.separator=;
java.vm.name=Java HotSpot(TM) 64-Bit Server VM
file.encoding.pkg=sun.io
user.country=FR
user.script=
sun.java.launcher=SUN_STANDARD
sun.os.patch.level=
java.vm.specification.name=Java Virtual Machine Specification
user.dir=C:\Users\formation\git\projects\SpringExpl
java.runtime.version=1.8.0_121-b13
java.awt.graphicsenv=sun.awt.Win32GraphicsEnvironment
java.endorsed.dirs=C:\Program Files\Java\jre1.8.0_121\lib\endorsed
os.arch=amd64
java.io.tmpdir=C:\Users\FORMAT~1\AppData\Local\Temp\
line.separator=

java.vm.specification.vendor=Oracle Corporation
user.variant=
os.name=Windows 10
sun.jnu.encoding=Cp1252
java.library.path=C:\Program Files\Java\jre1.8.0_121\bin;C:\windows\Sun\Java\bin;C:\windows\system32;C:\windows;C:/Program Files/Java/jre1.8.0_121/bin/server;C:/Program Files/Java/jre1.8.0_121/bin;C:/Program Files/Java/jre1.8.0_121/lib/amd64;C:\ProgramData\Oracle\Java\javapath;C:\windows\system32;C:\windows;C:\windows\System32\Wbem;C:\windows\System32\WindowsPowerShell\v1.0\;C:\Program Files\Java\jdk1.8.0_101\bin;C:\Outils\apache-maven-3.3.9\bin;C:\Users\formation\AppData\Local\Microsoft\WindowsApps;;C:\Users\formation\Desktop\JRE JDK ECLIPSE\sts-bundle\sts-3.8.3.RELEASE;;.
java.specification.name=Java Platform API Specification
java.class.version=52.0
sun.management.compiler=HotSpot 64-Bit Tiered Compilers
os.version=10.0
user.home=C:\Users\formation
user.timezone=Europe/Paris
java.awt.printerjob=sun.awt.windows.WPrinterJob
file.encoding=UTF-8
java.specification.version=1.8
java.class.path=C:\Users\formation\git\projects\SpringExpl\target\classes;C:\Users\formation\.m2\repository\org\springframework\spring-aspects\4.1.4.RELEASE\spring-aspects-4.1.4.RELEASE.jar;C:\Users\formation\.m2\repository\org\aspectj\aspectjrt\1.6.12\aspectjrt-1.6.12.jar;C:\Users\formation\.m2\repository\org\aspectj\aspectjweaver\1.6.12\aspectjweaver-1.6.12.jar;C:\Users\formation\.m2\repository\org\springframework\spring-core\4.1.6.RELEASE\spring-core-4.1.6.RELEASE.jar;C:\Users\formation\.m2\repository\commons-logging\commons-logging\1.2\commons-logging-1.2.jar;C:\Users\formation\.m2\repository\org\springframework\spring-context\4.1.6.RELEASE\spring-context-4.1.6.RELEASE.jar;C:\Users\formation\.m2\repository\org\springframework\spring-aop\4.1.6.RELEASE\spring-aop-4.1.6.RELEASE.jar;C:\Users\formation\.m2\repository\aopalliance\aopalliance\1.0\aopalliance-1.0.jar;C:\Users\formation\.m2\repository\org\springframework\spring-beans\4.1.6.RELEASE\spring-beans-4.1.6.RELEASE.jar;C:\Users\formation\.m2\repository\org\springframework\spring-expression\4.1.6.RELEASE\spring-expression-4.1.6.RELEASE.jar;C:\Users\formation\Desktop\spring-agent-2.5.6.jar
user.name=formation
java.vm.specification.version=1.8
sun.java.command=com.springExemple.presentation.Presentation2
java.home=C:\Program Files\Java\jre1.8.0_121
sun.arch.data.model=64
user.language=fr
java.specification.vendor=Oracle Corporation
awt.toolkit=sun.awt.windows.WToolkit
java.vm.info=mixed mode
java.version=1.8.0_121
java.ext.dirs=C:\Program Files\Java\jre1.8.0_121\lib\ext;C:\windows\Sun\Java\lib\ext
sun.boot.class.path=C:\Program Files\Java\jre1.8.0_121\lib\resources.jar;C:\Program Files\Java\jre1.8.0_121\lib\rt.jar;C:\Program Files\Java\jre1.8.0_121\lib\sunrsasign.jar;C:\Program Files\Java\jre1.8.0_121\lib\jsse.jar;C:\Program Files\Java\jre1.8.0_121\lib\jce.jar;C:\Program Files\Java\jre1.8.0_121\lib\charsets.jar;C:\Program Files\Java\jre1.8.0_121\lib\jfr.jar;C:\Program Files\Java\jre1.8.0_121\classes
java.vendor=Oracle Corporation
file.separator=\
java.vendor.url.bug=http://bugreport.sun.com/bugreport/
sun.io.unicode.encoding=UnicodeLittle
sun.cpu.endian=little
sun.desktop=windows
sun.cpu.isalist=amd64
---- Command Line ---
Empty
---- Full Classpath ---
Empty
---- Compiler Messages ---
Empty
