---- AspectJ Properties ---
AspectJ Compiler 1.6.12 built on Tuesday Oct 18, 2011 at 17:52:06 GMT
---- Dump Properties ---
Dump file: ajcore.20170412.115632.074.txt
Dump reason: org.aspectj.bridge.AbortException
Dump on exception: true
Dump at exit condition: abort
---- Exception Information ---
Message: abort trouble in: 
public abstract class org.springframework.core.CollectionFactory extends java.lang.Object:
  private static final java.util.Set approximableCollectionTypes [Signature(Ljava/util/Set<Ljava/lang/Class<*>;>;)]
  private static final java.util.Set approximableMapTypes [Signature(Ljava/util/Set<Ljava/lang/Class<*>;>;)]
  public void <init>():
                    ALOAD_0     // Lorg/springframework/core/CollectionFactory; this   (line 55)
                    INVOKESPECIAL java.lang.Object.<init> ()V
    constructor-execution(void org.springframework.core.CollectionFactory.<init>())
    |               RETURN
    constructor-execution(void org.springframework.core.CollectionFactory.<init>())
  end public void <init>()

  public static boolean isApproximableCollectionType(Class):
                    ALOAD_0     // Ljava/lang/Class; collectionType   (line 94)
                    IFNULL L0
                    GETSTATIC org.springframework.core.CollectionFactory.approximableCollectionTypes Ljava/util/Set;
                    ALOAD_0     // Ljava/lang/Class; collectionType
                    INVOKEINTERFACE java.util.Set.contains (Ljava/lang/Object;)Z
                    IFEQ L0
                    ICONST_1
                    GOTO L1
                L0: ICONST_0
                L1: IRETURN
  end public static boolean isApproximableCollectionType(Class)

  public static java.util.Collection createApproximateCollection(Object, int):
                    ALOAD_0     // Ljava/lang/Object; collection   (line 111)
                    INSTANCEOF java.util.LinkedList
                    IFEQ L0
                    NEW java.util.LinkedList   (line 112)
                    DUP
                    INVOKESPECIAL java.util.LinkedList.<init> ()V
                    ARETURN
                L0: ALOAD_0     // Ljava/lang/Object; collection   (line 114)
                    INSTANCEOF java.util.List
                    IFEQ L1
                    NEW java.util.ArrayList   (line 115)
                    DUP
                    ILOAD_1     // I capacity
                    INVOKESPECIAL java.util.ArrayList.<init> (I)V
                    ARETURN
                L1: ALOAD_0     // Ljava/lang/Object; collection   (line 117)
                    INSTANCEOF java.util.EnumSet
                    IFEQ L2
                    ALOAD_0     // Ljava/lang/Object; collection   (line 119)
                    CHECKCAST java.util.EnumSet
                    INVOKESTATIC java.util.EnumSet.copyOf (Ljava/util/EnumSet;)Ljava/util/EnumSet;
                    ASTORE_2
                    ALOAD_2     // Ljava/util/Collection; enumSet   (line 120)
                    INVOKEINTERFACE java.util.Collection.clear ()V
                    ALOAD_2     // Ljava/util/Collection; enumSet   (line 121)
                    ARETURN
                L2: ALOAD_0     // Ljava/lang/Object; collection   (line 123)
                    INSTANCEOF java.util.SortedSet
                    IFEQ L3
                    NEW java.util.TreeSet   (line 124)
                    DUP
                    ALOAD_0     // Ljava/lang/Object; collection
                    CHECKCAST java.util.SortedSet
                    INVOKEINTERFACE java.util.SortedSet.comparator ()Ljava/util/Comparator;
                    INVOKESPECIAL java.util.TreeSet.<init> (Ljava/util/Comparator;)V
                    ARETURN
                L3: NEW java.util.LinkedHashSet   (line 127)
                    DUP
                    ILOAD_1     // I capacity
                    INVOKESPECIAL java.util.LinkedHashSet.<init> (I)V
                    ARETURN
  end public static java.util.Collection createApproximateCollection(Object, int)

  public static java.util.Collection createCollection(Class, int):
                    ALOAD_0     // Ljava/lang/Class; collectionType   (line 140)
                    ACONST_NULL
                    ILOAD_1     // I capacity
                    INVOKESTATIC org.springframework.core.CollectionFactory.createCollection (Ljava/lang/Class;Ljava/lang/Class;I)Ljava/util/Collection;
                    ARETURN
  end public static java.util.Collection createCollection(Class, int)

  public static java.util.Collection createCollection(Class, Class, int):
                    ALOAD_0     // Ljava/lang/Class; collectionType   (line 158)
                    LDC "Collection type must not be null"
                    INVOKESTATIC org.springframework.util.Assert.notNull (Ljava/lang/Object;Ljava/lang/String;)V
                    ALOAD_0     // Ljava/lang/Class; collectionType   (line 159)
                    INVOKEVIRTUAL java.lang.Class.isInterface ()Z
                    IFEQ L5
                    LDC java.util.Set   (line 160)
                    ALOAD_0     // Ljava/lang/Class; collectionType
                    INVOKEVIRTUAL java.lang.Object.equals (Ljava/lang/Object;)Z
                    IFNE L0
                    LDC java.util.Collection
                    ALOAD_0     // Ljava/lang/Class; collectionType
                    INVOKEVIRTUAL java.lang.Object.equals (Ljava/lang/Object;)Z
                    IFEQ L1
                L0: NEW java.util.LinkedHashSet   (line 161)
                    DUP
                    ILOAD_2     // I capacity
                    INVOKESPECIAL java.util.LinkedHashSet.<init> (I)V
                    ARETURN
                L1: LDC java.util.List   (line 163)
                    ALOAD_0     // Ljava/lang/Class; collectionType
                    INVOKEVIRTUAL java.lang.Object.equals (Ljava/lang/Object;)Z
                    IFEQ L2
                    NEW java.util.ArrayList   (line 164)
                    DUP
                    ILOAD_2     // I capacity
                    INVOKESPECIAL java.util.ArrayList.<init> (I)V
                    ARETURN
                L2: LDC java.util.SortedSet   (line 166)
                    ALOAD_0     // Ljava/lang/Class; collectionType
                    INVOKEVIRTUAL java.lang.Object.equals (Ljava/lang/Object;)Z
                    IFNE L3
                    LDC java.util.NavigableSet
                    ALOAD_0     // Ljava/lang/Class; collectionType
                    INVOKEVIRTUAL java.lang.Object.equals (Ljava/lang/Object;)Z
                    IFEQ L4
                L3: NEW java.util.TreeSet   (line 167)
                    DUP
                    INVOKESPECIAL java.util.TreeSet.<init> ()V
                    ARETURN
                L4: NEW java.lang.IllegalArgumentException   (line 170)
                    DUP
                    NEW java.lang.StringBuilder
                    DUP
                    INVOKESPECIAL java.lang.StringBuilder.<init> ()V
                    LDC "Unsupported Collection interface: "
                    INVOKEVIRTUAL java.lang.StringBuilder.append (Ljava/lang/String;)Ljava/lang/StringBuilder;
                    ALOAD_0     // Ljava/lang/Class; collectionType
                    INVOKEVIRTUAL java.lang.Class.getName ()Ljava/lang/String;
                    INVOKEVIRTUAL java.lang.StringBuilder.append (Ljava/lang/String;)Ljava/lang/StringBuilder;
                    INVOKEVIRTUAL java.lang.StringBuilder.toString ()Ljava/lang/String;
                    INVOKESPECIAL java.lang.IllegalArgumentException.<init> (Ljava/lang/String;)V
                    ATHROW
                L5: LDC java.util.EnumSet   (line 173)
                    ALOAD_0     // Ljava/lang/Class; collectionType
                    INVOKEVIRTUAL java.lang.Object.equals (Ljava/lang/Object;)Z
                    IFEQ L6
                    ALOAD_1     // Ljava/lang/Class; elementType   (line 174)
                    LDC "Cannot create EnumSet for unknown element type"
                    INVOKESTATIC org.springframework.util.Assert.notNull (Ljava/lang/Object;Ljava/lang/String;)V
                    ALOAD_1     // Ljava/lang/Class; elementType   (line 176)
                    INVOKESTATIC org.springframework.core.CollectionFactory.asEnumType (Ljava/lang/Class;)Ljava/lang/Class;
                    INVOKESTATIC java.util.EnumSet.noneOf (Ljava/lang/Class;)Ljava/util/EnumSet;
                    ARETURN
                L6: LDC java.util.Collection   (line 179)
                    ALOAD_0     // Ljava/lang/Class; collectionType
                    INVOKEVIRTUAL java.lang.Class.isAssignableFrom (Ljava/lang/Class;)Z
                    IFNE L7
                    NEW java.lang.IllegalArgumentException   (line 180)
                    DUP
                    NEW java.lang.StringBuilder
                    DUP
                    INVOKESPECIAL java.lang.StringBuilder.<init> ()V
                    LDC "Unsupported Collection type: "
                    INVOKEVIRTUAL java.lang.StringBuilder.append (Ljava/lang/String;)Ljava/lang/StringBuilder;
                    ALOAD_0     // Ljava/lang/Class; collectionType
                    INVOKEVIRTUAL java.lang.Class.getName ()Ljava/lang/String;
                    INVOKEVIRTUAL java.lang.StringBuilder.append (Ljava/lang/String;)Ljava/lang/StringBuilder;
                    INVOKEVIRTUAL java.lang.StringBuilder.toString ()Ljava/lang/String;
                    INVOKESPECIAL java.lang.IllegalArgumentException.<init> (Ljava/lang/String;)V
                    ATHROW
    catch java.lang.Exception -> E0
    |           L7: ALOAD_0     // Ljava/lang/Class; collectionType   (line 183)
    |               INVOKEVIRTUAL java.lang.Class.newInstance ()Ljava/lang/Object;
    |               CHECKCAST java.util.Collection
    catch java.lang.Exception -> E0
                    ARETURN
                E0: ASTORE_3   (line 185)
                    NEW java.lang.IllegalArgumentException   (line 186)
                    DUP
                    NEW java.lang.StringBuilder
                    DUP
                    INVOKESPECIAL java.lang.StringBuilder.<init> ()V
                    LDC "Could not instantiate Collection type: "
                    INVOKEVIRTUAL java.lang.StringBuilder.append (Ljava/lang/String;)Ljava/lang/StringBuilder;
                    ALOAD_0     // Ljava/lang/Class; collectionType
                    INVOKEVIRTUAL java.lang.Class.getName ()Ljava/lang/String;   (line 187)
                    INVOKEVIRTUAL java.lang.StringBuilder.append (Ljava/lang/String;)Ljava/lang/StringBuilder;
                    INVOKEVIRTUAL java.lang.StringBuilder.toString ()Ljava/lang/String;
                    ALOAD_3     // Ljava/lang/Exception; ex
                    INVOKESPECIAL java.lang.IllegalArgumentException.<init> (Ljava/lang/String;Ljava/lang/Throwable;)V
                    ATHROW
  end public static java.util.Collection createCollection(Class, Class, int)

  public static boolean isApproximableMapType(Class):
                    ALOAD_0     // Ljava/lang/Class; mapType   (line 199)
                    IFNULL L0
                    GETSTATIC org.springframework.core.CollectionFactory.approximableMapTypes Ljava/util/Set;
                    ALOAD_0     // Ljava/lang/Class; mapType
                    INVOKEINTERFACE java.util.Set.contains (Ljava/lang/Object;)Z
                    IFEQ L0
                    ICONST_1
                    GOTO L1
                L0: ICONST_0
                L1: IRETURN
  end public static boolean isApproximableMapType(Class)

  public static java.util.Map createApproximateMap(Object, int):
                    ALOAD_0     // Ljava/lang/Object; map   (line 214)
                    INSTANCEOF java.util.EnumMap
                    IFEQ L0
                    NEW java.util.EnumMap   (line 215)
                    DUP
                    ALOAD_0     // Ljava/lang/Object; map
                    CHECKCAST java.util.EnumMap
                    INVOKESPECIAL java.util.EnumMap.<init> (Ljava/util/EnumMap;)V
                    ASTORE_2
                    ALOAD_2     // Ljava/util/EnumMap; enumMap   (line 216)
                    INVOKEVIRTUAL java.util.EnumMap.clear ()V
                    ALOAD_2     // Ljava/util/EnumMap; enumMap   (line 217)
                    ARETURN
                L0: ALOAD_0     // Ljava/lang/Object; map   (line 219)
                    INSTANCEOF java.util.SortedMap
                    IFEQ L1
                    NEW java.util.TreeMap   (line 220)
                    DUP
                    ALOAD_0     // Ljava/lang/Object; map
                    CHECKCAST java.util.SortedMap
                    INVOKEINTERFACE java.util.SortedMap.comparator ()Ljava/util/Comparator;
                    INVOKESPECIAL java.util.TreeMap.<init> (Ljava/util/Comparator;)V
                    ARETURN
                L1: NEW java.util.LinkedHashMap   (line 223)
                    DUP
                    ILOAD_1     // I capacity
                    INVOKESPECIAL java.util.LinkedHashMap.<init> (I)V
                    ARETURN
  end public static java.util.Map createApproximateMap(Object, int)

  public static java.util.Map createMap(Class, int):
                    ALOAD_0     // Ljava/lang/Class; mapType   (line 236)
                    ACONST_NULL
                    ILOAD_1     // I capacity
                    INVOKESTATIC org.springframework.core.CollectionFactory.createMap (Ljava/lang/Class;Ljava/lang/Class;I)Ljava/util/Map;
                    ARETURN
  end public static java.util.Map createMap(Class, int)

  public static java.util.Map createMap(Class, Class, int):
                    ALOAD_0     // Ljava/lang/Class; mapType   (line 254)
                    LDC "Map type must not be null"
                    INVOKESTATIC org.springframework.util.Assert.notNull (Ljava/lang/Object;Ljava/lang/String;)V
                    ALOAD_0     // Ljava/lang/Class; mapType   (line 255)
                    INVOKEVIRTUAL java.lang.Class.isInterface ()Z
                    IFEQ L4
                    LDC java.util.Map   (line 256)
                    ALOAD_0     // Ljava/lang/Class; mapType
                    INVOKEVIRTUAL java.lang.Object.equals (Ljava/lang/Object;)Z
                    IFEQ L0
                    NEW java.util.LinkedHashMap   (line 257)
                    DUP
                    ILOAD_2     // I capacity
                    INVOKESPECIAL java.util.LinkedHashMap.<init> (I)V
                    ARETURN
                L0: LDC java.util.SortedMap   (line 259)
                    ALOAD_0     // Ljava/lang/Class; mapType
                    INVOKEVIRTUAL java.lang.Object.equals (Ljava/lang/Object;)Z
                    IFNE L1
                    LDC java.util.NavigableMap
                    ALOAD_0     // Ljava/lang/Class; mapType
                    INVOKEVIRTUAL java.lang.Object.equals (Ljava/lang/Object;)Z
                    IFEQ L2
                L1: NEW java.util.TreeMap   (line 260)
                    DUP
                    INVOKESPECIAL java.util.TreeMap.<init> ()V
                    ARETURN
                L2: LDC org.springframework.util.MultiValueMap   (line 262)
                    ALOAD_0     // Ljava/lang/Class; mapType
                    INVOKEVIRTUAL java.lang.Object.equals (Ljava/lang/Object;)Z
                    IFEQ L3
                    NEW org.springframework.util.LinkedMultiValueMap   (line 263)
                    DUP
                    INVOKESPECIAL org.springframework.util.LinkedMultiValueMap.<init> ()V
                    ARETURN
                L3: NEW java.lang.IllegalArgumentException   (line 266)
                    DUP
                    NEW java.lang.StringBuilder
                    DUP
                    INVOKESPECIAL java.lang.StringBuilder.<init> ()V
                    LDC "Unsupported Map interface: "
                    INVOKEVIRTUAL java.lang.StringBuilder.append (Ljava/lang/String;)Ljava/lang/StringBuilder;
                    ALOAD_0     // Ljava/lang/Class; mapType
                    INVOKEVIRTUAL java.lang.Class.getName ()Ljava/lang/String;
                    INVOKEVIRTUAL java.lang.StringBuilder.append (Ljava/lang/String;)Ljava/lang/StringBuilder;
                    INVOKEVIRTUAL java.lang.StringBuilder.toString ()Ljava/lang/String;
                    INVOKESPECIAL java.lang.IllegalArgumentException.<init> (Ljava/lang/String;)V
                    ATHROW
                L4: LDC java.util.EnumMap   (line 269)
                    ALOAD_0     // Ljava/lang/Class; mapType
                    INVOKEVIRTUAL java.lang.Object.equals (Ljava/lang/Object;)Z
                    IFEQ L5
                    ALOAD_1     // Ljava/lang/Class; keyType   (line 270)
                    LDC "Cannot create EnumMap for unknown key type"
                    INVOKESTATIC org.springframework.util.Assert.notNull (Ljava/lang/Object;Ljava/lang/String;)V
                    NEW java.util.EnumMap   (line 271)
                    DUP
                    ALOAD_1     // Ljava/lang/Class; keyType
                    INVOKESTATIC org.springframework.core.CollectionFactory.asEnumType (Ljava/lang/Class;)Ljava/lang/Class;
                    INVOKESPECIAL java.util.EnumMap.<init> (Ljava/lang/Class;)V
                    ARETURN
                L5: LDC java.util.Map   (line 274)
                    ALOAD_0     // Ljava/lang/Class; mapType
                    INVOKEVIRTUAL java.lang.Class.isAssignableFrom (Ljava/lang/Class;)Z
                    IFNE L6
                    NEW java.lang.IllegalArgumentException   (line 275)
                    DUP
                    NEW java.lang.StringBuilder
                    DUP
                    INVOKESPECIAL java.lang.StringBuilder.<init> ()V
                    LDC "Unsupported Map type: "
                    INVOKEVIRTUAL java.lang.StringBuilder.append (Ljava/lang/String;)Ljava/lang/StringBuilder;
                    ALOAD_0     // Ljava/lang/Class; mapType
                    INVOKEVIRTUAL java.lang.Class.getName ()Ljava/lang/String;
                    INVOKEVIRTUAL java.lang.StringBuilder.append (Ljava/lang/String;)Ljava/lang/StringBuilder;
                    INVOKEVIRTUAL java.lang.StringBuilder.toString ()Ljava/lang/String;
                    INVOKESPECIAL java.lang.IllegalArgumentException.<init> (Ljava/lang/String;)V
                    ATHROW
    catch java.lang.Exception -> E0
    |           L6: ALOAD_0     // Ljava/lang/Class; mapType   (line 278)
    |               INVOKEVIRTUAL java.lang.Class.newInstance ()Ljava/lang/Object;
    |               CHECKCAST java.util.Map
    catch java.lang.Exception -> E0
                    ARETURN
                E0: ASTORE_3   (line 280)
                    NEW java.lang.IllegalArgumentException   (line 281)
                    DUP
                    NEW java.lang.StringBuilder
                    DUP
                    INVOKESPECIAL java.lang.StringBuilder.<init> ()V
                    LDC "Could not instantiate Map type: "
                    INVOKEVIRTUAL java.lang.StringBuilder.append (Ljava/lang/String;)Ljava/lang/StringBuilder;
                    ALOAD_0     // Ljava/lang/Class; mapType
                    INVOKEVIRTUAL java.lang.Class.getName ()Ljava/lang/String;
                    INVOKEVIRTUAL java.lang.StringBuilder.append (Ljava/lang/String;)Ljava/lang/StringBuilder;
                    INVOKEVIRTUAL java.lang.StringBuilder.toString ()Ljava/lang/String;
                    ALOAD_3     // Ljava/lang/Exception; ex
                    INVOKESPECIAL java.lang.IllegalArgumentException.<init> (Ljava/lang/String;Ljava/lang/Throwable;)V
                    ATHROW
  end public static java.util.Map createMap(Class, Class, int)

  private static Class asEnumType(Class):
                    ALOAD_0     // Ljava/lang/Class; enumType   (line 294)
                    LDC "Enum type must not be null"
                    INVOKESTATIC org.springframework.util.Assert.notNull (Ljava/lang/Object;Ljava/lang/String;)V
                    LDC java.lang.Enum   (line 295)
                    ALOAD_0     // Ljava/lang/Class; enumType
                    INVOKEVIRTUAL java.lang.Class.isAssignableFrom (Ljava/lang/Class;)Z
                    IFNE L0
                    NEW java.lang.IllegalArgumentException   (line 296)
                    DUP
                    NEW java.lang.StringBuilder
                    DUP
                    INVOKESPECIAL java.lang.StringBuilder.<init> ()V
                    LDC "Supplied type is not an enum: "
                    INVOKEVIRTUAL java.lang.StringBuilder.append (Ljava/lang/String;)Ljava/lang/StringBuilder;
                    ALOAD_0     // Ljava/lang/Class; enumType
                    INVOKEVIRTUAL java.lang.Class.getName ()Ljava/lang/String;
                    INVOKEVIRTUAL java.lang.StringBuilder.append (Ljava/lang/String;)Ljava/lang/StringBuilder;
                    INVOKEVIRTUAL java.lang.StringBuilder.toString ()Ljava/lang/String;
                    INVOKESPECIAL java.lang.IllegalArgumentException.<init> (Ljava/lang/String;)V
                    ATHROW
                L0: ALOAD_0     // Ljava/lang/Class; enumType   (line 298)
                    LDC java.lang.Enum
                    INVOKEVIRTUAL java.lang.Class.asSubclass (Ljava/lang/Class;)Ljava/lang/Class;
                    ARETURN
  end private static Class asEnumType(Class)

  static void <clinit>():
                    NEW java.util.HashSet   (line 57)
                    DUP
                    BIPUSH 11
                    INVOKESPECIAL java.util.HashSet.<init> (I)V
                    PUTSTATIC org.springframework.core.CollectionFactory.approximableCollectionTypes Ljava/util/Set;
                    NEW java.util.HashSet   (line 59)
                    DUP
                    BIPUSH 7
                    INVOKESPECIAL java.util.HashSet.<init> (I)V
                    PUTSTATIC org.springframework.core.CollectionFactory.approximableMapTypes Ljava/util/Set;
                    GETSTATIC org.springframework.core.CollectionFactory.approximableCollectionTypes Ljava/util/Set;   (line 64)
                    LDC java.util.Collection
                    INVOKEINTERFACE java.util.Set.add (Ljava/lang/Object;)Z
                    POP
                    GETSTATIC org.springframework.core.CollectionFactory.approximableCollectionTypes Ljava/util/Set;   (line 65)
                    LDC java.util.List
                    INVOKEINTERFACE java.util.Set.add (Ljava/lang/Object;)Z
                    POP
                    GETSTATIC org.springframework.core.CollectionFactory.approximableCollectionTypes Ljava/util/Set;   (line 66)
                    LDC java.util.Set
                    INVOKEINTERFACE java.util.Set.add (Ljava/lang/Object;)Z
                    POP
                    GETSTATIC org.springframework.core.CollectionFactory.approximableCollectionTypes Ljava/util/Set;   (line 67)
                    LDC java.util.SortedSet
                    INVOKEINTERFACE java.util.Set.add (Ljava/lang/Object;)Z
                    POP
                    GETSTATIC org.springframework.core.CollectionFactory.approximableCollectionTypes Ljava/util/Set;   (line 68)
                    LDC java.util.NavigableSet
                    INVOKEINTERFACE java.util.Set.add (Ljava/lang/Object;)Z
                    POP
                    GETSTATIC org.springframework.core.CollectionFactory.approximableMapTypes Ljava/util/Set;   (line 69)
                    LDC java.util.Map
                    INVOKEINTERFACE java.util.Set.add (Ljava/lang/Object;)Z
                    POP
                    GETSTATIC org.springframework.core.CollectionFactory.approximableMapTypes Ljava/util/Set;   (line 70)
                    LDC java.util.SortedMap
                    INVOKEINTERFACE java.util.Set.add (Ljava/lang/Object;)Z
                    POP
                    GETSTATIC org.springframework.core.CollectionFactory.approximableMapTypes Ljava/util/Set;   (line 71)
                    LDC java.util.NavigableMap
                    INVOKEINTERFACE java.util.Set.add (Ljava/lang/Object;)Z
                    POP
                    GETSTATIC org.springframework.core.CollectionFactory.approximableCollectionTypes Ljava/util/Set;   (line 74)
                    LDC java.util.ArrayList
                    INVOKEINTERFACE java.util.Set.add (Ljava/lang/Object;)Z
                    POP
                    GETSTATIC org.springframework.core.CollectionFactory.approximableCollectionTypes Ljava/util/Set;   (line 75)
                    LDC java.util.LinkedList
                    INVOKEINTERFACE java.util.Set.add (Ljava/lang/Object;)Z
                    POP
                    GETSTATIC org.springframework.core.CollectionFactory.approximableCollectionTypes Ljava/util/Set;   (line 76)
                    LDC java.util.HashSet
                    INVOKEINTERFACE java.util.Set.add (Ljava/lang/Object;)Z
                    POP
                    GETSTATIC org.springframework.core.CollectionFactory.approximableCollectionTypes Ljava/util/Set;   (line 77)
                    LDC java.util.LinkedHashSet
                    INVOKEINTERFACE java.util.Set.add (Ljava/lang/Object;)Z
                    POP
                    GETSTATIC org.springframework.core.CollectionFactory.approximableCollectionTypes Ljava/util/Set;   (line 78)
                    LDC java.util.TreeSet
                    INVOKEINTERFACE java.util.Set.add (Ljava/lang/Object;)Z
                    POP
                    GETSTATIC org.springframework.core.CollectionFactory.approximableCollectionTypes Ljava/util/Set;   (line 79)
                    LDC java.util.EnumSet
                    INVOKEINTERFACE java.util.Set.add (Ljava/lang/Object;)Z
                    POP
                    GETSTATIC org.springframework.core.CollectionFactory.approximableMapTypes Ljava/util/Set;   (line 80)
                    LDC java.util.HashMap
                    INVOKEINTERFACE java.util.Set.add (Ljava/lang/Object;)Z
                    POP
                    GETSTATIC org.springframework.core.CollectionFactory.approximableMapTypes Ljava/util/Set;   (line 81)
                    LDC java.util.LinkedHashMap
                    INVOKEINTERFACE java.util.Set.add (Ljava/lang/Object;)Z
                    POP
                    GETSTATIC org.springframework.core.CollectionFactory.approximableMapTypes Ljava/util/Set;   (line 82)
                    LDC java.util.TreeMap
                    INVOKEINTERFACE java.util.Set.add (Ljava/lang/Object;)Z
                    POP
                    GETSTATIC org.springframework.core.CollectionFactory.approximableMapTypes Ljava/util/Set;   (line 83)
                    LDC java.util.EnumMap
                    INVOKEINTERFACE java.util.Set.add (Ljava/lang/Object;)Z
                    POP
                    RETURN   (line 84)
  end static void <clinit>()
end public abstract class org.springframework.core.CollectionFactory
 -- (ClassFormatException) File: 'java.lang.reflect.AnnotatedElement': Invalid byte tag in constant pool: 15
File: 'java.lang.reflect.AnnotatedElement': Invalid byte tag in constant pool: 15
org.aspectj.apache.bcel.classfile.ClassFormatException: File: 'java.lang.reflect.AnnotatedElement': Invalid byte tag in constant pool: 15
	at org.aspectj.apache.bcel.classfile.ClassParser.readConstantPool(ClassParser.java:192)
	at org.aspectj.apache.bcel.classfile.ClassParser.parse(ClassParser.java:131)
	at org.aspectj.apache.bcel.util.ClassLoaderRepository.loadClass(ClassLoaderRepository.java:323)
	at org.aspectj.weaver.bcel.BcelWorld.lookupJavaClass(BcelWorld.java:402)
	at org.aspectj.weaver.bcel.BcelWorld.resolveDelegate(BcelWorld.java:376)
	at org.aspectj.weaver.ltw.LTWWorld.resolveDelegate(LTWWorld.java:107)
	at org.aspectj.weaver.World.resolveToReferenceType(World.java:485)
	at org.aspectj.weaver.World.resolve(World.java:326)
	at org.aspectj.weaver.World.resolve(World.java:236)
	at org.aspectj.weaver.bcel.BcelGenericSignatureToTypeXConverter.classTypeSignature2TypeX(BcelGenericSignatureToTypeXConverter.java:97)
	at org.aspectj.weaver.bcel.BcelGenericSignatureToTypeXConverter.classTypeSignature2TypeX(BcelGenericSignatureToTypeXConverter.java:41)
	at org.aspectj.weaver.bcel.BcelObjectType.ensureGenericSignatureUnpacked(BcelObjectType.java:810)
	at org.aspectj.weaver.bcel.BcelObjectType.getDeclaredInterfaces(BcelObjectType.java:257)
	at org.aspectj.weaver.ReferenceType.getDeclaredInterfaces(ReferenceType.java:626)
	at org.aspectj.weaver.ResolvedType.getDirectSupertypes(ResolvedType.java:82)
	at org.aspectj.weaver.patterns.TypePattern.matchesSubtypes(TypePattern.java:178)
	at org.aspectj.weaver.patterns.ExactTypePattern.matchesSubtypes(ExactTypePattern.java:74)
	at org.aspectj.weaver.patterns.TypePattern.matchesStatically(TypePattern.java:130)
	at org.aspectj.weaver.patterns.OrTypePattern.matchesStatically(OrTypePattern.java:76)
	at org.aspectj.weaver.patterns.SignaturePattern.matchesExactlyMethod(SignaturePattern.java:505)
	at org.aspectj.weaver.patterns.SignaturePattern.matchesExactly(SignaturePattern.java:360)
	at org.aspectj.weaver.patterns.SignaturePattern.matches(SignaturePattern.java:320)
	at org.aspectj.weaver.patterns.KindedPointcut.matchInternal(KindedPointcut.java:202)
	at org.aspectj.weaver.patterns.Pointcut.match(Pointcut.java:137)
	at org.aspectj.weaver.patterns.AndPointcut.matchInternal(AndPointcut.java:51)
	at org.aspectj.weaver.patterns.Pointcut.match(Pointcut.java:137)
	at org.aspectj.weaver.patterns.OrPointcut.matchInternal(OrPointcut.java:50)
	at org.aspectj.weaver.patterns.Pointcut.match(Pointcut.java:137)
	at org.aspectj.weaver.ShadowMunger.match(ShadowMunger.java:113)
	at org.aspectj.weaver.Advice.match(Advice.java:109)
	at org.aspectj.weaver.bcel.BcelAdvice.match(BcelAdvice.java:149)
	at org.aspectj.weaver.bcel.BcelClassWeaver.match(BcelClassWeaver.java:3173)
	at org.aspectj.weaver.bcel.BcelClassWeaver.match(BcelClassWeaver.java:2565)
	at org.aspectj.weaver.bcel.BcelClassWeaver.weave(BcelClassWeaver.java:480)
	at org.aspectj.weaver.bcel.BcelClassWeaver.weave(BcelClassWeaver.java:99)
	at org.aspectj.weaver.bcel.BcelWeaver.weave(BcelWeaver.java:1694)
	at org.aspectj.weaver.bcel.BcelWeaver.weaveWithoutDump(BcelWeaver.java:1638)
	at org.aspectj.weaver.bcel.BcelWeaver.weaveAndNotify(BcelWeaver.java:1401)
	at org.aspectj.weaver.bcel.BcelWeaver.weave(BcelWeaver.java:1187)
	at org.aspectj.weaver.tools.WeavingAdaptor.getWovenBytes(WeavingAdaptor.java:472)
	at org.aspectj.weaver.tools.WeavingAdaptor.weaveClass(WeavingAdaptor.java:323)
	at org.aspectj.weaver.loadtime.Aj.preProcess(Aj.java:99)
	at org.aspectj.weaver.loadtime.ClassPreProcessorAgentAdapter.transform(ClassPreProcessorAgentAdapter.java:54)
	at org.springframework.context.weaving.AspectJWeavingEnabler$AspectJClassBypassingClassFileTransformer.transform(AspectJWeavingEnabler.java:108)
	at org.springframework.instrument.classloading.InstrumentationLoadTimeWeaver$FilteringClassFileTransformer.transform(InstrumentationLoadTimeWeaver.java:184)
	at sun.instrument.TransformerManager.transform(Unknown Source)
	at sun.instrument.InstrumentationImpl.transform(Unknown Source)
	at java.lang.ClassLoader.defineClass1(Native Method)
	at java.lang.ClassLoader.defineClass(Unknown Source)
	at java.security.SecureClassLoader.defineClass(Unknown Source)
	at java.net.URLClassLoader.defineClass(Unknown Source)
	at java.net.URLClassLoader.access$100(Unknown Source)
	at java.net.URLClassLoader$1.run(Unknown Source)
	at java.net.URLClassLoader$1.run(Unknown Source)
	at java.security.AccessController.doPrivileged(Native Method)
	at java.net.URLClassLoader.findClass(Unknown Source)
	at java.lang.ClassLoader.loadClass(Unknown Source)
	at sun.misc.Launcher$AppClassLoader.loadClass(Unknown Source)
	at java.lang.ClassLoader.loadClass(Unknown Source)
	at org.springframework.beans.TypeConverterDelegate.convertToTypedCollection(TypeConverterDelegate.java:500)
	at org.springframework.beans.TypeConverterDelegate.convertIfNecessary(TypeConverterDelegate.java:216)
	at org.springframework.beans.TypeConverterDelegate.convertIfNecessary(TypeConverterDelegate.java:107)
	at org.springframework.beans.TypeConverterSupport.doConvert(TypeConverterSupport.java:64)
	at org.springframework.beans.TypeConverterSupport.convertIfNecessary(TypeConverterSupport.java:40)
	at org.springframework.beans.factory.support.DefaultListableBeanFactory.doResolveDependency(DefaultListableBeanFactory.java:1007)
	at org.springframework.beans.factory.support.DefaultListableBeanFactory.resolveDependency(DefaultListableBeanFactory.java:942)
	at org.springframework.beans.factory.annotation.AutowiredAnnotationBeanPostProcessor$AutowiredFieldElement.inject(AutowiredAnnotationBeanPostProcessor.java:533)
	at org.springframework.beans.factory.annotation.InjectionMetadata.inject(InjectionMetadata.java:88)
	at org.springframework.beans.factory.annotation.AutowiredAnnotationBeanPostProcessor.postProcessPropertyValues(AutowiredAnnotationBeanPostProcessor.java:331)
	at org.springframework.beans.factory.support.AbstractAutowireCapableBeanFactory.populateBean(AbstractAutowireCapableBeanFactory.java:1210)
	at org.springframework.beans.factory.support.AbstractAutowireCapableBeanFactory.doCreateBean(AbstractAutowireCapableBeanFactory.java:537)
	at org.springframework.beans.factory.support.AbstractAutowireCapableBeanFactory.createBean(AbstractAutowireCapableBeanFactory.java:476)
	at org.springframework.beans.factory.support.AbstractBeanFactory$1.getObject(AbstractBeanFactory.java:303)
	at org.springframework.beans.factory.support.DefaultSingletonBeanRegistry.getSingleton(DefaultSingletonBeanRegistry.java:230)
	at org.springframework.beans.factory.support.AbstractBeanFactory.doGetBean(AbstractBeanFactory.java:299)
	at org.springframework.beans.factory.support.AbstractBeanFactory.getBean(AbstractBeanFactory.java:194)
	at org.springframework.beans.factory.support.DefaultListableBeanFactory.preInstantiateSingletons(DefaultListableBeanFactory.java:755)
	at org.springframework.context.support.AbstractApplicationContext.finishBeanFactoryInitialization(AbstractApplicationContext.java:757)
	at org.springframework.context.support.AbstractApplicationContext.refresh(AbstractApplicationContext.java:480)
	at org.springframework.context.support.ClassPathXmlApplicationContext.<init>(ClassPathXmlApplicationContext.java:139)
	at org.springframework.context.support.ClassPathXmlApplicationContext.<init>(ClassPathXmlApplicationContext.java:93)
	at com.springExemple.presentation.Presentation2.main(Presentation2.java:13)

org.aspectj.bridge.AbortException: trouble in: 
public abstract class org.springframework.core.CollectionFactory extends java.lang.Object:
  private static final java.util.Set approximableCollectionTypes [Signature(Ljava/util/Set<Ljava/lang/Class<*>;>;)]
  private static final java.util.Set approximableMapTypes [Signature(Ljava/util/Set<Ljava/lang/Class<*>;>;)]
  public void <init>():
                    ALOAD_0     // Lorg/springframework/core/CollectionFactory; this   (line 55)
                    INVOKESPECIAL java.lang.Object.<init> ()V
    constructor-execution(void org.springframework.core.CollectionFactory.<init>())
    |               RETURN
    constructor-execution(void org.springframework.core.CollectionFactory.<init>())
  end public void <init>()

  public static boolean isApproximableCollectionType(Class):
                    ALOAD_0     // Ljava/lang/Class; collectionType   (line 94)
                    IFNULL L0
                    GETSTATIC org.springframework.core.CollectionFactory.approximableCollectionTypes Ljava/util/Set;
                    ALOAD_0     // Ljava/lang/Class; collectionType
                    INVOKEINTERFACE java.util.Set.contains (Ljava/lang/Object;)Z
                    IFEQ L0
                    ICONST_1
                    GOTO L1
                L0: ICONST_0
                L1: IRETURN
  end public static boolean isApproximableCollectionType(Class)

  public static java.util.Collection createApproximateCollection(Object, int):
                    ALOAD_0     // Ljava/lang/Object; collection   (line 111)
                    INSTANCEOF java.util.LinkedList
                    IFEQ L0
                    NEW java.util.LinkedList   (line 112)
                    DUP
                    INVOKESPECIAL java.util.LinkedList.<init> ()V
                    ARETURN
                L0: ALOAD_0     // Ljava/lang/Object; collection   (line 114)
                    INSTANCEOF java.util.List
                    IFEQ L1
                    NEW java.util.ArrayList   (line 115)
                    DUP
                    ILOAD_1     // I capacity
                    INVOKESPECIAL java.util.ArrayList.<init> (I)V
                    ARETURN
                L1: ALOAD_0     // Ljava/lang/Object; collection   (line 117)
                    INSTANCEOF java.util.EnumSet
                    IFEQ L2
                    ALOAD_0     // Ljava/lang/Object; collection   (line 119)
                    CHECKCAST java.util.EnumSet
                    INVOKESTATIC java.util.EnumSet.copyOf (Ljava/util/EnumSet;)Ljava/util/EnumSet;
                    ASTORE_2
                    ALOAD_2     // Ljava/util/Collection; enumSet   (line 120)
                    INVOKEINTERFACE java.util.Collection.clear ()V
                    ALOAD_2     // Ljava/util/Collection; enumSet   (line 121)
                    ARETURN
                L2: ALOAD_0     // Ljava/lang/Object; collection   (line 123)
                    INSTANCEOF java.util.SortedSet
                    IFEQ L3
                    NEW java.util.TreeSet   (line 124)
                    DUP
                    ALOAD_0     // Ljava/lang/Object; collection
                    CHECKCAST java.util.SortedSet
                    INVOKEINTERFACE java.util.SortedSet.comparator ()Ljava/util/Comparator;
                    INVOKESPECIAL java.util.TreeSet.<init> (Ljava/util/Comparator;)V
                    ARETURN
                L3: NEW java.util.LinkedHashSet   (line 127)
                    DUP
                    ILOAD_1     // I capacity
                    INVOKESPECIAL java.util.LinkedHashSet.<init> (I)V
                    ARETURN
  end public static java.util.Collection createApproximateCollection(Object, int)

  public static java.util.Collection createCollection(Class, int):
                    ALOAD_0     // Ljava/lang/Class; collectionType   (line 140)
                    ACONST_NULL
                    ILOAD_1     // I capacity
                    INVOKESTATIC org.springframework.core.CollectionFactory.createCollection (Ljava/lang/Class;Ljava/lang/Class;I)Ljava/util/Collection;
                    ARETURN
  end public static java.util.Collection createCollection(Class, int)

  public static java.util.Collection createCollection(Class, Class, int):
                    ALOAD_0     // Ljava/lang/Class; collectionType   (line 158)
                    LDC "Collection type must not be null"
                    INVOKESTATIC org.springframework.util.Assert.notNull (Ljava/lang/Object;Ljava/lang/String;)V
                    ALOAD_0     // Ljava/lang/Class; collectionType   (line 159)
                    INVOKEVIRTUAL java.lang.Class.isInterface ()Z
                    IFEQ L5
                    LDC java.util.Set   (line 160)
                    ALOAD_0     // Ljava/lang/Class; collectionType
                    INVOKEVIRTUAL java.lang.Object.equals (Ljava/lang/Object;)Z
                    IFNE L0
                    LDC java.util.Collection
                    ALOAD_0     // Ljava/lang/Class; collectionType
                    INVOKEVIRTUAL java.lang.Object.equals (Ljava/lang/Object;)Z
                    IFEQ L1
                L0: NEW java.util.LinkedHashSet   (line 161)
                    DUP
                    ILOAD_2     // I capacity
                    INVOKESPECIAL java.util.LinkedHashSet.<init> (I)V
                    ARETURN
                L1: LDC java.util.List   (line 163)
                    ALOAD_0     // Ljava/lang/Class; collectionType
                    INVOKEVIRTUAL java.lang.Object.equals (Ljava/lang/Object;)Z
                    IFEQ L2
                    NEW java.util.ArrayList   (line 164)
                    DUP
                    ILOAD_2     // I capacity
                    INVOKESPECIAL java.util.ArrayList.<init> (I)V
                    ARETURN
                L2: LDC java.util.SortedSet   (line 166)
                    ALOAD_0     // Ljava/lang/Class; collectionType
                    INVOKEVIRTUAL java.lang.Object.equals (Ljava/lang/Object;)Z
                    IFNE L3
                    LDC java.util.NavigableSet
                    ALOAD_0     // Ljava/lang/Class; collectionType
                    INVOKEVIRTUAL java.lang.Object.equals (Ljava/lang/Object;)Z
                    IFEQ L4
                L3: NEW java.util.TreeSet   (line 167)
                    DUP
                    INVOKESPECIAL java.util.TreeSet.<init> ()V
                    ARETURN
                L4: NEW java.lang.IllegalArgumentException   (line 170)
                    DUP
                    NEW java.lang.StringBuilder
                    DUP
                    INVOKESPECIAL java.lang.StringBuilder.<init> ()V
                    LDC "Unsupported Collection interface: "
                    INVOKEVIRTUAL java.lang.StringBuilder.append (Ljava/lang/String;)Ljava/lang/StringBuilder;
                    ALOAD_0     // Ljava/lang/Class; collectionType
                    INVOKEVIRTUAL java.lang.Class.getName ()Ljava/lang/String;
                    INVOKEVIRTUAL java.lang.StringBuilder.append (Ljava/lang/String;)Ljava/lang/StringBuilder;
                    INVOKEVIRTUAL java.lang.StringBuilder.toString ()Ljava/lang/String;
                    INVOKESPECIAL java.lang.IllegalArgumentException.<init> (Ljava/lang/String;)V
                    ATHROW
                L5: LDC java.util.EnumSet   (line 173)
                    ALOAD_0     // Ljava/lang/Class; collectionType
                    INVOKEVIRTUAL java.lang.Object.equals (Ljava/lang/Object;)Z
                    IFEQ L6
                    ALOAD_1     // Ljava/lang/Class; elementType   (line 174)
                    LDC "Cannot create EnumSet for unknown element type"
                    INVOKESTATIC org.springframework.util.Assert.notNull (Ljava/lang/Object;Ljava/lang/String;)V
                    ALOAD_1     // Ljava/lang/Class; elementType   (line 176)
                    INVOKESTATIC org.springframework.core.CollectionFactory.asEnumType (Ljava/lang/Class;)Ljava/lang/Class;
                    INVOKESTATIC java.util.EnumSet.noneOf (Ljava/lang/Class;)Ljava/util/EnumSet;
                    ARETURN
                L6: LDC java.util.Collection   (line 179)
                    ALOAD_0     // Ljava/lang/Class; collectionType
                    INVOKEVIRTUAL java.lang.Class.isAssignableFrom (Ljava/lang/Class;)Z
                    IFNE L7
                    NEW java.lang.IllegalArgumentException   (line 180)
                    DUP
                    NEW java.lang.StringBuilder
                    DUP
                    INVOKESPECIAL java.lang.StringBuilder.<init> ()V
                    LDC "Unsupported Collection type: "
                    INVOKEVIRTUAL java.lang.StringBuilder.append (Ljava/lang/String;)Ljava/lang/StringBuilder;
                    ALOAD_0     // Ljava/lang/Class; collectionType
                    INVOKEVIRTUAL java.lang.Class.getName ()Ljava/lang/String;
                    INVOKEVIRTUAL java.lang.StringBuilder.append (Ljava/lang/String;)Ljava/lang/StringBuilder;
                    INVOKEVIRTUAL java.lang.StringBuilder.toString ()Ljava/lang/String;
                    INVOKESPECIAL java.lang.IllegalArgumentException.<init> (Ljava/lang/String;)V
                    ATHROW
    catch java.lang.Exception -> E0
    |           L7: ALOAD_0     // Ljava/lang/Class; collectionType   (line 183)
    |               INVOKEVIRTUAL java.lang.Class.newInstance ()Ljava/lang/Object;
    |               CHECKCAST java.util.Collection
    catch java.lang.Exception -> E0
                    ARETURN
                E0: ASTORE_3   (line 185)
                    NEW java.lang.IllegalArgumentException   (line 186)
                    DUP
                    NEW java.lang.StringBuilder
                    DUP
                    INVOKESPECIAL java.lang.StringBuilder.<init> ()V
                    LDC "Could not instantiate Collection type: "
                    INVOKEVIRTUAL java.lang.StringBuilder.append (Ljava/lang/String;)Ljava/lang/StringBuilder;
                    ALOAD_0     // Ljava/lang/Class; collectionType
                    INVOKEVIRTUAL java.lang.Class.getName ()Ljava/lang/String;   (line 187)
                    INVOKEVIRTUAL java.lang.StringBuilder.append (Ljava/lang/String;)Ljava/lang/StringBuilder;
                    INVOKEVIRTUAL java.lang.StringBuilder.toString ()Ljava/lang/String;
                    ALOAD_3     // Ljava/lang/Exception; ex
                    INVOKESPECIAL java.lang.IllegalArgumentException.<init> (Ljava/lang/String;Ljava/lang/Throwable;)V
                    ATHROW
  end public static java.util.Collection createCollection(Class, Class, int)

  public static boolean isApproximableMapType(Class):
                    ALOAD_0     // Ljava/lang/Class; mapType   (line 199)
                    IFNULL L0
                    GETSTATIC org.springframework.core.CollectionFactory.approximableMapTypes Ljava/util/Set;
                    ALOAD_0     // Ljava/lang/Class; mapType
                    INVOKEINTERFACE java.util.Set.contains (Ljava/lang/Object;)Z
                    IFEQ L0
                    ICONST_1
                    GOTO L1
                L0: ICONST_0
                L1: IRETURN
  end public static boolean isApproximableMapType(Class)

  public static java.util.Map createApproximateMap(Object, int):
                    ALOAD_0     // Ljava/lang/Object; map   (line 214)
                    INSTANCEOF java.util.EnumMap
                    IFEQ L0
                    NEW java.util.EnumMap   (line 215)
                    DUP
                    ALOAD_0     // Ljava/lang/Object; map
                    CHECKCAST java.util.EnumMap
                    INVOKESPECIAL java.util.EnumMap.<init> (Ljava/util/EnumMap;)V
                    ASTORE_2
                    ALOAD_2     // Ljava/util/EnumMap; enumMap   (line 216)
                    INVOKEVIRTUAL java.util.EnumMap.clear ()V
                    ALOAD_2     // Ljava/util/EnumMap; enumMap   (line 217)
                    ARETURN
                L0: ALOAD_0     // Ljava/lang/Object; map   (line 219)
                    INSTANCEOF java.util.SortedMap
                    IFEQ L1
                    NEW java.util.TreeMap   (line 220)
                    DUP
                    ALOAD_0     // Ljava/lang/Object; map
                    CHECKCAST java.util.SortedMap
                    INVOKEINTERFACE java.util.SortedMap.comparator ()Ljava/util/Comparator;
                    INVOKESPECIAL java.util.TreeMap.<init> (Ljava/util/Comparator;)V
                    ARETURN
                L1: NEW java.util.LinkedHashMap   (line 223)
                    DUP
                    ILOAD_1     // I capacity
                    INVOKESPECIAL java.util.LinkedHashMap.<init> (I)V
                    ARETURN
  end public static java.util.Map createApproximateMap(Object, int)

  public static java.util.Map createMap(Class, int):
                    ALOAD_0     // Ljava/lang/Class; mapType   (line 236)
                    ACONST_NULL
                    ILOAD_1     // I capacity
                    INVOKESTATIC org.springframework.core.CollectionFactory.createMap (Ljava/lang/Class;Ljava/lang/Class;I)Ljava/util/Map;
                    ARETURN
  end public static java.util.Map createMap(Class, int)

  public static java.util.Map createMap(Class, Class, int):
                    ALOAD_0     // Ljava/lang/Class; mapType   (line 254)
                    LDC "Map type must not be null"
                    INVOKESTATIC org.springframework.util.Assert.notNull (Ljava/lang/Object;Ljava/lang/String;)V
                    ALOAD_0     // Ljava/lang/Class; mapType   (line 255)
                    INVOKEVIRTUAL java.lang.Class.isInterface ()Z
                    IFEQ L4
                    LDC java.util.Map   (line 256)
                    ALOAD_0     // Ljava/lang/Class; mapType
                    INVOKEVIRTUAL java.lang.Object.equals (Ljava/lang/Object;)Z
                    IFEQ L0
                    NEW java.util.LinkedHashMap   (line 257)
                    DUP
                    ILOAD_2     // I capacity
                    INVOKESPECIAL java.util.LinkedHashMap.<init> (I)V
                    ARETURN
                L0: LDC java.util.SortedMap   (line 259)
                    ALOAD_0     // Ljava/lang/Class; mapType
                    INVOKEVIRTUAL java.lang.Object.equals (Ljava/lang/Object;)Z
                    IFNE L1
                    LDC java.util.NavigableMap
                    ALOAD_0     // Ljava/lang/Class; mapType
                    INVOKEVIRTUAL java.lang.Object.equals (Ljava/lang/Object;)Z
                    IFEQ L2
                L1: NEW java.util.TreeMap   (line 260)
                    DUP
                    INVOKESPECIAL java.util.TreeMap.<init> ()V
                    ARETURN
                L2: LDC org.springframework.util.MultiValueMap   (line 262)
                    ALOAD_0     // Ljava/lang/Class; mapType
                    INVOKEVIRTUAL java.lang.Object.equals (Ljava/lang/Object;)Z
                    IFEQ L3
                    NEW org.springframework.util.LinkedMultiValueMap   (line 263)
                    DUP
                    INVOKESPECIAL org.springframework.util.LinkedMultiValueMap.<init> ()V
                    ARETURN
                L3: NEW java.lang.IllegalArgumentException   (line 266)
                    DUP
                    NEW java.lang.StringBuilder
                    DUP
                    INVOKESPECIAL java.lang.StringBuilder.<init> ()V
                    LDC "Unsupported Map interface: "
                    INVOKEVIRTUAL java.lang.StringBuilder.append (Ljava/lang/String;)Ljava/lang/StringBuilder;
                    ALOAD_0     // Ljava/lang/Class; mapType
                    INVOKEVIRTUAL java.lang.Class.getName ()Ljava/lang/String;
                    INVOKEVIRTUAL java.lang.StringBuilder.append (Ljava/lang/String;)Ljava/lang/StringBuilder;
                    INVOKEVIRTUAL java.lang.StringBuilder.toString ()Ljava/lang/String;
                    INVOKESPECIAL java.lang.IllegalArgumentException.<init> (Ljava/lang/String;)V
                    ATHROW
                L4: LDC java.util.EnumMap   (line 269)
                    ALOAD_0     // Ljava/lang/Class; mapType
                    INVOKEVIRTUAL java.lang.Object.equals (Ljava/lang/Object;)Z
                    IFEQ L5
                    ALOAD_1     // Ljava/lang/Class; keyType   (line 270)
                    LDC "Cannot create EnumMap for unknown key type"
                    INVOKESTATIC org.springframework.util.Assert.notNull (Ljava/lang/Object;Ljava/lang/String;)V
                    NEW java.util.EnumMap   (line 271)
                    DUP
                    ALOAD_1     // Ljava/lang/Class; keyType
                    INVOKESTATIC org.springframework.core.CollectionFactory.asEnumType (Ljava/lang/Class;)Ljava/lang/Class;
                    INVOKESPECIAL java.util.EnumMap.<init> (Ljava/lang/Class;)V
                    ARETURN
                L5: LDC java.util.Map   (line 274)
                    ALOAD_0     // Ljava/lang/Class; mapType
                    INVOKEVIRTUAL java.lang.Class.isAssignableFrom (Ljava/lang/Class;)Z
                    IFNE L6
                    NEW java.lang.IllegalArgumentException   (line 275)
                    DUP
                    NEW java.lang.StringBuilder
                    DUP
                    INVOKESPECIAL java.lang.StringBuilder.<init> ()V
                    LDC "Unsupported Map type: "
                    INVOKEVIRTUAL java.lang.StringBuilder.append (Ljava/lang/String;)Ljava/lang/StringBuilder;
                    ALOAD_0     // Ljava/lang/Class; mapType
                    INVOKEVIRTUAL java.lang.Class.getName ()Ljava/lang/String;
                    INVOKEVIRTUAL java.lang.StringBuilder.append (Ljava/lang/String;)Ljava/lang/StringBuilder;
                    INVOKEVIRTUAL java.lang.StringBuilder.toString ()Ljava/lang/String;
                    INVOKESPECIAL java.lang.IllegalArgumentException.<init> (Ljava/lang/String;)V
                    ATHROW
    catch java.lang.Exception -> E0
    |           L6: ALOAD_0     // Ljava/lang/Class; mapType   (line 278)
    |               INVOKEVIRTUAL java.lang.Class.newInstance ()Ljava/lang/Object;
    |               CHECKCAST java.util.Map
    catch java.lang.Exception -> E0
                    ARETURN
                E0: ASTORE_3   (line 280)
                    NEW java.lang.IllegalArgumentException   (line 281)
                    DUP
                    NEW java.lang.StringBuilder
                    DUP
                    INVOKESPECIAL java.lang.StringBuilder.<init> ()V
                    LDC "Could not instantiate Map type: "
                    INVOKEVIRTUAL java.lang.StringBuilder.append (Ljava/lang/String;)Ljava/lang/StringBuilder;
                    ALOAD_0     // Ljava/lang/Class; mapType
                    INVOKEVIRTUAL java.lang.Class.getName ()Ljava/lang/String;
                    INVOKEVIRTUAL java.lang.StringBuilder.append (Ljava/lang/String;)Ljava/lang/StringBuilder;
                    INVOKEVIRTUAL java.lang.StringBuilder.toString ()Ljava/lang/String;
                    ALOAD_3     // Ljava/lang/Exception; ex
                    INVOKESPECIAL java.lang.IllegalArgumentException.<init> (Ljava/lang/String;Ljava/lang/Throwable;)V
                    ATHROW
  end public static java.util.Map createMap(Class, Class, int)

  private static Class asEnumType(Class):
                    ALOAD_0     // Ljava/lang/Class; enumType   (line 294)
                    LDC "Enum type must not be null"
                    INVOKESTATIC org.springframework.util.Assert.notNull (Ljava/lang/Object;Ljava/lang/String;)V
                    LDC java.lang.Enum   (line 295)
                    ALOAD_0     // Ljava/lang/Class; enumType
                    INVOKEVIRTUAL java.lang.Class.isAssignableFrom (Ljava/lang/Class;)Z
                    IFNE L0
                    NEW java.lang.IllegalArgumentException   (line 296)
                    DUP
                    NEW java.lang.StringBuilder
                    DUP
                    INVOKESPECIAL java.lang.StringBuilder.<init> ()V
                    LDC "Supplied type is not an enum: "
                    INVOKEVIRTUAL java.lang.StringBuilder.append (Ljava/lang/String;)Ljava/lang/StringBuilder;
                    ALOAD_0     // Ljava/lang/Class; enumType
                    INVOKEVIRTUAL java.lang.Class.getName ()Ljava/lang/String;
                    INVOKEVIRTUAL java.lang.StringBuilder.append (Ljava/lang/String;)Ljava/lang/StringBuilder;
                    INVOKEVIRTUAL java.lang.StringBuilder.toString ()Ljava/lang/String;
                    INVOKESPECIAL java.lang.IllegalArgumentException.<init> (Ljava/lang/String;)V
                    ATHROW
                L0: ALOAD_0     // Ljava/lang/Class; enumType   (line 298)
                    LDC java.lang.Enum
                    INVOKEVIRTUAL java.lang.Class.asSubclass (Ljava/lang/Class;)Ljava/lang/Class;
                    ARETURN
  end private static Class asEnumType(Class)

  static void <clinit>():
                    NEW java.util.HashSet   (line 57)
                    DUP
                    BIPUSH 11
                    INVOKESPECIAL java.util.HashSet.<init> (I)V
                    PUTSTATIC org.springframework.core.CollectionFactory.approximableCollectionTypes Ljava/util/Set;
                    NEW java.util.HashSet   (line 59)
                    DUP
                    BIPUSH 7
                    INVOKESPECIAL java.util.HashSet.<init> (I)V
                    PUTSTATIC org.springframework.core.CollectionFactory.approximableMapTypes Ljava/util/Set;
                    GETSTATIC org.springframework.core.CollectionFactory.approximableCollectionTypes Ljava/util/Set;   (line 64)
                    LDC java.util.Collection
                    INVOKEINTERFACE java.util.Set.add (Ljava/lang/Object;)Z
                    POP
                    GETSTATIC org.springframework.core.CollectionFactory.approximableCollectionTypes Ljava/util/Set;   (line 65)
                    LDC java.util.List
                    INVOKEINTERFACE java.util.Set.add (Ljava/lang/Object;)Z
                    POP
                    GETSTATIC org.springframework.core.CollectionFactory.approximableCollectionTypes Ljava/util/Set;   (line 66)
                    LDC java.util.Set
                    INVOKEINTERFACE java.util.Set.add (Ljava/lang/Object;)Z
                    POP
                    GETSTATIC org.springframework.core.CollectionFactory.approximableCollectionTypes Ljava/util/Set;   (line 67)
                    LDC java.util.SortedSet
                    INVOKEINTERFACE java.util.Set.add (Ljava/lang/Object;)Z
                    POP
                    GETSTATIC org.springframework.core.CollectionFactory.approximableCollectionTypes Ljava/util/Set;   (line 68)
                    LDC java.util.NavigableSet
                    INVOKEINTERFACE java.util.Set.add (Ljava/lang/Object;)Z
                    POP
                    GETSTATIC org.springframework.core.CollectionFactory.approximableMapTypes Ljava/util/Set;   (line 69)
                    LDC java.util.Map
                    INVOKEINTERFACE java.util.Set.add (Ljava/lang/Object;)Z
                    POP
                    GETSTATIC org.springframework.core.CollectionFactory.approximableMapTypes Ljava/util/Set;   (line 70)
                    LDC java.util.SortedMap
                    INVOKEINTERFACE java.util.Set.add (Ljava/lang/Object;)Z
                    POP
                    GETSTATIC org.springframework.core.CollectionFactory.approximableMapTypes Ljava/util/Set;   (line 71)
                    LDC java.util.NavigableMap
                    INVOKEINTERFACE java.util.Set.add (Ljava/lang/Object;)Z
                    POP
                    GETSTATIC org.springframework.core.CollectionFactory.approximableCollectionTypes Ljava/util/Set;   (line 74)
                    LDC java.util.ArrayList
                    INVOKEINTERFACE java.util.Set.add (Ljava/lang/Object;)Z
                    POP
                    GETSTATIC org.springframework.core.CollectionFactory.approximableCollectionTypes Ljava/util/Set;   (line 75)
                    LDC java.util.LinkedList
                    INVOKEINTERFACE java.util.Set.add (Ljava/lang/Object;)Z
                    POP
                    GETSTATIC org.springframework.core.CollectionFactory.approximableCollectionTypes Ljava/util/Set;   (line 76)
                    LDC java.util.HashSet
                    INVOKEINTERFACE java.util.Set.add (Ljava/lang/Object;)Z
                    POP
                    GETSTATIC org.springframework.core.CollectionFactory.approximableCollectionTypes Ljava/util/Set;   (line 77)
                    LDC java.util.LinkedHashSet
                    INVOKEINTERFACE java.util.Set.add (Ljava/lang/Object;)Z
                    POP
                    GETSTATIC org.springframework.core.CollectionFactory.approximableCollectionTypes Ljava/util/Set;   (line 78)
                    LDC java.util.TreeSet
                    INVOKEINTERFACE java.util.Set.add (Ljava/lang/Object;)Z
                    POP
                    GETSTATIC org.springframework.core.CollectionFactory.approximableCollectionTypes Ljava/util/Set;   (line 79)
                    LDC java.util.EnumSet
                    INVOKEINTERFACE java.util.Set.add (Ljava/lang/Object;)Z
                    POP
                    GETSTATIC org.springframework.core.CollectionFactory.approximableMapTypes Ljava/util/Set;   (line 80)
                    LDC java.util.HashMap
                    INVOKEINTERFACE java.util.Set.add (Ljava/lang/Object;)Z
                    POP
                    GETSTATIC org.springframework.core.CollectionFactory.approximableMapTypes Ljava/util/Set;   (line 81)
                    LDC java.util.LinkedHashMap
                    INVOKEINTERFACE java.util.Set.add (Ljava/lang/Object;)Z
                    POP
                    GETSTATIC org.springframework.core.CollectionFactory.approximableMapTypes Ljava/util/Set;   (line 82)
                    LDC java.util.TreeMap
                    INVOKEINTERFACE java.util.Set.add (Ljava/lang/Object;)Z
                    POP
                    GETSTATIC org.springframework.core.CollectionFactory.approximableMapTypes Ljava/util/Set;   (line 83)
                    LDC java.util.EnumMap
                    INVOKEINTERFACE java.util.Set.add (Ljava/lang/Object;)Z
                    POP
                    RETURN   (line 84)
  end static void <clinit>()
end public abstract class org.springframework.core.CollectionFactory

	at org.aspectj.bridge.MessageWriter.handleMessage(MessageWriter.java:47)
	at org.aspectj.weaver.tools.WeavingAdaptor$WeavingAdaptorMessageWriter.handleMessage(WeavingAdaptor.java:742)
	at org.aspectj.weaver.tools.WeavingAdaptor$WeavingAdaptorMessageHolder.handleMessage(WeavingAdaptor.java:687)
	at org.aspectj.weaver.bcel.BcelWeaver.weave(BcelWeaver.java:1720)
	at org.aspectj.weaver.bcel.BcelWeaver.weaveWithoutDump(BcelWeaver.java:1638)
	at org.aspectj.weaver.bcel.BcelWeaver.weaveAndNotify(BcelWeaver.java:1401)
	at org.aspectj.weaver.bcel.BcelWeaver.weave(BcelWeaver.java:1187)
	at org.aspectj.weaver.tools.WeavingAdaptor.getWovenBytes(WeavingAdaptor.java:472)
	at org.aspectj.weaver.tools.WeavingAdaptor.weaveClass(WeavingAdaptor.java:323)
	at org.aspectj.weaver.loadtime.Aj.preProcess(Aj.java:99)
	at org.aspectj.weaver.loadtime.ClassPreProcessorAgentAdapter.transform(ClassPreProcessorAgentAdapter.java:54)
	at org.springframework.context.weaving.AspectJWeavingEnabler$AspectJClassBypassingClassFileTransformer.transform(AspectJWeavingEnabler.java:108)
	at org.springframework.instrument.classloading.InstrumentationLoadTimeWeaver$FilteringClassFileTransformer.transform(InstrumentationLoadTimeWeaver.java:184)
	at sun.instrument.TransformerManager.transform(Unknown Source)
	at sun.instrument.InstrumentationImpl.transform(Unknown Source)
	at java.lang.ClassLoader.defineClass1(Native Method)
	at java.lang.ClassLoader.defineClass(Unknown Source)
	at java.security.SecureClassLoader.defineClass(Unknown Source)
	at java.net.URLClassLoader.defineClass(Unknown Source)
	at java.net.URLClassLoader.access$100(Unknown Source)
	at java.net.URLClassLoader$1.run(Unknown Source)
	at java.net.URLClassLoader$1.run(Unknown Source)
	at java.security.AccessController.doPrivileged(Native Method)
	at java.net.URLClassLoader.findClass(Unknown Source)
	at java.lang.ClassLoader.loadClass(Unknown Source)
	at sun.misc.Launcher$AppClassLoader.loadClass(Unknown Source)
	at java.lang.ClassLoader.loadClass(Unknown Source)
	at org.springframework.beans.TypeConverterDelegate.convertToTypedCollection(TypeConverterDelegate.java:500)
	at org.springframework.beans.TypeConverterDelegate.convertIfNecessary(TypeConverterDelegate.java:216)
	at org.springframework.beans.TypeConverterDelegate.convertIfNecessary(TypeConverterDelegate.java:107)
	at org.springframework.beans.TypeConverterSupport.doConvert(TypeConverterSupport.java:64)
	at org.springframework.beans.TypeConverterSupport.convertIfNecessary(TypeConverterSupport.java:40)
	at org.springframework.beans.factory.support.DefaultListableBeanFactory.doResolveDependency(DefaultListableBeanFactory.java:1007)
	at org.springframework.beans.factory.support.DefaultListableBeanFactory.resolveDependency(DefaultListableBeanFactory.java:942)
	at org.springframework.beans.factory.annotation.AutowiredAnnotationBeanPostProcessor$AutowiredFieldElement.inject(AutowiredAnnotationBeanPostProcessor.java:533)
	at org.springframework.beans.factory.annotation.InjectionMetadata.inject(InjectionMetadata.java:88)
	at org.springframework.beans.factory.annotation.AutowiredAnnotationBeanPostProcessor.postProcessPropertyValues(AutowiredAnnotationBeanPostProcessor.java:331)
	at org.springframework.beans.factory.support.AbstractAutowireCapableBeanFactory.populateBean(AbstractAutowireCapableBeanFactory.java:1210)
	at org.springframework.beans.factory.support.AbstractAutowireCapableBeanFactory.doCreateBean(AbstractAutowireCapableBeanFactory.java:537)
	at org.springframework.beans.factory.support.AbstractAutowireCapableBeanFactory.createBean(AbstractAutowireCapableBeanFactory.java:476)
	at org.springframework.beans.factory.support.AbstractBeanFactory$1.getObject(AbstractBeanFactory.java:303)
	at org.springframework.beans.factory.support.DefaultSingletonBeanRegistry.getSingleton(DefaultSingletonBeanRegistry.java:230)
	at org.springframework.beans.factory.support.AbstractBeanFactory.doGetBean(AbstractBeanFactory.java:299)
	at org.springframework.beans.factory.support.AbstractBeanFactory.getBean(AbstractBeanFactory.java:194)
	at org.springframework.beans.factory.support.DefaultListableBeanFactory.preInstantiateSingletons(DefaultListableBeanFactory.java:755)
	at org.springframework.context.support.AbstractApplicationContext.finishBeanFactoryInitialization(AbstractApplicationContext.java:757)
	at org.springframework.context.support.AbstractApplicationContext.refresh(AbstractApplicationContext.java:480)
	at org.springframework.context.support.ClassPathXmlApplicationContext.<init>(ClassPathXmlApplicationContext.java:139)
	at org.springframework.context.support.ClassPathXmlApplicationContext.<init>(ClassPathXmlApplicationContext.java:93)
	at com.springExemple.presentation.Presentation2.main(Presentation2.java:13)
---- System Properties ---
java.runtime.name=Java(TM) SE Runtime Environment
sun.boot.library.path=C:\Program Files\Java\jre1.8.0_121\bin
java.vm.version=25.121-b13
java.vm.vendor=Oracle Corporation
java.vendor.url=http://java.oracle.com/
path.separator=;
java.vm.name=Java HotSpot(TM) 64-Bit Server VM
file.encoding.pkg=sun.io
user.country=FR
user.script=
sun.java.launcher=SUN_STANDARD
sun.os.patch.level=
java.vm.specification.name=Java Virtual Machine Specification
user.dir=C:\Users\formation\git\projects\SpringExpl
java.runtime.version=1.8.0_121-b13
java.awt.graphicsenv=sun.awt.Win32GraphicsEnvironment
java.endorsed.dirs=C:\Program Files\Java\jre1.8.0_121\lib\endorsed
os.arch=amd64
java.io.tmpdir=C:\Users\FORMAT~1\AppData\Local\Temp\
line.separator=

java.vm.specification.vendor=Oracle Corporation
user.variant=
os.name=Windows 10
sun.jnu.encoding=Cp1252
java.library.path=C:\Program Files\Java\jre1.8.0_121\bin;C:\windows\Sun\Java\bin;C:\windows\system32;C:\windows;C:/Program Files/Java/jre1.8.0_121/bin/server;C:/Program Files/Java/jre1.8.0_121/bin;C:/Program Files/Java/jre1.8.0_121/lib/amd64;C:\ProgramData\Oracle\Java\javapath;C:\windows\system32;C:\windows;C:\windows\System32\Wbem;C:\windows\System32\WindowsPowerShell\v1.0\;C:\Program Files\Java\jdk1.8.0_101\bin;C:\Outils\apache-maven-3.3.9\bin;C:\Users\formation\AppData\Local\Microsoft\WindowsApps;;C:\Users\formation\Desktop\JRE JDK ECLIPSE\sts-bundle\sts-3.8.3.RELEASE;;.
java.specification.name=Java Platform API Specification
java.class.version=52.0
sun.management.compiler=HotSpot 64-Bit Tiered Compilers
os.version=10.0
user.home=C:\Users\formation
user.timezone=Europe/Paris
java.awt.printerjob=sun.awt.windows.WPrinterJob
file.encoding=UTF-8
java.specification.version=1.8
java.class.path=C:\Users\formation\git\projects\SpringExpl\target\classes;C:\Users\formation\.m2\repository\org\springframework\spring-aspects\4.1.4.RELEASE\spring-aspects-4.1.4.RELEASE.jar;C:\Users\formation\.m2\repository\org\aspectj\aspectjrt\1.6.12\aspectjrt-1.6.12.jar;C:\Users\formation\.m2\repository\org\aspectj\aspectjweaver\1.6.12\aspectjweaver-1.6.12.jar;C:\Users\formation\.m2\repository\org\springframework\spring-core\4.1.6.RELEASE\spring-core-4.1.6.RELEASE.jar;C:\Users\formation\.m2\repository\commons-logging\commons-logging\1.2\commons-logging-1.2.jar;C:\Users\formation\.m2\repository\org\springframework\spring-context\4.1.6.RELEASE\spring-context-4.1.6.RELEASE.jar;C:\Users\formation\.m2\repository\org\springframework\spring-aop\4.1.6.RELEASE\spring-aop-4.1.6.RELEASE.jar;C:\Users\formation\.m2\repository\aopalliance\aopalliance\1.0\aopalliance-1.0.jar;C:\Users\formation\.m2\repository\org\springframework\spring-beans\4.1.6.RELEASE\spring-beans-4.1.6.RELEASE.jar;C:\Users\formation\.m2\repository\org\springframework\spring-expression\4.1.6.RELEASE\spring-expression-4.1.6.RELEASE.jar;C:\Users\formation\Desktop\spring-agent-2.5.6.jar
user.name=formation
java.vm.specification.version=1.8
sun.java.command=com.springExemple.presentation.Presentation2
java.home=C:\Program Files\Java\jre1.8.0_121
sun.arch.data.model=64
user.language=fr
java.specification.vendor=Oracle Corporation
awt.toolkit=sun.awt.windows.WToolkit
java.vm.info=mixed mode
java.version=1.8.0_121
java.ext.dirs=C:\Program Files\Java\jre1.8.0_121\lib\ext;C:\windows\Sun\Java\lib\ext
sun.boot.class.path=C:\Program Files\Java\jre1.8.0_121\lib\resources.jar;C:\Program Files\Java\jre1.8.0_121\lib\rt.jar;C:\Program Files\Java\jre1.8.0_121\lib\sunrsasign.jar;C:\Program Files\Java\jre1.8.0_121\lib\jsse.jar;C:\Program Files\Java\jre1.8.0_121\lib\jce.jar;C:\Program Files\Java\jre1.8.0_121\lib\charsets.jar;C:\Program Files\Java\jre1.8.0_121\lib\jfr.jar;C:\Program Files\Java\jre1.8.0_121\classes
java.vendor=Oracle Corporation
file.separator=\
java.vendor.url.bug=http://bugreport.sun.com/bugreport/
sun.io.unicode.encoding=UnicodeLittle
sun.cpu.endian=little
sun.desktop=windows
sun.cpu.isalist=amd64
---- Command Line ---
Empty
---- Full Classpath ---
Empty
---- Compiler Messages ---
Empty
