---- AspectJ Properties ---
AspectJ Compiler 1.6.12 built on Tuesday Oct 18, 2011 at 17:52:06 GMT
---- Dump Properties ---
Dump file: ajcore.20170412.114038.473.txt
Dump reason: org.aspectj.bridge.AbortException
Dump on exception: true
Dump at exit condition: abort
---- Exception Information ---
Message: abort trouble in: 
public class org.springframework.expression.spel.support.ReflectivePropertyAccessor extends java.lang.Object implements org.springframework.expression.PropertyAccessor:
  private static final java.util.Set BOOLEAN_TYPES [Signature(Ljava/util/Set<Ljava/lang/Class<*>;>;)]
  private static final java.util.Set ANY_TYPES [Signature(Ljava/util/Set<Ljava/lang/Class<*>;>;)]
  private final java.util.Map readerCache [Signature(Ljava/util/Map<Lorg/springframework/expression/spel/support/ReflectivePropertyAccessor$CacheKey;Lorg/springframework/expression/spel/support/ReflectivePropertyAccessor$InvokerPair;>;)]
  private final java.util.Map writerCache [Signature(Ljava/util/Map<Lorg/springframework/expression/spel/support/ReflectivePropertyAccessor$CacheKey;Ljava/lang/reflect/Member;>;)]
  private final java.util.Map typeDescriptorCache [Signature(Ljava/util/Map<Lorg/springframework/expression/spel/support/ReflectivePropertyAccessor$CacheKey;Lorg/springframework/core/convert/TypeDescriptor;>;)]
  private org.springframework.expression.spel.support.ReflectivePropertyAccessor$InvokerPair lastReadInvokerPair
  public void <init>():
                    ALOAD_0     // Lorg/springframework/expression/spel/support/ReflectivePropertyAccessor; this   (line 59)
                    INVOKESPECIAL java.lang.Object.<init> ()V
    constructor-execution(void org.springframework.expression.spel.support.ReflectivePropertyAccessor.<init>())
    |               ALOAD_0     // Lorg/springframework/expression/spel/support/ReflectivePropertyAccessor; this   (line 72)
    |               NEW java.util.concurrent.ConcurrentHashMap
    |               DUP
    |               BIPUSH 64
    |               INVOKESPECIAL java.util.concurrent.ConcurrentHashMap.<init> (I)V
    |               PUTFIELD org.springframework.expression.spel.support.ReflectivePropertyAccessor.readerCache Ljava/util/Map;
    |               ALOAD_0     // Lorg/springframework/expression/spel/support/ReflectivePropertyAccessor; this   (line 74)
    |               NEW java.util.concurrent.ConcurrentHashMap
    |               DUP
    |               BIPUSH 64
    |               INVOKESPECIAL java.util.concurrent.ConcurrentHashMap.<init> (I)V
    |               PUTFIELD org.springframework.expression.spel.support.ReflectivePropertyAccessor.writerCache Ljava/util/Map;
    |               ALOAD_0     // Lorg/springframework/expression/spel/support/ReflectivePropertyAccessor; this   (line 76)
    |               NEW java.util.concurrent.ConcurrentHashMap
    |               DUP
    |               BIPUSH 64
    |               INVOKESPECIAL java.util.concurrent.ConcurrentHashMap.<init> (I)V
    |               PUTFIELD org.springframework.expression.spel.support.ReflectivePropertyAccessor.typeDescriptorCache Ljava/util/Map;
    |               RETURN   (line 569)
    constructor-execution(void org.springframework.expression.spel.support.ReflectivePropertyAccessor.<init>())
  end public void <init>()

  public Class[] getSpecificTargetClasses():
                    ACONST_NULL   (line 86)
                    ARETURN
  end public Class[] getSpecificTargetClasses()

  public boolean canRead(org.springframework.expression.EvaluationContext, Object, String) throws org.springframework.expression.AccessException:
                    ALOAD_2     // Ljava/lang/Object; target   (line 91)
                    IFNONNULL L0
                    ICONST_0   (line 92)
                    IRETURN
                L0: ALOAD_2     // Ljava/lang/Object; target   (line 94)
                    INSTANCEOF java.lang.Class
                    IFEQ L1
                    ALOAD_2     // Ljava/lang/Object; target
                    CHECKCAST java.lang.Class
                    GOTO L2
                L1: ALOAD_2     // Ljava/lang/Object; target
                    INVOKEVIRTUAL java.lang.Object.getClass ()Ljava/lang/Class;
                L2: ASTORE 4
                    ALOAD 4     // Ljava/lang/Class; type   (line 95)
                    INVOKEVIRTUAL java.lang.Class.isArray ()Z
                    IFEQ L3
                    ALOAD_3     // Ljava/lang/String; name
                    LDC "length"
                    INVOKEVIRTUAL java.lang.String.equals (Ljava/lang/Object;)Z
                    IFEQ L3
                    ICONST_1   (line 96)
                    IRETURN
                L3: NEW org.springframework.expression.spel.support.ReflectivePropertyAccessor$CacheKey   (line 98)
                    DUP
                    ALOAD 4     // Ljava/lang/Class; type
                    ALOAD_3     // Ljava/lang/String; name
                    ALOAD_2     // Ljava/lang/Object; target
                    INSTANCEOF java.lang.Class
                    INVOKESPECIAL org.springframework.expression.spel.support.ReflectivePropertyAccessor$CacheKey.<init> (Ljava/lang/Class;Ljava/lang/String;Z)V
                    ASTORE 5
                    ALOAD_0     // Lorg/springframework/expression/spel/support/ReflectivePropertyAccessor; this   (line 99)
                    GETFIELD org.springframework.expression.spel.support.ReflectivePropertyAccessor.readerCache Ljava/util/Map;
                    ALOAD 5     // Lorg/springframework/expression/spel/support/ReflectivePropertyAccessor$CacheKey; cacheKey
                    INVOKEINTERFACE java.util.Map.containsKey (Ljava/lang/Object;)Z
                    IFEQ L4
                    ICONST_1   (line 100)
                    IRETURN
                L4: ALOAD_0     // Lorg/springframework/expression/spel/support/ReflectivePropertyAccessor; this   (line 102)
                    ALOAD_3     // Ljava/lang/String; name
                    ALOAD 4     // Ljava/lang/Class; type
                    ALOAD_2     // Ljava/lang/Object; target
                    INVOKESPECIAL org.springframework.expression.spel.support.ReflectivePropertyAccessor.findGetterForProperty (Ljava/lang/String;Ljava/lang/Class;Ljava/lang/Object;)Ljava/lang/reflect/Method;
                    ASTORE 6
                    ALOAD 6     // Ljava/lang/reflect/Method; method   (line 103)
                    IFNULL L5
                    NEW org.springframework.core.convert.Property   (line 106)
                    DUP
                    ALOAD 4     // Ljava/lang/Class; type
                    ALOAD 6     // Ljava/lang/reflect/Method; method
                    ACONST_NULL
                    INVOKESPECIAL org.springframework.core.convert.Property.<init> (Ljava/lang/Class;Ljava/lang/reflect/Method;Ljava/lang/reflect/Method;)V
                    ASTORE 7
                    NEW org.springframework.core.convert.TypeDescriptor   (line 107)
                    DUP
                    ALOAD 7     // Lorg/springframework/core/convert/Property; property
                    INVOKESPECIAL org.springframework.core.convert.TypeDescriptor.<init> (Lorg/springframework/core/convert/Property;)V
                    ASTORE 8
                    ALOAD_0     // Lorg/springframework/expression/spel/support/ReflectivePropertyAccessor; this   (line 108)
                    GETFIELD org.springframework.expression.spel.support.ReflectivePropertyAccessor.readerCache Ljava/util/Map;
                    ALOAD 5     // Lorg/springframework/expression/spel/support/ReflectivePropertyAccessor$CacheKey; cacheKey
                    NEW org.springframework.expression.spel.support.ReflectivePropertyAccessor$InvokerPair
                    DUP
                    ALOAD 6     // Ljava/lang/reflect/Method; method
                    ALOAD 8     // Lorg/springframework/core/convert/TypeDescriptor; typeDescriptor
                    INVOKESPECIAL org.springframework.expression.spel.support.ReflectivePropertyAccessor$InvokerPair.<init> (Ljava/lang/reflect/Member;Lorg/springframework/core/convert/TypeDescriptor;)V
                    INVOKEINTERFACE java.util.Map.put (Ljava/lang/Object;Ljava/lang/Object;)Ljava/lang/Object;
                    POP
                    ALOAD_0     // Lorg/springframework/expression/spel/support/ReflectivePropertyAccessor; this   (line 109)
                    GETFIELD org.springframework.expression.spel.support.ReflectivePropertyAccessor.typeDescriptorCache Ljava/util/Map;
                    ALOAD 5     // Lorg/springframework/expression/spel/support/ReflectivePropertyAccessor$CacheKey; cacheKey
                    ALOAD 8     // Lorg/springframework/core/convert/TypeDescriptor; typeDescriptor
                    INVOKEINTERFACE java.util.Map.put (Ljava/lang/Object;Ljava/lang/Object;)Ljava/lang/Object;
                    POP
                    ICONST_1   (line 110)
                    IRETURN
                L5: ALOAD_0     // Lorg/springframework/expression/spel/support/ReflectivePropertyAccessor; this   (line 113)
                    ALOAD_3     // Ljava/lang/String; name
                    ALOAD 4     // Ljava/lang/Class; type
                    ALOAD_2     // Ljava/lang/Object; target
                    INVOKESPECIAL org.springframework.expression.spel.support.ReflectivePropertyAccessor.findField (Ljava/lang/String;Ljava/lang/Class;Ljava/lang/Object;)Ljava/lang/reflect/Field;
                    ASTORE 7
                    ALOAD 7     // Ljava/lang/reflect/Field; field   (line 114)
                    IFNULL L6
                    NEW org.springframework.core.convert.TypeDescriptor   (line 115)
                    DUP
                    ALOAD 7     // Ljava/lang/reflect/Field; field
                    INVOKESPECIAL org.springframework.core.convert.TypeDescriptor.<init> (Ljava/lang/reflect/Field;)V
                    ASTORE 8
                    ALOAD_0     // Lorg/springframework/expression/spel/support/ReflectivePropertyAccessor; this   (line 116)
                    GETFIELD org.springframework.expression.spel.support.ReflectivePropertyAccessor.readerCache Ljava/util/Map;
                    ALOAD 5     // Lorg/springframework/expression/spel/support/ReflectivePropertyAccessor$CacheKey; cacheKey
                    NEW org.springframework.expression.spel.support.ReflectivePropertyAccessor$InvokerPair
                    DUP
                    ALOAD 7     // Ljava/lang/reflect/Field; field
                    ALOAD 8     // Lorg/springframework/core/convert/TypeDescriptor; typeDescriptor
                    INVOKESPECIAL org.springframework.expression.spel.support.ReflectivePropertyAccessor$InvokerPair.<init> (Ljava/lang/reflect/Member;Lorg/springframework/core/convert/TypeDescriptor;)V
                    INVOKEINTERFACE java.util.Map.put (Ljava/lang/Object;Ljava/lang/Object;)Ljava/lang/Object;
                    POP
                    ALOAD_0     // Lorg/springframework/expression/spel/support/ReflectivePropertyAccessor; this   (line 117)
                    GETFIELD org.springframework.expression.spel.support.ReflectivePropertyAccessor.typeDescriptorCache Ljava/util/Map;
                    ALOAD 5     // Lorg/springframework/expression/spel/support/ReflectivePropertyAccessor$CacheKey; cacheKey
                    ALOAD 8     // Lorg/springframework/core/convert/TypeDescriptor; typeDescriptor
                    INVOKEINTERFACE java.util.Map.put (Ljava/lang/Object;Ljava/lang/Object;)Ljava/lang/Object;
                    POP
                    ICONST_1   (line 118)
                    IRETURN
                L6: ICONST_0   (line 121)
                    IRETURN
  end public boolean canRead(org.springframework.expression.EvaluationContext, Object, String) throws org.springframework.expression.AccessException

  public java.lang.reflect.Member getLastReadInvokerPair():
                    ALOAD_0     // Lorg/springframework/expression/spel/support/ReflectivePropertyAccessor; this   (line 125)
                    GETFIELD org.springframework.expression.spel.support.ReflectivePropertyAccessor.lastReadInvokerPair Lorg/springframework/expression/spel/support/ReflectivePropertyAccessor$InvokerPair;
                    GETFIELD org.springframework.expression.spel.support.ReflectivePropertyAccessor$InvokerPair.member Ljava/lang/reflect/Member;
                    ARETURN
  end public java.lang.reflect.Member getLastReadInvokerPair()

  public org.springframework.expression.TypedValue read(org.springframework.expression.EvaluationContext, Object, String) throws org.springframework.expression.AccessException:
                    ALOAD_2     // Ljava/lang/Object; target   (line 130)
                    IFNONNULL L0
                    NEW org.springframework.expression.AccessException   (line 131)
                    DUP
                    LDC "Cannot read property of null target"
                    INVOKESPECIAL org.springframework.expression.AccessException.<init> (Ljava/lang/String;)V
                    ATHROW
                L0: ALOAD_2     // Ljava/lang/Object; target   (line 133)
                    INSTANCEOF java.lang.Class
                    IFEQ L1
                    ALOAD_2     // Ljava/lang/Object; target
                    CHECKCAST java.lang.Class
                    GOTO L2
                L1: ALOAD_2     // Ljava/lang/Object; target
                    INVOKEVIRTUAL java.lang.Object.getClass ()Ljava/lang/Class;
                L2: ASTORE 4
                    ALOAD 4     // Ljava/lang/Class; type   (line 135)
                    INVOKEVIRTUAL java.lang.Class.isArray ()Z
                    IFEQ L4
                    ALOAD_3     // Ljava/lang/String; name
                    LDC "length"
                    INVOKEVIRTUAL java.lang.String.equals (Ljava/lang/Object;)Z
                    IFEQ L4
                    ALOAD_2     // Ljava/lang/Object; target   (line 136)
                    INSTANCEOF java.lang.Class
                    IFEQ L3
                    NEW org.springframework.expression.AccessException   (line 137)
                    DUP
                    LDC "Cannot access length on array class itself"
                    INVOKESPECIAL org.springframework.expression.AccessException.<init> (Ljava/lang/String;)V
                    ATHROW
                L3: NEW org.springframework.expression.TypedValue   (line 139)
                    DUP
                    ALOAD_2     // Ljava/lang/Object; target
                    INVOKESTATIC java.lang.reflect.Array.getLength (Ljava/lang/Object;)I
                    INVOKESTATIC java.lang.Integer.valueOf (I)Ljava/lang/Integer;
                    INVOKESPECIAL org.springframework.expression.TypedValue.<init> (Ljava/lang/Object;)V
                    ARETURN
                L4: NEW org.springframework.expression.spel.support.ReflectivePropertyAccessor$CacheKey   (line 142)
                    DUP
                    ALOAD 4     // Ljava/lang/Class; type
                    ALOAD_3     // Ljava/lang/String; name
                    ALOAD_2     // Ljava/lang/Object; target
                    INSTANCEOF java.lang.Class
                    INVOKESPECIAL org.springframework.expression.spel.support.ReflectivePropertyAccessor$CacheKey.<init> (Ljava/lang/Class;Ljava/lang/String;Z)V
                    ASTORE 5
                    ALOAD_0     // Lorg/springframework/expression/spel/support/ReflectivePropertyAccessor; this   (line 143)
                    GETFIELD org.springframework.expression.spel.support.ReflectivePropertyAccessor.readerCache Ljava/util/Map;
                    ALOAD 5     // Lorg/springframework/expression/spel/support/ReflectivePropertyAccessor$CacheKey; cacheKey
                    INVOKEINTERFACE java.util.Map.get (Ljava/lang/Object;)Ljava/lang/Object;
                    CHECKCAST org.springframework.expression.spel.support.ReflectivePropertyAccessor$InvokerPair
                    ASTORE 6
                    ALOAD_0     // Lorg/springframework/expression/spel/support/ReflectivePropertyAccessor; this   (line 144)
                    ALOAD 6     // Lorg/springframework/expression/spel/support/ReflectivePropertyAccessor$InvokerPair; invoker
                    PUTFIELD org.springframework.expression.spel.support.ReflectivePropertyAccessor.lastReadInvokerPair Lorg/springframework/expression/spel/support/ReflectivePropertyAccessor$InvokerPair;
                    ALOAD 6     // Lorg/springframework/expression/spel/support/ReflectivePropertyAccessor$InvokerPair; invoker   (line 146)
                    IFNULL L5
                    ALOAD 6     // Lorg/springframework/expression/spel/support/ReflectivePropertyAccessor$InvokerPair; invoker
                    GETFIELD org.springframework.expression.spel.support.ReflectivePropertyAccessor$InvokerPair.member Ljava/lang/reflect/Member;
                    INSTANCEOF java.lang.reflect.Method
                    IFEQ L9
                L5: ALOAD 6     // Lorg/springframework/expression/spel/support/ReflectivePropertyAccessor$InvokerPair; invoker   (line 147)
                    IFNULL L6
                    ALOAD 6     // Lorg/springframework/expression/spel/support/ReflectivePropertyAccessor$InvokerPair; invoker
                    GETFIELD org.springframework.expression.spel.support.ReflectivePropertyAccessor$InvokerPair.member Ljava/lang/reflect/Member;
                    GOTO L7
                L6: ACONST_NULL
                L7: CHECKCAST java.lang.reflect.Method
                    CHECKCAST java.lang.reflect.Method
                    ASTORE 7
                    ALOAD 7     // Ljava/lang/reflect/Method; method   (line 148)
                    IFNONNULL L8
                    ALOAD_0     // Lorg/springframework/expression/spel/support/ReflectivePropertyAccessor; this   (line 149)
                    ALOAD_3     // Ljava/lang/String; name
                    ALOAD 4     // Ljava/lang/Class; type
                    ALOAD_2     // Ljava/lang/Object; target
                    INVOKESPECIAL org.springframework.expression.spel.support.ReflectivePropertyAccessor.findGetterForProperty (Ljava/lang/String;Ljava/lang/Class;Ljava/lang/Object;)Ljava/lang/reflect/Method;
                    ASTORE 7     // Ljava/lang/reflect/Method; method
                    ALOAD 7     // Ljava/lang/reflect/Method; method   (line 150)
                    IFNULL L8
                    NEW org.springframework.core.convert.Property   (line 154)
                    DUP
                    ALOAD 4     // Ljava/lang/Class; type
                    ALOAD 7     // Ljava/lang/reflect/Method; method
                    ACONST_NULL
                    INVOKESPECIAL org.springframework.core.convert.Property.<init> (Ljava/lang/Class;Ljava/lang/reflect/Method;Ljava/lang/reflect/Method;)V
                    ASTORE 8
                    NEW org.springframework.core.convert.TypeDescriptor   (line 155)
                    DUP
                    ALOAD 8     // Lorg/springframework/core/convert/Property; property
                    INVOKESPECIAL org.springframework.core.convert.TypeDescriptor.<init> (Lorg/springframework/core/convert/Property;)V
                    ASTORE 9
                    NEW org.springframework.expression.spel.support.ReflectivePropertyAccessor$InvokerPair   (line 156)
                    DUP
                    ALOAD 7     // Ljava/lang/reflect/Method; method
                    ALOAD 9     // Lorg/springframework/core/convert/TypeDescriptor; typeDescriptor
                    INVOKESPECIAL org.springframework.expression.spel.support.ReflectivePropertyAccessor$InvokerPair.<init> (Ljava/lang/reflect/Member;Lorg/springframework/core/convert/TypeDescriptor;)V
                    ASTORE 6     // Lorg/springframework/expression/spel/support/ReflectivePropertyAccessor$InvokerPair; invoker
                    ALOAD_0     // Lorg/springframework/expression/spel/support/ReflectivePropertyAccessor; this   (line 157)
                    ALOAD 6     // Lorg/springframework/expression/spel/support/ReflectivePropertyAccessor$InvokerPair; invoker
                    PUTFIELD org.springframework.expression.spel.support.ReflectivePropertyAccessor.lastReadInvokerPair Lorg/springframework/expression/spel/support/ReflectivePropertyAccessor$InvokerPair;
                    ALOAD_0     // Lorg/springframework/expression/spel/support/ReflectivePropertyAccessor; this   (line 158)
                    GETFIELD org.springframework.expression.spel.support.ReflectivePropertyAccessor.readerCache Ljava/util/Map;
                    ALOAD 5     // Lorg/springframework/expression/spel/support/ReflectivePropertyAccessor$CacheKey; cacheKey
                    ALOAD 6     // Lorg/springframework/expression/spel/support/ReflectivePropertyAccessor$InvokerPair; invoker
                    INVOKEINTERFACE java.util.Map.put (Ljava/lang/Object;Ljava/lang/Object;)Ljava/lang/Object;
                    POP
                L8: ALOAD 7     // Ljava/lang/reflect/Method; method   (line 161)
                    IFNULL L9
    catch java.lang.Exception -> E0
    |               ALOAD 7     // Ljava/lang/reflect/Method; method   (line 163)
    |               INVOKESTATIC org.springframework.util.ReflectionUtils.makeAccessible (Ljava/lang/reflect/Method;)V
    |               ALOAD 7     // Ljava/lang/reflect/Method; method   (line 164)
    |               ALOAD_2     // Ljava/lang/Object; target
    |               ICONST_0
    |               ANEWARRAY java.lang.Object
    |               INVOKEVIRTUAL java.lang.reflect.Method.invoke (Ljava/lang/Object;[Ljava/lang/Object;)Ljava/lang/Object;
    |               ASTORE 8
    |               NEW org.springframework.expression.TypedValue   (line 165)
    |               DUP
    |               ALOAD 8     // Ljava/lang/Object; value
    |               ALOAD 6     // Lorg/springframework/expression/spel/support/ReflectivePropertyAccessor$InvokerPair; invoker
    |               GETFIELD org.springframework.expression.spel.support.ReflectivePropertyAccessor$InvokerPair.typeDescriptor Lorg/springframework/core/convert/TypeDescriptor;
    |               ALOAD 8     // Ljava/lang/Object; value
    |               INVOKEVIRTUAL org.springframework.core.convert.TypeDescriptor.narrow (Ljava/lang/Object;)Lorg/springframework/core/convert/TypeDescriptor;
    |               INVOKESPECIAL org.springframework.expression.TypedValue.<init> (Ljava/lang/Object;Lorg/springframework/core/convert/TypeDescriptor;)V
    catch java.lang.Exception -> E0
                    ARETURN
                E0: ASTORE 8   (line 167)
                    NEW org.springframework.expression.AccessException   (line 168)
                    DUP
                    NEW java.lang.StringBuilder
                    DUP
                    INVOKESPECIAL java.lang.StringBuilder.<init> ()V
                    LDC "Unable to access property '"
                    INVOKEVIRTUAL java.lang.StringBuilder.append (Ljava/lang/String;)Ljava/lang/StringBuilder;
                    ALOAD_3     // Ljava/lang/String; name
                    INVOKEVIRTUAL java.lang.StringBuilder.append (Ljava/lang/String;)Ljava/lang/StringBuilder;
                    LDC "' through getter"
                    INVOKEVIRTUAL java.lang.StringBuilder.append (Ljava/lang/String;)Ljava/lang/StringBuilder;
                    INVOKEVIRTUAL java.lang.StringBuilder.toString ()Ljava/lang/String;
                    ALOAD 8     // Ljava/lang/Exception; ex
                    INVOKESPECIAL org.springframework.expression.AccessException.<init> (Ljava/lang/String;Ljava/lang/Exception;)V
                    ATHROW
                L9: ALOAD 6     // Lorg/springframework/expression/spel/support/ReflectivePropertyAccessor$InvokerPair; invoker   (line 173)
                    IFNULL L10
                    ALOAD 6     // Lorg/springframework/expression/spel/support/ReflectivePropertyAccessor$InvokerPair; invoker
                    GETFIELD org.springframework.expression.spel.support.ReflectivePropertyAccessor$InvokerPair.member Ljava/lang/reflect/Member;
                    INSTANCEOF java.lang.reflect.Field
                    IFEQ L14
               L10: ALOAD 6     // Lorg/springframework/expression/spel/support/ReflectivePropertyAccessor$InvokerPair; invoker   (line 174)
                    IFNONNULL L11
                    ACONST_NULL
                    GOTO L12
               L11: ALOAD 6     // Lorg/springframework/expression/spel/support/ReflectivePropertyAccessor$InvokerPair; invoker
                    GETFIELD org.springframework.expression.spel.support.ReflectivePropertyAccessor$InvokerPair.member Ljava/lang/reflect/Member;
               L12: CHECKCAST java.lang.reflect.Field
                    CHECKCAST java.lang.reflect.Field
                    ASTORE 7
                    ALOAD 7     // Ljava/lang/reflect/Field; field   (line 175)
                    IFNONNULL L13
                    ALOAD_0     // Lorg/springframework/expression/spel/support/ReflectivePropertyAccessor; this   (line 176)
                    ALOAD_3     // Ljava/lang/String; name
                    ALOAD 4     // Ljava/lang/Class; type
                    ALOAD_2     // Ljava/lang/Object; target
                    INVOKESPECIAL org.springframework.expression.spel.support.ReflectivePropertyAccessor.findField (Ljava/lang/String;Ljava/lang/Class;Ljava/lang/Object;)Ljava/lang/reflect/Field;
                    ASTORE 7     // Ljava/lang/reflect/Field; field
                    ALOAD 7     // Ljava/lang/reflect/Field; field   (line 177)
                    IFNULL L13
                    NEW org.springframework.expression.spel.support.ReflectivePropertyAccessor$InvokerPair   (line 178)
                    DUP
                    ALOAD 7     // Ljava/lang/reflect/Field; field
                    NEW org.springframework.core.convert.TypeDescriptor
                    DUP
                    ALOAD 7     // Ljava/lang/reflect/Field; field
                    INVOKESPECIAL org.springframework.core.convert.TypeDescriptor.<init> (Ljava/lang/reflect/Field;)V
                    INVOKESPECIAL org.springframework.expression.spel.support.ReflectivePropertyAccessor$InvokerPair.<init> (Ljava/lang/reflect/Member;Lorg/springframework/core/convert/TypeDescriptor;)V
                    ASTORE 6     // Lorg/springframework/expression/spel/support/ReflectivePropertyAccessor$InvokerPair; invoker
                    ALOAD_0     // Lorg/springframework/expression/spel/support/ReflectivePropertyAccessor; this   (line 179)
                    ALOAD 6     // Lorg/springframework/expression/spel/support/ReflectivePropertyAccessor$InvokerPair; invoker
                    PUTFIELD org.springframework.expression.spel.support.ReflectivePropertyAccessor.lastReadInvokerPair Lorg/springframework/expression/spel/support/ReflectivePropertyAccessor$InvokerPair;
                    ALOAD_0     // Lorg/springframework/expression/spel/support/ReflectivePropertyAccessor; this   (line 180)
                    GETFIELD org.springframework.expression.spel.support.ReflectivePropertyAccessor.readerCache Ljava/util/Map;
                    ALOAD 5     // Lorg/springframework/expression/spel/support/ReflectivePropertyAccessor$CacheKey; cacheKey
                    ALOAD 6     // Lorg/springframework/expression/spel/support/ReflectivePropertyAccessor$InvokerPair; invoker
                    INVOKEINTERFACE java.util.Map.put (Ljava/lang/Object;Ljava/lang/Object;)Ljava/lang/Object;
                    POP
               L13: ALOAD 7     // Ljava/lang/reflect/Field; field   (line 183)
                    IFNULL L14
    catch java.lang.Exception -> E1
    |               ALOAD 7     // Ljava/lang/reflect/Field; field   (line 185)
    |               INVOKESTATIC org.springframework.util.ReflectionUtils.makeAccessible (Ljava/lang/reflect/Field;)V
    |               ALOAD 7     // Ljava/lang/reflect/Field; field   (line 186)
    |               ALOAD_2     // Ljava/lang/Object; target
    |               INVOKEVIRTUAL java.lang.reflect.Field.get (Ljava/lang/Object;)Ljava/lang/Object;
    |               ASTORE 8
    |               NEW org.springframework.expression.TypedValue   (line 187)
    |               DUP
    |               ALOAD 8     // Ljava/lang/Object; value
    |               ALOAD 6     // Lorg/springframework/expression/spel/support/ReflectivePropertyAccessor$InvokerPair; invoker
    |               GETFIELD org.springframework.expression.spel.support.ReflectivePropertyAccessor$InvokerPair.typeDescriptor Lorg/springframework/core/convert/TypeDescriptor;
    |               ALOAD 8     // Ljava/lang/Object; value
    |               INVOKEVIRTUAL org.springframework.core.convert.TypeDescriptor.narrow (Ljava/lang/Object;)Lorg/springframework/core/convert/TypeDescriptor;
    |               INVOKESPECIAL org.springframework.expression.TypedValue.<init> (Ljava/lang/Object;Lorg/springframework/core/convert/TypeDescriptor;)V
    catch java.lang.Exception -> E1
                    ARETURN
                E1: ASTORE 8   (line 189)
                    NEW org.springframework.expression.AccessException   (line 190)
                    DUP
                    NEW java.lang.StringBuilder
                    DUP
                    INVOKESPECIAL java.lang.StringBuilder.<init> ()V
                    LDC "Unable to access field: "
                    INVOKEVIRTUAL java.lang.StringBuilder.append (Ljava/lang/String;)Ljava/lang/StringBuilder;
                    ALOAD_3     // Ljava/lang/String; name
                    INVOKEVIRTUAL java.lang.StringBuilder.append (Ljava/lang/String;)Ljava/lang/StringBuilder;
                    INVOKEVIRTUAL java.lang.StringBuilder.toString ()Ljava/lang/String;
                    ALOAD 8     // Ljava/lang/Exception; ex
                    INVOKESPECIAL org.springframework.expression.AccessException.<init> (Ljava/lang/String;Ljava/lang/Exception;)V
                    ATHROW
               L14: NEW org.springframework.expression.AccessException   (line 195)
                    DUP
                    NEW java.lang.StringBuilder
                    DUP
                    INVOKESPECIAL java.lang.StringBuilder.<init> ()V
                    LDC "Neither getter nor field found for property '"
                    INVOKEVIRTUAL java.lang.StringBuilder.append (Ljava/lang/String;)Ljava/lang/StringBuilder;
                    ALOAD_3     // Ljava/lang/String; name
                    INVOKEVIRTUAL java.lang.StringBuilder.append (Ljava/lang/String;)Ljava/lang/StringBuilder;
                    LDC "'"
                    INVOKEVIRTUAL java.lang.StringBuilder.append (Ljava/lang/String;)Ljava/lang/StringBuilder;
                    INVOKEVIRTUAL java.lang.StringBuilder.toString ()Ljava/lang/String;
                    INVOKESPECIAL org.springframework.expression.AccessException.<init> (Ljava/lang/String;)V
                    ATHROW
  end public org.springframework.expression.TypedValue read(org.springframework.expression.EvaluationContext, Object, String) throws org.springframework.expression.AccessException

  public boolean canWrite(org.springframework.expression.EvaluationContext, Object, String) throws org.springframework.expression.AccessException:
                    ALOAD_2     // Ljava/lang/Object; target   (line 200)
                    IFNONNULL L0
                    ICONST_0   (line 201)
                    IRETURN
                L0: ALOAD_2     // Ljava/lang/Object; target   (line 203)
                    INSTANCEOF java.lang.Class
                    IFEQ L1
                    ALOAD_2     // Ljava/lang/Object; target
                    CHECKCAST java.lang.Class
                    GOTO L2
                L1: ALOAD_2     // Ljava/lang/Object; target
                    INVOKEVIRTUAL java.lang.Object.getClass ()Ljava/lang/Class;
                L2: ASTORE 4
                    NEW org.springframework.expression.spel.support.ReflectivePropertyAccessor$CacheKey   (line 204)
                    DUP
                    ALOAD 4     // Ljava/lang/Class; type
                    ALOAD_3     // Ljava/lang/String; name
                    ALOAD_2     // Ljava/lang/Object; target
                    INSTANCEOF java.lang.Class
                    INVOKESPECIAL org.springframework.expression.spel.support.ReflectivePropertyAccessor$CacheKey.<init> (Ljava/lang/Class;Ljava/lang/String;Z)V
                    ASTORE 5
                    ALOAD_0     // Lorg/springframework/expression/spel/support/ReflectivePropertyAccessor; this   (line 205)
                    GETFIELD org.springframework.expression.spel.support.ReflectivePropertyAccessor.writerCache Ljava/util/Map;
                    ALOAD 5     // Lorg/springframework/expression/spel/support/ReflectivePropertyAccessor$CacheKey; cacheKey
                    INVOKEINTERFACE java.util.Map.containsKey (Ljava/lang/Object;)Z
                    IFEQ L3
                    ICONST_1   (line 206)
                    IRETURN
                L3: ALOAD_0     // Lorg/springframework/expression/spel/support/ReflectivePropertyAccessor; this   (line 208)
                    ALOAD_3     // Ljava/lang/String; name
                    ALOAD 4     // Ljava/lang/Class; type
                    ALOAD_2     // Ljava/lang/Object; target
                    INVOKESPECIAL org.springframework.expression.spel.support.ReflectivePropertyAccessor.findSetterForProperty (Ljava/lang/String;Ljava/lang/Class;Ljava/lang/Object;)Ljava/lang/reflect/Method;
                    ASTORE 6
                    ALOAD 6     // Ljava/lang/reflect/Method; method   (line 209)
                    IFNULL L4
                    NEW org.springframework.core.convert.Property   (line 211)
                    DUP
                    ALOAD 4     // Ljava/lang/Class; type
                    ACONST_NULL
                    ALOAD 6     // Ljava/lang/reflect/Method; method
                    INVOKESPECIAL org.springframework.core.convert.Property.<init> (Ljava/lang/Class;Ljava/lang/reflect/Method;Ljava/lang/reflect/Method;)V
                    ASTORE 7
                    NEW org.springframework.core.convert.TypeDescriptor   (line 212)
                    DUP
                    ALOAD 7     // Lorg/springframework/core/convert/Property; property
                    INVOKESPECIAL org.springframework.core.convert.TypeDescriptor.<init> (Lorg/springframework/core/convert/Property;)V
                    ASTORE 8
                    ALOAD_0     // Lorg/springframework/expression/spel/support/ReflectivePropertyAccessor; this   (line 213)
                    GETFIELD org.springframework.expression.spel.support.ReflectivePropertyAccessor.writerCache Ljava/util/Map;
                    ALOAD 5     // Lorg/springframework/expression/spel/support/ReflectivePropertyAccessor$CacheKey; cacheKey
                    ALOAD 6     // Ljava/lang/reflect/Method; method
                    INVOKEINTERFACE java.util.Map.put (Ljava/lang/Object;Ljava/lang/Object;)Ljava/lang/Object;
                    POP
                    ALOAD_0     // Lorg/springframework/expression/spel/support/ReflectivePropertyAccessor; this   (line 214)
                    GETFIELD org.springframework.expression.spel.support.ReflectivePropertyAccessor.typeDescriptorCache Ljava/util/Map;
                    ALOAD 5     // Lorg/springframework/expression/spel/support/ReflectivePropertyAccessor$CacheKey; cacheKey
                    ALOAD 8     // Lorg/springframework/core/convert/TypeDescriptor; typeDescriptor
                    INVOKEINTERFACE java.util.Map.put (Ljava/lang/Object;Ljava/lang/Object;)Ljava/lang/Object;
                    POP
                    ICONST_1   (line 215)
                    IRETURN
                L4: ALOAD_0     // Lorg/springframework/expression/spel/support/ReflectivePropertyAccessor; this   (line 218)
                    ALOAD_3     // Ljava/lang/String; name
                    ALOAD 4     // Ljava/lang/Class; type
                    ALOAD_2     // Ljava/lang/Object; target
                    INVOKESPECIAL org.springframework.expression.spel.support.ReflectivePropertyAccessor.findField (Ljava/lang/String;Ljava/lang/Class;Ljava/lang/Object;)Ljava/lang/reflect/Field;
                    ASTORE 7
                    ALOAD 7     // Ljava/lang/reflect/Field; field   (line 219)
                    IFNULL L5
                    ALOAD_0     // Lorg/springframework/expression/spel/support/ReflectivePropertyAccessor; this   (line 220)
                    GETFIELD org.springframework.expression.spel.support.ReflectivePropertyAccessor.writerCache Ljava/util/Map;
                    ALOAD 5     // Lorg/springframework/expression/spel/support/ReflectivePropertyAccessor$CacheKey; cacheKey
                    ALOAD 7     // Ljava/lang/reflect/Field; field
                    INVOKEINTERFACE java.util.Map.put (Ljava/lang/Object;Ljava/lang/Object;)Ljava/lang/Object;
                    POP
                    ALOAD_0     // Lorg/springframework/expression/spel/support/ReflectivePropertyAccessor; this   (line 221)
                    GETFIELD org.springframework.expression.spel.support.ReflectivePropertyAccessor.typeDescriptorCache Ljava/util/Map;
                    ALOAD 5     // Lorg/springframework/expression/spel/support/ReflectivePropertyAccessor$CacheKey; cacheKey
                    NEW org.springframework.core.convert.TypeDescriptor
                    DUP
                    ALOAD 7     // Ljava/lang/reflect/Field; field
                    INVOKESPECIAL org.springframework.core.convert.TypeDescriptor.<init> (Ljava/lang/reflect/Field;)V
                    INVOKEINTERFACE java.util.Map.put (Ljava/lang/Object;Ljava/lang/Object;)Ljava/lang/Object;
                    POP
                    ICONST_1   (line 222)
                    IRETURN
                L5: ICONST_0   (line 225)
                    IRETURN
  end public boolean canWrite(org.springframework.expression.EvaluationContext, Object, String) throws org.springframework.expression.AccessException

  public void write(org.springframework.expression.EvaluationContext, Object, String, Object) throws org.springframework.expression.AccessException:
                    ALOAD_2     // Ljava/lang/Object; target   (line 230)
                    IFNONNULL L0
                    NEW org.springframework.expression.AccessException   (line 231)
                    DUP
                    LDC "Cannot write property on null target"
                    INVOKESPECIAL org.springframework.expression.AccessException.<init> (Ljava/lang/String;)V
                    ATHROW
                L0: ALOAD_2     // Ljava/lang/Object; target   (line 233)
                    INSTANCEOF java.lang.Class
                    IFEQ L1
                    ALOAD_2     // Ljava/lang/Object; target
                    CHECKCAST java.lang.Class
                    GOTO L2
                L1: ALOAD_2     // Ljava/lang/Object; target
                    INVOKEVIRTUAL java.lang.Object.getClass ()Ljava/lang/Class;
                L2: ASTORE 5
                    ALOAD 4     // Ljava/lang/Object; newValue   (line 235)
                    ASTORE 6
                    ALOAD_0     // Lorg/springframework/expression/spel/support/ReflectivePropertyAccessor; this   (line 236)
                    ALOAD_1     // Lorg/springframework/expression/EvaluationContext; context
                    ALOAD_2     // Ljava/lang/Object; target
                    ALOAD_3     // Ljava/lang/String; name
                    INVOKESPECIAL org.springframework.expression.spel.support.ReflectivePropertyAccessor.getTypeDescriptor (Lorg/springframework/expression/EvaluationContext;Ljava/lang/Object;Ljava/lang/String;)Lorg/springframework/core/convert/TypeDescriptor;
                    ASTORE 7
                    ALOAD 7     // Lorg/springframework/core/convert/TypeDescriptor; typeDescriptor   (line 237)
                    IFNULL L3
    catch org.springframework.expression.EvaluationException -> E0
    |               ALOAD_1     // Lorg/springframework/expression/EvaluationContext; context   (line 239)
    |               INVOKEINTERFACE org.springframework.expression.EvaluationContext.getTypeConverter ()Lorg/springframework/expression/TypeConverter;
    |               ALOAD 4     // Ljava/lang/Object; newValue
    |               ALOAD 4     // Ljava/lang/Object; newValue
    |               INVOKESTATIC org.springframework.core.convert.TypeDescriptor.forObject (Ljava/lang/Object;)Lorg/springframework/core/convert/TypeDescriptor;   (line 240)
    |               ALOAD 7     // Lorg/springframework/core/convert/TypeDescriptor; typeDescriptor
    |               INVOKEINTERFACE org.springframework.expression.TypeConverter.convertValue (Ljava/lang/Object;Lorg/springframework/core/convert/TypeDescriptor;Lorg/springframework/core/convert/TypeDescriptor;)Ljava/lang/Object;   (line 239)
    |               ASTORE 6     // Ljava/lang/Object; possiblyConvertedNewValue
    catch org.springframework.expression.EvaluationException -> E0
                    GOTO L3   (line 244)
                E0: ASTORE 8   (line 242)
                    NEW org.springframework.expression.AccessException   (line 243)
                    DUP
                    LDC "Type conversion failure"
                    ALOAD 8     // Lorg/springframework/expression/EvaluationException; evaluationException
                    INVOKESPECIAL org.springframework.expression.AccessException.<init> (Ljava/lang/String;Ljava/lang/Exception;)V
                    ATHROW
                L3: NEW org.springframework.expression.spel.support.ReflectivePropertyAccessor$CacheKey   (line 246)
                    DUP
                    ALOAD 5     // Ljava/lang/Class; type
                    ALOAD_3     // Ljava/lang/String; name
                    ALOAD_2     // Ljava/lang/Object; target
                    INSTANCEOF java.lang.Class
                    INVOKESPECIAL org.springframework.expression.spel.support.ReflectivePropertyAccessor$CacheKey.<init> (Ljava/lang/Class;Ljava/lang/String;Z)V
                    ASTORE 8
                    ALOAD_0     // Lorg/springframework/expression/spel/support/ReflectivePropertyAccessor; this   (line 247)
                    GETFIELD org.springframework.expression.spel.support.ReflectivePropertyAccessor.writerCache Ljava/util/Map;
                    ALOAD 8     // Lorg/springframework/expression/spel/support/ReflectivePropertyAccessor$CacheKey; cacheKey
                    INVOKEINTERFACE java.util.Map.get (Ljava/lang/Object;)Ljava/lang/Object;
                    CHECKCAST java.lang.reflect.Member
                    ASTORE 9
                    ALOAD 9     // Ljava/lang/reflect/Member; cachedMember   (line 249)
                    IFNULL L4
                    ALOAD 9     // Ljava/lang/reflect/Member; cachedMember
                    INSTANCEOF java.lang.reflect.Method
                    IFEQ L6
                L4: ALOAD 9     // Ljava/lang/reflect/Member; cachedMember   (line 250)
                    CHECKCAST java.lang.reflect.Method
                    ASTORE 10
                    ALOAD 10     // Ljava/lang/reflect/Method; method   (line 251)
                    IFNONNULL L5
                    ALOAD_0     // Lorg/springframework/expression/spel/support/ReflectivePropertyAccessor; this   (line 252)
                    ALOAD_3     // Ljava/lang/String; name
                    ALOAD 5     // Ljava/lang/Class; type
                    ALOAD_2     // Ljava/lang/Object; target
                    INVOKESPECIAL org.springframework.expression.spel.support.ReflectivePropertyAccessor.findSetterForProperty (Ljava/lang/String;Ljava/lang/Class;Ljava/lang/Object;)Ljava/lang/reflect/Method;
                    ASTORE 10     // Ljava/lang/reflect/Method; method
                    ALOAD 10     // Ljava/lang/reflect/Method; method   (line 253)
                    IFNULL L5
                    ALOAD 10     // Ljava/lang/reflect/Method; method   (line 254)
                    ASTORE 9     // Ljava/lang/reflect/Member; cachedMember
                    ALOAD_0     // Lorg/springframework/expression/spel/support/ReflectivePropertyAccessor; this   (line 255)
                    GETFIELD org.springframework.expression.spel.support.ReflectivePropertyAccessor.writerCache Ljava/util/Map;
                    ALOAD 8     // Lorg/springframework/expression/spel/support/ReflectivePropertyAccessor$CacheKey; cacheKey
                    ALOAD 9     // Ljava/lang/reflect/Member; cachedMember
                    INVOKEINTERFACE java.util.Map.put (Ljava/lang/Object;Ljava/lang/Object;)Ljava/lang/Object;
                    POP
                L5: ALOAD 10     // Ljava/lang/reflect/Method; method   (line 258)
                    IFNULL L6
    catch java.lang.Exception -> E1
    |               ALOAD 10     // Ljava/lang/reflect/Method; method   (line 260)
    |               INVOKESTATIC org.springframework.util.ReflectionUtils.makeAccessible (Ljava/lang/reflect/Method;)V
    |               ALOAD 10     // Ljava/lang/reflect/Method; method   (line 261)
    |               ALOAD_2     // Ljava/lang/Object; target
    |               ICONST_1
    |               ANEWARRAY java.lang.Object
    |               DUP
    |               ICONST_0
    |               ALOAD 6     // Ljava/lang/Object; possiblyConvertedNewValue
    |               AASTORE
    |               INVOKEVIRTUAL java.lang.reflect.Method.invoke (Ljava/lang/Object;[Ljava/lang/Object;)Ljava/lang/Object;
    |               POP
    catch java.lang.Exception -> E1
                    RETURN   (line 262)
                E1: ASTORE 11   (line 264)
                    NEW org.springframework.expression.AccessException   (line 265)
                    DUP
                    NEW java.lang.StringBuilder
                    DUP
                    INVOKESPECIAL java.lang.StringBuilder.<init> ()V
                    LDC "Unable to access property '"
                    INVOKEVIRTUAL java.lang.StringBuilder.append (Ljava/lang/String;)Ljava/lang/StringBuilder;
                    ALOAD_3     // Ljava/lang/String; name
                    INVOKEVIRTUAL java.lang.StringBuilder.append (Ljava/lang/String;)Ljava/lang/StringBuilder;
                    LDC "' through setter"
                    INVOKEVIRTUAL java.lang.StringBuilder.append (Ljava/lang/String;)Ljava/lang/StringBuilder;
                    INVOKEVIRTUAL java.lang.StringBuilder.toString ()Ljava/lang/String;
                    ALOAD 11     // Ljava/lang/Exception; ex
                    INVOKESPECIAL org.springframework.expression.AccessException.<init> (Ljava/lang/String;Ljava/lang/Exception;)V
                    ATHROW
                L6: ALOAD 9     // Ljava/lang/reflect/Member; cachedMember   (line 270)
                    IFNULL L7
                    ALOAD 9     // Ljava/lang/reflect/Member; cachedMember
                    INSTANCEOF java.lang.reflect.Field
                    IFEQ L9
                L7: ALOAD 9     // Ljava/lang/reflect/Member; cachedMember   (line 271)
                    CHECKCAST java.lang.reflect.Field
                    ASTORE 10
                    ALOAD 10     // Ljava/lang/reflect/Field; field   (line 272)
                    IFNONNULL L8
                    ALOAD_0     // Lorg/springframework/expression/spel/support/ReflectivePropertyAccessor; this   (line 273)
                    ALOAD_3     // Ljava/lang/String; name
                    ALOAD 5     // Ljava/lang/Class; type
                    ALOAD_2     // Ljava/lang/Object; target
                    INVOKESPECIAL org.springframework.expression.spel.support.ReflectivePropertyAccessor.findField (Ljava/lang/String;Ljava/lang/Class;Ljava/lang/Object;)Ljava/lang/reflect/Field;
                    ASTORE 10     // Ljava/lang/reflect/Field; field
                    ALOAD 10     // Ljava/lang/reflect/Field; field   (line 274)
                    IFNULL L8
                    ALOAD 10     // Ljava/lang/reflect/Field; field   (line 275)
                    ASTORE 9     // Ljava/lang/reflect/Member; cachedMember
                    ALOAD_0     // Lorg/springframework/expression/spel/support/ReflectivePropertyAccessor; this   (line 276)
                    GETFIELD org.springframework.expression.spel.support.ReflectivePropertyAccessor.writerCache Ljava/util/Map;
                    ALOAD 8     // Lorg/springframework/expression/spel/support/ReflectivePropertyAccessor$CacheKey; cacheKey
                    ALOAD 9     // Ljava/lang/reflect/Member; cachedMember
                    INVOKEINTERFACE java.util.Map.put (Ljava/lang/Object;Ljava/lang/Object;)Ljava/lang/Object;
                    POP
                L8: ALOAD 10     // Ljava/lang/reflect/Field; field   (line 279)
                    IFNULL L9
    catch java.lang.Exception -> E2
    |               ALOAD 10     // Ljava/lang/reflect/Field; field   (line 281)
    |               INVOKESTATIC org.springframework.util.ReflectionUtils.makeAccessible (Ljava/lang/reflect/Field;)V
    |               ALOAD 10     // Ljava/lang/reflect/Field; field   (line 282)
    |               ALOAD_2     // Ljava/lang/Object; target
    |               ALOAD 6     // Ljava/lang/Object; possiblyConvertedNewValue
    |               INVOKEVIRTUAL java.lang.reflect.Field.set (Ljava/lang/Object;Ljava/lang/Object;)V
    catch java.lang.Exception -> E2
                    RETURN   (line 283)
                E2: ASTORE 11   (line 285)
                    NEW org.springframework.expression.AccessException   (line 286)
                    DUP
                    NEW java.lang.StringBuilder
                    DUP
                    INVOKESPECIAL java.lang.StringBuilder.<init> ()V
                    LDC "Unable to access field: "
                    INVOKEVIRTUAL java.lang.StringBuilder.append (Ljava/lang/String;)Ljava/lang/StringBuilder;
                    ALOAD_3     // Ljava/lang/String; name
                    INVOKEVIRTUAL java.lang.StringBuilder.append (Ljava/lang/String;)Ljava/lang/StringBuilder;
                    INVOKEVIRTUAL java.lang.StringBuilder.toString ()Ljava/lang/String;
                    ALOAD 11     // Ljava/lang/Exception; ex
                    INVOKESPECIAL org.springframework.expression.AccessException.<init> (Ljava/lang/String;Ljava/lang/Exception;)V
                    ATHROW
                L9: NEW org.springframework.expression.AccessException   (line 291)
                    DUP
                    NEW java.lang.StringBuilder
                    DUP
                    INVOKESPECIAL java.lang.StringBuilder.<init> ()V
                    LDC "Neither setter nor field found for property '"
                    INVOKEVIRTUAL java.lang.StringBuilder.append (Ljava/lang/String;)Ljava/lang/StringBuilder;
                    ALOAD_3     // Ljava/lang/String; name
                    INVOKEVIRTUAL java.lang.StringBuilder.append (Ljava/lang/String;)Ljava/lang/StringBuilder;
                    LDC "'"
                    INVOKEVIRTUAL java.lang.StringBuilder.append (Ljava/lang/String;)Ljava/lang/StringBuilder;
                    INVOKEVIRTUAL java.lang.StringBuilder.toString ()Ljava/lang/String;
                    INVOKESPECIAL org.springframework.expression.AccessException.<init> (Ljava/lang/String;)V
                    ATHROW
  end public void write(org.springframework.expression.EvaluationContext, Object, String, Object) throws org.springframework.expression.AccessException

  private org.springframework.core.convert.TypeDescriptor getTypeDescriptor(org.springframework.expression.EvaluationContext, Object, String):
                    ALOAD_2     // Ljava/lang/Object; target   (line 295)
                    IFNONNULL L0
                    ACONST_NULL   (line 296)
                    ARETURN
                L0: ALOAD_2     // Ljava/lang/Object; target   (line 298)
                    INSTANCEOF java.lang.Class
                    IFEQ L1
                    ALOAD_2     // Ljava/lang/Object; target
                    CHECKCAST java.lang.Class
                    GOTO L2
                L1: ALOAD_2     // Ljava/lang/Object; target
                    INVOKEVIRTUAL java.lang.Object.getClass ()Ljava/lang/Class;
                L2: ASTORE 4
                    ALOAD 4     // Ljava/lang/Class; type   (line 300)
                    INVOKEVIRTUAL java.lang.Class.isArray ()Z
                    IFEQ L3
                    ALOAD_3     // Ljava/lang/String; name
                    LDC "length"
                    INVOKEVIRTUAL java.lang.String.equals (Ljava/lang/Object;)Z
                    IFEQ L3
                    GETSTATIC java.lang.Integer.TYPE Ljava/lang/Class;   (line 301)
                    INVOKESTATIC org.springframework.core.convert.TypeDescriptor.valueOf (Ljava/lang/Class;)Lorg/springframework/core/convert/TypeDescriptor;
                    ARETURN
                L3: NEW org.springframework.expression.spel.support.ReflectivePropertyAccessor$CacheKey   (line 303)
                    DUP
                    ALOAD 4     // Ljava/lang/Class; type
                    ALOAD_3     // Ljava/lang/String; name
                    ALOAD_2     // Ljava/lang/Object; target
                    INSTANCEOF java.lang.Class
                    INVOKESPECIAL org.springframework.expression.spel.support.ReflectivePropertyAccessor$CacheKey.<init> (Ljava/lang/Class;Ljava/lang/String;Z)V
                    ASTORE 5
                    ALOAD_0     // Lorg/springframework/expression/spel/support/ReflectivePropertyAccessor; this   (line 304)
                    GETFIELD org.springframework.expression.spel.support.ReflectivePropertyAccessor.typeDescriptorCache Ljava/util/Map;
                    ALOAD 5     // Lorg/springframework/expression/spel/support/ReflectivePropertyAccessor$CacheKey; cacheKey
                    INVOKEINTERFACE java.util.Map.get (Ljava/lang/Object;)Ljava/lang/Object;
                    CHECKCAST org.springframework.core.convert.TypeDescriptor
                    ASTORE 6
                    ALOAD 6     // Lorg/springframework/core/convert/TypeDescriptor; typeDescriptor   (line 305)
                    IFNONNULL L6
    catch org.springframework.expression.AccessException -> E0
    |               ALOAD_0     // Lorg/springframework/expression/spel/support/ReflectivePropertyAccessor; this   (line 308)
    |               ALOAD_1     // Lorg/springframework/expression/EvaluationContext; context
    |               ALOAD_2     // Ljava/lang/Object; target
    |               ALOAD_3     // Ljava/lang/String; name
    |               INVOKEVIRTUAL org.springframework.expression.spel.support.ReflectivePropertyAccessor.canRead (Lorg/springframework/expression/EvaluationContext;Ljava/lang/Object;Ljava/lang/String;)Z
    |               IFEQ L4
    |               ALOAD_0     // Lorg/springframework/expression/spel/support/ReflectivePropertyAccessor; this   (line 309)
    |               GETFIELD org.springframework.expression.spel.support.ReflectivePropertyAccessor.typeDescriptorCache Ljava/util/Map;
    |               ALOAD 5     // Lorg/springframework/expression/spel/support/ReflectivePropertyAccessor$CacheKey; cacheKey
    |               INVOKEINTERFACE java.util.Map.get (Ljava/lang/Object;)Ljava/lang/Object;
    |               CHECKCAST org.springframework.core.convert.TypeDescriptor
    |               ASTORE 6     // Lorg/springframework/core/convert/TypeDescriptor; typeDescriptor
    |               GOTO L5
    |           L4: ALOAD_0     // Lorg/springframework/expression/spel/support/ReflectivePropertyAccessor; this   (line 311)
    |               ALOAD_1     // Lorg/springframework/expression/EvaluationContext; context
    |               ALOAD_2     // Ljava/lang/Object; target
    |               ALOAD_3     // Ljava/lang/String; name
    |               INVOKEVIRTUAL org.springframework.expression.spel.support.ReflectivePropertyAccessor.canWrite (Lorg/springframework/expression/EvaluationContext;Ljava/lang/Object;Ljava/lang/String;)Z
    |               IFEQ L5
    |               ALOAD_0     // Lorg/springframework/expression/spel/support/ReflectivePropertyAccessor; this   (line 312)
    |               GETFIELD org.springframework.expression.spel.support.ReflectivePropertyAccessor.typeDescriptorCache Ljava/util/Map;
    |               ALOAD 5     // Lorg/springframework/expression/spel/support/ReflectivePropertyAccessor$CacheKey; cacheKey
    |               INVOKEINTERFACE java.util.Map.get (Ljava/lang/Object;)Ljava/lang/Object;
    |               CHECKCAST org.springframework.core.convert.TypeDescriptor
    |               ASTORE 6     // Lorg/springframework/core/convert/TypeDescriptor; typeDescriptor
    catch org.springframework.expression.AccessException -> E0
                L5: GOTO L6   (line 317)
                E0: ASTORE 7   (line 315)
                L6: ALOAD 6     // Lorg/springframework/core/convert/TypeDescriptor; typeDescriptor   (line 319)
                    ARETURN
  end private org.springframework.core.convert.TypeDescriptor getTypeDescriptor(org.springframework.expression.EvaluationContext, Object, String)

  private java.lang.reflect.Method findGetterForProperty(String, Class, Object):
                    ALOAD_0     // Lorg/springframework/expression/spel/support/ReflectivePropertyAccessor; this   (line 323)
                    ALOAD_1     // Ljava/lang/String; propertyName
                    ALOAD_2     // Ljava/lang/Class; clazz
                    ALOAD_3     // Ljava/lang/Object; target
                    INSTANCEOF java.lang.Class
                    INVOKEVIRTUAL org.springframework.expression.spel.support.ReflectivePropertyAccessor.findGetterForProperty (Ljava/lang/String;Ljava/lang/Class;Z)Ljava/lang/reflect/Method;
                    ASTORE 4
                    ALOAD 4     // Ljava/lang/reflect/Method; method   (line 324)
                    IFNONNULL L0
                    ALOAD_3     // Ljava/lang/Object; target
                    INSTANCEOF java.lang.Class
                    IFEQ L0
                    ALOAD_0     // Lorg/springframework/expression/spel/support/ReflectivePropertyAccessor; this   (line 325)
                    ALOAD_1     // Ljava/lang/String; propertyName
                    ALOAD_3     // Ljava/lang/Object; target
                    INVOKEVIRTUAL java.lang.Object.getClass ()Ljava/lang/Class;
                    ICONST_0
                    INVOKEVIRTUAL org.springframework.expression.spel.support.ReflectivePropertyAccessor.findGetterForProperty (Ljava/lang/String;Ljava/lang/Class;Z)Ljava/lang/reflect/Method;
                    ASTORE 4     // Ljava/lang/reflect/Method; method
                L0: ALOAD 4     // Ljava/lang/reflect/Method; method   (line 327)
                    ARETURN
  end private java.lang.reflect.Method findGetterForProperty(String, Class, Object)

  private java.lang.reflect.Method findSetterForProperty(String, Class, Object):
                    ALOAD_0     // Lorg/springframework/expression/spel/support/ReflectivePropertyAccessor; this   (line 331)
                    ALOAD_1     // Ljava/lang/String; propertyName
                    ALOAD_2     // Ljava/lang/Class; clazz
                    ALOAD_3     // Ljava/lang/Object; target
                    INSTANCEOF java.lang.Class
                    INVOKEVIRTUAL org.springframework.expression.spel.support.ReflectivePropertyAccessor.findSetterForProperty (Ljava/lang/String;Ljava/lang/Class;Z)Ljava/lang/reflect/Method;
                    ASTORE 4
                    ALOAD 4     // Ljava/lang/reflect/Method; method   (line 332)
                    IFNONNULL L0
                    ALOAD_3     // Ljava/lang/Object; target
                    INSTANCEOF java.lang.Class
                    IFEQ L0
                    ALOAD_0     // Lorg/springframework/expression/spel/support/ReflectivePropertyAccessor; this   (line 333)
                    ALOAD_1     // Ljava/lang/String; propertyName
                    ALOAD_3     // Ljava/lang/Object; target
                    INVOKEVIRTUAL java.lang.Object.getClass ()Ljava/lang/Class;
                    ICONST_0
                    INVOKEVIRTUAL org.springframework.expression.spel.support.ReflectivePropertyAccessor.findSetterForProperty (Ljava/lang/String;Ljava/lang/Class;Z)Ljava/lang/reflect/Method;
                    ASTORE 4     // Ljava/lang/reflect/Method; method
                L0: ALOAD 4     // Ljava/lang/reflect/Method; method   (line 335)
                    ARETURN
  end private java.lang.reflect.Method findSetterForProperty(String, Class, Object)

  private java.lang.reflect.Field findField(String, Class, Object):
                    ALOAD_0     // Lorg/springframework/expression/spel/support/ReflectivePropertyAccessor; this   (line 339)
                    ALOAD_1     // Ljava/lang/String; name
                    ALOAD_2     // Ljava/lang/Class; clazz
                    ALOAD_3     // Ljava/lang/Object; target
                    INSTANCEOF java.lang.Class
                    INVOKEVIRTUAL org.springframework.expression.spel.support.ReflectivePropertyAccessor.findField (Ljava/lang/String;Ljava/lang/Class;Z)Ljava/lang/reflect/Field;
                    ASTORE 4
                    ALOAD 4     // Ljava/lang/reflect/Field; field   (line 340)
                    IFNONNULL L0
                    ALOAD_3     // Ljava/lang/Object; target
                    INSTANCEOF java.lang.Class
                    IFEQ L0
                    ALOAD_0     // Lorg/springframework/expression/spel/support/ReflectivePropertyAccessor; this   (line 341)
                    ALOAD_1     // Ljava/lang/String; name
                    ALOAD_3     // Ljava/lang/Object; target
                    INVOKEVIRTUAL java.lang.Object.getClass ()Ljava/lang/Class;
                    ICONST_0
                    INVOKEVIRTUAL org.springframework.expression.spel.support.ReflectivePropertyAccessor.findField (Ljava/lang/String;Ljava/lang/Class;Z)Ljava/lang/reflect/Field;
                    ASTORE 4     // Ljava/lang/reflect/Field; field
                L0: ALOAD 4     // Ljava/lang/reflect/Field; field   (line 343)
                    ARETURN
  end private java.lang.reflect.Field findField(String, Class, Object)

  protected java.lang.reflect.Method findGetterForProperty(String, Class, boolean):
                    ALOAD_0     // Lorg/springframework/expression/spel/support/ReflectivePropertyAccessor; this   (line 350)
                    ALOAD_0     // Lorg/springframework/expression/spel/support/ReflectivePropertyAccessor; this
                    ALOAD_1     // Ljava/lang/String; propertyName
                    INVOKEVIRTUAL org.springframework.expression.spel.support.ReflectivePropertyAccessor.getPropertyMethodSuffixes (Ljava/lang/String;)[Ljava/lang/String;
                    LDC "get"
                    ALOAD_2     // Ljava/lang/Class; clazz
                    ILOAD_3     // Z mustBeStatic
                    ICONST_0
                    GETSTATIC org.springframework.expression.spel.support.ReflectivePropertyAccessor.ANY_TYPES Ljava/util/Set;
                    INVOKESPECIAL org.springframework.expression.spel.support.ReflectivePropertyAccessor.findMethodForProperty ([Ljava/lang/String;Ljava/lang/String;Ljava/lang/Class;ZILjava/util/Set;)Ljava/lang/reflect/Method;
                    ASTORE 4
                    ALOAD 4     // Ljava/lang/reflect/Method; method   (line 352)
                    IFNONNULL L0
                    ALOAD_0     // Lorg/springframework/expression/spel/support/ReflectivePropertyAccessor; this   (line 353)
                    ALOAD_0     // Lorg/springframework/expression/spel/support/ReflectivePropertyAccessor; this
                    ALOAD_1     // Ljava/lang/String; propertyName
                    INVOKEVIRTUAL org.springframework.expression.spel.support.ReflectivePropertyAccessor.getPropertyMethodSuffixes (Ljava/lang/String;)[Ljava/lang/String;
                    LDC "is"
                    ALOAD_2     // Ljava/lang/Class; clazz
                    ILOAD_3     // Z mustBeStatic
                    ICONST_0
                    GETSTATIC org.springframework.expression.spel.support.ReflectivePropertyAccessor.BOOLEAN_TYPES Ljava/util/Set;
                    INVOKESPECIAL org.springframework.expression.spel.support.ReflectivePropertyAccessor.findMethodForProperty ([Ljava/lang/String;Ljava/lang/String;Ljava/lang/Class;ZILjava/util/Set;)Ljava/lang/reflect/Method;
                    ASTORE 4     // Ljava/lang/reflect/Method; method
                L0: ALOAD 4     // Ljava/lang/reflect/Method; method   (line 356)
                    ARETURN
  end protected java.lang.reflect.Method findGetterForProperty(String, Class, boolean)

  protected java.lang.reflect.Method findSetterForProperty(String, Class, boolean):
                    ALOAD_0     // Lorg/springframework/expression/spel/support/ReflectivePropertyAccessor; this   (line 363)
                    ALOAD_0     // Lorg/springframework/expression/spel/support/ReflectivePropertyAccessor; this
                    ALOAD_1     // Ljava/lang/String; propertyName
                    INVOKEVIRTUAL org.springframework.expression.spel.support.ReflectivePropertyAccessor.getPropertyMethodSuffixes (Ljava/lang/String;)[Ljava/lang/String;
                    LDC "set"
                    ALOAD_2     // Ljava/lang/Class; clazz
                    ILOAD_3     // Z mustBeStatic
                    ICONST_1
                    GETSTATIC org.springframework.expression.spel.support.ReflectivePropertyAccessor.ANY_TYPES Ljava/util/Set;
                    INVOKESPECIAL org.springframework.expression.spel.support.ReflectivePropertyAccessor.findMethodForProperty ([Ljava/lang/String;Ljava/lang/String;Ljava/lang/Class;ZILjava/util/Set;)Ljava/lang/reflect/Method;
                    ARETURN
  end protected java.lang.reflect.Method findSetterForProperty(String, Class, boolean)

  private java.lang.reflect.Method findMethodForProperty(String[], String, Class, boolean, int, java.util.Set):
                    ALOAD_0     // Lorg/springframework/expression/spel/support/ReflectivePropertyAccessor; this   (line 370)
                    ALOAD_3     // Ljava/lang/Class; clazz
                    INVOKESPECIAL org.springframework.expression.spel.support.ReflectivePropertyAccessor.getSortedClassMethods (Ljava/lang/Class;)[Ljava/lang/reflect/Method;
                    ASTORE 7
                    ALOAD_1     // [Ljava/lang/String; methodSuffixes   (line 371)
                    ASTORE 8
                    ALOAD 8
                    ARRAYLENGTH
                    ISTORE 9
                    ICONST_0
                    ISTORE 10
                L0: ILOAD 10
                    ILOAD 9
                    IF_ICMPGE L6
                    ALOAD 8
                    ILOAD 10
                    AALOAD
                    ASTORE 11
                    ALOAD 7     // [Ljava/lang/reflect/Method; methods   (line 372)
                    ASTORE 12
                    ALOAD 12
                    ARRAYLENGTH
                    ISTORE 13
                    ICONST_0
                    ISTORE 14
                L1: ILOAD 14
                    ILOAD 13
                    IF_ICMPGE L5
                    ALOAD 12
                    ILOAD 14
                    AALOAD
                    ASTORE 15
                    ALOAD 15     // Ljava/lang/reflect/Method; method   (line 373)
                    INVOKEVIRTUAL java.lang.reflect.Method.getName ()Ljava/lang/String;
                    NEW java.lang.StringBuilder
                    DUP
                    INVOKESPECIAL java.lang.StringBuilder.<init> ()V
                    ALOAD_2     // Ljava/lang/String; prefix
                    INVOKEVIRTUAL java.lang.StringBuilder.append (Ljava/lang/String;)Ljava/lang/StringBuilder;
                    ALOAD 11     // Ljava/lang/String; methodSuffix
                    INVOKEVIRTUAL java.lang.StringBuilder.append (Ljava/lang/String;)Ljava/lang/StringBuilder;
                    INVOKEVIRTUAL java.lang.StringBuilder.toString ()Ljava/lang/String;
                    INVOKEVIRTUAL java.lang.String.equals (Ljava/lang/Object;)Z
                    IFEQ L4
                    ALOAD 15     // Ljava/lang/reflect/Method; method
                    INVOKEVIRTUAL java.lang.reflect.Method.getParameterTypes ()[Ljava/lang/Class;   (line 374)
                    ARRAYLENGTH
                    ILOAD 5     // I numberOfParams
                    IF_ICMPNE L4
                    ILOAD 4     // Z mustBeStatic
                    IFEQ L2
                    ALOAD 15     // Ljava/lang/reflect/Method; method
                    INVOKEVIRTUAL java.lang.reflect.Method.getModifiers ()I   (line 375)
                    INVOKESTATIC java.lang.reflect.Modifier.isStatic (I)Z
                    IFEQ L4
                L2: ALOAD 6     // Ljava/util/Set; requiredReturnTypes
                    INVOKEINTERFACE java.util.Set.isEmpty ()Z   (line 376)
                    IFNE L3
                    ALOAD 6     // Ljava/util/Set; requiredReturnTypes
                    ALOAD 15     // Ljava/lang/reflect/Method; method
                    INVOKEVIRTUAL java.lang.reflect.Method.getReturnType ()Ljava/lang/Class;
                    INVOKEINTERFACE java.util.Set.contains (Ljava/lang/Object;)Z
                    IFEQ L4
                L3: ALOAD 15     // Ljava/lang/reflect/Method; method   (line 377)
                    ARETURN
                L4: IINC 14 1   (line 372)
                    GOTO L1
                L5: IINC 10 1   (line 371)
                    GOTO L0
                L6: ACONST_NULL   (line 381)
                    ARETURN
  end private java.lang.reflect.Method findMethodForProperty(String[], String, Class, boolean, int, java.util.Set)

  private java.lang.reflect.Method[] getSortedClassMethods(Class):
                    ALOAD_1     // Ljava/lang/Class; clazz   (line 389)
                    INVOKEVIRTUAL java.lang.Class.getMethods ()[Ljava/lang/reflect/Method;
                    ASTORE_2
                    ALOAD_2     // [Ljava/lang/reflect/Method; methods   (line 390)
                    NEW org.springframework.expression.spel.support.ReflectivePropertyAccessor$1
                    DUP
                    ALOAD_0     // Lorg/springframework/expression/spel/support/ReflectivePropertyAccessor; this
                    INVOKESPECIAL org.springframework.expression.spel.support.ReflectivePropertyAccessor$1.<init> (Lorg/springframework/expression/spel/support/ReflectivePropertyAccessor;)V
                    INVOKESTATIC java.util.Arrays.sort ([Ljava/lang/Object;Ljava/util/Comparator;)V
                    ALOAD_2     // [Ljava/lang/reflect/Method; methods   (line 396)
                    ARETURN
  end private java.lang.reflect.Method[] getSortedClassMethods(Class)

  protected String[] getPropertyMethodSuffixes(String):
                    ALOAD_0     // Lorg/springframework/expression/spel/support/ReflectivePropertyAccessor; this   (line 406)
                    ALOAD_1     // Ljava/lang/String; propertyName
                    INVOKEVIRTUAL org.springframework.expression.spel.support.ReflectivePropertyAccessor.getPropertyMethodSuffix (Ljava/lang/String;)Ljava/lang/String;
                    ASTORE_2
                    ALOAD_2     // Ljava/lang/String; suffix   (line 407)
                    INVOKEVIRTUAL java.lang.String.length ()I
                    IFLE L0
                    ALOAD_2     // Ljava/lang/String; suffix
                    ICONST_0
                    INVOKEVIRTUAL java.lang.String.charAt (I)C
                    INVOKESTATIC java.lang.Character.isUpperCase (C)Z
                    IFEQ L0
                    ICONST_1   (line 408)
                    ANEWARRAY java.lang.String
                    DUP
                    ICONST_0
                    ALOAD_2     // Ljava/lang/String; suffix
                    AASTORE
                    ARETURN
                L0: ICONST_2   (line 410)
                    ANEWARRAY java.lang.String
                    DUP
                    ICONST_0
                    ALOAD_2     // Ljava/lang/String; suffix
                    AASTORE
                    DUP
                    ICONST_1
                    ALOAD_2     // Ljava/lang/String; suffix
                    INVOKESTATIC org.springframework.util.StringUtils.capitalize (Ljava/lang/String;)Ljava/lang/String;
                    AASTORE
                    ARETURN
  end protected String[] getPropertyMethodSuffixes(String)

  protected String getPropertyMethodSuffix(String):
                    ALOAD_1     // Ljava/lang/String; propertyName   (line 418)
                    INVOKEVIRTUAL java.lang.String.length ()I
                    ICONST_1
                    IF_ICMPLE L0
                    ALOAD_1     // Ljava/lang/String; propertyName
                    ICONST_1
                    INVOKEVIRTUAL java.lang.String.charAt (I)C
                    INVOKESTATIC java.lang.Character.isUpperCase (C)Z
                    IFEQ L0
                    ALOAD_1     // Ljava/lang/String; propertyName   (line 419)
                    ARETURN
                L0: ALOAD_1     // Ljava/lang/String; propertyName   (line 421)
                    INVOKESTATIC org.springframework.util.StringUtils.capitalize (Ljava/lang/String;)Ljava/lang/String;
                    ARETURN
  end protected String getPropertyMethodSuffix(String)

  protected java.lang.reflect.Field findField(String, Class, boolean):
                    ALOAD_2     // Ljava/lang/Class; clazz   (line 428)
                    INVOKEVIRTUAL java.lang.Class.getFields ()[Ljava/lang/reflect/Field;
                    ASTORE 4
                    ALOAD 4     // [Ljava/lang/reflect/Field; fields   (line 429)
                    ASTORE 5
                    ALOAD 5
                    ARRAYLENGTH
                    ISTORE 6
                    ICONST_0
                    ISTORE 7
                L0: ILOAD 7
                    ILOAD 6
                    IF_ICMPGE L3
                    ALOAD 5
                    ILOAD 7
                    AALOAD
                    ASTORE 8
                    ALOAD 8     // Ljava/lang/reflect/Field; field   (line 430)
                    INVOKEVIRTUAL java.lang.reflect.Field.getName ()Ljava/lang/String;
                    ALOAD_1     // Ljava/lang/String; name
                    INVOKEVIRTUAL java.lang.String.equals (Ljava/lang/Object;)Z
                    IFEQ L2
                    ILOAD_3     // Z mustBeStatic
                    IFEQ L1
                    ALOAD 8     // Ljava/lang/reflect/Field; field
                    INVOKEVIRTUAL java.lang.reflect.Field.getModifiers ()I
                    INVOKESTATIC java.lang.reflect.Modifier.isStatic (I)Z
                    IFEQ L2
                L1: ALOAD 8     // Ljava/lang/reflect/Field; field   (line 431)
                    ARETURN
                L2: IINC 7 1   (line 429)
                    GOTO L0
                L3: ALOAD_2     // Ljava/lang/Class; clazz   (line 436)
                    INVOKEVIRTUAL java.lang.Class.getSuperclass ()Ljava/lang/Class;
                    IFNULL L4
                    ALOAD_0     // Lorg/springframework/expression/spel/support/ReflectivePropertyAccessor; this   (line 437)
                    ALOAD_1     // Ljava/lang/String; name
                    ALOAD_2     // Ljava/lang/Class; clazz
                    INVOKEVIRTUAL java.lang.Class.getSuperclass ()Ljava/lang/Class;
                    ILOAD_3     // Z mustBeStatic
                    INVOKEVIRTUAL org.springframework.expression.spel.support.ReflectivePropertyAccessor.findField (Ljava/lang/String;Ljava/lang/Class;Z)Ljava/lang/reflect/Field;
                    ASTORE 5
                    ALOAD 5     // Ljava/lang/reflect/Field; field   (line 438)
                    IFNULL L4
                    ALOAD 5     // Ljava/lang/reflect/Field; field   (line 439)
                    ARETURN
                L4: ALOAD_2     // Ljava/lang/Class; clazz   (line 442)
                    INVOKEVIRTUAL java.lang.Class.getInterfaces ()[Ljava/lang/Class;
                    ASTORE 5
                    ALOAD 5
                    ARRAYLENGTH
                    ISTORE 6
                    ICONST_0
                    ISTORE 7
                L5: ILOAD 7
                    ILOAD 6
                    IF_ICMPGE L7
                    ALOAD 5
                    ILOAD 7
                    AALOAD
                    ASTORE 8
                    ALOAD_0     // Lorg/springframework/expression/spel/support/ReflectivePropertyAccessor; this   (line 443)
                    ALOAD_1     // Ljava/lang/String; name
                    ALOAD 8     // Ljava/lang/Class; implementedInterface
                    ILOAD_3     // Z mustBeStatic
                    INVOKEVIRTUAL org.springframework.expression.spel.support.ReflectivePropertyAccessor.findField (Ljava/lang/String;Ljava/lang/Class;Z)Ljava/lang/reflect/Field;
                    ASTORE 9
                    ALOAD 9     // Ljava/lang/reflect/Field; field   (line 444)
                    IFNULL L6
                    ALOAD 9     // Ljava/lang/reflect/Field; field   (line 445)
                    ARETURN
                L6: IINC 7 1   (line 442)
                    GOTO L5
                L7: ACONST_NULL   (line 448)
                    ARETURN
  end protected java.lang.reflect.Field findField(String, Class, boolean)

  public org.springframework.expression.PropertyAccessor createOptimalAccessor(org.springframework.expression.EvaluationContext, Object, String):
                    ALOAD_2     // Ljava/lang/Object; target   (line 460)
                    IFNONNULL L0
                    ALOAD_0     // Lorg/springframework/expression/spel/support/ReflectivePropertyAccessor; this   (line 461)
                    ARETURN
                L0: ALOAD_2     // Ljava/lang/Object; target   (line 463)
                    INSTANCEOF java.lang.Class
                    IFEQ L1
                    ALOAD_2     // Ljava/lang/Object; target
                    CHECKCAST java.lang.Class
                    GOTO L2
                L1: ALOAD_2     // Ljava/lang/Object; target
                    INVOKEVIRTUAL java.lang.Object.getClass ()Ljava/lang/Class;
                L2: ASTORE 4
                    ALOAD 4     // Ljava/lang/Class; type   (line 464)
                    INVOKEVIRTUAL java.lang.Class.isArray ()Z
                    IFEQ L3
                    ALOAD_0     // Lorg/springframework/expression/spel/support/ReflectivePropertyAccessor; this   (line 465)
                    ARETURN
                L3: NEW org.springframework.expression.spel.support.ReflectivePropertyAccessor$CacheKey   (line 468)
                    DUP
                    ALOAD 4     // Ljava/lang/Class; type
                    ALOAD_3     // Ljava/lang/String; name
                    ALOAD_2     // Ljava/lang/Object; target
                    INSTANCEOF java.lang.Class
                    INVOKESPECIAL org.springframework.expression.spel.support.ReflectivePropertyAccessor$CacheKey.<init> (Ljava/lang/Class;Ljava/lang/String;Z)V
                    ASTORE 5
                    ALOAD_0     // Lorg/springframework/expression/spel/support/ReflectivePropertyAccessor; this   (line 469)
                    GETFIELD org.springframework.expression.spel.support.ReflectivePropertyAccessor.readerCache Ljava/util/Map;
                    ALOAD 5     // Lorg/springframework/expression/spel/support/ReflectivePropertyAccessor$CacheKey; cacheKey
                    INVOKEINTERFACE java.util.Map.get (Ljava/lang/Object;)Ljava/lang/Object;
                    CHECKCAST org.springframework.expression.spel.support.ReflectivePropertyAccessor$InvokerPair
                    ASTORE 6
                    ALOAD 6     // Lorg/springframework/expression/spel/support/ReflectivePropertyAccessor$InvokerPair; invocationTarget   (line 471)
                    IFNULL L4
                    ALOAD 6     // Lorg/springframework/expression/spel/support/ReflectivePropertyAccessor$InvokerPair; invocationTarget
                    GETFIELD org.springframework.expression.spel.support.ReflectivePropertyAccessor$InvokerPair.member Ljava/lang/reflect/Member;
                    INSTANCEOF java.lang.reflect.Method
                    IFEQ L8
                L4: ALOAD 6     // Lorg/springframework/expression/spel/support/ReflectivePropertyAccessor$InvokerPair; invocationTarget   (line 472)
                    IFNONNULL L5
                    ACONST_NULL
                    GOTO L6
                L5: ALOAD 6     // Lorg/springframework/expression/spel/support/ReflectivePropertyAccessor$InvokerPair; invocationTarget
                    GETFIELD org.springframework.expression.spel.support.ReflectivePropertyAccessor$InvokerPair.member Ljava/lang/reflect/Member;
                L6: CHECKCAST java.lang.reflect.Method
                    CHECKCAST java.lang.reflect.Method
                    ASTORE 7
                    ALOAD 7     // Ljava/lang/reflect/Method; method   (line 473)
                    IFNONNULL L7
                    ALOAD_0     // Lorg/springframework/expression/spel/support/ReflectivePropertyAccessor; this   (line 474)
                    ALOAD_3     // Ljava/lang/String; name
                    ALOAD 4     // Ljava/lang/Class; type
                    ALOAD_2     // Ljava/lang/Object; target
                    INVOKESPECIAL org.springframework.expression.spel.support.ReflectivePropertyAccessor.findGetterForProperty (Ljava/lang/String;Ljava/lang/Class;Ljava/lang/Object;)Ljava/lang/reflect/Method;
                    ASTORE 7     // Ljava/lang/reflect/Method; method
                    ALOAD 7     // Ljava/lang/reflect/Method; method   (line 475)
                    IFNULL L7
                    NEW org.springframework.expression.spel.support.ReflectivePropertyAccessor$InvokerPair   (line 476)
                    DUP
                    ALOAD 7     // Ljava/lang/reflect/Method; method
                    NEW org.springframework.core.convert.TypeDescriptor
                    DUP
                    NEW org.springframework.core.MethodParameter
                    DUP
                    ALOAD 7     // Ljava/lang/reflect/Method; method
                    ICONST_M1
                    INVOKESPECIAL org.springframework.core.MethodParameter.<init> (Ljava/lang/reflect/Method;I)V
                    INVOKESPECIAL org.springframework.core.convert.TypeDescriptor.<init> (Lorg/springframework/core/MethodParameter;)V
                    INVOKESPECIAL org.springframework.expression.spel.support.ReflectivePropertyAccessor$InvokerPair.<init> (Ljava/lang/reflect/Member;Lorg/springframework/core/convert/TypeDescriptor;)V
                    ASTORE 6     // Lorg/springframework/expression/spel/support/ReflectivePropertyAccessor$InvokerPair; invocationTarget
                    ALOAD 7     // Ljava/lang/reflect/Method; method   (line 477)
                    INVOKESTATIC org.springframework.util.ReflectionUtils.makeAccessible (Ljava/lang/reflect/Method;)V
                    ALOAD_0     // Lorg/springframework/expression/spel/support/ReflectivePropertyAccessor; this   (line 478)
                    GETFIELD org.springframework.expression.spel.support.ReflectivePropertyAccessor.readerCache Ljava/util/Map;
                    ALOAD 5     // Lorg/springframework/expression/spel/support/ReflectivePropertyAccessor$CacheKey; cacheKey
                    ALOAD 6     // Lorg/springframework/expression/spel/support/ReflectivePropertyAccessor$InvokerPair; invocationTarget
                    INVOKEINTERFACE java.util.Map.put (Ljava/lang/Object;Ljava/lang/Object;)Ljava/lang/Object;
                    POP
                L7: ALOAD 7     // Ljava/lang/reflect/Method; method   (line 481)
                    IFNULL L8
                    NEW org.springframework.expression.spel.support.ReflectivePropertyAccessor$OptimalPropertyAccessor   (line 482)
                    DUP
                    ALOAD 6     // Lorg/springframework/expression/spel/support/ReflectivePropertyAccessor$InvokerPair; invocationTarget
                    INVOKESPECIAL org.springframework.expression.spel.support.ReflectivePropertyAccessor$OptimalPropertyAccessor.<init> (Lorg/springframework/expression/spel/support/ReflectivePropertyAccessor$InvokerPair;)V
                    ARETURN
                L8: ALOAD 6     // Lorg/springframework/expression/spel/support/ReflectivePropertyAccessor$InvokerPair; invocationTarget   (line 486)
                    IFNULL L9
                    ALOAD 6     // Lorg/springframework/expression/spel/support/ReflectivePropertyAccessor$InvokerPair; invocationTarget
                    GETFIELD org.springframework.expression.spel.support.ReflectivePropertyAccessor$InvokerPair.member Ljava/lang/reflect/Member;
                    INSTANCEOF java.lang.reflect.Field
                    IFEQ L13
                L9: ALOAD 6     // Lorg/springframework/expression/spel/support/ReflectivePropertyAccessor$InvokerPair; invocationTarget   (line 487)
                    IFNULL L10
                    ALOAD 6     // Lorg/springframework/expression/spel/support/ReflectivePropertyAccessor$InvokerPair; invocationTarget
                    GETFIELD org.springframework.expression.spel.support.ReflectivePropertyAccessor$InvokerPair.member Ljava/lang/reflect/Member;
                    CHECKCAST java.lang.reflect.Field
                    GOTO L11
               L10: ACONST_NULL
               L11: ASTORE 7
                    ALOAD 7     // Ljava/lang/reflect/Field; field   (line 488)
                    IFNONNULL L12
                    ALOAD_0     // Lorg/springframework/expression/spel/support/ReflectivePropertyAccessor; this   (line 489)
                    ALOAD_3     // Ljava/lang/String; name
                    ALOAD 4     // Ljava/lang/Class; type
                    ALOAD_2     // Ljava/lang/Object; target
                    INSTANCEOF java.lang.Class
                    INVOKEVIRTUAL org.springframework.expression.spel.support.ReflectivePropertyAccessor.findField (Ljava/lang/String;Ljava/lang/Class;Z)Ljava/lang/reflect/Field;
                    ASTORE 7     // Ljava/lang/reflect/Field; field
                    ALOAD 7     // Ljava/lang/reflect/Field; field   (line 490)
                    IFNULL L12
                    NEW org.springframework.expression.spel.support.ReflectivePropertyAccessor$InvokerPair   (line 491)
                    DUP
                    ALOAD 7     // Ljava/lang/reflect/Field; field
                    NEW org.springframework.core.convert.TypeDescriptor
                    DUP
                    ALOAD 7     // Ljava/lang/reflect/Field; field
                    INVOKESPECIAL org.springframework.core.convert.TypeDescriptor.<init> (Ljava/lang/reflect/Field;)V
                    INVOKESPECIAL org.springframework.expression.spel.support.ReflectivePropertyAccessor$InvokerPair.<init> (Ljava/lang/reflect/Member;Lorg/springframework/core/convert/TypeDescriptor;)V
                    ASTORE 6     // Lorg/springframework/expression/spel/support/ReflectivePropertyAccessor$InvokerPair; invocationTarget
                    ALOAD 7     // Ljava/lang/reflect/Field; field   (line 492)
                    INVOKESTATIC org.springframework.util.ReflectionUtils.makeAccessible (Ljava/lang/reflect/Field;)V
                    ALOAD_0     // Lorg/springframework/expression/spel/support/ReflectivePropertyAccessor; this   (line 493)
                    GETFIELD org.springframework.expression.spel.support.ReflectivePropertyAccessor.readerCache Ljava/util/Map;
                    ALOAD 5     // Lorg/springframework/expression/spel/support/ReflectivePropertyAccessor$CacheKey; cacheKey
                    ALOAD 6     // Lorg/springframework/expression/spel/support/ReflectivePropertyAccessor$InvokerPair; invocationTarget
                    INVOKEINTERFACE java.util.Map.put (Ljava/lang/Object;Ljava/lang/Object;)Ljava/lang/Object;
                    POP
               L12: ALOAD 7     // Ljava/lang/reflect/Field; field   (line 496)
                    IFNULL L13
                    NEW org.springframework.expression.spel.support.ReflectivePropertyAccessor$OptimalPropertyAccessor   (line 497)
                    DUP
                    ALOAD 6     // Lorg/springframework/expression/spel/support/ReflectivePropertyAccessor$InvokerPair; invocationTarget
                    INVOKESPECIAL org.springframework.expression.spel.support.ReflectivePropertyAccessor$OptimalPropertyAccessor.<init> (Lorg/springframework/expression/spel/support/ReflectivePropertyAccessor$InvokerPair;)V
                    ARETURN
               L13: ALOAD_0     // Lorg/springframework/expression/spel/support/ReflectivePropertyAccessor; this   (line 500)
                    ARETURN
  end public org.springframework.expression.PropertyAccessor createOptimalAccessor(org.springframework.expression.EvaluationContext, Object, String)

  static void <clinit>():
                    NEW java.util.HashSet   (line 63)
                    DUP
                    INVOKESPECIAL java.util.HashSet.<init> ()V
                    ASTORE_0
                    ALOAD_0     // Ljava/util/Set; booleanTypes   (line 64)
                    LDC java.lang.Boolean
                    INVOKEINTERFACE java.util.Set.add (Ljava/lang/Object;)Z
                    POP
                    ALOAD_0     // Ljava/util/Set; booleanTypes   (line 65)
                    GETSTATIC java.lang.Boolean.TYPE Ljava/lang/Class;
                    INVOKEINTERFACE java.util.Set.add (Ljava/lang/Object;)Z
                    POP
                    ALOAD_0     // Ljava/util/Set; booleanTypes   (line 66)
                    INVOKESTATIC java.util.Collections.unmodifiableSet (Ljava/util/Set;)Ljava/util/Set;
                    PUTSTATIC org.springframework.expression.spel.support.ReflectivePropertyAccessor.BOOLEAN_TYPES Ljava/util/Set;
                    INVOKESTATIC java.util.Collections.emptySet ()Ljava/util/Set;   (line 69)
                    PUTSTATIC org.springframework.expression.spel.support.ReflectivePropertyAccessor.ANY_TYPES Ljava/util/Set;
                    RETURN
  end static void <clinit>()
end public class org.springframework.expression.spel.support.ReflectivePropertyAccessor
 -- (ClassFormatException) File: 'java.lang.reflect.AnnotatedElement': Invalid byte tag in constant pool: 15
File: 'java.lang.reflect.AnnotatedElement': Invalid byte tag in constant pool: 15
org.aspectj.apache.bcel.classfile.ClassFormatException: File: 'java.lang.reflect.AnnotatedElement': Invalid byte tag in constant pool: 15
	at org.aspectj.apache.bcel.classfile.ClassParser.readConstantPool(ClassParser.java:192)
	at org.aspectj.apache.bcel.classfile.ClassParser.parse(ClassParser.java:131)
	at org.aspectj.apache.bcel.util.ClassLoaderRepository.loadClass(ClassLoaderRepository.java:323)
	at org.aspectj.weaver.bcel.BcelWorld.lookupJavaClass(BcelWorld.java:402)
	at org.aspectj.weaver.bcel.BcelWorld.resolveDelegate(BcelWorld.java:376)
	at org.aspectj.weaver.ltw.LTWWorld.resolveDelegate(LTWWorld.java:107)
	at org.aspectj.weaver.World.resolveToReferenceType(World.java:485)
	at org.aspectj.weaver.World.resolve(World.java:326)
	at org.aspectj.weaver.World.resolve(World.java:236)
	at org.aspectj.weaver.bcel.BcelObjectType.getDeclaredInterfaces(BcelObjectType.java:268)
	at org.aspectj.weaver.ReferenceType.getDeclaredInterfaces(ReferenceType.java:626)
	at org.aspectj.weaver.ResolvedType.getDirectSupertypes(ResolvedType.java:82)
	at org.aspectj.weaver.patterns.TypePattern.matchesSubtypes(TypePattern.java:201)
	at org.aspectj.weaver.patterns.TypePattern.matchesSubtypes(TypePattern.java:203)
	at org.aspectj.weaver.patterns.TypePattern.matchesSubtypes(TypePattern.java:183)
	at org.aspectj.weaver.patterns.ExactTypePattern.matchesSubtypes(ExactTypePattern.java:74)
	at org.aspectj.weaver.patterns.TypePattern.matchesStatically(TypePattern.java:130)
	at org.aspectj.weaver.patterns.OrTypePattern.matchesStatically(OrTypePattern.java:76)
	at org.aspectj.weaver.patterns.SignaturePattern.matchesExactlyMethod(SignaturePattern.java:505)
	at org.aspectj.weaver.patterns.SignaturePattern.matchesExactly(SignaturePattern.java:360)
	at org.aspectj.weaver.patterns.SignaturePattern.matches(SignaturePattern.java:320)
	at org.aspectj.weaver.patterns.KindedPointcut.matchInternal(KindedPointcut.java:202)
	at org.aspectj.weaver.patterns.Pointcut.match(Pointcut.java:137)
	at org.aspectj.weaver.patterns.AndPointcut.matchInternal(AndPointcut.java:51)
	at org.aspectj.weaver.patterns.Pointcut.match(Pointcut.java:137)
	at org.aspectj.weaver.patterns.OrPointcut.matchInternal(OrPointcut.java:54)
	at org.aspectj.weaver.patterns.Pointcut.match(Pointcut.java:137)
	at org.aspectj.weaver.ShadowMunger.match(ShadowMunger.java:113)
	at org.aspectj.weaver.Advice.match(Advice.java:109)
	at org.aspectj.weaver.bcel.BcelAdvice.match(BcelAdvice.java:149)
	at org.aspectj.weaver.bcel.BcelClassWeaver.match(BcelClassWeaver.java:3173)
	at org.aspectj.weaver.bcel.BcelClassWeaver.match(BcelClassWeaver.java:2565)
	at org.aspectj.weaver.bcel.BcelClassWeaver.weave(BcelClassWeaver.java:480)
	at org.aspectj.weaver.bcel.BcelClassWeaver.weave(BcelClassWeaver.java:99)
	at org.aspectj.weaver.bcel.BcelWeaver.weave(BcelWeaver.java:1694)
	at org.aspectj.weaver.bcel.BcelWeaver.weaveWithoutDump(BcelWeaver.java:1638)
	at org.aspectj.weaver.bcel.BcelWeaver.weaveAndNotify(BcelWeaver.java:1401)
	at org.aspectj.weaver.bcel.BcelWeaver.weave(BcelWeaver.java:1187)
	at org.aspectj.weaver.tools.WeavingAdaptor.getWovenBytes(WeavingAdaptor.java:472)
	at org.aspectj.weaver.tools.WeavingAdaptor.weaveClass(WeavingAdaptor.java:323)
	at org.aspectj.weaver.loadtime.Aj.preProcess(Aj.java:99)
	at org.aspectj.weaver.loadtime.ClassPreProcessorAgentAdapter.transform(ClassPreProcessorAgentAdapter.java:54)
	at org.springframework.context.weaving.AspectJWeavingEnabler$AspectJClassBypassingClassFileTransformer.transform(AspectJWeavingEnabler.java:108)
	at org.springframework.instrument.classloading.InstrumentationLoadTimeWeaver$FilteringClassFileTransformer.transform(InstrumentationLoadTimeWeaver.java:184)
	at sun.instrument.TransformerManager.transform(Unknown Source)
	at sun.instrument.InstrumentationImpl.transform(Unknown Source)
	at java.lang.ClassLoader.defineClass1(Native Method)
	at java.lang.ClassLoader.defineClass(Unknown Source)
	at java.security.SecureClassLoader.defineClass(Unknown Source)
	at java.net.URLClassLoader.defineClass(Unknown Source)
	at java.net.URLClassLoader.access$100(Unknown Source)
	at java.net.URLClassLoader$1.run(Unknown Source)
	at java.net.URLClassLoader$1.run(Unknown Source)
	at java.security.AccessController.doPrivileged(Native Method)
	at java.net.URLClassLoader.findClass(Unknown Source)
	at java.lang.ClassLoader.loadClass(Unknown Source)
	at sun.misc.Launcher$AppClassLoader.loadClass(Unknown Source)
	at java.lang.ClassLoader.loadClass(Unknown Source)
	at org.springframework.expression.spel.support.StandardEvaluationContext.initializePropertyAccessors(StandardEvaluationContext.java:256)
	at org.springframework.expression.spel.support.StandardEvaluationContext.ensurePropertyAccessorsInitialized(StandardEvaluationContext.java:249)
	at org.springframework.expression.spel.support.StandardEvaluationContext.addPropertyAccessor(StandardEvaluationContext.java:146)
	at org.springframework.context.expression.StandardBeanExpressionResolver.evaluate(StandardBeanExpressionResolver.java:148)
	at org.springframework.beans.factory.support.AbstractBeanFactory.evaluateBeanDefinitionString(AbstractBeanFactory.java:1365)
	at org.springframework.beans.factory.support.BeanDefinitionValueResolver.doEvaluate(BeanDefinitionValueResolver.java:255)
	at org.springframework.beans.factory.support.BeanDefinitionValueResolver.resolveReference(BeanDefinitionValueResolver.java:340)
	at org.springframework.beans.factory.support.BeanDefinitionValueResolver.resolveValueIfNecessary(BeanDefinitionValueResolver.java:108)
	at org.springframework.beans.factory.support.AbstractAutowireCapableBeanFactory.applyPropertyValues(AbstractAutowireCapableBeanFactory.java:1477)
	at org.springframework.beans.factory.support.AbstractAutowireCapableBeanFactory.populateBean(AbstractAutowireCapableBeanFactory.java:1222)
	at org.springframework.beans.factory.support.AbstractAutowireCapableBeanFactory.doCreateBean(AbstractAutowireCapableBeanFactory.java:537)
	at org.springframework.beans.factory.support.AbstractAutowireCapableBeanFactory.createBean(AbstractAutowireCapableBeanFactory.java:476)
	at org.springframework.beans.factory.support.AbstractBeanFactory$1.getObject(AbstractBeanFactory.java:303)
	at org.springframework.beans.factory.support.DefaultSingletonBeanRegistry.getSingleton(DefaultSingletonBeanRegistry.java:230)
	at org.springframework.beans.factory.support.AbstractBeanFactory.doGetBean(AbstractBeanFactory.java:299)
	at org.springframework.beans.factory.support.AbstractBeanFactory.getBean(AbstractBeanFactory.java:194)
	at org.springframework.beans.factory.support.DefaultListableBeanFactory.findAutowireCandidates(DefaultListableBeanFactory.java:1120)
	at org.springframework.beans.factory.support.DefaultListableBeanFactory.doResolveDependency(DefaultListableBeanFactory.java:996)
	at org.springframework.beans.factory.support.DefaultListableBeanFactory.resolveDependency(DefaultListableBeanFactory.java:942)
	at org.springframework.beans.factory.annotation.AutowiredAnnotationBeanPostProcessor$AutowiredFieldElement.inject(AutowiredAnnotationBeanPostProcessor.java:533)
	at org.springframework.beans.factory.annotation.InjectionMetadata.inject(InjectionMetadata.java:88)
	at org.springframework.beans.factory.annotation.AutowiredAnnotationBeanPostProcessor.postProcessPropertyValues(AutowiredAnnotationBeanPostProcessor.java:331)
	at org.springframework.beans.factory.support.AbstractAutowireCapableBeanFactory.populateBean(AbstractAutowireCapableBeanFactory.java:1210)
	at org.springframework.beans.factory.support.AbstractAutowireCapableBeanFactory.doCreateBean(AbstractAutowireCapableBeanFactory.java:537)
	at org.springframework.beans.factory.support.AbstractAutowireCapableBeanFactory.createBean(AbstractAutowireCapableBeanFactory.java:476)
	at org.springframework.beans.factory.support.AbstractBeanFactory$1.getObject(AbstractBeanFactory.java:303)
	at org.springframework.beans.factory.support.DefaultSingletonBeanRegistry.getSingleton(DefaultSingletonBeanRegistry.java:230)
	at org.springframework.beans.factory.support.AbstractBeanFactory.doGetBean(AbstractBeanFactory.java:299)
	at org.springframework.beans.factory.support.AbstractBeanFactory.getBean(AbstractBeanFactory.java:194)
	at org.springframework.beans.factory.support.DefaultListableBeanFactory.preInstantiateSingletons(DefaultListableBeanFactory.java:755)
	at org.springframework.context.support.AbstractApplicationContext.finishBeanFactoryInitialization(AbstractApplicationContext.java:757)
	at org.springframework.context.support.AbstractApplicationContext.refresh(AbstractApplicationContext.java:480)
	at org.springframework.context.support.ClassPathXmlApplicationContext.<init>(ClassPathXmlApplicationContext.java:139)
	at org.springframework.context.support.ClassPathXmlApplicationContext.<init>(ClassPathXmlApplicationContext.java:93)
	at com.springExemple.presentation.Presentation2.main(Presentation2.java:13)

org.aspectj.bridge.AbortException: trouble in: 
public class org.springframework.expression.spel.support.ReflectivePropertyAccessor extends java.lang.Object implements org.springframework.expression.PropertyAccessor:
  private static final java.util.Set BOOLEAN_TYPES [Signature(Ljava/util/Set<Ljava/lang/Class<*>;>;)]
  private static final java.util.Set ANY_TYPES [Signature(Ljava/util/Set<Ljava/lang/Class<*>;>;)]
  private final java.util.Map readerCache [Signature(Ljava/util/Map<Lorg/springframework/expression/spel/support/ReflectivePropertyAccessor$CacheKey;Lorg/springframework/expression/spel/support/ReflectivePropertyAccessor$InvokerPair;>;)]
  private final java.util.Map writerCache [Signature(Ljava/util/Map<Lorg/springframework/expression/spel/support/ReflectivePropertyAccessor$CacheKey;Ljava/lang/reflect/Member;>;)]
  private final java.util.Map typeDescriptorCache [Signature(Ljava/util/Map<Lorg/springframework/expression/spel/support/ReflectivePropertyAccessor$CacheKey;Lorg/springframework/core/convert/TypeDescriptor;>;)]
  private org.springframework.expression.spel.support.ReflectivePropertyAccessor$InvokerPair lastReadInvokerPair
  public void <init>():
                    ALOAD_0     // Lorg/springframework/expression/spel/support/ReflectivePropertyAccessor; this   (line 59)
                    INVOKESPECIAL java.lang.Object.<init> ()V
    constructor-execution(void org.springframework.expression.spel.support.ReflectivePropertyAccessor.<init>())
    |               ALOAD_0     // Lorg/springframework/expression/spel/support/ReflectivePropertyAccessor; this   (line 72)
    |               NEW java.util.concurrent.ConcurrentHashMap
    |               DUP
    |               BIPUSH 64
    |               INVOKESPECIAL java.util.concurrent.ConcurrentHashMap.<init> (I)V
    |               PUTFIELD org.springframework.expression.spel.support.ReflectivePropertyAccessor.readerCache Ljava/util/Map;
    |               ALOAD_0     // Lorg/springframework/expression/spel/support/ReflectivePropertyAccessor; this   (line 74)
    |               NEW java.util.concurrent.ConcurrentHashMap
    |               DUP
    |               BIPUSH 64
    |               INVOKESPECIAL java.util.concurrent.ConcurrentHashMap.<init> (I)V
    |               PUTFIELD org.springframework.expression.spel.support.ReflectivePropertyAccessor.writerCache Ljava/util/Map;
    |               ALOAD_0     // Lorg/springframework/expression/spel/support/ReflectivePropertyAccessor; this   (line 76)
    |               NEW java.util.concurrent.ConcurrentHashMap
    |               DUP
    |               BIPUSH 64
    |               INVOKESPECIAL java.util.concurrent.ConcurrentHashMap.<init> (I)V
    |               PUTFIELD org.springframework.expression.spel.support.ReflectivePropertyAccessor.typeDescriptorCache Ljava/util/Map;
    |               RETURN   (line 569)
    constructor-execution(void org.springframework.expression.spel.support.ReflectivePropertyAccessor.<init>())
  end public void <init>()

  public Class[] getSpecificTargetClasses():
                    ACONST_NULL   (line 86)
                    ARETURN
  end public Class[] getSpecificTargetClasses()

  public boolean canRead(org.springframework.expression.EvaluationContext, Object, String) throws org.springframework.expression.AccessException:
                    ALOAD_2     // Ljava/lang/Object; target   (line 91)
                    IFNONNULL L0
                    ICONST_0   (line 92)
                    IRETURN
                L0: ALOAD_2     // Ljava/lang/Object; target   (line 94)
                    INSTANCEOF java.lang.Class
                    IFEQ L1
                    ALOAD_2     // Ljava/lang/Object; target
                    CHECKCAST java.lang.Class
                    GOTO L2
                L1: ALOAD_2     // Ljava/lang/Object; target
                    INVOKEVIRTUAL java.lang.Object.getClass ()Ljava/lang/Class;
                L2: ASTORE 4
                    ALOAD 4     // Ljava/lang/Class; type   (line 95)
                    INVOKEVIRTUAL java.lang.Class.isArray ()Z
                    IFEQ L3
                    ALOAD_3     // Ljava/lang/String; name
                    LDC "length"
                    INVOKEVIRTUAL java.lang.String.equals (Ljava/lang/Object;)Z
                    IFEQ L3
                    ICONST_1   (line 96)
                    IRETURN
                L3: NEW org.springframework.expression.spel.support.ReflectivePropertyAccessor$CacheKey   (line 98)
                    DUP
                    ALOAD 4     // Ljava/lang/Class; type
                    ALOAD_3     // Ljava/lang/String; name
                    ALOAD_2     // Ljava/lang/Object; target
                    INSTANCEOF java.lang.Class
                    INVOKESPECIAL org.springframework.expression.spel.support.ReflectivePropertyAccessor$CacheKey.<init> (Ljava/lang/Class;Ljava/lang/String;Z)V
                    ASTORE 5
                    ALOAD_0     // Lorg/springframework/expression/spel/support/ReflectivePropertyAccessor; this   (line 99)
                    GETFIELD org.springframework.expression.spel.support.ReflectivePropertyAccessor.readerCache Ljava/util/Map;
                    ALOAD 5     // Lorg/springframework/expression/spel/support/ReflectivePropertyAccessor$CacheKey; cacheKey
                    INVOKEINTERFACE java.util.Map.containsKey (Ljava/lang/Object;)Z
                    IFEQ L4
                    ICONST_1   (line 100)
                    IRETURN
                L4: ALOAD_0     // Lorg/springframework/expression/spel/support/ReflectivePropertyAccessor; this   (line 102)
                    ALOAD_3     // Ljava/lang/String; name
                    ALOAD 4     // Ljava/lang/Class; type
                    ALOAD_2     // Ljava/lang/Object; target
                    INVOKESPECIAL org.springframework.expression.spel.support.ReflectivePropertyAccessor.findGetterForProperty (Ljava/lang/String;Ljava/lang/Class;Ljava/lang/Object;)Ljava/lang/reflect/Method;
                    ASTORE 6
                    ALOAD 6     // Ljava/lang/reflect/Method; method   (line 103)
                    IFNULL L5
                    NEW org.springframework.core.convert.Property   (line 106)
                    DUP
                    ALOAD 4     // Ljava/lang/Class; type
                    ALOAD 6     // Ljava/lang/reflect/Method; method
                    ACONST_NULL
                    INVOKESPECIAL org.springframework.core.convert.Property.<init> (Ljava/lang/Class;Ljava/lang/reflect/Method;Ljava/lang/reflect/Method;)V
                    ASTORE 7
                    NEW org.springframework.core.convert.TypeDescriptor   (line 107)
                    DUP
                    ALOAD 7     // Lorg/springframework/core/convert/Property; property
                    INVOKESPECIAL org.springframework.core.convert.TypeDescriptor.<init> (Lorg/springframework/core/convert/Property;)V
                    ASTORE 8
                    ALOAD_0     // Lorg/springframework/expression/spel/support/ReflectivePropertyAccessor; this   (line 108)
                    GETFIELD org.springframework.expression.spel.support.ReflectivePropertyAccessor.readerCache Ljava/util/Map;
                    ALOAD 5     // Lorg/springframework/expression/spel/support/ReflectivePropertyAccessor$CacheKey; cacheKey
                    NEW org.springframework.expression.spel.support.ReflectivePropertyAccessor$InvokerPair
                    DUP
                    ALOAD 6     // Ljava/lang/reflect/Method; method
                    ALOAD 8     // Lorg/springframework/core/convert/TypeDescriptor; typeDescriptor
                    INVOKESPECIAL org.springframework.expression.spel.support.ReflectivePropertyAccessor$InvokerPair.<init> (Ljava/lang/reflect/Member;Lorg/springframework/core/convert/TypeDescriptor;)V
                    INVOKEINTERFACE java.util.Map.put (Ljava/lang/Object;Ljava/lang/Object;)Ljava/lang/Object;
                    POP
                    ALOAD_0     // Lorg/springframework/expression/spel/support/ReflectivePropertyAccessor; this   (line 109)
                    GETFIELD org.springframework.expression.spel.support.ReflectivePropertyAccessor.typeDescriptorCache Ljava/util/Map;
                    ALOAD 5     // Lorg/springframework/expression/spel/support/ReflectivePropertyAccessor$CacheKey; cacheKey
                    ALOAD 8     // Lorg/springframework/core/convert/TypeDescriptor; typeDescriptor
                    INVOKEINTERFACE java.util.Map.put (Ljava/lang/Object;Ljava/lang/Object;)Ljava/lang/Object;
                    POP
                    ICONST_1   (line 110)
                    IRETURN
                L5: ALOAD_0     // Lorg/springframework/expression/spel/support/ReflectivePropertyAccessor; this   (line 113)
                    ALOAD_3     // Ljava/lang/String; name
                    ALOAD 4     // Ljava/lang/Class; type
                    ALOAD_2     // Ljava/lang/Object; target
                    INVOKESPECIAL org.springframework.expression.spel.support.ReflectivePropertyAccessor.findField (Ljava/lang/String;Ljava/lang/Class;Ljava/lang/Object;)Ljava/lang/reflect/Field;
                    ASTORE 7
                    ALOAD 7     // Ljava/lang/reflect/Field; field   (line 114)
                    IFNULL L6
                    NEW org.springframework.core.convert.TypeDescriptor   (line 115)
                    DUP
                    ALOAD 7     // Ljava/lang/reflect/Field; field
                    INVOKESPECIAL org.springframework.core.convert.TypeDescriptor.<init> (Ljava/lang/reflect/Field;)V
                    ASTORE 8
                    ALOAD_0     // Lorg/springframework/expression/spel/support/ReflectivePropertyAccessor; this   (line 116)
                    GETFIELD org.springframework.expression.spel.support.ReflectivePropertyAccessor.readerCache Ljava/util/Map;
                    ALOAD 5     // Lorg/springframework/expression/spel/support/ReflectivePropertyAccessor$CacheKey; cacheKey
                    NEW org.springframework.expression.spel.support.ReflectivePropertyAccessor$InvokerPair
                    DUP
                    ALOAD 7     // Ljava/lang/reflect/Field; field
                    ALOAD 8     // Lorg/springframework/core/convert/TypeDescriptor; typeDescriptor
                    INVOKESPECIAL org.springframework.expression.spel.support.ReflectivePropertyAccessor$InvokerPair.<init> (Ljava/lang/reflect/Member;Lorg/springframework/core/convert/TypeDescriptor;)V
                    INVOKEINTERFACE java.util.Map.put (Ljava/lang/Object;Ljava/lang/Object;)Ljava/lang/Object;
                    POP
                    ALOAD_0     // Lorg/springframework/expression/spel/support/ReflectivePropertyAccessor; this   (line 117)
                    GETFIELD org.springframework.expression.spel.support.ReflectivePropertyAccessor.typeDescriptorCache Ljava/util/Map;
                    ALOAD 5     // Lorg/springframework/expression/spel/support/ReflectivePropertyAccessor$CacheKey; cacheKey
                    ALOAD 8     // Lorg/springframework/core/convert/TypeDescriptor; typeDescriptor
                    INVOKEINTERFACE java.util.Map.put (Ljava/lang/Object;Ljava/lang/Object;)Ljava/lang/Object;
                    POP
                    ICONST_1   (line 118)
                    IRETURN
                L6: ICONST_0   (line 121)
                    IRETURN
  end public boolean canRead(org.springframework.expression.EvaluationContext, Object, String) throws org.springframework.expression.AccessException

  public java.lang.reflect.Member getLastReadInvokerPair():
                    ALOAD_0     // Lorg/springframework/expression/spel/support/ReflectivePropertyAccessor; this   (line 125)
                    GETFIELD org.springframework.expression.spel.support.ReflectivePropertyAccessor.lastReadInvokerPair Lorg/springframework/expression/spel/support/ReflectivePropertyAccessor$InvokerPair;
                    GETFIELD org.springframework.expression.spel.support.ReflectivePropertyAccessor$InvokerPair.member Ljava/lang/reflect/Member;
                    ARETURN
  end public java.lang.reflect.Member getLastReadInvokerPair()

  public org.springframework.expression.TypedValue read(org.springframework.expression.EvaluationContext, Object, String) throws org.springframework.expression.AccessException:
                    ALOAD_2     // Ljava/lang/Object; target   (line 130)
                    IFNONNULL L0
                    NEW org.springframework.expression.AccessException   (line 131)
                    DUP
                    LDC "Cannot read property of null target"
                    INVOKESPECIAL org.springframework.expression.AccessException.<init> (Ljava/lang/String;)V
                    ATHROW
                L0: ALOAD_2     // Ljava/lang/Object; target   (line 133)
                    INSTANCEOF java.lang.Class
                    IFEQ L1
                    ALOAD_2     // Ljava/lang/Object; target
                    CHECKCAST java.lang.Class
                    GOTO L2
                L1: ALOAD_2     // Ljava/lang/Object; target
                    INVOKEVIRTUAL java.lang.Object.getClass ()Ljava/lang/Class;
                L2: ASTORE 4
                    ALOAD 4     // Ljava/lang/Class; type   (line 135)
                    INVOKEVIRTUAL java.lang.Class.isArray ()Z
                    IFEQ L4
                    ALOAD_3     // Ljava/lang/String; name
                    LDC "length"
                    INVOKEVIRTUAL java.lang.String.equals (Ljava/lang/Object;)Z
                    IFEQ L4
                    ALOAD_2     // Ljava/lang/Object; target   (line 136)
                    INSTANCEOF java.lang.Class
                    IFEQ L3
                    NEW org.springframework.expression.AccessException   (line 137)
                    DUP
                    LDC "Cannot access length on array class itself"
                    INVOKESPECIAL org.springframework.expression.AccessException.<init> (Ljava/lang/String;)V
                    ATHROW
                L3: NEW org.springframework.expression.TypedValue   (line 139)
                    DUP
                    ALOAD_2     // Ljava/lang/Object; target
                    INVOKESTATIC java.lang.reflect.Array.getLength (Ljava/lang/Object;)I
                    INVOKESTATIC java.lang.Integer.valueOf (I)Ljava/lang/Integer;
                    INVOKESPECIAL org.springframework.expression.TypedValue.<init> (Ljava/lang/Object;)V
                    ARETURN
                L4: NEW org.springframework.expression.spel.support.ReflectivePropertyAccessor$CacheKey   (line 142)
                    DUP
                    ALOAD 4     // Ljava/lang/Class; type
                    ALOAD_3     // Ljava/lang/String; name
                    ALOAD_2     // Ljava/lang/Object; target
                    INSTANCEOF java.lang.Class
                    INVOKESPECIAL org.springframework.expression.spel.support.ReflectivePropertyAccessor$CacheKey.<init> (Ljava/lang/Class;Ljava/lang/String;Z)V
                    ASTORE 5
                    ALOAD_0     // Lorg/springframework/expression/spel/support/ReflectivePropertyAccessor; this   (line 143)
                    GETFIELD org.springframework.expression.spel.support.ReflectivePropertyAccessor.readerCache Ljava/util/Map;
                    ALOAD 5     // Lorg/springframework/expression/spel/support/ReflectivePropertyAccessor$CacheKey; cacheKey
                    INVOKEINTERFACE java.util.Map.get (Ljava/lang/Object;)Ljava/lang/Object;
                    CHECKCAST org.springframework.expression.spel.support.ReflectivePropertyAccessor$InvokerPair
                    ASTORE 6
                    ALOAD_0     // Lorg/springframework/expression/spel/support/ReflectivePropertyAccessor; this   (line 144)
                    ALOAD 6     // Lorg/springframework/expression/spel/support/ReflectivePropertyAccessor$InvokerPair; invoker
                    PUTFIELD org.springframework.expression.spel.support.ReflectivePropertyAccessor.lastReadInvokerPair Lorg/springframework/expression/spel/support/ReflectivePropertyAccessor$InvokerPair;
                    ALOAD 6     // Lorg/springframework/expression/spel/support/ReflectivePropertyAccessor$InvokerPair; invoker   (line 146)
                    IFNULL L5
                    ALOAD 6     // Lorg/springframework/expression/spel/support/ReflectivePropertyAccessor$InvokerPair; invoker
                    GETFIELD org.springframework.expression.spel.support.ReflectivePropertyAccessor$InvokerPair.member Ljava/lang/reflect/Member;
                    INSTANCEOF java.lang.reflect.Method
                    IFEQ L9
                L5: ALOAD 6     // Lorg/springframework/expression/spel/support/ReflectivePropertyAccessor$InvokerPair; invoker   (line 147)
                    IFNULL L6
                    ALOAD 6     // Lorg/springframework/expression/spel/support/ReflectivePropertyAccessor$InvokerPair; invoker
                    GETFIELD org.springframework.expression.spel.support.ReflectivePropertyAccessor$InvokerPair.member Ljava/lang/reflect/Member;
                    GOTO L7
                L6: ACONST_NULL
                L7: CHECKCAST java.lang.reflect.Method
                    CHECKCAST java.lang.reflect.Method
                    ASTORE 7
                    ALOAD 7     // Ljava/lang/reflect/Method; method   (line 148)
                    IFNONNULL L8
                    ALOAD_0     // Lorg/springframework/expression/spel/support/ReflectivePropertyAccessor; this   (line 149)
                    ALOAD_3     // Ljava/lang/String; name
                    ALOAD 4     // Ljava/lang/Class; type
                    ALOAD_2     // Ljava/lang/Object; target
                    INVOKESPECIAL org.springframework.expression.spel.support.ReflectivePropertyAccessor.findGetterForProperty (Ljava/lang/String;Ljava/lang/Class;Ljava/lang/Object;)Ljava/lang/reflect/Method;
                    ASTORE 7     // Ljava/lang/reflect/Method; method
                    ALOAD 7     // Ljava/lang/reflect/Method; method   (line 150)
                    IFNULL L8
                    NEW org.springframework.core.convert.Property   (line 154)
                    DUP
                    ALOAD 4     // Ljava/lang/Class; type
                    ALOAD 7     // Ljava/lang/reflect/Method; method
                    ACONST_NULL
                    INVOKESPECIAL org.springframework.core.convert.Property.<init> (Ljava/lang/Class;Ljava/lang/reflect/Method;Ljava/lang/reflect/Method;)V
                    ASTORE 8
                    NEW org.springframework.core.convert.TypeDescriptor   (line 155)
                    DUP
                    ALOAD 8     // Lorg/springframework/core/convert/Property; property
                    INVOKESPECIAL org.springframework.core.convert.TypeDescriptor.<init> (Lorg/springframework/core/convert/Property;)V
                    ASTORE 9
                    NEW org.springframework.expression.spel.support.ReflectivePropertyAccessor$InvokerPair   (line 156)
                    DUP
                    ALOAD 7     // Ljava/lang/reflect/Method; method
                    ALOAD 9     // Lorg/springframework/core/convert/TypeDescriptor; typeDescriptor
                    INVOKESPECIAL org.springframework.expression.spel.support.ReflectivePropertyAccessor$InvokerPair.<init> (Ljava/lang/reflect/Member;Lorg/springframework/core/convert/TypeDescriptor;)V
                    ASTORE 6     // Lorg/springframework/expression/spel/support/ReflectivePropertyAccessor$InvokerPair; invoker
                    ALOAD_0     // Lorg/springframework/expression/spel/support/ReflectivePropertyAccessor; this   (line 157)
                    ALOAD 6     // Lorg/springframework/expression/spel/support/ReflectivePropertyAccessor$InvokerPair; invoker
                    PUTFIELD org.springframework.expression.spel.support.ReflectivePropertyAccessor.lastReadInvokerPair Lorg/springframework/expression/spel/support/ReflectivePropertyAccessor$InvokerPair;
                    ALOAD_0     // Lorg/springframework/expression/spel/support/ReflectivePropertyAccessor; this   (line 158)
                    GETFIELD org.springframework.expression.spel.support.ReflectivePropertyAccessor.readerCache Ljava/util/Map;
                    ALOAD 5     // Lorg/springframework/expression/spel/support/ReflectivePropertyAccessor$CacheKey; cacheKey
                    ALOAD 6     // Lorg/springframework/expression/spel/support/ReflectivePropertyAccessor$InvokerPair; invoker
                    INVOKEINTERFACE java.util.Map.put (Ljava/lang/Object;Ljava/lang/Object;)Ljava/lang/Object;
                    POP
                L8: ALOAD 7     // Ljava/lang/reflect/Method; method   (line 161)
                    IFNULL L9
    catch java.lang.Exception -> E0
    |               ALOAD 7     // Ljava/lang/reflect/Method; method   (line 163)
    |               INVOKESTATIC org.springframework.util.ReflectionUtils.makeAccessible (Ljava/lang/reflect/Method;)V
    |               ALOAD 7     // Ljava/lang/reflect/Method; method   (line 164)
    |               ALOAD_2     // Ljava/lang/Object; target
    |               ICONST_0
    |               ANEWARRAY java.lang.Object
    |               INVOKEVIRTUAL java.lang.reflect.Method.invoke (Ljava/lang/Object;[Ljava/lang/Object;)Ljava/lang/Object;
    |               ASTORE 8
    |               NEW org.springframework.expression.TypedValue   (line 165)
    |               DUP
    |               ALOAD 8     // Ljava/lang/Object; value
    |               ALOAD 6     // Lorg/springframework/expression/spel/support/ReflectivePropertyAccessor$InvokerPair; invoker
    |               GETFIELD org.springframework.expression.spel.support.ReflectivePropertyAccessor$InvokerPair.typeDescriptor Lorg/springframework/core/convert/TypeDescriptor;
    |               ALOAD 8     // Ljava/lang/Object; value
    |               INVOKEVIRTUAL org.springframework.core.convert.TypeDescriptor.narrow (Ljava/lang/Object;)Lorg/springframework/core/convert/TypeDescriptor;
    |               INVOKESPECIAL org.springframework.expression.TypedValue.<init> (Ljava/lang/Object;Lorg/springframework/core/convert/TypeDescriptor;)V
    catch java.lang.Exception -> E0
                    ARETURN
                E0: ASTORE 8   (line 167)
                    NEW org.springframework.expression.AccessException   (line 168)
                    DUP
                    NEW java.lang.StringBuilder
                    DUP
                    INVOKESPECIAL java.lang.StringBuilder.<init> ()V
                    LDC "Unable to access property '"
                    INVOKEVIRTUAL java.lang.StringBuilder.append (Ljava/lang/String;)Ljava/lang/StringBuilder;
                    ALOAD_3     // Ljava/lang/String; name
                    INVOKEVIRTUAL java.lang.StringBuilder.append (Ljava/lang/String;)Ljava/lang/StringBuilder;
                    LDC "' through getter"
                    INVOKEVIRTUAL java.lang.StringBuilder.append (Ljava/lang/String;)Ljava/lang/StringBuilder;
                    INVOKEVIRTUAL java.lang.StringBuilder.toString ()Ljava/lang/String;
                    ALOAD 8     // Ljava/lang/Exception; ex
                    INVOKESPECIAL org.springframework.expression.AccessException.<init> (Ljava/lang/String;Ljava/lang/Exception;)V
                    ATHROW
                L9: ALOAD 6     // Lorg/springframework/expression/spel/support/ReflectivePropertyAccessor$InvokerPair; invoker   (line 173)
                    IFNULL L10
                    ALOAD 6     // Lorg/springframework/expression/spel/support/ReflectivePropertyAccessor$InvokerPair; invoker
                    GETFIELD org.springframework.expression.spel.support.ReflectivePropertyAccessor$InvokerPair.member Ljava/lang/reflect/Member;
                    INSTANCEOF java.lang.reflect.Field
                    IFEQ L14
               L10: ALOAD 6     // Lorg/springframework/expression/spel/support/ReflectivePropertyAccessor$InvokerPair; invoker   (line 174)
                    IFNONNULL L11
                    ACONST_NULL
                    GOTO L12
               L11: ALOAD 6     // Lorg/springframework/expression/spel/support/ReflectivePropertyAccessor$InvokerPair; invoker
                    GETFIELD org.springframework.expression.spel.support.ReflectivePropertyAccessor$InvokerPair.member Ljava/lang/reflect/Member;
               L12: CHECKCAST java.lang.reflect.Field
                    CHECKCAST java.lang.reflect.Field
                    ASTORE 7
                    ALOAD 7     // Ljava/lang/reflect/Field; field   (line 175)
                    IFNONNULL L13
                    ALOAD_0     // Lorg/springframework/expression/spel/support/ReflectivePropertyAccessor; this   (line 176)
                    ALOAD_3     // Ljava/lang/String; name
                    ALOAD 4     // Ljava/lang/Class; type
                    ALOAD_2     // Ljava/lang/Object; target
                    INVOKESPECIAL org.springframework.expression.spel.support.ReflectivePropertyAccessor.findField (Ljava/lang/String;Ljava/lang/Class;Ljava/lang/Object;)Ljava/lang/reflect/Field;
                    ASTORE 7     // Ljava/lang/reflect/Field; field
                    ALOAD 7     // Ljava/lang/reflect/Field; field   (line 177)
                    IFNULL L13
                    NEW org.springframework.expression.spel.support.ReflectivePropertyAccessor$InvokerPair   (line 178)
                    DUP
                    ALOAD 7     // Ljava/lang/reflect/Field; field
                    NEW org.springframework.core.convert.TypeDescriptor
                    DUP
                    ALOAD 7     // Ljava/lang/reflect/Field; field
                    INVOKESPECIAL org.springframework.core.convert.TypeDescriptor.<init> (Ljava/lang/reflect/Field;)V
                    INVOKESPECIAL org.springframework.expression.spel.support.ReflectivePropertyAccessor$InvokerPair.<init> (Ljava/lang/reflect/Member;Lorg/springframework/core/convert/TypeDescriptor;)V
                    ASTORE 6     // Lorg/springframework/expression/spel/support/ReflectivePropertyAccessor$InvokerPair; invoker
                    ALOAD_0     // Lorg/springframework/expression/spel/support/ReflectivePropertyAccessor; this   (line 179)
                    ALOAD 6     // Lorg/springframework/expression/spel/support/ReflectivePropertyAccessor$InvokerPair; invoker
                    PUTFIELD org.springframework.expression.spel.support.ReflectivePropertyAccessor.lastReadInvokerPair Lorg/springframework/expression/spel/support/ReflectivePropertyAccessor$InvokerPair;
                    ALOAD_0     // Lorg/springframework/expression/spel/support/ReflectivePropertyAccessor; this   (line 180)
                    GETFIELD org.springframework.expression.spel.support.ReflectivePropertyAccessor.readerCache Ljava/util/Map;
                    ALOAD 5     // Lorg/springframework/expression/spel/support/ReflectivePropertyAccessor$CacheKey; cacheKey
                    ALOAD 6     // Lorg/springframework/expression/spel/support/ReflectivePropertyAccessor$InvokerPair; invoker
                    INVOKEINTERFACE java.util.Map.put (Ljava/lang/Object;Ljava/lang/Object;)Ljava/lang/Object;
                    POP
               L13: ALOAD 7     // Ljava/lang/reflect/Field; field   (line 183)
                    IFNULL L14
    catch java.lang.Exception -> E1
    |               ALOAD 7     // Ljava/lang/reflect/Field; field   (line 185)
    |               INVOKESTATIC org.springframework.util.ReflectionUtils.makeAccessible (Ljava/lang/reflect/Field;)V
    |               ALOAD 7     // Ljava/lang/reflect/Field; field   (line 186)
    |               ALOAD_2     // Ljava/lang/Object; target
    |               INVOKEVIRTUAL java.lang.reflect.Field.get (Ljava/lang/Object;)Ljava/lang/Object;
    |               ASTORE 8
    |               NEW org.springframework.expression.TypedValue   (line 187)
    |               DUP
    |               ALOAD 8     // Ljava/lang/Object; value
    |               ALOAD 6     // Lorg/springframework/expression/spel/support/ReflectivePropertyAccessor$InvokerPair; invoker
    |               GETFIELD org.springframework.expression.spel.support.ReflectivePropertyAccessor$InvokerPair.typeDescriptor Lorg/springframework/core/convert/TypeDescriptor;
    |               ALOAD 8     // Ljava/lang/Object; value
    |               INVOKEVIRTUAL org.springframework.core.convert.TypeDescriptor.narrow (Ljava/lang/Object;)Lorg/springframework/core/convert/TypeDescriptor;
    |               INVOKESPECIAL org.springframework.expression.TypedValue.<init> (Ljava/lang/Object;Lorg/springframework/core/convert/TypeDescriptor;)V
    catch java.lang.Exception -> E1
                    ARETURN
                E1: ASTORE 8   (line 189)
                    NEW org.springframework.expression.AccessException   (line 190)
                    DUP
                    NEW java.lang.StringBuilder
                    DUP
                    INVOKESPECIAL java.lang.StringBuilder.<init> ()V
                    LDC "Unable to access field: "
                    INVOKEVIRTUAL java.lang.StringBuilder.append (Ljava/lang/String;)Ljava/lang/StringBuilder;
                    ALOAD_3     // Ljava/lang/String; name
                    INVOKEVIRTUAL java.lang.StringBuilder.append (Ljava/lang/String;)Ljava/lang/StringBuilder;
                    INVOKEVIRTUAL java.lang.StringBuilder.toString ()Ljava/lang/String;
                    ALOAD 8     // Ljava/lang/Exception; ex
                    INVOKESPECIAL org.springframework.expression.AccessException.<init> (Ljava/lang/String;Ljava/lang/Exception;)V
                    ATHROW
               L14: NEW org.springframework.expression.AccessException   (line 195)
                    DUP
                    NEW java.lang.StringBuilder
                    DUP
                    INVOKESPECIAL java.lang.StringBuilder.<init> ()V
                    LDC "Neither getter nor field found for property '"
                    INVOKEVIRTUAL java.lang.StringBuilder.append (Ljava/lang/String;)Ljava/lang/StringBuilder;
                    ALOAD_3     // Ljava/lang/String; name
                    INVOKEVIRTUAL java.lang.StringBuilder.append (Ljava/lang/String;)Ljava/lang/StringBuilder;
                    LDC "'"
                    INVOKEVIRTUAL java.lang.StringBuilder.append (Ljava/lang/String;)Ljava/lang/StringBuilder;
                    INVOKEVIRTUAL java.lang.StringBuilder.toString ()Ljava/lang/String;
                    INVOKESPECIAL org.springframework.expression.AccessException.<init> (Ljava/lang/String;)V
                    ATHROW
  end public org.springframework.expression.TypedValue read(org.springframework.expression.EvaluationContext, Object, String) throws org.springframework.expression.AccessException

  public boolean canWrite(org.springframework.expression.EvaluationContext, Object, String) throws org.springframework.expression.AccessException:
                    ALOAD_2     // Ljava/lang/Object; target   (line 200)
                    IFNONNULL L0
                    ICONST_0   (line 201)
                    IRETURN
                L0: ALOAD_2     // Ljava/lang/Object; target   (line 203)
                    INSTANCEOF java.lang.Class
                    IFEQ L1
                    ALOAD_2     // Ljava/lang/Object; target
                    CHECKCAST java.lang.Class
                    GOTO L2
                L1: ALOAD_2     // Ljava/lang/Object; target
                    INVOKEVIRTUAL java.lang.Object.getClass ()Ljava/lang/Class;
                L2: ASTORE 4
                    NEW org.springframework.expression.spel.support.ReflectivePropertyAccessor$CacheKey   (line 204)
                    DUP
                    ALOAD 4     // Ljava/lang/Class; type
                    ALOAD_3     // Ljava/lang/String; name
                    ALOAD_2     // Ljava/lang/Object; target
                    INSTANCEOF java.lang.Class
                    INVOKESPECIAL org.springframework.expression.spel.support.ReflectivePropertyAccessor$CacheKey.<init> (Ljava/lang/Class;Ljava/lang/String;Z)V
                    ASTORE 5
                    ALOAD_0     // Lorg/springframework/expression/spel/support/ReflectivePropertyAccessor; this   (line 205)
                    GETFIELD org.springframework.expression.spel.support.ReflectivePropertyAccessor.writerCache Ljava/util/Map;
                    ALOAD 5     // Lorg/springframework/expression/spel/support/ReflectivePropertyAccessor$CacheKey; cacheKey
                    INVOKEINTERFACE java.util.Map.containsKey (Ljava/lang/Object;)Z
                    IFEQ L3
                    ICONST_1   (line 206)
                    IRETURN
                L3: ALOAD_0     // Lorg/springframework/expression/spel/support/ReflectivePropertyAccessor; this   (line 208)
                    ALOAD_3     // Ljava/lang/String; name
                    ALOAD 4     // Ljava/lang/Class; type
                    ALOAD_2     // Ljava/lang/Object; target
                    INVOKESPECIAL org.springframework.expression.spel.support.ReflectivePropertyAccessor.findSetterForProperty (Ljava/lang/String;Ljava/lang/Class;Ljava/lang/Object;)Ljava/lang/reflect/Method;
                    ASTORE 6
                    ALOAD 6     // Ljava/lang/reflect/Method; method   (line 209)
                    IFNULL L4
                    NEW org.springframework.core.convert.Property   (line 211)
                    DUP
                    ALOAD 4     // Ljava/lang/Class; type
                    ACONST_NULL
                    ALOAD 6     // Ljava/lang/reflect/Method; method
                    INVOKESPECIAL org.springframework.core.convert.Property.<init> (Ljava/lang/Class;Ljava/lang/reflect/Method;Ljava/lang/reflect/Method;)V
                    ASTORE 7
                    NEW org.springframework.core.convert.TypeDescriptor   (line 212)
                    DUP
                    ALOAD 7     // Lorg/springframework/core/convert/Property; property
                    INVOKESPECIAL org.springframework.core.convert.TypeDescriptor.<init> (Lorg/springframework/core/convert/Property;)V
                    ASTORE 8
                    ALOAD_0     // Lorg/springframework/expression/spel/support/ReflectivePropertyAccessor; this   (line 213)
                    GETFIELD org.springframework.expression.spel.support.ReflectivePropertyAccessor.writerCache Ljava/util/Map;
                    ALOAD 5     // Lorg/springframework/expression/spel/support/ReflectivePropertyAccessor$CacheKey; cacheKey
                    ALOAD 6     // Ljava/lang/reflect/Method; method
                    INVOKEINTERFACE java.util.Map.put (Ljava/lang/Object;Ljava/lang/Object;)Ljava/lang/Object;
                    POP
                    ALOAD_0     // Lorg/springframework/expression/spel/support/ReflectivePropertyAccessor; this   (line 214)
                    GETFIELD org.springframework.expression.spel.support.ReflectivePropertyAccessor.typeDescriptorCache Ljava/util/Map;
                    ALOAD 5     // Lorg/springframework/expression/spel/support/ReflectivePropertyAccessor$CacheKey; cacheKey
                    ALOAD 8     // Lorg/springframework/core/convert/TypeDescriptor; typeDescriptor
                    INVOKEINTERFACE java.util.Map.put (Ljava/lang/Object;Ljava/lang/Object;)Ljava/lang/Object;
                    POP
                    ICONST_1   (line 215)
                    IRETURN
                L4: ALOAD_0     // Lorg/springframework/expression/spel/support/ReflectivePropertyAccessor; this   (line 218)
                    ALOAD_3     // Ljava/lang/String; name
                    ALOAD 4     // Ljava/lang/Class; type
                    ALOAD_2     // Ljava/lang/Object; target
                    INVOKESPECIAL org.springframework.expression.spel.support.ReflectivePropertyAccessor.findField (Ljava/lang/String;Ljava/lang/Class;Ljava/lang/Object;)Ljava/lang/reflect/Field;
                    ASTORE 7
                    ALOAD 7     // Ljava/lang/reflect/Field; field   (line 219)
                    IFNULL L5
                    ALOAD_0     // Lorg/springframework/expression/spel/support/ReflectivePropertyAccessor; this   (line 220)
                    GETFIELD org.springframework.expression.spel.support.ReflectivePropertyAccessor.writerCache Ljava/util/Map;
                    ALOAD 5     // Lorg/springframework/expression/spel/support/ReflectivePropertyAccessor$CacheKey; cacheKey
                    ALOAD 7     // Ljava/lang/reflect/Field; field
                    INVOKEINTERFACE java.util.Map.put (Ljava/lang/Object;Ljava/lang/Object;)Ljava/lang/Object;
                    POP
                    ALOAD_0     // Lorg/springframework/expression/spel/support/ReflectivePropertyAccessor; this   (line 221)
                    GETFIELD org.springframework.expression.spel.support.ReflectivePropertyAccessor.typeDescriptorCache Ljava/util/Map;
                    ALOAD 5     // Lorg/springframework/expression/spel/support/ReflectivePropertyAccessor$CacheKey; cacheKey
                    NEW org.springframework.core.convert.TypeDescriptor
                    DUP
                    ALOAD 7     // Ljava/lang/reflect/Field; field
                    INVOKESPECIAL org.springframework.core.convert.TypeDescriptor.<init> (Ljava/lang/reflect/Field;)V
                    INVOKEINTERFACE java.util.Map.put (Ljava/lang/Object;Ljava/lang/Object;)Ljava/lang/Object;
                    POP
                    ICONST_1   (line 222)
                    IRETURN
                L5: ICONST_0   (line 225)
                    IRETURN
  end public boolean canWrite(org.springframework.expression.EvaluationContext, Object, String) throws org.springframework.expression.AccessException

  public void write(org.springframework.expression.EvaluationContext, Object, String, Object) throws org.springframework.expression.AccessException:
                    ALOAD_2     // Ljava/lang/Object; target   (line 230)
                    IFNONNULL L0
                    NEW org.springframework.expression.AccessException   (line 231)
                    DUP
                    LDC "Cannot write property on null target"
                    INVOKESPECIAL org.springframework.expression.AccessException.<init> (Ljava/lang/String;)V
                    ATHROW
                L0: ALOAD_2     // Ljava/lang/Object; target   (line 233)
                    INSTANCEOF java.lang.Class
                    IFEQ L1
                    ALOAD_2     // Ljava/lang/Object; target
                    CHECKCAST java.lang.Class
                    GOTO L2
                L1: ALOAD_2     // Ljava/lang/Object; target
                    INVOKEVIRTUAL java.lang.Object.getClass ()Ljava/lang/Class;
                L2: ASTORE 5
                    ALOAD 4     // Ljava/lang/Object; newValue   (line 235)
                    ASTORE 6
                    ALOAD_0     // Lorg/springframework/expression/spel/support/ReflectivePropertyAccessor; this   (line 236)
                    ALOAD_1     // Lorg/springframework/expression/EvaluationContext; context
                    ALOAD_2     // Ljava/lang/Object; target
                    ALOAD_3     // Ljava/lang/String; name
                    INVOKESPECIAL org.springframework.expression.spel.support.ReflectivePropertyAccessor.getTypeDescriptor (Lorg/springframework/expression/EvaluationContext;Ljava/lang/Object;Ljava/lang/String;)Lorg/springframework/core/convert/TypeDescriptor;
                    ASTORE 7
                    ALOAD 7     // Lorg/springframework/core/convert/TypeDescriptor; typeDescriptor   (line 237)
                    IFNULL L3
    catch org.springframework.expression.EvaluationException -> E0
    |               ALOAD_1     // Lorg/springframework/expression/EvaluationContext; context   (line 239)
    |               INVOKEINTERFACE org.springframework.expression.EvaluationContext.getTypeConverter ()Lorg/springframework/expression/TypeConverter;
    |               ALOAD 4     // Ljava/lang/Object; newValue
    |               ALOAD 4     // Ljava/lang/Object; newValue
    |               INVOKESTATIC org.springframework.core.convert.TypeDescriptor.forObject (Ljava/lang/Object;)Lorg/springframework/core/convert/TypeDescriptor;   (line 240)
    |               ALOAD 7     // Lorg/springframework/core/convert/TypeDescriptor; typeDescriptor
    |               INVOKEINTERFACE org.springframework.expression.TypeConverter.convertValue (Ljava/lang/Object;Lorg/springframework/core/convert/TypeDescriptor;Lorg/springframework/core/convert/TypeDescriptor;)Ljava/lang/Object;   (line 239)
    |               ASTORE 6     // Ljava/lang/Object; possiblyConvertedNewValue
    catch org.springframework.expression.EvaluationException -> E0
                    GOTO L3   (line 244)
                E0: ASTORE 8   (line 242)
                    NEW org.springframework.expression.AccessException   (line 243)
                    DUP
                    LDC "Type conversion failure"
                    ALOAD 8     // Lorg/springframework/expression/EvaluationException; evaluationException
                    INVOKESPECIAL org.springframework.expression.AccessException.<init> (Ljava/lang/String;Ljava/lang/Exception;)V
                    ATHROW
                L3: NEW org.springframework.expression.spel.support.ReflectivePropertyAccessor$CacheKey   (line 246)
                    DUP
                    ALOAD 5     // Ljava/lang/Class; type
                    ALOAD_3     // Ljava/lang/String; name
                    ALOAD_2     // Ljava/lang/Object; target
                    INSTANCEOF java.lang.Class
                    INVOKESPECIAL org.springframework.expression.spel.support.ReflectivePropertyAccessor$CacheKey.<init> (Ljava/lang/Class;Ljava/lang/String;Z)V
                    ASTORE 8
                    ALOAD_0     // Lorg/springframework/expression/spel/support/ReflectivePropertyAccessor; this   (line 247)
                    GETFIELD org.springframework.expression.spel.support.ReflectivePropertyAccessor.writerCache Ljava/util/Map;
                    ALOAD 8     // Lorg/springframework/expression/spel/support/ReflectivePropertyAccessor$CacheKey; cacheKey
                    INVOKEINTERFACE java.util.Map.get (Ljava/lang/Object;)Ljava/lang/Object;
                    CHECKCAST java.lang.reflect.Member
                    ASTORE 9
                    ALOAD 9     // Ljava/lang/reflect/Member; cachedMember   (line 249)
                    IFNULL L4
                    ALOAD 9     // Ljava/lang/reflect/Member; cachedMember
                    INSTANCEOF java.lang.reflect.Method
                    IFEQ L6
                L4: ALOAD 9     // Ljava/lang/reflect/Member; cachedMember   (line 250)
                    CHECKCAST java.lang.reflect.Method
                    ASTORE 10
                    ALOAD 10     // Ljava/lang/reflect/Method; method   (line 251)
                    IFNONNULL L5
                    ALOAD_0     // Lorg/springframework/expression/spel/support/ReflectivePropertyAccessor; this   (line 252)
                    ALOAD_3     // Ljava/lang/String; name
                    ALOAD 5     // Ljava/lang/Class; type
                    ALOAD_2     // Ljava/lang/Object; target
                    INVOKESPECIAL org.springframework.expression.spel.support.ReflectivePropertyAccessor.findSetterForProperty (Ljava/lang/String;Ljava/lang/Class;Ljava/lang/Object;)Ljava/lang/reflect/Method;
                    ASTORE 10     // Ljava/lang/reflect/Method; method
                    ALOAD 10     // Ljava/lang/reflect/Method; method   (line 253)
                    IFNULL L5
                    ALOAD 10     // Ljava/lang/reflect/Method; method   (line 254)
                    ASTORE 9     // Ljava/lang/reflect/Member; cachedMember
                    ALOAD_0     // Lorg/springframework/expression/spel/support/ReflectivePropertyAccessor; this   (line 255)
                    GETFIELD org.springframework.expression.spel.support.ReflectivePropertyAccessor.writerCache Ljava/util/Map;
                    ALOAD 8     // Lorg/springframework/expression/spel/support/ReflectivePropertyAccessor$CacheKey; cacheKey
                    ALOAD 9     // Ljava/lang/reflect/Member; cachedMember
                    INVOKEINTERFACE java.util.Map.put (Ljava/lang/Object;Ljava/lang/Object;)Ljava/lang/Object;
                    POP
                L5: ALOAD 10     // Ljava/lang/reflect/Method; method   (line 258)
                    IFNULL L6
    catch java.lang.Exception -> E1
    |               ALOAD 10     // Ljava/lang/reflect/Method; method   (line 260)
    |               INVOKESTATIC org.springframework.util.ReflectionUtils.makeAccessible (Ljava/lang/reflect/Method;)V
    |               ALOAD 10     // Ljava/lang/reflect/Method; method   (line 261)
    |               ALOAD_2     // Ljava/lang/Object; target
    |               ICONST_1
    |               ANEWARRAY java.lang.Object
    |               DUP
    |               ICONST_0
    |               ALOAD 6     // Ljava/lang/Object; possiblyConvertedNewValue
    |               AASTORE
    |               INVOKEVIRTUAL java.lang.reflect.Method.invoke (Ljava/lang/Object;[Ljava/lang/Object;)Ljava/lang/Object;
    |               POP
    catch java.lang.Exception -> E1
                    RETURN   (line 262)
                E1: ASTORE 11   (line 264)
                    NEW org.springframework.expression.AccessException   (line 265)
                    DUP
                    NEW java.lang.StringBuilder
                    DUP
                    INVOKESPECIAL java.lang.StringBuilder.<init> ()V
                    LDC "Unable to access property '"
                    INVOKEVIRTUAL java.lang.StringBuilder.append (Ljava/lang/String;)Ljava/lang/StringBuilder;
                    ALOAD_3     // Ljava/lang/String; name
                    INVOKEVIRTUAL java.lang.StringBuilder.append (Ljava/lang/String;)Ljava/lang/StringBuilder;
                    LDC "' through setter"
                    INVOKEVIRTUAL java.lang.StringBuilder.append (Ljava/lang/String;)Ljava/lang/StringBuilder;
                    INVOKEVIRTUAL java.lang.StringBuilder.toString ()Ljava/lang/String;
                    ALOAD 11     // Ljava/lang/Exception; ex
                    INVOKESPECIAL org.springframework.expression.AccessException.<init> (Ljava/lang/String;Ljava/lang/Exception;)V
                    ATHROW
                L6: ALOAD 9     // Ljava/lang/reflect/Member; cachedMember   (line 270)
                    IFNULL L7
                    ALOAD 9     // Ljava/lang/reflect/Member; cachedMember
                    INSTANCEOF java.lang.reflect.Field
                    IFEQ L9
                L7: ALOAD 9     // Ljava/lang/reflect/Member; cachedMember   (line 271)
                    CHECKCAST java.lang.reflect.Field
                    ASTORE 10
                    ALOAD 10     // Ljava/lang/reflect/Field; field   (line 272)
                    IFNONNULL L8
                    ALOAD_0     // Lorg/springframework/expression/spel/support/ReflectivePropertyAccessor; this   (line 273)
                    ALOAD_3     // Ljava/lang/String; name
                    ALOAD 5     // Ljava/lang/Class; type
                    ALOAD_2     // Ljava/lang/Object; target
                    INVOKESPECIAL org.springframework.expression.spel.support.ReflectivePropertyAccessor.findField (Ljava/lang/String;Ljava/lang/Class;Ljava/lang/Object;)Ljava/lang/reflect/Field;
                    ASTORE 10     // Ljava/lang/reflect/Field; field
                    ALOAD 10     // Ljava/lang/reflect/Field; field   (line 274)
                    IFNULL L8
                    ALOAD 10     // Ljava/lang/reflect/Field; field   (line 275)
                    ASTORE 9     // Ljava/lang/reflect/Member; cachedMember
                    ALOAD_0     // Lorg/springframework/expression/spel/support/ReflectivePropertyAccessor; this   (line 276)
                    GETFIELD org.springframework.expression.spel.support.ReflectivePropertyAccessor.writerCache Ljava/util/Map;
                    ALOAD 8     // Lorg/springframework/expression/spel/support/ReflectivePropertyAccessor$CacheKey; cacheKey
                    ALOAD 9     // Ljava/lang/reflect/Member; cachedMember
                    INVOKEINTERFACE java.util.Map.put (Ljava/lang/Object;Ljava/lang/Object;)Ljava/lang/Object;
                    POP
                L8: ALOAD 10     // Ljava/lang/reflect/Field; field   (line 279)
                    IFNULL L9
    catch java.lang.Exception -> E2
    |               ALOAD 10     // Ljava/lang/reflect/Field; field   (line 281)
    |               INVOKESTATIC org.springframework.util.ReflectionUtils.makeAccessible (Ljava/lang/reflect/Field;)V
    |               ALOAD 10     // Ljava/lang/reflect/Field; field   (line 282)
    |               ALOAD_2     // Ljava/lang/Object; target
    |               ALOAD 6     // Ljava/lang/Object; possiblyConvertedNewValue
    |               INVOKEVIRTUAL java.lang.reflect.Field.set (Ljava/lang/Object;Ljava/lang/Object;)V
    catch java.lang.Exception -> E2
                    RETURN   (line 283)
                E2: ASTORE 11   (line 285)
                    NEW org.springframework.expression.AccessException   (line 286)
                    DUP
                    NEW java.lang.StringBuilder
                    DUP
                    INVOKESPECIAL java.lang.StringBuilder.<init> ()V
                    LDC "Unable to access field: "
                    INVOKEVIRTUAL java.lang.StringBuilder.append (Ljava/lang/String;)Ljava/lang/StringBuilder;
                    ALOAD_3     // Ljava/lang/String; name
                    INVOKEVIRTUAL java.lang.StringBuilder.append (Ljava/lang/String;)Ljava/lang/StringBuilder;
                    INVOKEVIRTUAL java.lang.StringBuilder.toString ()Ljava/lang/String;
                    ALOAD 11     // Ljava/lang/Exception; ex
                    INVOKESPECIAL org.springframework.expression.AccessException.<init> (Ljava/lang/String;Ljava/lang/Exception;)V
                    ATHROW
                L9: NEW org.springframework.expression.AccessException   (line 291)
                    DUP
                    NEW java.lang.StringBuilder
                    DUP
                    INVOKESPECIAL java.lang.StringBuilder.<init> ()V
                    LDC "Neither setter nor field found for property '"
                    INVOKEVIRTUAL java.lang.StringBuilder.append (Ljava/lang/String;)Ljava/lang/StringBuilder;
                    ALOAD_3     // Ljava/lang/String; name
                    INVOKEVIRTUAL java.lang.StringBuilder.append (Ljava/lang/String;)Ljava/lang/StringBuilder;
                    LDC "'"
                    INVOKEVIRTUAL java.lang.StringBuilder.append (Ljava/lang/String;)Ljava/lang/StringBuilder;
                    INVOKEVIRTUAL java.lang.StringBuilder.toString ()Ljava/lang/String;
                    INVOKESPECIAL org.springframework.expression.AccessException.<init> (Ljava/lang/String;)V
                    ATHROW
  end public void write(org.springframework.expression.EvaluationContext, Object, String, Object) throws org.springframework.expression.AccessException

  private org.springframework.core.convert.TypeDescriptor getTypeDescriptor(org.springframework.expression.EvaluationContext, Object, String):
                    ALOAD_2     // Ljava/lang/Object; target   (line 295)
                    IFNONNULL L0
                    ACONST_NULL   (line 296)
                    ARETURN
                L0: ALOAD_2     // Ljava/lang/Object; target   (line 298)
                    INSTANCEOF java.lang.Class
                    IFEQ L1
                    ALOAD_2     // Ljava/lang/Object; target
                    CHECKCAST java.lang.Class
                    GOTO L2
                L1: ALOAD_2     // Ljava/lang/Object; target
                    INVOKEVIRTUAL java.lang.Object.getClass ()Ljava/lang/Class;
                L2: ASTORE 4
                    ALOAD 4     // Ljava/lang/Class; type   (line 300)
                    INVOKEVIRTUAL java.lang.Class.isArray ()Z
                    IFEQ L3
                    ALOAD_3     // Ljava/lang/String; name
                    LDC "length"
                    INVOKEVIRTUAL java.lang.String.equals (Ljava/lang/Object;)Z
                    IFEQ L3
                    GETSTATIC java.lang.Integer.TYPE Ljava/lang/Class;   (line 301)
                    INVOKESTATIC org.springframework.core.convert.TypeDescriptor.valueOf (Ljava/lang/Class;)Lorg/springframework/core/convert/TypeDescriptor;
                    ARETURN
                L3: NEW org.springframework.expression.spel.support.ReflectivePropertyAccessor$CacheKey   (line 303)
                    DUP
                    ALOAD 4     // Ljava/lang/Class; type
                    ALOAD_3     // Ljava/lang/String; name
                    ALOAD_2     // Ljava/lang/Object; target
                    INSTANCEOF java.lang.Class
                    INVOKESPECIAL org.springframework.expression.spel.support.ReflectivePropertyAccessor$CacheKey.<init> (Ljava/lang/Class;Ljava/lang/String;Z)V
                    ASTORE 5
                    ALOAD_0     // Lorg/springframework/expression/spel/support/ReflectivePropertyAccessor; this   (line 304)
                    GETFIELD org.springframework.expression.spel.support.ReflectivePropertyAccessor.typeDescriptorCache Ljava/util/Map;
                    ALOAD 5     // Lorg/springframework/expression/spel/support/ReflectivePropertyAccessor$CacheKey; cacheKey
                    INVOKEINTERFACE java.util.Map.get (Ljava/lang/Object;)Ljava/lang/Object;
                    CHECKCAST org.springframework.core.convert.TypeDescriptor
                    ASTORE 6
                    ALOAD 6     // Lorg/springframework/core/convert/TypeDescriptor; typeDescriptor   (line 305)
                    IFNONNULL L6
    catch org.springframework.expression.AccessException -> E0
    |               ALOAD_0     // Lorg/springframework/expression/spel/support/ReflectivePropertyAccessor; this   (line 308)
    |               ALOAD_1     // Lorg/springframework/expression/EvaluationContext; context
    |               ALOAD_2     // Ljava/lang/Object; target
    |               ALOAD_3     // Ljava/lang/String; name
    |               INVOKEVIRTUAL org.springframework.expression.spel.support.ReflectivePropertyAccessor.canRead (Lorg/springframework/expression/EvaluationContext;Ljava/lang/Object;Ljava/lang/String;)Z
    |               IFEQ L4
    |               ALOAD_0     // Lorg/springframework/expression/spel/support/ReflectivePropertyAccessor; this   (line 309)
    |               GETFIELD org.springframework.expression.spel.support.ReflectivePropertyAccessor.typeDescriptorCache Ljava/util/Map;
    |               ALOAD 5     // Lorg/springframework/expression/spel/support/ReflectivePropertyAccessor$CacheKey; cacheKey
    |               INVOKEINTERFACE java.util.Map.get (Ljava/lang/Object;)Ljava/lang/Object;
    |               CHECKCAST org.springframework.core.convert.TypeDescriptor
    |               ASTORE 6     // Lorg/springframework/core/convert/TypeDescriptor; typeDescriptor
    |               GOTO L5
    |           L4: ALOAD_0     // Lorg/springframework/expression/spel/support/ReflectivePropertyAccessor; this   (line 311)
    |               ALOAD_1     // Lorg/springframework/expression/EvaluationContext; context
    |               ALOAD_2     // Ljava/lang/Object; target
    |               ALOAD_3     // Ljava/lang/String; name
    |               INVOKEVIRTUAL org.springframework.expression.spel.support.ReflectivePropertyAccessor.canWrite (Lorg/springframework/expression/EvaluationContext;Ljava/lang/Object;Ljava/lang/String;)Z
    |               IFEQ L5
    |               ALOAD_0     // Lorg/springframework/expression/spel/support/ReflectivePropertyAccessor; this   (line 312)
    |               GETFIELD org.springframework.expression.spel.support.ReflectivePropertyAccessor.typeDescriptorCache Ljava/util/Map;
    |               ALOAD 5     // Lorg/springframework/expression/spel/support/ReflectivePropertyAccessor$CacheKey; cacheKey
    |               INVOKEINTERFACE java.util.Map.get (Ljava/lang/Object;)Ljava/lang/Object;
    |               CHECKCAST org.springframework.core.convert.TypeDescriptor
    |               ASTORE 6     // Lorg/springframework/core/convert/TypeDescriptor; typeDescriptor
    catch org.springframework.expression.AccessException -> E0
                L5: GOTO L6   (line 317)
                E0: ASTORE 7   (line 315)
                L6: ALOAD 6     // Lorg/springframework/core/convert/TypeDescriptor; typeDescriptor   (line 319)
                    ARETURN
  end private org.springframework.core.convert.TypeDescriptor getTypeDescriptor(org.springframework.expression.EvaluationContext, Object, String)

  private java.lang.reflect.Method findGetterForProperty(String, Class, Object):
                    ALOAD_0     // Lorg/springframework/expression/spel/support/ReflectivePropertyAccessor; this   (line 323)
                    ALOAD_1     // Ljava/lang/String; propertyName
                    ALOAD_2     // Ljava/lang/Class; clazz
                    ALOAD_3     // Ljava/lang/Object; target
                    INSTANCEOF java.lang.Class
                    INVOKEVIRTUAL org.springframework.expression.spel.support.ReflectivePropertyAccessor.findGetterForProperty (Ljava/lang/String;Ljava/lang/Class;Z)Ljava/lang/reflect/Method;
                    ASTORE 4
                    ALOAD 4     // Ljava/lang/reflect/Method; method   (line 324)
                    IFNONNULL L0
                    ALOAD_3     // Ljava/lang/Object; target
                    INSTANCEOF java.lang.Class
                    IFEQ L0
                    ALOAD_0     // Lorg/springframework/expression/spel/support/ReflectivePropertyAccessor; this   (line 325)
                    ALOAD_1     // Ljava/lang/String; propertyName
                    ALOAD_3     // Ljava/lang/Object; target
                    INVOKEVIRTUAL java.lang.Object.getClass ()Ljava/lang/Class;
                    ICONST_0
                    INVOKEVIRTUAL org.springframework.expression.spel.support.ReflectivePropertyAccessor.findGetterForProperty (Ljava/lang/String;Ljava/lang/Class;Z)Ljava/lang/reflect/Method;
                    ASTORE 4     // Ljava/lang/reflect/Method; method
                L0: ALOAD 4     // Ljava/lang/reflect/Method; method   (line 327)
                    ARETURN
  end private java.lang.reflect.Method findGetterForProperty(String, Class, Object)

  private java.lang.reflect.Method findSetterForProperty(String, Class, Object):
                    ALOAD_0     // Lorg/springframework/expression/spel/support/ReflectivePropertyAccessor; this   (line 331)
                    ALOAD_1     // Ljava/lang/String; propertyName
                    ALOAD_2     // Ljava/lang/Class; clazz
                    ALOAD_3     // Ljava/lang/Object; target
                    INSTANCEOF java.lang.Class
                    INVOKEVIRTUAL org.springframework.expression.spel.support.ReflectivePropertyAccessor.findSetterForProperty (Ljava/lang/String;Ljava/lang/Class;Z)Ljava/lang/reflect/Method;
                    ASTORE 4
                    ALOAD 4     // Ljava/lang/reflect/Method; method   (line 332)
                    IFNONNULL L0
                    ALOAD_3     // Ljava/lang/Object; target
                    INSTANCEOF java.lang.Class
                    IFEQ L0
                    ALOAD_0     // Lorg/springframework/expression/spel/support/ReflectivePropertyAccessor; this   (line 333)
                    ALOAD_1     // Ljava/lang/String; propertyName
                    ALOAD_3     // Ljava/lang/Object; target
                    INVOKEVIRTUAL java.lang.Object.getClass ()Ljava/lang/Class;
                    ICONST_0
                    INVOKEVIRTUAL org.springframework.expression.spel.support.ReflectivePropertyAccessor.findSetterForProperty (Ljava/lang/String;Ljava/lang/Class;Z)Ljava/lang/reflect/Method;
                    ASTORE 4     // Ljava/lang/reflect/Method; method
                L0: ALOAD 4     // Ljava/lang/reflect/Method; method   (line 335)
                    ARETURN
  end private java.lang.reflect.Method findSetterForProperty(String, Class, Object)

  private java.lang.reflect.Field findField(String, Class, Object):
                    ALOAD_0     // Lorg/springframework/expression/spel/support/ReflectivePropertyAccessor; this   (line 339)
                    ALOAD_1     // Ljava/lang/String; name
                    ALOAD_2     // Ljava/lang/Class; clazz
                    ALOAD_3     // Ljava/lang/Object; target
                    INSTANCEOF java.lang.Class
                    INVOKEVIRTUAL org.springframework.expression.spel.support.ReflectivePropertyAccessor.findField (Ljava/lang/String;Ljava/lang/Class;Z)Ljava/lang/reflect/Field;
                    ASTORE 4
                    ALOAD 4     // Ljava/lang/reflect/Field; field   (line 340)
                    IFNONNULL L0
                    ALOAD_3     // Ljava/lang/Object; target
                    INSTANCEOF java.lang.Class
                    IFEQ L0
                    ALOAD_0     // Lorg/springframework/expression/spel/support/ReflectivePropertyAccessor; this   (line 341)
                    ALOAD_1     // Ljava/lang/String; name
                    ALOAD_3     // Ljava/lang/Object; target
                    INVOKEVIRTUAL java.lang.Object.getClass ()Ljava/lang/Class;
                    ICONST_0
                    INVOKEVIRTUAL org.springframework.expression.spel.support.ReflectivePropertyAccessor.findField (Ljava/lang/String;Ljava/lang/Class;Z)Ljava/lang/reflect/Field;
                    ASTORE 4     // Ljava/lang/reflect/Field; field
                L0: ALOAD 4     // Ljava/lang/reflect/Field; field   (line 343)
                    ARETURN
  end private java.lang.reflect.Field findField(String, Class, Object)

  protected java.lang.reflect.Method findGetterForProperty(String, Class, boolean):
                    ALOAD_0     // Lorg/springframework/expression/spel/support/ReflectivePropertyAccessor; this   (line 350)
                    ALOAD_0     // Lorg/springframework/expression/spel/support/ReflectivePropertyAccessor; this
                    ALOAD_1     // Ljava/lang/String; propertyName
                    INVOKEVIRTUAL org.springframework.expression.spel.support.ReflectivePropertyAccessor.getPropertyMethodSuffixes (Ljava/lang/String;)[Ljava/lang/String;
                    LDC "get"
                    ALOAD_2     // Ljava/lang/Class; clazz
                    ILOAD_3     // Z mustBeStatic
                    ICONST_0
                    GETSTATIC org.springframework.expression.spel.support.ReflectivePropertyAccessor.ANY_TYPES Ljava/util/Set;
                    INVOKESPECIAL org.springframework.expression.spel.support.ReflectivePropertyAccessor.findMethodForProperty ([Ljava/lang/String;Ljava/lang/String;Ljava/lang/Class;ZILjava/util/Set;)Ljava/lang/reflect/Method;
                    ASTORE 4
                    ALOAD 4     // Ljava/lang/reflect/Method; method   (line 352)
                    IFNONNULL L0
                    ALOAD_0     // Lorg/springframework/expression/spel/support/ReflectivePropertyAccessor; this   (line 353)
                    ALOAD_0     // Lorg/springframework/expression/spel/support/ReflectivePropertyAccessor; this
                    ALOAD_1     // Ljava/lang/String; propertyName
                    INVOKEVIRTUAL org.springframework.expression.spel.support.ReflectivePropertyAccessor.getPropertyMethodSuffixes (Ljava/lang/String;)[Ljava/lang/String;
                    LDC "is"
                    ALOAD_2     // Ljava/lang/Class; clazz
                    ILOAD_3     // Z mustBeStatic
                    ICONST_0
                    GETSTATIC org.springframework.expression.spel.support.ReflectivePropertyAccessor.BOOLEAN_TYPES Ljava/util/Set;
                    INVOKESPECIAL org.springframework.expression.spel.support.ReflectivePropertyAccessor.findMethodForProperty ([Ljava/lang/String;Ljava/lang/String;Ljava/lang/Class;ZILjava/util/Set;)Ljava/lang/reflect/Method;
                    ASTORE 4     // Ljava/lang/reflect/Method; method
                L0: ALOAD 4     // Ljava/lang/reflect/Method; method   (line 356)
                    ARETURN
  end protected java.lang.reflect.Method findGetterForProperty(String, Class, boolean)

  protected java.lang.reflect.Method findSetterForProperty(String, Class, boolean):
                    ALOAD_0     // Lorg/springframework/expression/spel/support/ReflectivePropertyAccessor; this   (line 363)
                    ALOAD_0     // Lorg/springframework/expression/spel/support/ReflectivePropertyAccessor; this
                    ALOAD_1     // Ljava/lang/String; propertyName
                    INVOKEVIRTUAL org.springframework.expression.spel.support.ReflectivePropertyAccessor.getPropertyMethodSuffixes (Ljava/lang/String;)[Ljava/lang/String;
                    LDC "set"
                    ALOAD_2     // Ljava/lang/Class; clazz
                    ILOAD_3     // Z mustBeStatic
                    ICONST_1
                    GETSTATIC org.springframework.expression.spel.support.ReflectivePropertyAccessor.ANY_TYPES Ljava/util/Set;
                    INVOKESPECIAL org.springframework.expression.spel.support.ReflectivePropertyAccessor.findMethodForProperty ([Ljava/lang/String;Ljava/lang/String;Ljava/lang/Class;ZILjava/util/Set;)Ljava/lang/reflect/Method;
                    ARETURN
  end protected java.lang.reflect.Method findSetterForProperty(String, Class, boolean)

  private java.lang.reflect.Method findMethodForProperty(String[], String, Class, boolean, int, java.util.Set):
                    ALOAD_0     // Lorg/springframework/expression/spel/support/ReflectivePropertyAccessor; this   (line 370)
                    ALOAD_3     // Ljava/lang/Class; clazz
                    INVOKESPECIAL org.springframework.expression.spel.support.ReflectivePropertyAccessor.getSortedClassMethods (Ljava/lang/Class;)[Ljava/lang/reflect/Method;
                    ASTORE 7
                    ALOAD_1     // [Ljava/lang/String; methodSuffixes   (line 371)
                    ASTORE 8
                    ALOAD 8
                    ARRAYLENGTH
                    ISTORE 9
                    ICONST_0
                    ISTORE 10
                L0: ILOAD 10
                    ILOAD 9
                    IF_ICMPGE L6
                    ALOAD 8
                    ILOAD 10
                    AALOAD
                    ASTORE 11
                    ALOAD 7     // [Ljava/lang/reflect/Method; methods   (line 372)
                    ASTORE 12
                    ALOAD 12
                    ARRAYLENGTH
                    ISTORE 13
                    ICONST_0
                    ISTORE 14
                L1: ILOAD 14
                    ILOAD 13
                    IF_ICMPGE L5
                    ALOAD 12
                    ILOAD 14
                    AALOAD
                    ASTORE 15
                    ALOAD 15     // Ljava/lang/reflect/Method; method   (line 373)
                    INVOKEVIRTUAL java.lang.reflect.Method.getName ()Ljava/lang/String;
                    NEW java.lang.StringBuilder
                    DUP
                    INVOKESPECIAL java.lang.StringBuilder.<init> ()V
                    ALOAD_2     // Ljava/lang/String; prefix
                    INVOKEVIRTUAL java.lang.StringBuilder.append (Ljava/lang/String;)Ljava/lang/StringBuilder;
                    ALOAD 11     // Ljava/lang/String; methodSuffix
                    INVOKEVIRTUAL java.lang.StringBuilder.append (Ljava/lang/String;)Ljava/lang/StringBuilder;
                    INVOKEVIRTUAL java.lang.StringBuilder.toString ()Ljava/lang/String;
                    INVOKEVIRTUAL java.lang.String.equals (Ljava/lang/Object;)Z
                    IFEQ L4
                    ALOAD 15     // Ljava/lang/reflect/Method; method
                    INVOKEVIRTUAL java.lang.reflect.Method.getParameterTypes ()[Ljava/lang/Class;   (line 374)
                    ARRAYLENGTH
                    ILOAD 5     // I numberOfParams
                    IF_ICMPNE L4
                    ILOAD 4     // Z mustBeStatic
                    IFEQ L2
                    ALOAD 15     // Ljava/lang/reflect/Method; method
                    INVOKEVIRTUAL java.lang.reflect.Method.getModifiers ()I   (line 375)
                    INVOKESTATIC java.lang.reflect.Modifier.isStatic (I)Z
                    IFEQ L4
                L2: ALOAD 6     // Ljava/util/Set; requiredReturnTypes
                    INVOKEINTERFACE java.util.Set.isEmpty ()Z   (line 376)
                    IFNE L3
                    ALOAD 6     // Ljava/util/Set; requiredReturnTypes
                    ALOAD 15     // Ljava/lang/reflect/Method; method
                    INVOKEVIRTUAL java.lang.reflect.Method.getReturnType ()Ljava/lang/Class;
                    INVOKEINTERFACE java.util.Set.contains (Ljava/lang/Object;)Z
                    IFEQ L4
                L3: ALOAD 15     // Ljava/lang/reflect/Method; method   (line 377)
                    ARETURN
                L4: IINC 14 1   (line 372)
                    GOTO L1
                L5: IINC 10 1   (line 371)
                    GOTO L0
                L6: ACONST_NULL   (line 381)
                    ARETURN
  end private java.lang.reflect.Method findMethodForProperty(String[], String, Class, boolean, int, java.util.Set)

  private java.lang.reflect.Method[] getSortedClassMethods(Class):
                    ALOAD_1     // Ljava/lang/Class; clazz   (line 389)
                    INVOKEVIRTUAL java.lang.Class.getMethods ()[Ljava/lang/reflect/Method;
                    ASTORE_2
                    ALOAD_2     // [Ljava/lang/reflect/Method; methods   (line 390)
                    NEW org.springframework.expression.spel.support.ReflectivePropertyAccessor$1
                    DUP
                    ALOAD_0     // Lorg/springframework/expression/spel/support/ReflectivePropertyAccessor; this
                    INVOKESPECIAL org.springframework.expression.spel.support.ReflectivePropertyAccessor$1.<init> (Lorg/springframework/expression/spel/support/ReflectivePropertyAccessor;)V
                    INVOKESTATIC java.util.Arrays.sort ([Ljava/lang/Object;Ljava/util/Comparator;)V
                    ALOAD_2     // [Ljava/lang/reflect/Method; methods   (line 396)
                    ARETURN
  end private java.lang.reflect.Method[] getSortedClassMethods(Class)

  protected String[] getPropertyMethodSuffixes(String):
                    ALOAD_0     // Lorg/springframework/expression/spel/support/ReflectivePropertyAccessor; this   (line 406)
                    ALOAD_1     // Ljava/lang/String; propertyName
                    INVOKEVIRTUAL org.springframework.expression.spel.support.ReflectivePropertyAccessor.getPropertyMethodSuffix (Ljava/lang/String;)Ljava/lang/String;
                    ASTORE_2
                    ALOAD_2     // Ljava/lang/String; suffix   (line 407)
                    INVOKEVIRTUAL java.lang.String.length ()I
                    IFLE L0
                    ALOAD_2     // Ljava/lang/String; suffix
                    ICONST_0
                    INVOKEVIRTUAL java.lang.String.charAt (I)C
                    INVOKESTATIC java.lang.Character.isUpperCase (C)Z
                    IFEQ L0
                    ICONST_1   (line 408)
                    ANEWARRAY java.lang.String
                    DUP
                    ICONST_0
                    ALOAD_2     // Ljava/lang/String; suffix
                    AASTORE
                    ARETURN
                L0: ICONST_2   (line 410)
                    ANEWARRAY java.lang.String
                    DUP
                    ICONST_0
                    ALOAD_2     // Ljava/lang/String; suffix
                    AASTORE
                    DUP
                    ICONST_1
                    ALOAD_2     // Ljava/lang/String; suffix
                    INVOKESTATIC org.springframework.util.StringUtils.capitalize (Ljava/lang/String;)Ljava/lang/String;
                    AASTORE
                    ARETURN
  end protected String[] getPropertyMethodSuffixes(String)

  protected String getPropertyMethodSuffix(String):
                    ALOAD_1     // Ljava/lang/String; propertyName   (line 418)
                    INVOKEVIRTUAL java.lang.String.length ()I
                    ICONST_1
                    IF_ICMPLE L0
                    ALOAD_1     // Ljava/lang/String; propertyName
                    ICONST_1
                    INVOKEVIRTUAL java.lang.String.charAt (I)C
                    INVOKESTATIC java.lang.Character.isUpperCase (C)Z
                    IFEQ L0
                    ALOAD_1     // Ljava/lang/String; propertyName   (line 419)
                    ARETURN
                L0: ALOAD_1     // Ljava/lang/String; propertyName   (line 421)
                    INVOKESTATIC org.springframework.util.StringUtils.capitalize (Ljava/lang/String;)Ljava/lang/String;
                    ARETURN
  end protected String getPropertyMethodSuffix(String)

  protected java.lang.reflect.Field findField(String, Class, boolean):
                    ALOAD_2     // Ljava/lang/Class; clazz   (line 428)
                    INVOKEVIRTUAL java.lang.Class.getFields ()[Ljava/lang/reflect/Field;
                    ASTORE 4
                    ALOAD 4     // [Ljava/lang/reflect/Field; fields   (line 429)
                    ASTORE 5
                    ALOAD 5
                    ARRAYLENGTH
                    ISTORE 6
                    ICONST_0
                    ISTORE 7
                L0: ILOAD 7
                    ILOAD 6
                    IF_ICMPGE L3
                    ALOAD 5
                    ILOAD 7
                    AALOAD
                    ASTORE 8
                    ALOAD 8     // Ljava/lang/reflect/Field; field   (line 430)
                    INVOKEVIRTUAL java.lang.reflect.Field.getName ()Ljava/lang/String;
                    ALOAD_1     // Ljava/lang/String; name
                    INVOKEVIRTUAL java.lang.String.equals (Ljava/lang/Object;)Z
                    IFEQ L2
                    ILOAD_3     // Z mustBeStatic
                    IFEQ L1
                    ALOAD 8     // Ljava/lang/reflect/Field; field
                    INVOKEVIRTUAL java.lang.reflect.Field.getModifiers ()I
                    INVOKESTATIC java.lang.reflect.Modifier.isStatic (I)Z
                    IFEQ L2
                L1: ALOAD 8     // Ljava/lang/reflect/Field; field   (line 431)
                    ARETURN
                L2: IINC 7 1   (line 429)
                    GOTO L0
                L3: ALOAD_2     // Ljava/lang/Class; clazz   (line 436)
                    INVOKEVIRTUAL java.lang.Class.getSuperclass ()Ljava/lang/Class;
                    IFNULL L4
                    ALOAD_0     // Lorg/springframework/expression/spel/support/ReflectivePropertyAccessor; this   (line 437)
                    ALOAD_1     // Ljava/lang/String; name
                    ALOAD_2     // Ljava/lang/Class; clazz
                    INVOKEVIRTUAL java.lang.Class.getSuperclass ()Ljava/lang/Class;
                    ILOAD_3     // Z mustBeStatic
                    INVOKEVIRTUAL org.springframework.expression.spel.support.ReflectivePropertyAccessor.findField (Ljava/lang/String;Ljava/lang/Class;Z)Ljava/lang/reflect/Field;
                    ASTORE 5
                    ALOAD 5     // Ljava/lang/reflect/Field; field   (line 438)
                    IFNULL L4
                    ALOAD 5     // Ljava/lang/reflect/Field; field   (line 439)
                    ARETURN
                L4: ALOAD_2     // Ljava/lang/Class; clazz   (line 442)
                    INVOKEVIRTUAL java.lang.Class.getInterfaces ()[Ljava/lang/Class;
                    ASTORE 5
                    ALOAD 5
                    ARRAYLENGTH
                    ISTORE 6
                    ICONST_0
                    ISTORE 7
                L5: ILOAD 7
                    ILOAD 6
                    IF_ICMPGE L7
                    ALOAD 5
                    ILOAD 7
                    AALOAD
                    ASTORE 8
                    ALOAD_0     // Lorg/springframework/expression/spel/support/ReflectivePropertyAccessor; this   (line 443)
                    ALOAD_1     // Ljava/lang/String; name
                    ALOAD 8     // Ljava/lang/Class; implementedInterface
                    ILOAD_3     // Z mustBeStatic
                    INVOKEVIRTUAL org.springframework.expression.spel.support.ReflectivePropertyAccessor.findField (Ljava/lang/String;Ljava/lang/Class;Z)Ljava/lang/reflect/Field;
                    ASTORE 9
                    ALOAD 9     // Ljava/lang/reflect/Field; field   (line 444)
                    IFNULL L6
                    ALOAD 9     // Ljava/lang/reflect/Field; field   (line 445)
                    ARETURN
                L6: IINC 7 1   (line 442)
                    GOTO L5
                L7: ACONST_NULL   (line 448)
                    ARETURN
  end protected java.lang.reflect.Field findField(String, Class, boolean)

  public org.springframework.expression.PropertyAccessor createOptimalAccessor(org.springframework.expression.EvaluationContext, Object, String):
                    ALOAD_2     // Ljava/lang/Object; target   (line 460)
                    IFNONNULL L0
                    ALOAD_0     // Lorg/springframework/expression/spel/support/ReflectivePropertyAccessor; this   (line 461)
                    ARETURN
                L0: ALOAD_2     // Ljava/lang/Object; target   (line 463)
                    INSTANCEOF java.lang.Class
                    IFEQ L1
                    ALOAD_2     // Ljava/lang/Object; target
                    CHECKCAST java.lang.Class
                    GOTO L2
                L1: ALOAD_2     // Ljava/lang/Object; target
                    INVOKEVIRTUAL java.lang.Object.getClass ()Ljava/lang/Class;
                L2: ASTORE 4
                    ALOAD 4     // Ljava/lang/Class; type   (line 464)
                    INVOKEVIRTUAL java.lang.Class.isArray ()Z
                    IFEQ L3
                    ALOAD_0     // Lorg/springframework/expression/spel/support/ReflectivePropertyAccessor; this   (line 465)
                    ARETURN
                L3: NEW org.springframework.expression.spel.support.ReflectivePropertyAccessor$CacheKey   (line 468)
                    DUP
                    ALOAD 4     // Ljava/lang/Class; type
                    ALOAD_3     // Ljava/lang/String; name
                    ALOAD_2     // Ljava/lang/Object; target
                    INSTANCEOF java.lang.Class
                    INVOKESPECIAL org.springframework.expression.spel.support.ReflectivePropertyAccessor$CacheKey.<init> (Ljava/lang/Class;Ljava/lang/String;Z)V
                    ASTORE 5
                    ALOAD_0     // Lorg/springframework/expression/spel/support/ReflectivePropertyAccessor; this   (line 469)
                    GETFIELD org.springframework.expression.spel.support.ReflectivePropertyAccessor.readerCache Ljava/util/Map;
                    ALOAD 5     // Lorg/springframework/expression/spel/support/ReflectivePropertyAccessor$CacheKey; cacheKey
                    INVOKEINTERFACE java.util.Map.get (Ljava/lang/Object;)Ljava/lang/Object;
                    CHECKCAST org.springframework.expression.spel.support.ReflectivePropertyAccessor$InvokerPair
                    ASTORE 6
                    ALOAD 6     // Lorg/springframework/expression/spel/support/ReflectivePropertyAccessor$InvokerPair; invocationTarget   (line 471)
                    IFNULL L4
                    ALOAD 6     // Lorg/springframework/expression/spel/support/ReflectivePropertyAccessor$InvokerPair; invocationTarget
                    GETFIELD org.springframework.expression.spel.support.ReflectivePropertyAccessor$InvokerPair.member Ljava/lang/reflect/Member;
                    INSTANCEOF java.lang.reflect.Method
                    IFEQ L8
                L4: ALOAD 6     // Lorg/springframework/expression/spel/support/ReflectivePropertyAccessor$InvokerPair; invocationTarget   (line 472)
                    IFNONNULL L5
                    ACONST_NULL
                    GOTO L6
                L5: ALOAD 6     // Lorg/springframework/expression/spel/support/ReflectivePropertyAccessor$InvokerPair; invocationTarget
                    GETFIELD org.springframework.expression.spel.support.ReflectivePropertyAccessor$InvokerPair.member Ljava/lang/reflect/Member;
                L6: CHECKCAST java.lang.reflect.Method
                    CHECKCAST java.lang.reflect.Method
                    ASTORE 7
                    ALOAD 7     // Ljava/lang/reflect/Method; method   (line 473)
                    IFNONNULL L7
                    ALOAD_0     // Lorg/springframework/expression/spel/support/ReflectivePropertyAccessor; this   (line 474)
                    ALOAD_3     // Ljava/lang/String; name
                    ALOAD 4     // Ljava/lang/Class; type
                    ALOAD_2     // Ljava/lang/Object; target
                    INVOKESPECIAL org.springframework.expression.spel.support.ReflectivePropertyAccessor.findGetterForProperty (Ljava/lang/String;Ljava/lang/Class;Ljava/lang/Object;)Ljava/lang/reflect/Method;
                    ASTORE 7     // Ljava/lang/reflect/Method; method
                    ALOAD 7     // Ljava/lang/reflect/Method; method   (line 475)
                    IFNULL L7
                    NEW org.springframework.expression.spel.support.ReflectivePropertyAccessor$InvokerPair   (line 476)
                    DUP
                    ALOAD 7     // Ljava/lang/reflect/Method; method
                    NEW org.springframework.core.convert.TypeDescriptor
                    DUP
                    NEW org.springframework.core.MethodParameter
                    DUP
                    ALOAD 7     // Ljava/lang/reflect/Method; method
                    ICONST_M1
                    INVOKESPECIAL org.springframework.core.MethodParameter.<init> (Ljava/lang/reflect/Method;I)V
                    INVOKESPECIAL org.springframework.core.convert.TypeDescriptor.<init> (Lorg/springframework/core/MethodParameter;)V
                    INVOKESPECIAL org.springframework.expression.spel.support.ReflectivePropertyAccessor$InvokerPair.<init> (Ljava/lang/reflect/Member;Lorg/springframework/core/convert/TypeDescriptor;)V
                    ASTORE 6     // Lorg/springframework/expression/spel/support/ReflectivePropertyAccessor$InvokerPair; invocationTarget
                    ALOAD 7     // Ljava/lang/reflect/Method; method   (line 477)
                    INVOKESTATIC org.springframework.util.ReflectionUtils.makeAccessible (Ljava/lang/reflect/Method;)V
                    ALOAD_0     // Lorg/springframework/expression/spel/support/ReflectivePropertyAccessor; this   (line 478)
                    GETFIELD org.springframework.expression.spel.support.ReflectivePropertyAccessor.readerCache Ljava/util/Map;
                    ALOAD 5     // Lorg/springframework/expression/spel/support/ReflectivePropertyAccessor$CacheKey; cacheKey
                    ALOAD 6     // Lorg/springframework/expression/spel/support/ReflectivePropertyAccessor$InvokerPair; invocationTarget
                    INVOKEINTERFACE java.util.Map.put (Ljava/lang/Object;Ljava/lang/Object;)Ljava/lang/Object;
                    POP
                L7: ALOAD 7     // Ljava/lang/reflect/Method; method   (line 481)
                    IFNULL L8
                    NEW org.springframework.expression.spel.support.ReflectivePropertyAccessor$OptimalPropertyAccessor   (line 482)
                    DUP
                    ALOAD 6     // Lorg/springframework/expression/spel/support/ReflectivePropertyAccessor$InvokerPair; invocationTarget
                    INVOKESPECIAL org.springframework.expression.spel.support.ReflectivePropertyAccessor$OptimalPropertyAccessor.<init> (Lorg/springframework/expression/spel/support/ReflectivePropertyAccessor$InvokerPair;)V
                    ARETURN
                L8: ALOAD 6     // Lorg/springframework/expression/spel/support/ReflectivePropertyAccessor$InvokerPair; invocationTarget   (line 486)
                    IFNULL L9
                    ALOAD 6     // Lorg/springframework/expression/spel/support/ReflectivePropertyAccessor$InvokerPair; invocationTarget
                    GETFIELD org.springframework.expression.spel.support.ReflectivePropertyAccessor$InvokerPair.member Ljava/lang/reflect/Member;
                    INSTANCEOF java.lang.reflect.Field
                    IFEQ L13
                L9: ALOAD 6     // Lorg/springframework/expression/spel/support/ReflectivePropertyAccessor$InvokerPair; invocationTarget   (line 487)
                    IFNULL L10
                    ALOAD 6     // Lorg/springframework/expression/spel/support/ReflectivePropertyAccessor$InvokerPair; invocationTarget
                    GETFIELD org.springframework.expression.spel.support.ReflectivePropertyAccessor$InvokerPair.member Ljava/lang/reflect/Member;
                    CHECKCAST java.lang.reflect.Field
                    GOTO L11
               L10: ACONST_NULL
               L11: ASTORE 7
                    ALOAD 7     // Ljava/lang/reflect/Field; field   (line 488)
                    IFNONNULL L12
                    ALOAD_0     // Lorg/springframework/expression/spel/support/ReflectivePropertyAccessor; this   (line 489)
                    ALOAD_3     // Ljava/lang/String; name
                    ALOAD 4     // Ljava/lang/Class; type
                    ALOAD_2     // Ljava/lang/Object; target
                    INSTANCEOF java.lang.Class
                    INVOKEVIRTUAL org.springframework.expression.spel.support.ReflectivePropertyAccessor.findField (Ljava/lang/String;Ljava/lang/Class;Z)Ljava/lang/reflect/Field;
                    ASTORE 7     // Ljava/lang/reflect/Field; field
                    ALOAD 7     // Ljava/lang/reflect/Field; field   (line 490)
                    IFNULL L12
                    NEW org.springframework.expression.spel.support.ReflectivePropertyAccessor$InvokerPair   (line 491)
                    DUP
                    ALOAD 7     // Ljava/lang/reflect/Field; field
                    NEW org.springframework.core.convert.TypeDescriptor
                    DUP
                    ALOAD 7     // Ljava/lang/reflect/Field; field
                    INVOKESPECIAL org.springframework.core.convert.TypeDescriptor.<init> (Ljava/lang/reflect/Field;)V
                    INVOKESPECIAL org.springframework.expression.spel.support.ReflectivePropertyAccessor$InvokerPair.<init> (Ljava/lang/reflect/Member;Lorg/springframework/core/convert/TypeDescriptor;)V
                    ASTORE 6     // Lorg/springframework/expression/spel/support/ReflectivePropertyAccessor$InvokerPair; invocationTarget
                    ALOAD 7     // Ljava/lang/reflect/Field; field   (line 492)
                    INVOKESTATIC org.springframework.util.ReflectionUtils.makeAccessible (Ljava/lang/reflect/Field;)V
                    ALOAD_0     // Lorg/springframework/expression/spel/support/ReflectivePropertyAccessor; this   (line 493)
                    GETFIELD org.springframework.expression.spel.support.ReflectivePropertyAccessor.readerCache Ljava/util/Map;
                    ALOAD 5     // Lorg/springframework/expression/spel/support/ReflectivePropertyAccessor$CacheKey; cacheKey
                    ALOAD 6     // Lorg/springframework/expression/spel/support/ReflectivePropertyAccessor$InvokerPair; invocationTarget
                    INVOKEINTERFACE java.util.Map.put (Ljava/lang/Object;Ljava/lang/Object;)Ljava/lang/Object;
                    POP
               L12: ALOAD 7     // Ljava/lang/reflect/Field; field   (line 496)
                    IFNULL L13
                    NEW org.springframework.expression.spel.support.ReflectivePropertyAccessor$OptimalPropertyAccessor   (line 497)
                    DUP
                    ALOAD 6     // Lorg/springframework/expression/spel/support/ReflectivePropertyAccessor$InvokerPair; invocationTarget
                    INVOKESPECIAL org.springframework.expression.spel.support.ReflectivePropertyAccessor$OptimalPropertyAccessor.<init> (Lorg/springframework/expression/spel/support/ReflectivePropertyAccessor$InvokerPair;)V
                    ARETURN
               L13: ALOAD_0     // Lorg/springframework/expression/spel/support/ReflectivePropertyAccessor; this   (line 500)
                    ARETURN
  end public org.springframework.expression.PropertyAccessor createOptimalAccessor(org.springframework.expression.EvaluationContext, Object, String)

  static void <clinit>():
                    NEW java.util.HashSet   (line 63)
                    DUP
                    INVOKESPECIAL java.util.HashSet.<init> ()V
                    ASTORE_0
                    ALOAD_0     // Ljava/util/Set; booleanTypes   (line 64)
                    LDC java.lang.Boolean
                    INVOKEINTERFACE java.util.Set.add (Ljava/lang/Object;)Z
                    POP
                    ALOAD_0     // Ljava/util/Set; booleanTypes   (line 65)
                    GETSTATIC java.lang.Boolean.TYPE Ljava/lang/Class;
                    INVOKEINTERFACE java.util.Set.add (Ljava/lang/Object;)Z
                    POP
                    ALOAD_0     // Ljava/util/Set; booleanTypes   (line 66)
                    INVOKESTATIC java.util.Collections.unmodifiableSet (Ljava/util/Set;)Ljava/util/Set;
                    PUTSTATIC org.springframework.expression.spel.support.ReflectivePropertyAccessor.BOOLEAN_TYPES Ljava/util/Set;
                    INVOKESTATIC java.util.Collections.emptySet ()Ljava/util/Set;   (line 69)
                    PUTSTATIC org.springframework.expression.spel.support.ReflectivePropertyAccessor.ANY_TYPES Ljava/util/Set;
                    RETURN
  end static void <clinit>()
end public class org.springframework.expression.spel.support.ReflectivePropertyAccessor

	at org.aspectj.bridge.MessageWriter.handleMessage(MessageWriter.java:47)
	at org.aspectj.weaver.tools.WeavingAdaptor$WeavingAdaptorMessageWriter.handleMessage(WeavingAdaptor.java:742)
	at org.aspectj.weaver.tools.WeavingAdaptor$WeavingAdaptorMessageHolder.handleMessage(WeavingAdaptor.java:687)
	at org.aspectj.weaver.bcel.BcelWeaver.weave(BcelWeaver.java:1720)
	at org.aspectj.weaver.bcel.BcelWeaver.weaveWithoutDump(BcelWeaver.java:1638)
	at org.aspectj.weaver.bcel.BcelWeaver.weaveAndNotify(BcelWeaver.java:1401)
	at org.aspectj.weaver.bcel.BcelWeaver.weave(BcelWeaver.java:1187)
	at org.aspectj.weaver.tools.WeavingAdaptor.getWovenBytes(WeavingAdaptor.java:472)
	at org.aspectj.weaver.tools.WeavingAdaptor.weaveClass(WeavingAdaptor.java:323)
	at org.aspectj.weaver.loadtime.Aj.preProcess(Aj.java:99)
	at org.aspectj.weaver.loadtime.ClassPreProcessorAgentAdapter.transform(ClassPreProcessorAgentAdapter.java:54)
	at org.springframework.context.weaving.AspectJWeavingEnabler$AspectJClassBypassingClassFileTransformer.transform(AspectJWeavingEnabler.java:108)
	at org.springframework.instrument.classloading.InstrumentationLoadTimeWeaver$FilteringClassFileTransformer.transform(InstrumentationLoadTimeWeaver.java:184)
	at sun.instrument.TransformerManager.transform(Unknown Source)
	at sun.instrument.InstrumentationImpl.transform(Unknown Source)
	at java.lang.ClassLoader.defineClass1(Native Method)
	at java.lang.ClassLoader.defineClass(Unknown Source)
	at java.security.SecureClassLoader.defineClass(Unknown Source)
	at java.net.URLClassLoader.defineClass(Unknown Source)
	at java.net.URLClassLoader.access$100(Unknown Source)
	at java.net.URLClassLoader$1.run(Unknown Source)
	at java.net.URLClassLoader$1.run(Unknown Source)
	at java.security.AccessController.doPrivileged(Native Method)
	at java.net.URLClassLoader.findClass(Unknown Source)
	at java.lang.ClassLoader.loadClass(Unknown Source)
	at sun.misc.Launcher$AppClassLoader.loadClass(Unknown Source)
	at java.lang.ClassLoader.loadClass(Unknown Source)
	at org.springframework.expression.spel.support.StandardEvaluationContext.initializePropertyAccessors(StandardEvaluationContext.java:256)
	at org.springframework.expression.spel.support.StandardEvaluationContext.ensurePropertyAccessorsInitialized(StandardEvaluationContext.java:249)
	at org.springframework.expression.spel.support.StandardEvaluationContext.addPropertyAccessor(StandardEvaluationContext.java:146)
	at org.springframework.context.expression.StandardBeanExpressionResolver.evaluate(StandardBeanExpressionResolver.java:148)
	at org.springframework.beans.factory.support.AbstractBeanFactory.evaluateBeanDefinitionString(AbstractBeanFactory.java:1365)
	at org.springframework.beans.factory.support.BeanDefinitionValueResolver.doEvaluate(BeanDefinitionValueResolver.java:255)
	at org.springframework.beans.factory.support.BeanDefinitionValueResolver.resolveReference(BeanDefinitionValueResolver.java:340)
	at org.springframework.beans.factory.support.BeanDefinitionValueResolver.resolveValueIfNecessary(BeanDefinitionValueResolver.java:108)
	at org.springframework.beans.factory.support.AbstractAutowireCapableBeanFactory.applyPropertyValues(AbstractAutowireCapableBeanFactory.java:1477)
	at org.springframework.beans.factory.support.AbstractAutowireCapableBeanFactory.populateBean(AbstractAutowireCapableBeanFactory.java:1222)
	at org.springframework.beans.factory.support.AbstractAutowireCapableBeanFactory.doCreateBean(AbstractAutowireCapableBeanFactory.java:537)
	at org.springframework.beans.factory.support.AbstractAutowireCapableBeanFactory.createBean(AbstractAutowireCapableBeanFactory.java:476)
	at org.springframework.beans.factory.support.AbstractBeanFactory$1.getObject(AbstractBeanFactory.java:303)
	at org.springframework.beans.factory.support.DefaultSingletonBeanRegistry.getSingleton(DefaultSingletonBeanRegistry.java:230)
	at org.springframework.beans.factory.support.AbstractBeanFactory.doGetBean(AbstractBeanFactory.java:299)
	at org.springframework.beans.factory.support.AbstractBeanFactory.getBean(AbstractBeanFactory.java:194)
	at org.springframework.beans.factory.support.DefaultListableBeanFactory.findAutowireCandidates(DefaultListableBeanFactory.java:1120)
	at org.springframework.beans.factory.support.DefaultListableBeanFactory.doResolveDependency(DefaultListableBeanFactory.java:996)
	at org.springframework.beans.factory.support.DefaultListableBeanFactory.resolveDependency(DefaultListableBeanFactory.java:942)
	at org.springframework.beans.factory.annotation.AutowiredAnnotationBeanPostProcessor$AutowiredFieldElement.inject(AutowiredAnnotationBeanPostProcessor.java:533)
	at org.springframework.beans.factory.annotation.InjectionMetadata.inject(InjectionMetadata.java:88)
	at org.springframework.beans.factory.annotation.AutowiredAnnotationBeanPostProcessor.postProcessPropertyValues(AutowiredAnnotationBeanPostProcessor.java:331)
	at org.springframework.beans.factory.support.AbstractAutowireCapableBeanFactory.populateBean(AbstractAutowireCapableBeanFactory.java:1210)
	at org.springframework.beans.factory.support.AbstractAutowireCapableBeanFactory.doCreateBean(AbstractAutowireCapableBeanFactory.java:537)
	at org.springframework.beans.factory.support.AbstractAutowireCapableBeanFactory.createBean(AbstractAutowireCapableBeanFactory.java:476)
	at org.springframework.beans.factory.support.AbstractBeanFactory$1.getObject(AbstractBeanFactory.java:303)
	at org.springframework.beans.factory.support.DefaultSingletonBeanRegistry.getSingleton(DefaultSingletonBeanRegistry.java:230)
	at org.springframework.beans.factory.support.AbstractBeanFactory.doGetBean(AbstractBeanFactory.java:299)
	at org.springframework.beans.factory.support.AbstractBeanFactory.getBean(AbstractBeanFactory.java:194)
	at org.springframework.beans.factory.support.DefaultListableBeanFactory.preInstantiateSingletons(DefaultListableBeanFactory.java:755)
	at org.springframework.context.support.AbstractApplicationContext.finishBeanFactoryInitialization(AbstractApplicationContext.java:757)
	at org.springframework.context.support.AbstractApplicationContext.refresh(AbstractApplicationContext.java:480)
	at org.springframework.context.support.ClassPathXmlApplicationContext.<init>(ClassPathXmlApplicationContext.java:139)
	at org.springframework.context.support.ClassPathXmlApplicationContext.<init>(ClassPathXmlApplicationContext.java:93)
	at com.springExemple.presentation.Presentation2.main(Presentation2.java:13)
---- System Properties ---
java.runtime.name=Java(TM) SE Runtime Environment
sun.boot.library.path=C:\Program Files\Java\jre1.8.0_121\bin
java.vm.version=25.121-b13
java.vm.vendor=Oracle Corporation
java.vendor.url=http://java.oracle.com/
path.separator=;
java.vm.name=Java HotSpot(TM) 64-Bit Server VM
file.encoding.pkg=sun.io
user.country=FR
user.script=
sun.java.launcher=SUN_STANDARD
sun.os.patch.level=
java.vm.specification.name=Java Virtual Machine Specification
user.dir=C:\Users\formation\git\projects\SpringExpl
java.runtime.version=1.8.0_121-b13
java.awt.graphicsenv=sun.awt.Win32GraphicsEnvironment
java.endorsed.dirs=C:\Program Files\Java\jre1.8.0_121\lib\endorsed
os.arch=amd64
java.io.tmpdir=C:\Users\FORMAT~1\AppData\Local\Temp\
line.separator=

java.vm.specification.vendor=Oracle Corporation
user.variant=
os.name=Windows 10
sun.jnu.encoding=Cp1252
java.library.path=C:\Program Files\Java\jre1.8.0_121\bin;C:\windows\Sun\Java\bin;C:\windows\system32;C:\windows;C:/Program Files/Java/jre1.8.0_121/bin/server;C:/Program Files/Java/jre1.8.0_121/bin;C:/Program Files/Java/jre1.8.0_121/lib/amd64;C:\ProgramData\Oracle\Java\javapath;C:\windows\system32;C:\windows;C:\windows\System32\Wbem;C:\windows\System32\WindowsPowerShell\v1.0\;C:\Program Files\Java\jdk1.8.0_101\bin;C:\Outils\apache-maven-3.3.9\bin;C:\Users\formation\AppData\Local\Microsoft\WindowsApps;;C:\Users\formation\Desktop\JRE JDK ECLIPSE\sts-bundle\sts-3.8.3.RELEASE;;.
java.specification.name=Java Platform API Specification
java.class.version=52.0
sun.management.compiler=HotSpot 64-Bit Tiered Compilers
os.version=10.0
user.home=C:\Users\formation
user.timezone=Europe/Paris
java.awt.printerjob=sun.awt.windows.WPrinterJob
file.encoding=UTF-8
java.specification.version=1.8
java.class.path=C:\Users\formation\git\projects\SpringExpl\target\classes;C:\Users\formation\.m2\repository\org\springframework\spring-aspects\4.1.4.RELEASE\spring-aspects-4.1.4.RELEASE.jar;C:\Users\formation\.m2\repository\org\aspectj\aspectjrt\1.6.12\aspectjrt-1.6.12.jar;C:\Users\formation\.m2\repository\org\aspectj\aspectjweaver\1.6.12\aspectjweaver-1.6.12.jar;C:\Users\formation\.m2\repository\org\springframework\spring-core\4.1.6.RELEASE\spring-core-4.1.6.RELEASE.jar;C:\Users\formation\.m2\repository\commons-logging\commons-logging\1.2\commons-logging-1.2.jar;C:\Users\formation\.m2\repository\org\springframework\spring-context\4.1.6.RELEASE\spring-context-4.1.6.RELEASE.jar;C:\Users\formation\.m2\repository\org\springframework\spring-aop\4.1.6.RELEASE\spring-aop-4.1.6.RELEASE.jar;C:\Users\formation\.m2\repository\aopalliance\aopalliance\1.0\aopalliance-1.0.jar;C:\Users\formation\.m2\repository\org\springframework\spring-beans\4.1.6.RELEASE\spring-beans-4.1.6.RELEASE.jar;C:\Users\formation\.m2\repository\org\springframework\spring-expression\4.1.6.RELEASE\spring-expression-4.1.6.RELEASE.jar;C:\Users\formation\Desktop\spring-agent-2.5.6.jar
user.name=formation
java.vm.specification.version=1.8
sun.java.command=com.springExemple.presentation.Presentation2
java.home=C:\Program Files\Java\jre1.8.0_121
sun.arch.data.model=64
user.language=fr
java.specification.vendor=Oracle Corporation
awt.toolkit=sun.awt.windows.WToolkit
java.vm.info=mixed mode
java.version=1.8.0_121
java.ext.dirs=C:\Program Files\Java\jre1.8.0_121\lib\ext;C:\windows\Sun\Java\lib\ext
sun.boot.class.path=C:\Program Files\Java\jre1.8.0_121\lib\resources.jar;C:\Program Files\Java\jre1.8.0_121\lib\rt.jar;C:\Program Files\Java\jre1.8.0_121\lib\sunrsasign.jar;C:\Program Files\Java\jre1.8.0_121\lib\jsse.jar;C:\Program Files\Java\jre1.8.0_121\lib\jce.jar;C:\Program Files\Java\jre1.8.0_121\lib\charsets.jar;C:\Program Files\Java\jre1.8.0_121\lib\jfr.jar;C:\Program Files\Java\jre1.8.0_121\classes
java.vendor=Oracle Corporation
file.separator=\
java.vendor.url.bug=http://bugreport.sun.com/bugreport/
sun.io.unicode.encoding=UnicodeLittle
sun.cpu.endian=little
sun.desktop=windows
sun.cpu.isalist=amd64
---- Command Line ---
Empty
---- Full Classpath ---
Empty
---- Compiler Messages ---
Empty
