---- AspectJ Properties ---
AspectJ Compiler 1.6.12 built on Tuesday Oct 18, 2011 at 17:52:06 GMT
---- Dump Properties ---
Dump file: ajcore.20170412.120240.364.txt
Dump reason: abort
Dump on exception: true
Dump at exit condition: abort
---- System Properties ---
java.runtime.name=Java(TM) SE Runtime Environment
sun.boot.library.path=C:\Program Files\Java\jre1.8.0_121\bin
java.vm.version=25.121-b13
java.vm.vendor=Oracle Corporation
java.vendor.url=http://java.oracle.com/
path.separator=;
java.vm.name=Java HotSpot(TM) 64-Bit Server VM
file.encoding.pkg=sun.io
user.country=FR
user.script=
sun.java.launcher=SUN_STANDARD
sun.os.patch.level=
java.vm.specification.name=Java Virtual Machine Specification
user.dir=C:\Users\formation\git\projects\SpringExpl
java.runtime.version=1.8.0_121-b13
java.awt.graphicsenv=sun.awt.Win32GraphicsEnvironment
java.endorsed.dirs=C:\Program Files\Java\jre1.8.0_121\lib\endorsed
os.arch=amd64
java.io.tmpdir=C:\Users\FORMAT~1\AppData\Local\Temp\
line.separator=

java.vm.specification.vendor=Oracle Corporation
user.variant=
os.name=Windows 10
sun.jnu.encoding=Cp1252
java.library.path=C:\Program Files\Java\jre1.8.0_121\bin;C:\windows\Sun\Java\bin;C:\windows\system32;C:\windows;C:/Program Files/Java/jre1.8.0_121/bin/server;C:/Program Files/Java/jre1.8.0_121/bin;C:/Program Files/Java/jre1.8.0_121/lib/amd64;C:\ProgramData\Oracle\Java\javapath;C:\windows\system32;C:\windows;C:\windows\System32\Wbem;C:\windows\System32\WindowsPowerShell\v1.0\;C:\Program Files\Java\jdk1.8.0_101\bin;C:\Outils\apache-maven-3.3.9\bin;C:\Users\formation\AppData\Local\Microsoft\WindowsApps;;C:\Users\formation\Desktop\JRE JDK ECLIPSE\sts-bundle\sts-3.8.3.RELEASE;;.
java.specification.name=Java Platform API Specification
java.class.version=52.0
sun.management.compiler=HotSpot 64-Bit Tiered Compilers
os.version=10.0
user.home=C:\Users\formation
user.timezone=Europe/Paris
java.awt.printerjob=sun.awt.windows.WPrinterJob
file.encoding=UTF-8
java.specification.version=1.8
java.class.path=C:\Users\formation\git\projects\SpringExpl\target\classes;C:\Users\formation\.m2\repository\org\springframework\spring-aspects\4.1.4.RELEASE\spring-aspects-4.1.4.RELEASE.jar;C:\Users\formation\.m2\repository\org\aspectj\aspectjrt\1.6.12\aspectjrt-1.6.12.jar;C:\Users\formation\.m2\repository\org\aspectj\aspectjweaver\1.6.12\aspectjweaver-1.6.12.jar;C:\Users\formation\.m2\repository\org\springframework\spring-core\4.1.6.RELEASE\spring-core-4.1.6.RELEASE.jar;C:\Users\formation\.m2\repository\commons-logging\commons-logging\1.2\commons-logging-1.2.jar;C:\Users\formation\.m2\repository\org\springframework\spring-context\4.1.6.RELEASE\spring-context-4.1.6.RELEASE.jar;C:\Users\formation\.m2\repository\org\springframework\spring-aop\4.1.6.RELEASE\spring-aop-4.1.6.RELEASE.jar;C:\Users\formation\.m2\repository\aopalliance\aopalliance\1.0\aopalliance-1.0.jar;C:\Users\formation\.m2\repository\org\springframework\spring-beans\4.1.6.RELEASE\spring-beans-4.1.6.RELEASE.jar;C:\Users\formation\.m2\repository\org\springframework\spring-expression\4.1.6.RELEASE\spring-expression-4.1.6.RELEASE.jar;C:\Users\formation\Desktop\spring-agent-2.5.6.jar
user.name=formation
java.vm.specification.version=1.8
sun.java.command=com.springExemple.presentation.Presentation2
java.home=C:\Program Files\Java\jre1.8.0_121
sun.arch.data.model=64
user.language=fr
java.specification.vendor=Oracle Corporation
awt.toolkit=sun.awt.windows.WToolkit
java.vm.info=mixed mode
java.version=1.8.0_121
java.ext.dirs=C:\Program Files\Java\jre1.8.0_121\lib\ext;C:\windows\Sun\Java\lib\ext
sun.boot.class.path=C:\Program Files\Java\jre1.8.0_121\lib\resources.jar;C:\Program Files\Java\jre1.8.0_121\lib\rt.jar;C:\Program Files\Java\jre1.8.0_121\lib\sunrsasign.jar;C:\Program Files\Java\jre1.8.0_121\lib\jsse.jar;C:\Program Files\Java\jre1.8.0_121\lib\jce.jar;C:\Program Files\Java\jre1.8.0_121\lib\charsets.jar;C:\Program Files\Java\jre1.8.0_121\lib\jfr.jar;C:\Program Files\Java\jre1.8.0_121\classes
java.vendor=Oracle Corporation
file.separator=\
java.vendor.url.bug=http://bugreport.sun.com/bugreport/
sun.io.unicode.encoding=UnicodeLittle
sun.cpu.endian=little
sun.desktop=windows
sun.cpu.isalist=amd64
---- Command Line ---
Empty
---- Full Classpath ---
Empty
---- Compiler Messages ---
info AspectJ Weaver Version 1.6.12 built on Tuesday Oct 18, 2011 at 17:52:06 GMT
info register classloader sun.misc.Launcher$AppClassLoader@18b4aac2
info using configuration file:/C:/Users/formation/.m2/repository/org/springframework/spring-aspects/4.1.4.RELEASE/spring-aspects-4.1.4.RELEASE.jar!/META-INF/aop.xml
error can't determine annotations of missing type org.springframework.transaction.annotation.Transactional
when weaving type org.springframework.beans.factory.support.AutowireUtils
when weaving classes 
when weaving 
 [Xlint:cantFindType]
abort trouble in: 
abstract class org.springframework.beans.factory.support.AutowireUtils extends java.lang.Object:
  void <init>():
                    ALOAD_0     // Lorg/springframework/beans/factory/support/AutowireUtils; this   (line 50)
                    INVOKESPECIAL java.lang.Object.<init> ()V
    constructor-execution(void org.springframework.beans.factory.support.AutowireUtils.<init>())
    |               RETURN   (line 283)
    constructor-execution(void org.springframework.beans.factory.support.AutowireUtils.<init>())
  end void <init>()

  public static void sortConstructors(java.lang.reflect.Constructor[]):
                    ALOAD_0     // [Ljava/lang/reflect/Constructor; constructors   (line 60)
                    NEW org.springframework.beans.factory.support.AutowireUtils$1
                    DUP
                    INVOKESPECIAL org.springframework.beans.factory.support.AutowireUtils$1.<init> ()V
                    INVOKESTATIC java.util.Arrays.sort ([Ljava/lang/Object;Ljava/util/Comparator;)V
                    RETURN   (line 73)
  end public static void sortConstructors(java.lang.reflect.Constructor[])

  public static void sortFactoryMethods(java.lang.reflect.Method[]):
                    ALOAD_0     // [Ljava/lang/reflect/Method; factoryMethods   (line 83)
                    NEW org.springframework.beans.factory.support.AutowireUtils$2
                    DUP
                    INVOKESPECIAL org.springframework.beans.factory.support.AutowireUtils$2.<init> ()V
                    INVOKESTATIC java.util.Arrays.sort ([Ljava/lang/Object;Ljava/util/Comparator;)V
                    RETURN   (line 96)
  end public static void sortFactoryMethods(java.lang.reflect.Method[])

  public static boolean isExcludedFromDependencyCheck(java.beans.PropertyDescriptor):
                    ALOAD_0     // Ljava/beans/PropertyDescriptor; pd   (line 105)
                    INVOKEVIRTUAL java.beans.PropertyDescriptor.getWriteMethod ()Ljava/lang/reflect/Method;
                    ASTORE_1
                    ALOAD_1     // Ljava/lang/reflect/Method; wm   (line 106)
                    IFNONNULL L0
                    ICONST_0   (line 107)
                    IRETURN
                L0: ALOAD_1     // Ljava/lang/reflect/Method; wm   (line 109)
                    INVOKEVIRTUAL java.lang.reflect.Method.getDeclaringClass ()Ljava/lang/Class;
                    INVOKEVIRTUAL java.lang.Class.getName ()Ljava/lang/String;
                    LDC "$$"
                    INVOKEVIRTUAL java.lang.String.contains (Ljava/lang/CharSequence;)Z
                    IFNE L1
                    ICONST_0   (line 111)
                    IRETURN
                L1: ALOAD_1     // Ljava/lang/reflect/Method; wm   (line 115)
                    INVOKEVIRTUAL java.lang.reflect.Method.getDeclaringClass ()Ljava/lang/Class;
                    INVOKEVIRTUAL java.lang.Class.getSuperclass ()Ljava/lang/Class;
                    ASTORE_2
                    ALOAD_2     // Ljava/lang/Class; superclass   (line 116)
                    ALOAD_1     // Ljava/lang/reflect/Method; wm
                    INVOKEVIRTUAL java.lang.reflect.Method.getName ()Ljava/lang/String;
                    ALOAD_1     // Ljava/lang/reflect/Method; wm
                    INVOKEVIRTUAL java.lang.reflect.Method.getParameterTypes ()[Ljava/lang/Class;
                    INVOKESTATIC org.springframework.util.ClassUtils.hasMethod (Ljava/lang/Class;Ljava/lang/String;[Ljava/lang/Class;)Z
                    IFNE L2
                    ICONST_1
                    GOTO L3
                L2: ICONST_0
                L3: IRETURN
  end public static boolean isExcludedFromDependencyCheck(java.beans.PropertyDescriptor)

  public static boolean isSetterDefinedInInterface(java.beans.PropertyDescriptor, java.util.Set):
                    ALOAD_0     // Ljava/beans/PropertyDescriptor; pd   (line 127)
                    INVOKEVIRTUAL java.beans.PropertyDescriptor.getWriteMethod ()Ljava/lang/reflect/Method;
                    ASTORE_2
                    ALOAD_2     // Ljava/lang/reflect/Method; setter   (line 128)
                    IFNULL L2
                    ALOAD_2     // Ljava/lang/reflect/Method; setter   (line 129)
                    INVOKEVIRTUAL java.lang.reflect.Method.getDeclaringClass ()Ljava/lang/Class;
                    ASTORE_3
                    ALOAD_1     // Ljava/util/Set; interfaces   (line 130)
                    INVOKEINTERFACE java.util.Set.iterator ()Ljava/util/Iterator;
                    ASTORE 4
                L0: ALOAD 4
                    INVOKEINTERFACE java.util.Iterator.hasNext ()Z
                    IFEQ L2
                    ALOAD 4
                    INVOKEINTERFACE java.util.Iterator.next ()Ljava/lang/Object;
                    CHECKCAST java.lang.Class
                    ASTORE 5
                    ALOAD 5     // Ljava/lang/Class; ifc   (line 131)
                    ALOAD_3     // Ljava/lang/Class; targetClass
                    INVOKEVIRTUAL java.lang.Class.isAssignableFrom (Ljava/lang/Class;)Z
                    IFEQ L1
                    ALOAD 5     // Ljava/lang/Class; ifc
                    ALOAD_2     // Ljava/lang/reflect/Method; setter
                    INVOKEVIRTUAL java.lang.reflect.Method.getName ()Ljava/lang/String;   (line 132)
                    ALOAD_2     // Ljava/lang/reflect/Method; setter
                    INVOKEVIRTUAL java.lang.reflect.Method.getParameterTypes ()[Ljava/lang/Class;
                    INVOKESTATIC org.springframework.util.ClassUtils.hasMethod (Ljava/lang/Class;Ljava/lang/String;[Ljava/lang/Class;)Z
                    IFEQ L1
                    ICONST_1   (line 133)
                    IRETURN
                L1: GOTO L0   (line 135)
                L2: ICONST_0   (line 137)
                    IRETURN
  end public static boolean isSetterDefinedInInterface(java.beans.PropertyDescriptor, java.util.Set)

  public static Object resolveAutowiringValue(Object, Class):
                    ALOAD_0     // Ljava/lang/Object; autowiringValue   (line 148)
                    INSTANCEOF org.springframework.beans.factory.ObjectFactory
                    IFEQ L1
                    ALOAD_1     // Ljava/lang/Class; requiredType
                    ALOAD_0     // Ljava/lang/Object; autowiringValue
                    INVOKEVIRTUAL java.lang.Class.isInstance (Ljava/lang/Object;)Z
                    IFNE L1
                    ALOAD_0     // Ljava/lang/Object; autowiringValue   (line 149)
                    CHECKCAST org.springframework.beans.factory.ObjectFactory
                    ASTORE_2
                    ALOAD_0     // Ljava/lang/Object; autowiringValue   (line 150)
                    INSTANCEOF java.io.Serializable
                    IFEQ L0
                    ALOAD_1     // Ljava/lang/Class; requiredType
                    INVOKEVIRTUAL java.lang.Class.isInterface ()Z
                    IFEQ L0
                    ALOAD_1     // Ljava/lang/Class; requiredType   (line 151)
                    INVOKEVIRTUAL java.lang.Class.getClassLoader ()Ljava/lang/ClassLoader;
                    ICONST_1
                    ANEWARRAY java.lang.Class
                    DUP
                    ICONST_0
                    ALOAD_1     // Ljava/lang/Class; requiredType
                    AASTORE
                    NEW org.springframework.beans.factory.support.AutowireUtils$ObjectFactoryDelegatingInvocationHandler
                    DUP
                    ALOAD_2     // Lorg/springframework/beans/factory/ObjectFactory; factory
                    INVOKESPECIAL org.springframework.beans.factory.support.AutowireUtils$ObjectFactoryDelegatingInvocationHandler.<init> (Lorg/springframework/beans/factory/ObjectFactory;)V
                    INVOKESTATIC java.lang.reflect.Proxy.newProxyInstance (Ljava/lang/ClassLoader;[Ljava/lang/Class;Ljava/lang/reflect/InvocationHandler;)Ljava/lang/Object;
                    ASTORE_0     // Ljava/lang/Object; autowiringValue
                    GOTO L1
                L0: ALOAD_2     // Lorg/springframework/beans/factory/ObjectFactory; factory   (line 155)
                    INVOKEINTERFACE org.springframework.beans.factory.ObjectFactory.getObject ()Ljava/lang/Object;
                    ARETURN
                L1: ALOAD_0     // Ljava/lang/Object; autowiringValue   (line 158)
                    ARETURN
  end public static Object resolveAutowiringValue(Object, Class)

  public static Class resolveReturnTypeForFactoryMethod(java.lang.reflect.Method, Object[], ClassLoader):
                    ALOAD_0     // Ljava/lang/reflect/Method; method   (line 193)
                    LDC "Method must not be null"
                    INVOKESTATIC org.springframework.util.Assert.notNull (Ljava/lang/Object;Ljava/lang/String;)V
                    ALOAD_1     // [Ljava/lang/Object; args   (line 194)
                    LDC "Argument array must not be null"
                    INVOKESTATIC org.springframework.util.Assert.notNull (Ljava/lang/Object;Ljava/lang/String;)V
                    ALOAD_2     // Ljava/lang/ClassLoader; classLoader   (line 195)
                    LDC "ClassLoader must not be null"
                    INVOKESTATIC org.springframework.util.Assert.notNull (Ljava/lang/Object;Ljava/lang/String;)V
                    ALOAD_0     // Ljava/lang/reflect/Method; method   (line 197)
                    INVOKEVIRTUAL java.lang.reflect.Method.getTypeParameters ()[Ljava/lang/reflect/TypeVariable;
                    ASTORE_3
                    ALOAD_0     // Ljava/lang/reflect/Method; method   (line 198)
                    INVOKEVIRTUAL java.lang.reflect.Method.getGenericReturnType ()Ljava/lang/reflect/Type;
                    ASTORE 4
                    ALOAD_0     // Ljava/lang/reflect/Method; method   (line 199)
                    INVOKEVIRTUAL java.lang.reflect.Method.getGenericParameterTypes ()[Ljava/lang/reflect/Type;
                    ASTORE 5
                    ALOAD_1     // [Ljava/lang/Object; args   (line 200)
                    ARRAYLENGTH
                    ALOAD 5     // [Ljava/lang/reflect/Type; methodParameterTypes
                    ARRAYLENGTH
                    IF_ICMPNE L0
                    ICONST_1
                    GOTO L1
                L0: ICONST_0
                L1: LDC "Argument array does not match parameter count"
                    INVOKESTATIC org.springframework.util.Assert.isTrue (ZLjava/lang/String;)V
                    ICONST_0   (line 204)
                    ISTORE 6
                    ALOAD_3     // [Ljava/lang/reflect/TypeVariable; declaredTypeVariables   (line 205)
                    ASTORE 7
                    ALOAD 7
                    ARRAYLENGTH
                    ISTORE 8
                    ICONST_0
                    ISTORE 9
                L2: ILOAD 9
                    ILOAD 8
                    IF_ICMPGE L4
                    ALOAD 7
                    ILOAD 9
                    AALOAD
                    ASTORE 10
                    ALOAD 10     // Ljava/lang/reflect/TypeVariable; currentTypeVariable   (line 206)
                    ALOAD 4     // Ljava/lang/reflect/Type; genericReturnType
                    INVOKEVIRTUAL java.lang.Object.equals (Ljava/lang/Object;)Z
                    IFEQ L3
                    ICONST_1   (line 207)
                    ISTORE 6     // Z locallyDeclaredTypeVariableMatchesReturnType
                    GOTO L4   (line 208)
                L3: IINC 9 1   (line 205)
                    GOTO L2
                L4: ILOAD 6     // Z locallyDeclaredTypeVariableMatchesReturnType   (line 212)
                    IFEQ L18
                    ICONST_0   (line 213)
                    ISTORE 7
                L5: ILOAD 7     // I i
                    ALOAD 5     // [Ljava/lang/reflect/Type; methodParameterTypes
                    ARRAYLENGTH
                    IF_ICMPGE L18
                    ALOAD 5     // [Ljava/lang/reflect/Type; methodParameterTypes   (line 214)
                    ILOAD 7     // I i
                    AALOAD
                    ASTORE 8
                    ALOAD_1     // [Ljava/lang/Object; args   (line 215)
                    ILOAD 7     // I i
                    AALOAD
                    ASTORE 9
                    ALOAD 8     // Ljava/lang/reflect/Type; methodParameterType   (line 216)
                    ALOAD 4     // Ljava/lang/reflect/Type; genericReturnType
                    INVOKEVIRTUAL java.lang.Object.equals (Ljava/lang/Object;)Z
                    IFEQ L9
                    ALOAD 9     // Ljava/lang/Object; arg   (line 217)
                    INSTANCEOF org.springframework.beans.factory.config.TypedStringValue
                    IFEQ L7
                    ALOAD 9     // Ljava/lang/Object; arg   (line 218)
                    CHECKCAST org.springframework.beans.factory.config.TypedStringValue
                    ASTORE 10
                    ALOAD 10     // Lorg/springframework/beans/factory/config/TypedStringValue; typedValue   (line 219)
                    INVOKEVIRTUAL org.springframework.beans.factory.config.TypedStringValue.hasTargetType ()Z
                    IFEQ L6
                    ALOAD 10     // Lorg/springframework/beans/factory/config/TypedStringValue; typedValue   (line 220)
                    INVOKEVIRTUAL org.springframework.beans.factory.config.TypedStringValue.getTargetType ()Ljava/lang/Class;
                    ARETURN
    catch java.lang.ClassNotFoundException -> E0
    |           L6: ALOAD 10     // Lorg/springframework/beans/factory/config/TypedStringValue; typedValue   (line 223)
    |               ALOAD_2     // Ljava/lang/ClassLoader; classLoader
    |               INVOKEVIRTUAL org.springframework.beans.factory.config.TypedStringValue.resolveTargetType (Ljava/lang/ClassLoader;)Ljava/lang/Class;
    catch java.lang.ClassNotFoundException -> E0
                    ARETURN
                E0: ASTORE 11   (line 225)
                    NEW java.lang.IllegalStateException   (line 226)
                    DUP
                    NEW java.lang.StringBuilder
                    DUP
                    INVOKESPECIAL java.lang.StringBuilder.<init> ()V
                    LDC "Failed to resolve value type ["
                    INVOKEVIRTUAL java.lang.StringBuilder.append (Ljava/lang/String;)Ljava/lang/StringBuilder;
                    ALOAD 10     // Lorg/springframework/beans/factory/config/TypedStringValue; typedValue
                    INVOKEVIRTUAL org.springframework.beans.factory.config.TypedStringValue.getTargetTypeName ()Ljava/lang/String;   (line 227)
                    INVOKEVIRTUAL java.lang.StringBuilder.append (Ljava/lang/String;)Ljava/lang/StringBuilder;
                    LDC "] for factory method argument"
                    INVOKEVIRTUAL java.lang.StringBuilder.append (Ljava/lang/String;)Ljava/lang/StringBuilder;
                    INVOKEVIRTUAL java.lang.StringBuilder.toString ()Ljava/lang/String;
                    ALOAD 11     // Ljava/lang/ClassNotFoundException; ex
                    INVOKESPECIAL java.lang.IllegalStateException.<init> (Ljava/lang/String;Ljava/lang/Throwable;)V
                    ATHROW
                L7: ALOAD 9     // Ljava/lang/Object; arg   (line 231)
                    IFNULL L8
                    ALOAD 9     // Ljava/lang/Object; arg
                    INSTANCEOF org.springframework.beans.BeanMetadataElement
                    IFNE L8
                    ALOAD 9     // Ljava/lang/Object; arg   (line 232)
                    INVOKEVIRTUAL java.lang.Object.getClass ()Ljava/lang/Class;
                    ARETURN
                L8: ALOAD_0     // Ljava/lang/reflect/Method; method   (line 234)
                    INVOKEVIRTUAL java.lang.reflect.Method.getReturnType ()Ljava/lang/Class;
                    ARETURN
                L9: ALOAD 8     // Ljava/lang/reflect/Type; methodParameterType   (line 236)
                    INSTANCEOF java.lang.reflect.ParameterizedType
                    IFEQ L17
                    ALOAD 8     // Ljava/lang/reflect/Type; methodParameterType   (line 237)
                    CHECKCAST java.lang.reflect.ParameterizedType
                    ASTORE 10
                    ALOAD 10     // Ljava/lang/reflect/ParameterizedType; parameterizedType   (line 238)
                    INVOKEINTERFACE java.lang.reflect.ParameterizedType.getActualTypeArguments ()[Ljava/lang/reflect/Type;
                    ASTORE 11
                    ALOAD 11     // [Ljava/lang/reflect/Type; actualTypeArguments   (line 239)
                    ASTORE 12
                    ALOAD 12
                    ARRAYLENGTH
                    ISTORE 13
                    ICONST_0
                    ISTORE 14
               L10: ILOAD 14
                    ILOAD 13
                    IF_ICMPGE L17
                    ALOAD 12
                    ILOAD 14
                    AALOAD
                    ASTORE 15
                    ALOAD 15     // Ljava/lang/reflect/Type; typeArg   (line 240)
                    ALOAD 4     // Ljava/lang/reflect/Type; genericReturnType
                    INVOKEVIRTUAL java.lang.Object.equals (Ljava/lang/Object;)Z
                    IFEQ L16
                    ALOAD 9     // Ljava/lang/Object; arg   (line 241)
                    INSTANCEOF java.lang.Class
                    IFEQ L11
                    ALOAD 9     // Ljava/lang/Object; arg   (line 242)
                    CHECKCAST java.lang.Class
                    ARETURN
               L11: ACONST_NULL   (line 245)
                    ASTORE 16
                    ALOAD 9     // Ljava/lang/Object; arg   (line 246)
                    INSTANCEOF java.lang.String
                    IFEQ L12
                    ALOAD 9     // Ljava/lang/Object; arg   (line 247)
                    CHECKCAST java.lang.String
                    ASTORE 16     // Ljava/lang/String; className
                    GOTO L14
               L12: ALOAD 9     // Ljava/lang/Object; arg   (line 249)
                    INSTANCEOF org.springframework.beans.factory.config.TypedStringValue
                    IFEQ L14
                    ALOAD 9     // Ljava/lang/Object; arg   (line 250)
                    CHECKCAST org.springframework.beans.factory.config.TypedStringValue
                    ASTORE 17
                    ALOAD 17     // Lorg/springframework/beans/factory/config/TypedStringValue; typedValue   (line 251)
                    INVOKEVIRTUAL org.springframework.beans.factory.config.TypedStringValue.getTargetTypeName ()Ljava/lang/String;
                    ASTORE 18
                    ALOAD 18     // Ljava/lang/String; targetTypeName   (line 252)
                    IFNULL L13
                    LDC java.lang.Class
                    INVOKEVIRTUAL java.lang.Class.getName ()Ljava/lang/String;
                    ALOAD 18     // Ljava/lang/String; targetTypeName
                    INVOKEVIRTUAL java.lang.String.equals (Ljava/lang/Object;)Z
                    IFEQ L14
               L13: ALOAD 17     // Lorg/springframework/beans/factory/config/TypedStringValue; typedValue   (line 253)
                    INVOKEVIRTUAL org.springframework.beans.factory.config.TypedStringValue.getValue ()Ljava/lang/String;
                    ASTORE 16     // Ljava/lang/String; className
               L14: ALOAD 16     // Ljava/lang/String; className   (line 256)
                    IFNULL L15
    catch java.lang.ClassNotFoundException -> E1
    |               ALOAD 16     // Ljava/lang/String; className   (line 258)
    |               ALOAD_2     // Ljava/lang/ClassLoader; classLoader
    |               INVOKESTATIC org.springframework.util.ClassUtils.forName (Ljava/lang/String;Ljava/lang/ClassLoader;)Ljava/lang/Class;
    catch java.lang.ClassNotFoundException -> E1
                    ARETURN
                E1: ASTORE 17   (line 260)
                    NEW java.lang.IllegalStateException   (line 261)
                    DUP
                    NEW java.lang.StringBuilder
                    DUP
                    INVOKESPECIAL java.lang.StringBuilder.<init> ()V
                    LDC "Could not resolve class name ["
                    INVOKEVIRTUAL java.lang.StringBuilder.append (Ljava/lang/String;)Ljava/lang/StringBuilder;
                    ALOAD 9     // Ljava/lang/Object; arg
                    INVOKEVIRTUAL java.lang.StringBuilder.append (Ljava/lang/Object;)Ljava/lang/StringBuilder;
                    LDC "] for factory method argument"
                    INVOKEVIRTUAL java.lang.StringBuilder.append (Ljava/lang/String;)Ljava/lang/StringBuilder;
                    INVOKEVIRTUAL java.lang.StringBuilder.toString ()Ljava/lang/String;
                    ALOAD 17     // Ljava/lang/ClassNotFoundException; ex
                    INVOKESPECIAL java.lang.IllegalStateException.<init> (Ljava/lang/String;Ljava/lang/Throwable;)V
                    ATHROW
               L15: ALOAD_0     // Ljava/lang/reflect/Method; method   (line 267)
                    INVOKEVIRTUAL java.lang.reflect.Method.getReturnType ()Ljava/lang/Class;
                    ARETURN
               L16: IINC 14 1   (line 239)
                    GOTO L10
               L17: IINC 7 1     // I i   (line 213)
                    GOTO L5
               L18: ALOAD_0     // Ljava/lang/reflect/Method; method   (line 276)
                    INVOKEVIRTUAL java.lang.reflect.Method.getReturnType ()Ljava/lang/Class;
                    ARETURN
  end public static Class resolveReturnTypeForFactoryMethod(java.lang.reflect.Method, Object[], ClassLoader)

end abstract class org.springframework.beans.factory.support.AutowireUtils
 -- (ClassFormatException) File: 'java.lang.reflect.AnnotatedElement': Invalid byte tag in constant pool: 15
File: 'java.lang.reflect.AnnotatedElement': Invalid byte tag in constant pool: 15
org.aspectj.apache.bcel.classfile.ClassFormatException: File: 'java.lang.reflect.AnnotatedElement': Invalid byte tag in constant pool: 15
	at org.aspectj.apache.bcel.classfile.ClassParser.readConstantPool(ClassParser.java:192)
	at org.aspectj.apache.bcel.classfile.ClassParser.parse(ClassParser.java:131)
	at org.aspectj.apache.bcel.util.ClassLoaderRepository.loadClass(ClassLoaderRepository.java:323)
	at org.aspectj.weaver.bcel.BcelWorld.lookupJavaClass(BcelWorld.java:402)
	at org.aspectj.weaver.bcel.BcelWorld.resolveDelegate(BcelWorld.java:376)
	at org.aspectj.weaver.ltw.LTWWorld.resolveDelegate(LTWWorld.java:107)
	at org.aspectj.weaver.World.resolveToReferenceType(World.java:485)
	at org.aspectj.weaver.World.resolve(World.java:326)
	at org.aspectj.weaver.World.resolve(World.java:236)
	at org.aspectj.weaver.bcel.BcelGenericSignatureToTypeXConverter.classTypeSignature2TypeX(BcelGenericSignatureToTypeXConverter.java:97)
	at org.aspectj.weaver.bcel.BcelGenericSignatureToTypeXConverter.classTypeSignature2TypeX(BcelGenericSignatureToTypeXConverter.java:41)
	at org.aspectj.weaver.bcel.BcelObjectType.ensureGenericSignatureUnpacked(BcelObjectType.java:810)
	at org.aspectj.weaver.bcel.BcelObjectType.getDeclaredInterfaces(BcelObjectType.java:257)
	at org.aspectj.weaver.ReferenceType.getDeclaredInterfaces(ReferenceType.java:626)
	at org.aspectj.weaver.ResolvedType.getDirectSupertypes(ResolvedType.java:82)
	at org.aspectj.weaver.patterns.TypePattern.matchesSubtypes(TypePattern.java:178)
	at org.aspectj.weaver.patterns.ExactTypePattern.matchesSubtypes(ExactTypePattern.java:74)
	at org.aspectj.weaver.patterns.TypePattern.matchesStatically(TypePattern.java:130)
	at org.aspectj.weaver.patterns.OrTypePattern.matchesStatically(OrTypePattern.java:76)
	at org.aspectj.weaver.patterns.SignaturePattern.matchesExactlyMethod(SignaturePattern.java:505)
	at org.aspectj.weaver.patterns.SignaturePattern.matchesExactly(SignaturePattern.java:360)
	at org.aspectj.weaver.patterns.SignaturePattern.matches(SignaturePattern.java:320)
	at org.aspectj.weaver.patterns.KindedPointcut.matchInternal(KindedPointcut.java:202)
	at org.aspectj.weaver.patterns.Pointcut.match(Pointcut.java:137)
	at org.aspectj.weaver.patterns.AndPointcut.matchInternal(AndPointcut.java:51)
	at org.aspectj.weaver.patterns.Pointcut.match(Pointcut.java:137)
	at org.aspectj.weaver.patterns.OrPointcut.matchInternal(OrPointcut.java:54)
	at org.aspectj.weaver.patterns.Pointcut.match(Pointcut.java:137)
	at org.aspectj.weaver.ShadowMunger.match(ShadowMunger.java:113)
	at org.aspectj.weaver.Advice.match(Advice.java:109)
	at org.aspectj.weaver.bcel.BcelAdvice.match(BcelAdvice.java:149)
	at org.aspectj.weaver.bcel.BcelClassWeaver.match(BcelClassWeaver.java:3173)
	at org.aspectj.weaver.bcel.BcelClassWeaver.match(BcelClassWeaver.java:2565)
	at org.aspectj.weaver.bcel.BcelClassWeaver.weave(BcelClassWeaver.java:480)
	at org.aspectj.weaver.bcel.BcelClassWeaver.weave(BcelClassWeaver.java:99)
	at org.aspectj.weaver.bcel.BcelWeaver.weave(BcelWeaver.java:1694)
	at org.aspectj.weaver.bcel.BcelWeaver.weaveWithoutDump(BcelWeaver.java:1638)
	at org.aspectj.weaver.bcel.BcelWeaver.weaveAndNotify(BcelWeaver.java:1401)
	at org.aspectj.weaver.bcel.BcelWeaver.weave(BcelWeaver.java:1187)
	at org.aspectj.weaver.tools.WeavingAdaptor.getWovenBytes(WeavingAdaptor.java:472)
	at org.aspectj.weaver.tools.WeavingAdaptor.weaveClass(WeavingAdaptor.java:323)
	at org.aspectj.weaver.loadtime.Aj.preProcess(Aj.java:99)
	at org.aspectj.weaver.loadtime.ClassPreProcessorAgentAdapter.transform(ClassPreProcessorAgentAdapter.java:54)
	at org.springframework.context.weaving.AspectJWeavingEnabler$AspectJClassBypassingClassFileTransformer.transform(AspectJWeavingEnabler.java:108)
	at org.springframework.instrument.classloading.InstrumentationLoadTimeWeaver$FilteringClassFileTransformer.transform(InstrumentationLoadTimeWeaver.java:184)
	at sun.instrument.TransformerManager.transform(Unknown Source)
	at sun.instrument.InstrumentationImpl.transform(Unknown Source)
	at java.lang.ClassLoader.defineClass1(Native Method)
	at java.lang.ClassLoader.defineClass(Unknown Source)
	at java.security.SecureClassLoader.defineClass(Unknown Source)
	at java.net.URLClassLoader.defineClass(Unknown Source)
	at java.net.URLClassLoader.access$100(Unknown Source)
	at java.net.URLClassLoader$1.run(Unknown Source)
	at java.net.URLClassLoader$1.run(Unknown Source)
	at java.security.AccessController.doPrivileged(Native Method)
	at java.net.URLClassLoader.findClass(Unknown Source)
	at java.lang.ClassLoader.loadClass(Unknown Source)
	at sun.misc.Launcher$AppClassLoader.loadClass(Unknown Source)
	at java.lang.ClassLoader.loadClass(Unknown Source)
	at org.springframework.beans.factory.support.ConstructorResolver.instantiateUsingFactoryMethod(ConstructorResolver.java:428)
	at org.springframework.beans.factory.support.AbstractAutowireCapableBeanFactory.instantiateUsingFactoryMethod(AbstractAutowireCapableBeanFactory.java:1119)
	at org.springframework.beans.factory.support.AbstractAutowireCapableBeanFactory.createBeanInstance(AbstractAutowireCapableBeanFactory.java:1014)
	at org.springframework.beans.factory.support.AbstractAutowireCapableBeanFactory.doCreateBean(AbstractAutowireCapableBeanFactory.java:504)
	at org.springframework.beans.factory.support.AbstractAutowireCapableBeanFactory.createBean(AbstractAutowireCapableBeanFactory.java:476)
	at org.springframework.beans.factory.support.AbstractBeanFactory$1.getObject(AbstractBeanFactory.java:303)
	at org.springframework.beans.factory.support.DefaultSingletonBeanRegistry.getSingleton(DefaultSingletonBeanRegistry.java:230)
	at org.springframework.beans.factory.support.AbstractBeanFactory.doGetBean(AbstractBeanFactory.java:299)
	at org.springframework.beans.factory.support.AbstractBeanFactory.getBean(AbstractBeanFactory.java:194)
	at org.springframework.beans.factory.support.DefaultListableBeanFactory.preInstantiateSingletons(DefaultListableBeanFactory.java:755)
	at org.springframework.context.support.AbstractApplicationContext.finishBeanFactoryInitialization(AbstractApplicationContext.java:757)
	at org.springframework.context.support.AbstractApplicationContext.refresh(AbstractApplicationContext.java:480)
	at org.springframework.context.support.ClassPathXmlApplicationContext.<init>(ClassPathXmlApplicationContext.java:139)
	at org.springframework.context.support.ClassPathXmlApplicationContext.<init>(ClassPathXmlApplicationContext.java:93)
	at com.springExemple.presentation.Presentation2.main(Presentation2.java:13)

error can't determine annotations of missing type org.springframework.transaction.annotation.Transactional
when weaving type org.springframework.beans.factory.support.BeanDefinitionValueResolver
when weaving classes 
when weaving 
 [Xlint:cantFindType]
abort trouble in: 
 class org.springframework.beans.factory.support.BeanDefinitionValueResolver extends java.lang.Object:
  private final org.springframework.beans.factory.support.AbstractBeanFactory beanFactory
  private final String beanName
  private final org.springframework.beans.factory.config.BeanDefinition beanDefinition
  private final org.springframework.beans.TypeConverter typeConverter
  public void <init>(org.springframework.beans.factory.support.AbstractBeanFactory, String, org.springframework.beans.factory.config.BeanDefinition, org.springframework.beans.TypeConverter):
                    ALOAD_0     // Lorg/springframework/beans/factory/support/BeanDefinitionValueResolver; this   (line 76)
                    INVOKESPECIAL java.lang.Object.<init> ()V
    constructor-execution(void org.springframework.beans.factory.support.BeanDefinitionValueResolver.<init>(org.springframework.beans.factory.support.AbstractBeanFactory, java.lang.String, org.springframework.beans.factory.config.BeanDefinition, org.springframework.beans.TypeConverter))
    |               ALOAD_0     // Lorg/springframework/beans/factory/support/BeanDefinitionValueResolver; this   (line 78)
    |               ALOAD_1     // Lorg/springframework/beans/factory/support/AbstractBeanFactory; beanFactory
    |               PUTFIELD org.springframework.beans.factory.support.BeanDefinitionValueResolver.beanFactory Lorg/springframework/beans/factory/support/AbstractBeanFactory;
    |               ALOAD_0     // Lorg/springframework/beans/factory/support/BeanDefinitionValueResolver; this   (line 79)
    |               ALOAD_2     // Ljava/lang/String; beanName
    |               PUTFIELD org.springframework.beans.factory.support.BeanDefinitionValueResolver.beanName Ljava/lang/String;
    |               ALOAD_0     // Lorg/springframework/beans/factory/support/BeanDefinitionValueResolver; this   (line 80)
    |               ALOAD_3     // Lorg/springframework/beans/factory/config/BeanDefinition; beanDefinition
    |               PUTFIELD org.springframework.beans.factory.support.BeanDefinitionValueResolver.beanDefinition Lorg/springframework/beans/factory/config/BeanDefinition;
    |               ALOAD_0     // Lorg/springframework/beans/factory/support/BeanDefinitionValueResolver; this   (line 81)
    |               ALOAD 4     // Lorg/springframework/beans/TypeConverter; typeConverter
    |               PUTFIELD org.springframework.beans.factory.support.BeanDefinitionValueResolver.typeConverter Lorg/springframework/beans/TypeConverter;
    |               RETURN   (line 82)
    constructor-execution(void org.springframework.beans.factory.support.BeanDefinitionValueResolver.<init>(org.springframework.beans.factory.support.AbstractBeanFactory, java.lang.String, org.springframework.beans.factory.config.BeanDefinition, org.springframework.beans.TypeConverter))
  end public void <init>(org.springframework.beans.factory.support.AbstractBeanFactory, String, org.springframework.beans.factory.config.BeanDefinition, org.springframework.beans.TypeConverter)

  public Object resolveValueIfNecessary(Object, Object):
                    ALOAD_2     // Ljava/lang/Object; value   (line 106)
                    INSTANCEOF org.springframework.beans.factory.config.RuntimeBeanReference
                    IFEQ L0
                    ALOAD_2     // Ljava/lang/Object; value   (line 107)
                    CHECKCAST org.springframework.beans.factory.config.RuntimeBeanReference
                    ASTORE_3
                    ALOAD_0     // Lorg/springframework/beans/factory/support/BeanDefinitionValueResolver; this   (line 108)
                    ALOAD_1     // Ljava/lang/Object; argName
                    ALOAD_3     // Lorg/springframework/beans/factory/config/RuntimeBeanReference; ref
                    INVOKESPECIAL org.springframework.beans.factory.support.BeanDefinitionValueResolver.resolveReference (Ljava/lang/Object;Lorg/springframework/beans/factory/config/RuntimeBeanReference;)Ljava/lang/Object;
                    ARETURN
                L0: ALOAD_2     // Ljava/lang/Object; value   (line 110)
                    INSTANCEOF org.springframework.beans.factory.config.RuntimeBeanNameReference
                    IFEQ L2
                    ALOAD_2     // Ljava/lang/Object; value   (line 111)
                    CHECKCAST org.springframework.beans.factory.config.RuntimeBeanNameReference
                    INVOKEVIRTUAL org.springframework.beans.factory.config.RuntimeBeanNameReference.getBeanName ()Ljava/lang/String;
                    ASTORE_3
                    ALOAD_0     // Lorg/springframework/beans/factory/support/BeanDefinitionValueResolver; this   (line 112)
                    ALOAD_3     // Ljava/lang/String; refName
                    INVOKESPECIAL org.springframework.beans.factory.support.BeanDefinitionValueResolver.doEvaluate (Ljava/lang/String;)Ljava/lang/Object;
                    INVOKESTATIC java.lang.String.valueOf (Ljava/lang/Object;)Ljava/lang/String;
                    ASTORE_3     // Ljava/lang/String; refName
                    ALOAD_0     // Lorg/springframework/beans/factory/support/BeanDefinitionValueResolver; this   (line 113)
                    GETFIELD org.springframework.beans.factory.support.BeanDefinitionValueResolver.beanFactory Lorg/springframework/beans/factory/support/AbstractBeanFactory;
                    ALOAD_3     // Ljava/lang/String; refName
                    INVOKEVIRTUAL org.springframework.beans.factory.support.AbstractBeanFactory.containsBean (Ljava/lang/String;)Z
                    IFNE L1
                    NEW org.springframework.beans.factory.BeanDefinitionStoreException   (line 114)
                    DUP
                    NEW java.lang.StringBuilder
                    DUP
                    INVOKESPECIAL java.lang.StringBuilder.<init> ()V
                    LDC "Invalid bean name '"
                    INVOKEVIRTUAL java.lang.StringBuilder.append (Ljava/lang/String;)Ljava/lang/StringBuilder;
                    ALOAD_3     // Ljava/lang/String; refName
                    INVOKEVIRTUAL java.lang.StringBuilder.append (Ljava/lang/String;)Ljava/lang/StringBuilder;
                    LDC "' in bean reference for "
                    INVOKEVIRTUAL java.lang.StringBuilder.append (Ljava/lang/String;)Ljava/lang/StringBuilder;
                    ALOAD_1     // Ljava/lang/Object; argName
                    INVOKEVIRTUAL java.lang.StringBuilder.append (Ljava/lang/Object;)Ljava/lang/StringBuilder;
                    INVOKEVIRTUAL java.lang.StringBuilder.toString ()Ljava/lang/String;
                    INVOKESPECIAL org.springframework.beans.factory.BeanDefinitionStoreException.<init> (Ljava/lang/String;)V
                    ATHROW
                L1: ALOAD_3     // Ljava/lang/String; refName   (line 117)
                    ARETURN
                L2: ALOAD_2     // Ljava/lang/Object; value   (line 119)
                    INSTANCEOF org.springframework.beans.factory.config.BeanDefinitionHolder
                    IFEQ L3
                    ALOAD_2     // Ljava/lang/Object; value   (line 121)
                    CHECKCAST org.springframework.beans.factory.config.BeanDefinitionHolder
                    ASTORE_3
                    ALOAD_0     // Lorg/springframework/beans/factory/support/BeanDefinitionValueResolver; this   (line 122)
                    ALOAD_1     // Ljava/lang/Object; argName
                    ALOAD_3     // Lorg/springframework/beans/factory/config/BeanDefinitionHolder; bdHolder
                    INVOKEVIRTUAL org.springframework.beans.factory.config.BeanDefinitionHolder.getBeanName ()Ljava/lang/String;
                    ALOAD_3     // Lorg/springframework/beans/factory/config/BeanDefinitionHolder; bdHolder
                    INVOKEVIRTUAL org.springframework.beans.factory.config.BeanDefinitionHolder.getBeanDefinition ()Lorg/springframework/beans/factory/config/BeanDefinition;
                    INVOKESPECIAL org.springframework.beans.factory.support.BeanDefinitionValueResolver.resolveInnerBean (Ljava/lang/Object;Ljava/lang/String;Lorg/springframework/beans/factory/config/BeanDefinition;)Ljava/lang/Object;
                    ARETURN
                L3: ALOAD_2     // Ljava/lang/Object; value   (line 124)
                    INSTANCEOF org.springframework.beans.factory.config.BeanDefinition
                    IFEQ L4
                    ALOAD_2     // Ljava/lang/Object; value   (line 126)
                    CHECKCAST org.springframework.beans.factory.config.BeanDefinition
                    ASTORE_3
                    NEW java.lang.StringBuilder   (line 127)
                    DUP
                    INVOKESPECIAL java.lang.StringBuilder.<init> ()V
                    LDC "(inner bean)#"
                    INVOKEVIRTUAL java.lang.StringBuilder.append (Ljava/lang/String;)Ljava/lang/StringBuilder;
                    ALOAD_3     // Lorg/springframework/beans/factory/config/BeanDefinition; bd
                    INVOKESTATIC org.springframework.util.ObjectUtils.getIdentityHexString (Ljava/lang/Object;)Ljava/lang/String;   (line 128)
                    INVOKEVIRTUAL java.lang.StringBuilder.append (Ljava/lang/String;)Ljava/lang/StringBuilder;
                    INVOKEVIRTUAL java.lang.StringBuilder.toString ()Ljava/lang/String;
                    ASTORE 4
                    ALOAD_0     // Lorg/springframework/beans/factory/support/BeanDefinitionValueResolver; this   (line 129)
                    ALOAD_1     // Ljava/lang/Object; argName
                    ALOAD 4     // Ljava/lang/String; innerBeanName
                    ALOAD_3     // Lorg/springframework/beans/factory/config/BeanDefinition; bd
                    INVOKESPECIAL org.springframework.beans.factory.support.BeanDefinitionValueResolver.resolveInnerBean (Ljava/lang/Object;Ljava/lang/String;Lorg/springframework/beans/factory/config/BeanDefinition;)Ljava/lang/Object;
                    ARETURN
                L4: ALOAD_2     // Ljava/lang/Object; value   (line 131)
                    INSTANCEOF org.springframework.beans.factory.support.ManagedArray
                    IFEQ L7
                    ALOAD_2     // Ljava/lang/Object; value   (line 133)
                    CHECKCAST org.springframework.beans.factory.support.ManagedArray
                    ASTORE_3
                    ALOAD_3     // Lorg/springframework/beans/factory/support/ManagedArray; array   (line 134)
                    GETFIELD org.springframework.beans.factory.support.ManagedArray.resolvedElementType Ljava/lang/Class;
                    ASTORE 4
                    ALOAD 4     // Ljava/lang/Class; elementType   (line 135)
                    IFNONNULL L6
                    ALOAD_3     // Lorg/springframework/beans/factory/support/ManagedArray; array   (line 136)
                    INVOKEVIRTUAL org.springframework.beans.factory.support.ManagedArray.getElementTypeName ()Ljava/lang/String;
                    ASTORE 5
                    ALOAD 5     // Ljava/lang/String; elementTypeName   (line 137)
                    INVOKESTATIC org.springframework.util.StringUtils.hasText (Ljava/lang/String;)Z
                    IFEQ L5
    catch java.lang.Throwable -> E0
    |               ALOAD 5     // Ljava/lang/String; elementTypeName   (line 139)
    |               ALOAD_0     // Lorg/springframework/beans/factory/support/BeanDefinitionValueResolver; this
    |               GETFIELD org.springframework.beans.factory.support.BeanDefinitionValueResolver.beanFactory Lorg/springframework/beans/factory/support/AbstractBeanFactory;
    |               INVOKEVIRTUAL org.springframework.beans.factory.support.AbstractBeanFactory.getBeanClassLoader ()Ljava/lang/ClassLoader;
    |               INVOKESTATIC org.springframework.util.ClassUtils.forName (Ljava/lang/String;Ljava/lang/ClassLoader;)Ljava/lang/Class;
    |               ASTORE 4     // Ljava/lang/Class; elementType
    |               ALOAD_3     // Lorg/springframework/beans/factory/support/ManagedArray; array   (line 140)
    |               ALOAD 4     // Ljava/lang/Class; elementType
    |               PUTFIELD org.springframework.beans.factory.support.ManagedArray.resolvedElementType Ljava/lang/Class;
    catch java.lang.Throwable -> E0
                    GOTO L6   (line 147)
                E0: ASTORE 6   (line 142)
                    NEW org.springframework.beans.factory.BeanCreationException   (line 144)
                    DUP
                    ALOAD_0     // Lorg/springframework/beans/factory/support/BeanDefinitionValueResolver; this
                    GETFIELD org.springframework.beans.factory.support.BeanDefinitionValueResolver.beanDefinition Lorg/springframework/beans/factory/config/BeanDefinition;
                    INVOKEINTERFACE org.springframework.beans.factory.config.BeanDefinition.getResourceDescription ()Ljava/lang/String;   (line 145)
                    ALOAD_0     // Lorg/springframework/beans/factory/support/BeanDefinitionValueResolver; this
                    GETFIELD org.springframework.beans.factory.support.BeanDefinitionValueResolver.beanName Ljava/lang/String;
                    NEW java.lang.StringBuilder
                    DUP
                    INVOKESPECIAL java.lang.StringBuilder.<init> ()V
                    LDC "Error resolving array type for "
                    INVOKEVIRTUAL java.lang.StringBuilder.append (Ljava/lang/String;)Ljava/lang/StringBuilder;
                    ALOAD_1     // Ljava/lang/Object; argName
                    INVOKEVIRTUAL java.lang.StringBuilder.append (Ljava/lang/Object;)Ljava/lang/StringBuilder;
                    INVOKEVIRTUAL java.lang.StringBuilder.toString ()Ljava/lang/String;
                    ALOAD 6     // Ljava/lang/Throwable; ex
                    INVOKESPECIAL org.springframework.beans.factory.BeanCreationException.<init> (Ljava/lang/String;Ljava/lang/String;Ljava/lang/String;Ljava/lang/Throwable;)V
                    ATHROW
                L5: LDC java.lang.Object   (line 150)
                    ASTORE 4     // Ljava/lang/Class; elementType
                L6: ALOAD_0     // Lorg/springframework/beans/factory/support/BeanDefinitionValueResolver; this   (line 153)
                    ALOAD_1     // Ljava/lang/Object; argName
                    ALOAD_2     // Ljava/lang/Object; value
                    CHECKCAST java.util.List
                    ALOAD 4     // Ljava/lang/Class; elementType
                    INVOKESPECIAL org.springframework.beans.factory.support.BeanDefinitionValueResolver.resolveManagedArray (Ljava/lang/Object;Ljava/util/List;Ljava/lang/Class;)Ljava/lang/Object;
                    ARETURN
                L7: ALOAD_2     // Ljava/lang/Object; value   (line 155)
                    INSTANCEOF org.springframework.beans.factory.support.ManagedList
                    IFEQ L8
                    ALOAD_0     // Lorg/springframework/beans/factory/support/BeanDefinitionValueResolver; this   (line 157)
                    ALOAD_1     // Ljava/lang/Object; argName
                    ALOAD_2     // Ljava/lang/Object; value
                    CHECKCAST java.util.List
                    INVOKESPECIAL org.springframework.beans.factory.support.BeanDefinitionValueResolver.resolveManagedList (Ljava/lang/Object;Ljava/util/List;)Ljava/util/List;
                    ARETURN
                L8: ALOAD_2     // Ljava/lang/Object; value   (line 159)
                    INSTANCEOF org.springframework.beans.factory.support.ManagedSet
                    IFEQ L9
                    ALOAD_0     // Lorg/springframework/beans/factory/support/BeanDefinitionValueResolver; this   (line 161)
                    ALOAD_1     // Ljava/lang/Object; argName
                    ALOAD_2     // Ljava/lang/Object; value
                    CHECKCAST java.util.Set
                    INVOKESPECIAL org.springframework.beans.factory.support.BeanDefinitionValueResolver.resolveManagedSet (Ljava/lang/Object;Ljava/util/Set;)Ljava/util/Set;
                    ARETURN
                L9: ALOAD_2     // Ljava/lang/Object; value   (line 163)
                    INSTANCEOF org.springframework.beans.factory.support.ManagedMap
                    IFEQ L10
                    ALOAD_0     // Lorg/springframework/beans/factory/support/BeanDefinitionValueResolver; this   (line 165)
                    ALOAD_1     // Ljava/lang/Object; argName
                    ALOAD_2     // Ljava/lang/Object; value
                    CHECKCAST java.util.Map
                    INVOKESPECIAL org.springframework.beans.factory.support.BeanDefinitionValueResolver.resolveManagedMap (Ljava/lang/Object;Ljava/util/Map;)Ljava/util/Map;
                    ARETURN
               L10: ALOAD_2     // Ljava/lang/Object; value   (line 167)
                    INSTANCEOF org.springframework.beans.factory.support.ManagedProperties
                    IFEQ L15
                    ALOAD_2     // Ljava/lang/Object; value   (line 168)
                    CHECKCAST java.util.Properties
                    ASTORE_3
                    NEW java.util.Properties   (line 169)
                    DUP
                    INVOKESPECIAL java.util.Properties.<init> ()V
                    ASTORE 4
                    ALOAD_3     // Ljava/util/Properties; original   (line 170)
                    INVOKEVIRTUAL java.util.Properties.entrySet ()Ljava/util/Set;
                    INVOKEINTERFACE java.util.Set.iterator ()Ljava/util/Iterator;
                    ASTORE 5
               L11: ALOAD 5
                    INVOKEINTERFACE java.util.Iterator.hasNext ()Z
                    IFEQ L14
                    ALOAD 5
                    INVOKEINTERFACE java.util.Iterator.next ()Ljava/lang/Object;
                    CHECKCAST java.util.Map$Entry
                    ASTORE 6
                    ALOAD 6     // Ljava/util/Map$Entry; propEntry   (line 171)
                    INVOKEINTERFACE java.util.Map$Entry.getKey ()Ljava/lang/Object;
                    ASTORE 7
                    ALOAD 6     // Ljava/util/Map$Entry; propEntry   (line 172)
                    INVOKEINTERFACE java.util.Map$Entry.getValue ()Ljava/lang/Object;
                    ASTORE 8
                    ALOAD 7     // Ljava/lang/Object; propKey   (line 173)
                    INSTANCEOF org.springframework.beans.factory.config.TypedStringValue
                    IFEQ L12
                    ALOAD_0     // Lorg/springframework/beans/factory/support/BeanDefinitionValueResolver; this   (line 174)
                    ALOAD 7     // Ljava/lang/Object; propKey
                    CHECKCAST org.springframework.beans.factory.config.TypedStringValue
                    INVOKEVIRTUAL org.springframework.beans.factory.support.BeanDefinitionValueResolver.evaluate (Lorg/springframework/beans/factory/config/TypedStringValue;)Ljava/lang/Object;
                    ASTORE 7     // Ljava/lang/Object; propKey
               L12: ALOAD 8     // Ljava/lang/Object; propValue   (line 176)
                    INSTANCEOF org.springframework.beans.factory.config.TypedStringValue
                    IFEQ L13
                    ALOAD_0     // Lorg/springframework/beans/factory/support/BeanDefinitionValueResolver; this   (line 177)
                    ALOAD 8     // Ljava/lang/Object; propValue
                    CHECKCAST org.springframework.beans.factory.config.TypedStringValue
                    INVOKEVIRTUAL org.springframework.beans.factory.support.BeanDefinitionValueResolver.evaluate (Lorg/springframework/beans/factory/config/TypedStringValue;)Ljava/lang/Object;
                    ASTORE 8     // Ljava/lang/Object; propValue
               L13: ALOAD 4     // Ljava/util/Properties; copy   (line 179)
                    ALOAD 7     // Ljava/lang/Object; propKey
                    ALOAD 8     // Ljava/lang/Object; propValue
                    INVOKEVIRTUAL java.util.Properties.put (Ljava/lang/Object;Ljava/lang/Object;)Ljava/lang/Object;
                    POP
                    GOTO L11   (line 180)
               L14: ALOAD 4     // Ljava/util/Properties; copy   (line 181)
                    ARETURN
               L15: ALOAD_2     // Ljava/lang/Object; value   (line 183)
                    INSTANCEOF org.springframework.beans.factory.config.TypedStringValue
                    IFEQ L17
                    ALOAD_2     // Ljava/lang/Object; value   (line 185)
                    CHECKCAST org.springframework.beans.factory.config.TypedStringValue
                    ASTORE_3
                    ALOAD_0     // Lorg/springframework/beans/factory/support/BeanDefinitionValueResolver; this   (line 186)
                    ALOAD_3     // Lorg/springframework/beans/factory/config/TypedStringValue; typedStringValue
                    INVOKEVIRTUAL org.springframework.beans.factory.support.BeanDefinitionValueResolver.evaluate (Lorg/springframework/beans/factory/config/TypedStringValue;)Ljava/lang/Object;
                    ASTORE 4
    catch java.lang.Throwable -> E2
    |               ALOAD_0     // Lorg/springframework/beans/factory/support/BeanDefinitionValueResolver; this   (line 188)
    |               ALOAD_3     // Lorg/springframework/beans/factory/config/TypedStringValue; typedStringValue
    |               INVOKEVIRTUAL org.springframework.beans.factory.support.BeanDefinitionValueResolver.resolveTargetType (Lorg/springframework/beans/factory/config/TypedStringValue;)Ljava/lang/Class;
    |               ASTORE 5
    |               ALOAD 5     // Ljava/lang/Class; resolvedTargetType   (line 189)
    |               IFNULL L16
    |               ALOAD_0     // Lorg/springframework/beans/factory/support/BeanDefinitionValueResolver; this   (line 190)
    |               GETFIELD org.springframework.beans.factory.support.BeanDefinitionValueResolver.typeConverter Lorg/springframework/beans/TypeConverter;
    |               ALOAD 4     // Ljava/lang/Object; valueObject
    |               ALOAD 5     // Ljava/lang/Class; resolvedTargetType
    |               INVOKEINTERFACE org.springframework.beans.TypeConverter.convertIfNecessary (Ljava/lang/Object;Ljava/lang/Class;)Ljava/lang/Object;
    catch java.lang.Throwable -> E2
                    ARETURN
    catch java.lang.Throwable -> E2
    |          L16: ALOAD 4     // Ljava/lang/Object; valueObject   (line 193)
    catch java.lang.Throwable -> E2
                    ARETURN
                E2: ASTORE 5   (line 196)
                    NEW org.springframework.beans.factory.BeanCreationException   (line 198)
                    DUP
                    ALOAD_0     // Lorg/springframework/beans/factory/support/BeanDefinitionValueResolver; this
                    GETFIELD org.springframework.beans.factory.support.BeanDefinitionValueResolver.beanDefinition Lorg/springframework/beans/factory/config/BeanDefinition;
                    INVOKEINTERFACE org.springframework.beans.factory.config.BeanDefinition.getResourceDescription ()Ljava/lang/String;   (line 199)
                    ALOAD_0     // Lorg/springframework/beans/factory/support/BeanDefinitionValueResolver; this
                    GETFIELD org.springframework.beans.factory.support.BeanDefinitionValueResolver.beanName Ljava/lang/String;
                    NEW java.lang.StringBuilder
                    DUP
                    INVOKESPECIAL java.lang.StringBuilder.<init> ()V
                    LDC "Error converting typed String value for "
                    INVOKEVIRTUAL java.lang.StringBuilder.append (Ljava/lang/String;)Ljava/lang/StringBuilder;
                    ALOAD_1     // Ljava/lang/Object; argName
                    INVOKEVIRTUAL java.lang.StringBuilder.append (Ljava/lang/Object;)Ljava/lang/StringBuilder;
                    INVOKEVIRTUAL java.lang.StringBuilder.toString ()Ljava/lang/String;
                    ALOAD 5     // Ljava/lang/Throwable; ex
                    INVOKESPECIAL org.springframework.beans.factory.BeanCreationException.<init> (Ljava/lang/String;Ljava/lang/String;Ljava/lang/String;Ljava/lang/Throwable;)V
                    ATHROW
               L17: ALOAD_0     // Lorg/springframework/beans/factory/support/BeanDefinitionValueResolver; this   (line 204)
                    ALOAD_2     // Ljava/lang/Object; value
                    INVOKEVIRTUAL org.springframework.beans.factory.support.BeanDefinitionValueResolver.evaluate (Ljava/lang/Object;)Ljava/lang/Object;
                    ARETURN
  end public Object resolveValueIfNecessary(Object, Object)

  protected Object evaluate(org.springframework.beans.factory.config.TypedStringValue):
                    ALOAD_0     // Lorg/springframework/beans/factory/support/BeanDefinitionValueResolver; this   (line 214)
                    ALOAD_1     // Lorg/springframework/beans/factory/config/TypedStringValue; value
                    INVOKEVIRTUAL org.springframework.beans.factory.config.TypedStringValue.getValue ()Ljava/lang/String;
                    INVOKESPECIAL org.springframework.beans.factory.support.BeanDefinitionValueResolver.doEvaluate (Ljava/lang/String;)Ljava/lang/Object;
                    ASTORE_2
                    ALOAD_2     // Ljava/lang/Object; result   (line 215)
                    ALOAD_1     // Lorg/springframework/beans/factory/config/TypedStringValue; value
                    INVOKEVIRTUAL org.springframework.beans.factory.config.TypedStringValue.getValue ()Ljava/lang/String;
                    INVOKESTATIC org.springframework.util.ObjectUtils.nullSafeEquals (Ljava/lang/Object;Ljava/lang/Object;)Z
                    IFNE L0
                    ALOAD_1     // Lorg/springframework/beans/factory/config/TypedStringValue; value   (line 216)
                    INVOKEVIRTUAL org.springframework.beans.factory.config.TypedStringValue.setDynamic ()V
                L0: ALOAD_2     // Ljava/lang/Object; result   (line 218)
                    ARETURN
  end protected Object evaluate(org.springframework.beans.factory.config.TypedStringValue)

  protected Object evaluate(Object):
                    ALOAD_1     // Ljava/lang/Object; value   (line 227)
                    INSTANCEOF java.lang.String
                    IFEQ L0
                    ALOAD_0     // Lorg/springframework/beans/factory/support/BeanDefinitionValueResolver; this   (line 228)
                    ALOAD_1     // Ljava/lang/Object; value
                    CHECKCAST java.lang.String
                    INVOKESPECIAL org.springframework.beans.factory.support.BeanDefinitionValueResolver.doEvaluate (Ljava/lang/String;)Ljava/lang/Object;
                    ARETURN
                L0: ALOAD_1     // Ljava/lang/Object; value   (line 230)
                    INSTANCEOF [Ljava.lang.String;
                    IFEQ L6
                    ALOAD_1     // Ljava/lang/Object; value   (line 231)
                    CHECKCAST [Ljava.lang.String;
                    CHECKCAST [Ljava.lang.String;
                    ASTORE_2
                    ICONST_0   (line 232)
                    ISTORE_3
                    ALOAD_2     // [Ljava/lang/String; values   (line 233)
                    ARRAYLENGTH
                    ANEWARRAY java.lang.Object
                    ASTORE 4
                    ICONST_0   (line 234)
                    ISTORE 5
                L1: ILOAD 5     // I i
                    ALOAD_2     // [Ljava/lang/String; values
                    ARRAYLENGTH
                    IF_ICMPGE L3
                    ALOAD_2     // [Ljava/lang/String; values   (line 235)
                    ILOAD 5     // I i
                    AALOAD
                    ASTORE 6
                    ALOAD_0     // Lorg/springframework/beans/factory/support/BeanDefinitionValueResolver; this   (line 236)
                    ALOAD 6     // Ljava/lang/String; originalValue
                    INVOKESPECIAL org.springframework.beans.factory.support.BeanDefinitionValueResolver.doEvaluate (Ljava/lang/String;)Ljava/lang/Object;
                    ASTORE 7
                    ALOAD 7     // Ljava/lang/Object; resolvedValue   (line 237)
                    ALOAD 6     // Ljava/lang/String; originalValue
                    IF_ACMPEQ L2
                    ICONST_1   (line 238)
                    ISTORE_3     // Z actuallyResolved
                L2: ALOAD 4     // [Ljava/lang/Object; resolvedValues   (line 240)
                    ILOAD 5     // I i
                    ALOAD 7     // Ljava/lang/Object; resolvedValue
                    AASTORE
                    IINC 5 1     // I i   (line 234)
                    GOTO L1
                L3: ILOAD_3     // Z actuallyResolved   (line 242)
                    IFEQ L4
                    ALOAD 4     // [Ljava/lang/Object; resolvedValues
                    GOTO L5
                L4: ALOAD_2     // [Ljava/lang/String; values
                L5: ARETURN
                L6: ALOAD_1     // Ljava/lang/Object; value   (line 245)
                    ARETURN
  end protected Object evaluate(Object)

  private Object doEvaluate(String):
                    ALOAD_0     // Lorg/springframework/beans/factory/support/BeanDefinitionValueResolver; this   (line 255)
                    GETFIELD org.springframework.beans.factory.support.BeanDefinitionValueResolver.beanFactory Lorg/springframework/beans/factory/support/AbstractBeanFactory;
                    ALOAD_1     // Ljava/lang/String; value
                    ALOAD_0     // Lorg/springframework/beans/factory/support/BeanDefinitionValueResolver; this
                    GETFIELD org.springframework.beans.factory.support.BeanDefinitionValueResolver.beanDefinition Lorg/springframework/beans/factory/config/BeanDefinition;
                    INVOKEVIRTUAL org.springframework.beans.factory.support.AbstractBeanFactory.evaluateBeanDefinitionString (Ljava/lang/String;Lorg/springframework/beans/factory/config/BeanDefinition;)Ljava/lang/Object;
                    ARETURN
  end private Object doEvaluate(String)

  protected Class resolveTargetType(org.springframework.beans.factory.config.TypedStringValue) throws java.lang.ClassNotFoundException:
                    ALOAD_1     // Lorg/springframework/beans/factory/config/TypedStringValue; value   (line 266)
                    INVOKEVIRTUAL org.springframework.beans.factory.config.TypedStringValue.hasTargetType ()Z
                    IFEQ L0
                    ALOAD_1     // Lorg/springframework/beans/factory/config/TypedStringValue; value   (line 267)
                    INVOKEVIRTUAL org.springframework.beans.factory.config.TypedStringValue.getTargetType ()Ljava/lang/Class;
                    ARETURN
                L0: ALOAD_1     // Lorg/springframework/beans/factory/config/TypedStringValue; value   (line 269)
                    ALOAD_0     // Lorg/springframework/beans/factory/support/BeanDefinitionValueResolver; this
                    GETFIELD org.springframework.beans.factory.support.BeanDefinitionValueResolver.beanFactory Lorg/springframework/beans/factory/support/AbstractBeanFactory;
                    INVOKEVIRTUAL org.springframework.beans.factory.support.AbstractBeanFactory.getBeanClassLoader ()Ljava/lang/ClassLoader;
                    INVOKEVIRTUAL org.springframework.beans.factory.config.TypedStringValue.resolveTargetType (Ljava/lang/ClassLoader;)Ljava/lang/Class;
                    ARETURN
  end protected Class resolveTargetType(org.springframework.beans.factory.config.TypedStringValue) throws java.lang.ClassNotFoundException

  private Object resolveInnerBean(Object, String, org.springframework.beans.factory.config.BeanDefinition):
                    ACONST_NULL   (line 280)
                    ASTORE 4
    catch org.springframework.beans.BeansException -> E1
    |               ALOAD_0     // Lorg/springframework/beans/factory/support/BeanDefinitionValueResolver; this   (line 282)
    |               GETFIELD org.springframework.beans.factory.support.BeanDefinitionValueResolver.beanFactory Lorg/springframework/beans/factory/support/AbstractBeanFactory;
    |               ALOAD_2     // Ljava/lang/String; innerBeanName
    |               ALOAD_3     // Lorg/springframework/beans/factory/config/BeanDefinition; innerBd
    |               ALOAD_0     // Lorg/springframework/beans/factory/support/BeanDefinitionValueResolver; this
    |               GETFIELD org.springframework.beans.factory.support.BeanDefinitionValueResolver.beanDefinition Lorg/springframework/beans/factory/config/BeanDefinition;
    |               INVOKEVIRTUAL org.springframework.beans.factory.support.AbstractBeanFactory.getMergedBeanDefinition (Ljava/lang/String;Lorg/springframework/beans/factory/config/BeanDefinition;Lorg/springframework/beans/factory/config/BeanDefinition;)Lorg/springframework/beans/factory/support/RootBeanDefinition;
    |               ASTORE 4     // Lorg/springframework/beans/factory/support/RootBeanDefinition; mbd
    |               ALOAD_2     // Ljava/lang/String; innerBeanName   (line 285)
    |               ASTORE 5
    |               ALOAD 4     // Lorg/springframework/beans/factory/support/RootBeanDefinition; mbd   (line 286)
    |               INVOKEVIRTUAL org.springframework.beans.factory.support.RootBeanDefinition.isSingleton ()Z
    |               IFEQ L0
    |               ALOAD_0     // Lorg/springframework/beans/factory/support/BeanDefinitionValueResolver; this   (line 287)
    |               ALOAD_2     // Ljava/lang/String; innerBeanName
    |               INVOKESPECIAL org.springframework.beans.factory.support.BeanDefinitionValueResolver.adaptInnerBeanName (Ljava/lang/String;)Ljava/lang/String;
    |               ASTORE 5     // Ljava/lang/String; actualInnerBeanName
    |           L0: ALOAD_0     // Lorg/springframework/beans/factory/support/BeanDefinitionValueResolver; this   (line 289)
    |               GETFIELD org.springframework.beans.factory.support.BeanDefinitionValueResolver.beanFactory Lorg/springframework/beans/factory/support/AbstractBeanFactory;
    |               ALOAD 5     // Ljava/lang/String; actualInnerBeanName
    |               ALOAD_0     // Lorg/springframework/beans/factory/support/BeanDefinitionValueResolver; this
    |               GETFIELD org.springframework.beans.factory.support.BeanDefinitionValueResolver.beanName Ljava/lang/String;
    |               INVOKEVIRTUAL org.springframework.beans.factory.support.AbstractBeanFactory.registerContainedBean (Ljava/lang/String;Ljava/lang/String;)V
    |               ALOAD 4     // Lorg/springframework/beans/factory/support/RootBeanDefinition; mbd   (line 291)
    |               INVOKEVIRTUAL org.springframework.beans.factory.support.RootBeanDefinition.getDependsOn ()[Ljava/lang/String;
    |               ASTORE 6
    |               ALOAD 6     // [Ljava/lang/String; dependsOn   (line 292)
    |               IFNULL L2
    |               ALOAD 6     // [Ljava/lang/String; dependsOn   (line 293)
    |               ASTORE 7
    |               ALOAD 7
    |               ARRAYLENGTH
    |               ISTORE 8
    |               ICONST_0
    |               ISTORE 9
    |           L1: ILOAD 9
    |               ILOAD 8
    |               IF_ICMPGE L2
    |               ALOAD 7
    |               ILOAD 9
    |               AALOAD
    |               ASTORE 10
    |               ALOAD_0     // Lorg/springframework/beans/factory/support/BeanDefinitionValueResolver; this   (line 294)
    |               GETFIELD org.springframework.beans.factory.support.BeanDefinitionValueResolver.beanFactory Lorg/springframework/beans/factory/support/AbstractBeanFactory;
    |               ALOAD 10     // Ljava/lang/String; dependsOnBean
    |               ALOAD 5     // Ljava/lang/String; actualInnerBeanName
    |               INVOKEVIRTUAL org.springframework.beans.factory.support.AbstractBeanFactory.registerDependentBean (Ljava/lang/String;Ljava/lang/String;)V
    |               ALOAD_0     // Lorg/springframework/beans/factory/support/BeanDefinitionValueResolver; this   (line 295)
    |               GETFIELD org.springframework.beans.factory.support.BeanDefinitionValueResolver.beanFactory Lorg/springframework/beans/factory/support/AbstractBeanFactory;
    |               ALOAD 10     // Ljava/lang/String; dependsOnBean
    |               INVOKEVIRTUAL org.springframework.beans.factory.support.AbstractBeanFactory.getBean (Ljava/lang/String;)Ljava/lang/Object;
    |               POP
    |               IINC 9 1   (line 293)
    |               GOTO L1
    |           L2: ALOAD_0     // Lorg/springframework/beans/factory/support/BeanDefinitionValueResolver; this   (line 299)
    |               GETFIELD org.springframework.beans.factory.support.BeanDefinitionValueResolver.beanFactory Lorg/springframework/beans/factory/support/AbstractBeanFactory;
    |               ALOAD 5     // Ljava/lang/String; actualInnerBeanName
    |               ALOAD 4     // Lorg/springframework/beans/factory/support/RootBeanDefinition; mbd
    |               ACONST_NULL
    |               INVOKEVIRTUAL org.springframework.beans.factory.support.AbstractBeanFactory.createBean (Ljava/lang/String;Lorg/springframework/beans/factory/support/RootBeanDefinition;[Ljava/lang/Object;)Ljava/lang/Object;
    |               ASTORE 7
    |               ALOAD 7     // Ljava/lang/Object; innerBean   (line 300)
    |               INSTANCEOF org.springframework.beans.factory.FactoryBean
    |               IFEQ L5
    |               ALOAD 4     // Lorg/springframework/beans/factory/support/RootBeanDefinition; mbd   (line 301)
    |               INVOKEVIRTUAL org.springframework.beans.factory.support.RootBeanDefinition.isSynthetic ()Z
    |               ISTORE 8
    |               ALOAD_0     // Lorg/springframework/beans/factory/support/BeanDefinitionValueResolver; this   (line 302)
    |               GETFIELD org.springframework.beans.factory.support.BeanDefinitionValueResolver.beanFactory Lorg/springframework/beans/factory/support/AbstractBeanFactory;
    |               ALOAD 7     // Ljava/lang/Object; innerBean
    |               CHECKCAST org.springframework.beans.factory.FactoryBean
    |               ALOAD 5     // Ljava/lang/String; actualInnerBeanName
    |               ILOAD 8     // Z synthetic
    |               IFNE L3
    |               ICONST_1
    |               GOTO L4
    |           L3: ICONST_0
    |           L4: INVOKEVIRTUAL org.springframework.beans.factory.support.AbstractBeanFactory.getObjectFromFactoryBean (Lorg/springframework/beans/factory/FactoryBean;Ljava/lang/String;Z)Ljava/lang/Object;
    catch org.springframework.beans.BeansException -> E1
                    ARETURN
    catch org.springframework.beans.BeansException -> E1
    |           L5: ALOAD 7     // Ljava/lang/Object; innerBean   (line 306)
    catch org.springframework.beans.BeansException -> E1
                    ARETURN
                E1: ASTORE 5   (line 309)
                    NEW org.springframework.beans.factory.BeanCreationException   (line 310)
                    DUP
                    ALOAD_0     // Lorg/springframework/beans/factory/support/BeanDefinitionValueResolver; this
                    GETFIELD org.springframework.beans.factory.support.BeanDefinitionValueResolver.beanDefinition Lorg/springframework/beans/factory/config/BeanDefinition;
                    INVOKEINTERFACE org.springframework.beans.factory.config.BeanDefinition.getResourceDescription ()Ljava/lang/String;   (line 311)
                    ALOAD_0     // Lorg/springframework/beans/factory/support/BeanDefinitionValueResolver; this
                    GETFIELD org.springframework.beans.factory.support.BeanDefinitionValueResolver.beanName Ljava/lang/String;
                    NEW java.lang.StringBuilder
                    DUP
                    INVOKESPECIAL java.lang.StringBuilder.<init> ()V
                    LDC "Cannot create inner bean '"
                    INVOKEVIRTUAL java.lang.StringBuilder.append (Ljava/lang/String;)Ljava/lang/StringBuilder;
                    ALOAD_2     // Ljava/lang/String; innerBeanName
                    INVOKEVIRTUAL java.lang.StringBuilder.append (Ljava/lang/String;)Ljava/lang/StringBuilder;
                    LDC "' "
                    INVOKEVIRTUAL java.lang.StringBuilder.append (Ljava/lang/String;)Ljava/lang/StringBuilder;
                    ALOAD 4     // Lorg/springframework/beans/factory/support/RootBeanDefinition; mbd
                    IFNULL L6
                    ALOAD 4     // Lorg/springframework/beans/factory/support/RootBeanDefinition; mbd
                    INVOKEVIRTUAL org.springframework.beans.factory.support.RootBeanDefinition.getBeanClassName ()Ljava/lang/String;   (line 313)
                    IFNULL L6
                    NEW java.lang.StringBuilder
                    DUP
                    INVOKESPECIAL java.lang.StringBuilder.<init> ()V
                    LDC "of type ["
                    INVOKEVIRTUAL java.lang.StringBuilder.append (Ljava/lang/String;)Ljava/lang/StringBuilder;
                    ALOAD 4     // Lorg/springframework/beans/factory/support/RootBeanDefinition; mbd
                    INVOKEVIRTUAL org.springframework.beans.factory.support.RootBeanDefinition.getBeanClassName ()Ljava/lang/String;
                    INVOKEVIRTUAL java.lang.StringBuilder.append (Ljava/lang/String;)Ljava/lang/StringBuilder;
                    LDC "] "
                    INVOKEVIRTUAL java.lang.StringBuilder.append (Ljava/lang/String;)Ljava/lang/StringBuilder;
                    INVOKEVIRTUAL java.lang.StringBuilder.toString ()Ljava/lang/String;
                    GOTO L7
                L6: LDC ""
                L7: INVOKEVIRTUAL java.lang.StringBuilder.append (Ljava/lang/String;)Ljava/lang/StringBuilder;
                    LDC "while setting "
                    INVOKEVIRTUAL java.lang.StringBuilder.append (Ljava/lang/String;)Ljava/lang/StringBuilder;
                    ALOAD_1     // Ljava/lang/Object; argName
                    INVOKEVIRTUAL java.lang.StringBuilder.append (Ljava/lang/Object;)Ljava/lang/StringBuilder;
                    INVOKEVIRTUAL java.lang.StringBuilder.toString ()Ljava/lang/String;
                    ALOAD 5     // Lorg/springframework/beans/BeansException; ex
                    INVOKESPECIAL org.springframework.beans.factory.BeanCreationException.<init> (Ljava/lang/String;Ljava/lang/String;Ljava/lang/String;Ljava/lang/Throwable;)V
                    ATHROW
  end private Object resolveInnerBean(Object, String, org.springframework.beans.factory.config.BeanDefinition)

  private String adaptInnerBeanName(String):
                    ALOAD_1     // Ljava/lang/String; innerBeanName   (line 325)
                    ASTORE_2
                    ICONST_0   (line 326)
                    ISTORE_3
                L0: ALOAD_0     // Lorg/springframework/beans/factory/support/BeanDefinitionValueResolver; this   (line 327)
                    GETFIELD org.springframework.beans.factory.support.BeanDefinitionValueResolver.beanFactory Lorg/springframework/beans/factory/support/AbstractBeanFactory;
                    ALOAD_2     // Ljava/lang/String; actualInnerBeanName
                    INVOKEVIRTUAL org.springframework.beans.factory.support.AbstractBeanFactory.isBeanNameInUse (Ljava/lang/String;)Z
                    IFEQ L1
                    IINC_3 1     // I counter   (line 328)
                    NEW java.lang.StringBuilder   (line 329)
                    DUP
                    INVOKESPECIAL java.lang.StringBuilder.<init> ()V
                    ALOAD_1     // Ljava/lang/String; innerBeanName
                    INVOKEVIRTUAL java.lang.StringBuilder.append (Ljava/lang/String;)Ljava/lang/StringBuilder;
                    LDC "#"
                    INVOKEVIRTUAL java.lang.StringBuilder.append (Ljava/lang/String;)Ljava/lang/StringBuilder;
                    ILOAD_3     // I counter
                    INVOKEVIRTUAL java.lang.StringBuilder.append (I)Ljava/lang/StringBuilder;
                    INVOKEVIRTUAL java.lang.StringBuilder.toString ()Ljava/lang/String;
                    ASTORE_2     // Ljava/lang/String; actualInnerBeanName
                    GOTO L0
                L1: ALOAD_2     // Ljava/lang/String; actualInnerBeanName   (line 331)
                    ARETURN
  end private String adaptInnerBeanName(String)

  private Object resolveReference(Object, org.springframework.beans.factory.config.RuntimeBeanReference):
    catch org.springframework.beans.BeansException -> E1
    |               ALOAD_2     // Lorg/springframework/beans/factory/config/RuntimeBeanReference; ref   (line 339)
    |               INVOKEVIRTUAL org.springframework.beans.factory.config.RuntimeBeanReference.getBeanName ()Ljava/lang/String;
    |               ASTORE_3
    |               ALOAD_0     // Lorg/springframework/beans/factory/support/BeanDefinitionValueResolver; this   (line 340)
    |               ALOAD_3     // Ljava/lang/String; refName
    |               INVOKESPECIAL org.springframework.beans.factory.support.BeanDefinitionValueResolver.doEvaluate (Ljava/lang/String;)Ljava/lang/Object;
    |               INVOKESTATIC java.lang.String.valueOf (Ljava/lang/Object;)Ljava/lang/String;
    |               ASTORE_3     // Ljava/lang/String; refName
    |               ALOAD_2     // Lorg/springframework/beans/factory/config/RuntimeBeanReference; ref   (line 341)
    |               INVOKEVIRTUAL org.springframework.beans.factory.config.RuntimeBeanReference.isToParent ()Z
    |               IFEQ L1
    |               ALOAD_0     // Lorg/springframework/beans/factory/support/BeanDefinitionValueResolver; this   (line 342)
    |               GETFIELD org.springframework.beans.factory.support.BeanDefinitionValueResolver.beanFactory Lorg/springframework/beans/factory/support/AbstractBeanFactory;
    |               INVOKEVIRTUAL org.springframework.beans.factory.support.AbstractBeanFactory.getParentBeanFactory ()Lorg/springframework/beans/factory/BeanFactory;
    |               IFNONNULL L0
    |               NEW org.springframework.beans.factory.BeanCreationException   (line 343)
    |               DUP
    |               ALOAD_0     // Lorg/springframework/beans/factory/support/BeanDefinitionValueResolver; this
    |               GETFIELD org.springframework.beans.factory.support.BeanDefinitionValueResolver.beanDefinition Lorg/springframework/beans/factory/config/BeanDefinition;
    |               INVOKEINTERFACE org.springframework.beans.factory.config.BeanDefinition.getResourceDescription ()Ljava/lang/String;   (line 344)
    |               ALOAD_0     // Lorg/springframework/beans/factory/support/BeanDefinitionValueResolver; this
    |               GETFIELD org.springframework.beans.factory.support.BeanDefinitionValueResolver.beanName Ljava/lang/String;
    |               NEW java.lang.StringBuilder
    |               DUP
    |               INVOKESPECIAL java.lang.StringBuilder.<init> ()V
    |               LDC "Can't resolve reference to bean '"
    |               INVOKEVIRTUAL java.lang.StringBuilder.append (Ljava/lang/String;)Ljava/lang/StringBuilder;
    |               ALOAD_3     // Ljava/lang/String; refName
    |               INVOKEVIRTUAL java.lang.StringBuilder.append (Ljava/lang/String;)Ljava/lang/StringBuilder;
    |               LDC "' in parent factory: no parent factory available"
    |               INVOKEVIRTUAL java.lang.StringBuilder.append (Ljava/lang/String;)Ljava/lang/StringBuilder;
    |               INVOKEVIRTUAL java.lang.StringBuilder.toString ()Ljava/lang/String;
    |               INVOKESPECIAL org.springframework.beans.factory.BeanCreationException.<init> (Ljava/lang/String;Ljava/lang/String;Ljava/lang/String;)V
    |               ATHROW
    |           L0: ALOAD_0     // Lorg/springframework/beans/factory/support/BeanDefinitionValueResolver; this   (line 348)
    |               GETFIELD org.springframework.beans.factory.support.BeanDefinitionValueResolver.beanFactory Lorg/springframework/beans/factory/support/AbstractBeanFactory;
    |               INVOKEVIRTUAL org.springframework.beans.factory.support.AbstractBeanFactory.getParentBeanFactory ()Lorg/springframework/beans/factory/BeanFactory;
    |               ALOAD_3     // Ljava/lang/String; refName
    |               INVOKEINTERFACE org.springframework.beans.factory.BeanFactory.getBean (Ljava/lang/String;)Ljava/lang/Object;
    catch org.springframework.beans.BeansException -> E1
                    ARETURN
    catch org.springframework.beans.BeansException -> E1
    |           L1: ALOAD_0     // Lorg/springframework/beans/factory/support/BeanDefinitionValueResolver; this   (line 351)
    |               GETFIELD org.springframework.beans.factory.support.BeanDefinitionValueResolver.beanFactory Lorg/springframework/beans/factory/support/AbstractBeanFactory;
    |               ALOAD_3     // Ljava/lang/String; refName
    |               INVOKEVIRTUAL org.springframework.beans.factory.support.AbstractBeanFactory.getBean (Ljava/lang/String;)Ljava/lang/Object;
    |               ASTORE 4
    |               ALOAD_0     // Lorg/springframework/beans/factory/support/BeanDefinitionValueResolver; this   (line 352)
    |               GETFIELD org.springframework.beans.factory.support.BeanDefinitionValueResolver.beanFactory Lorg/springframework/beans/factory/support/AbstractBeanFactory;
    |               ALOAD_3     // Ljava/lang/String; refName
    |               ALOAD_0     // Lorg/springframework/beans/factory/support/BeanDefinitionValueResolver; this
    |               GETFIELD org.springframework.beans.factory.support.BeanDefinitionValueResolver.beanName Ljava/lang/String;
    |               INVOKEVIRTUAL org.springframework.beans.factory.support.AbstractBeanFactory.registerDependentBean (Ljava/lang/String;Ljava/lang/String;)V
    |               ALOAD 4     // Ljava/lang/Object; bean   (line 353)
    catch org.springframework.beans.BeansException -> E1
                    ARETURN
                E1: ASTORE_3   (line 356)
                    NEW org.springframework.beans.factory.BeanCreationException   (line 357)
                    DUP
                    ALOAD_0     // Lorg/springframework/beans/factory/support/BeanDefinitionValueResolver; this
                    GETFIELD org.springframework.beans.factory.support.BeanDefinitionValueResolver.beanDefinition Lorg/springframework/beans/factory/config/BeanDefinition;
                    INVOKEINTERFACE org.springframework.beans.factory.config.BeanDefinition.getResourceDescription ()Ljava/lang/String;   (line 358)
                    ALOAD_0     // Lorg/springframework/beans/factory/support/BeanDefinitionValueResolver; this
                    GETFIELD org.springframework.beans.factory.support.BeanDefinitionValueResolver.beanName Ljava/lang/String;
                    NEW java.lang.StringBuilder
                    DUP
                    INVOKESPECIAL java.lang.StringBuilder.<init> ()V
                    LDC "Cannot resolve reference to bean '"
                    INVOKEVIRTUAL java.lang.StringBuilder.append (Ljava/lang/String;)Ljava/lang/StringBuilder;
                    ALOAD_2     // Lorg/springframework/beans/factory/config/RuntimeBeanReference; ref
                    INVOKEVIRTUAL org.springframework.beans.factory.config.RuntimeBeanReference.getBeanName ()Ljava/lang/String;   (line 359)
                    INVOKEVIRTUAL java.lang.StringBuilder.append (Ljava/lang/String;)Ljava/lang/StringBuilder;
                    LDC "' while setting "
                    INVOKEVIRTUAL java.lang.StringBuilder.append (Ljava/lang/String;)Ljava/lang/StringBuilder;
                    ALOAD_1     // Ljava/lang/Object; argName
                    INVOKEVIRTUAL java.lang.StringBuilder.append (Ljava/lang/Object;)Ljava/lang/StringBuilder;
                    INVOKEVIRTUAL java.lang.StringBuilder.toString ()Ljava/lang/String;
                    ALOAD_3     // Lorg/springframework/beans/BeansException; ex
                    INVOKESPECIAL org.springframework.beans.factory.BeanCreationException.<init> (Ljava/lang/String;Ljava/lang/String;Ljava/lang/String;Ljava/lang/Throwable;)V
                    ATHROW
  end private Object resolveReference(Object, org.springframework.beans.factory.config.RuntimeBeanReference)

  private Object resolveManagedArray(Object, java.util.List, Class):
                    ALOAD_3     // Ljava/lang/Class; elementType   (line 367)
                    ALOAD_2     // Ljava/util/List; ml
                    INVOKEINTERFACE java.util.List.size ()I
                    INVOKESTATIC java.lang.reflect.Array.newInstance (Ljava/lang/Class;I)Ljava/lang/Object;
                    ASTORE 4
                    ICONST_0   (line 368)
                    ISTORE 5
                L0: ILOAD 5     // I i
                    ALOAD_2     // Ljava/util/List; ml
                    INVOKEINTERFACE java.util.List.size ()I
                    IF_ICMPGE L1
                    ALOAD 4     // Ljava/lang/Object; resolved   (line 369)
                    ILOAD 5     // I i
                    ALOAD_0     // Lorg/springframework/beans/factory/support/BeanDefinitionValueResolver; this
                    NEW org.springframework.beans.factory.support.BeanDefinitionValueResolver$KeyedArgName
                    DUP
                    ALOAD_1     // Ljava/lang/Object; argName
                    ILOAD 5     // I i
                    INVOKESTATIC java.lang.Integer.valueOf (I)Ljava/lang/Integer;   (line 370)
                    INVOKESPECIAL org.springframework.beans.factory.support.BeanDefinitionValueResolver$KeyedArgName.<init> (Ljava/lang/Object;Ljava/lang/Object;)V
                    ALOAD_2     // Ljava/util/List; ml
                    ILOAD 5     // I i
                    INVOKEINTERFACE java.util.List.get (I)Ljava/lang/Object;
                    INVOKEVIRTUAL org.springframework.beans.factory.support.BeanDefinitionValueResolver.resolveValueIfNecessary (Ljava/lang/Object;Ljava/lang/Object;)Ljava/lang/Object;
                    INVOKESTATIC java.lang.reflect.Array.set (Ljava/lang/Object;ILjava/lang/Object;)V   (line 369)
                    IINC 5 1     // I i   (line 368)
                    GOTO L0
                L1: ALOAD 4     // Ljava/lang/Object; resolved   (line 372)
                    ARETURN
  end private Object resolveManagedArray(Object, java.util.List, Class)

  private java.util.List resolveManagedList(Object, java.util.List):
                    NEW java.util.ArrayList   (line 379)
                    DUP
                    ALOAD_2     // Ljava/util/List; ml
                    INVOKEINTERFACE java.util.List.size ()I
                    INVOKESPECIAL java.util.ArrayList.<init> (I)V
                    ASTORE_3
                    ICONST_0   (line 380)
                    ISTORE 4
                L0: ILOAD 4     // I i
                    ALOAD_2     // Ljava/util/List; ml
                    INVOKEINTERFACE java.util.List.size ()I
                    IF_ICMPGE L1
                    ALOAD_3     // Ljava/util/List; resolved   (line 381)
                    ALOAD_0     // Lorg/springframework/beans/factory/support/BeanDefinitionValueResolver; this
                    NEW org.springframework.beans.factory.support.BeanDefinitionValueResolver$KeyedArgName
                    DUP
                    ALOAD_1     // Ljava/lang/Object; argName
                    ILOAD 4     // I i
                    INVOKESTATIC java.lang.Integer.valueOf (I)Ljava/lang/Integer;   (line 382)
                    INVOKESPECIAL org.springframework.beans.factory.support.BeanDefinitionValueResolver$KeyedArgName.<init> (Ljava/lang/Object;Ljava/lang/Object;)V
                    ALOAD_2     // Ljava/util/List; ml
                    ILOAD 4     // I i
                    INVOKEINTERFACE java.util.List.get (I)Ljava/lang/Object;
                    INVOKEVIRTUAL org.springframework.beans.factory.support.BeanDefinitionValueResolver.resolveValueIfNecessary (Ljava/lang/Object;Ljava/lang/Object;)Ljava/lang/Object;
                    INVOKEINTERFACE java.util.List.add (Ljava/lang/Object;)Z   (line 381)
                    POP
                    IINC 4 1     // I i   (line 380)
                    GOTO L0
                L1: ALOAD_3     // Ljava/util/List; resolved   (line 384)
                    ARETURN
  end private java.util.List resolveManagedList(Object, java.util.List)

  private java.util.Set resolveManagedSet(Object, java.util.Set):
                    NEW java.util.LinkedHashSet   (line 391)
                    DUP
                    ALOAD_2     // Ljava/util/Set; ms
                    INVOKEINTERFACE java.util.Set.size ()I
                    INVOKESPECIAL java.util.LinkedHashSet.<init> (I)V
                    ASTORE_3
                    ICONST_0   (line 392)
                    ISTORE 4
                    ALOAD_2     // Ljava/util/Set; ms   (line 393)
                    INVOKEINTERFACE java.util.Set.iterator ()Ljava/util/Iterator;
                    ASTORE 5
                L0: ALOAD 5
                    INVOKEINTERFACE java.util.Iterator.hasNext ()Z
                    IFEQ L1
                    ALOAD 5
                    INVOKEINTERFACE java.util.Iterator.next ()Ljava/lang/Object;
                    ASTORE 6
                    ALOAD_3     // Ljava/util/Set; resolved   (line 394)
                    ALOAD_0     // Lorg/springframework/beans/factory/support/BeanDefinitionValueResolver; this
                    NEW org.springframework.beans.factory.support.BeanDefinitionValueResolver$KeyedArgName
                    DUP
                    ALOAD_1     // Ljava/lang/Object; argName
                    ILOAD 4     // I i
                    INVOKESTATIC java.lang.Integer.valueOf (I)Ljava/lang/Integer;
                    INVOKESPECIAL org.springframework.beans.factory.support.BeanDefinitionValueResolver$KeyedArgName.<init> (Ljava/lang/Object;Ljava/lang/Object;)V
                    ALOAD 6     // Ljava/lang/Object; m
                    INVOKEVIRTUAL org.springframework.beans.factory.support.BeanDefinitionValueResolver.resolveValueIfNecessary (Ljava/lang/Object;Ljava/lang/Object;)Ljava/lang/Object;
                    INVOKEINTERFACE java.util.Set.add (Ljava/lang/Object;)Z
                    POP
                    IINC 4 1     // I i   (line 395)
                    GOTO L0   (line 396)
                L1: ALOAD_3     // Ljava/util/Set; resolved   (line 397)
                    ARETURN
  end private java.util.Set resolveManagedSet(Object, java.util.Set)

  private java.util.Map resolveManagedMap(Object, java.util.Map):
                    NEW java.util.LinkedHashMap   (line 404)
                    DUP
                    ALOAD_2     // Ljava/util/Map; mm
                    INVOKEINTERFACE java.util.Map.size ()I
                    INVOKESPECIAL java.util.LinkedHashMap.<init> (I)V
                    ASTORE_3
                    ALOAD_2     // Ljava/util/Map; mm   (line 405)
                    INVOKEINTERFACE java.util.Map.entrySet ()Ljava/util/Set;
                    INVOKEINTERFACE java.util.Set.iterator ()Ljava/util/Iterator;
                    ASTORE 4
                L0: ALOAD 4
                    INVOKEINTERFACE java.util.Iterator.hasNext ()Z
                    IFEQ L1
                    ALOAD 4
                    INVOKEINTERFACE java.util.Iterator.next ()Ljava/lang/Object;
                    CHECKCAST java.util.Map$Entry
                    ASTORE 5
                    ALOAD_0     // Lorg/springframework/beans/factory/support/BeanDefinitionValueResolver; this   (line 406)
                    ALOAD_1     // Ljava/lang/Object; argName
                    ALOAD 5     // Ljava/util/Map$Entry; entry
                    INVOKEINTERFACE java.util.Map$Entry.getKey ()Ljava/lang/Object;
                    INVOKEVIRTUAL org.springframework.beans.factory.support.BeanDefinitionValueResolver.resolveValueIfNecessary (Ljava/lang/Object;Ljava/lang/Object;)Ljava/lang/Object;
                    ASTORE 6
                    ALOAD_0     // Lorg/springframework/beans/factory/support/BeanDefinitionValueResolver; this   (line 407)
                    NEW org.springframework.beans.factory.support.BeanDefinitionValueResolver$KeyedArgName
                    DUP
                    ALOAD_1     // Ljava/lang/Object; argName
                    ALOAD 5     // Ljava/util/Map$Entry; entry
                    INVOKEINTERFACE java.util.Map$Entry.getKey ()Ljava/lang/Object;   (line 408)
                    INVOKESPECIAL org.springframework.beans.factory.support.BeanDefinitionValueResolver$KeyedArgName.<init> (Ljava/lang/Object;Ljava/lang/Object;)V
                    ALOAD 5     // Ljava/util/Map$Entry; entry
                    INVOKEINTERFACE java.util.Map$Entry.getValue ()Ljava/lang/Object;
                    INVOKEVIRTUAL org.springframework.beans.factory.support.BeanDefinitionValueResolver.resolveValueIfNecessary (Ljava/lang/Object;Ljava/lang/Object;)Ljava/lang/Object;   (line 407)
                    ASTORE 7
                    ALOAD_3     // Ljava/util/Map; resolved   (line 409)
                    ALOAD 6     // Ljava/lang/Object; resolvedKey
                    ALOAD 7     // Ljava/lang/Object; resolvedValue
                    INVOKEINTERFACE java.util.Map.put (Ljava/lang/Object;Ljava/lang/Object;)Ljava/lang/Object;
                    POP
                    GOTO L0   (line 410)
                L1: ALOAD_3     // Ljava/util/Map; resolved   (line 411)
                    ARETURN
  end private java.util.Map resolveManagedMap(Object, java.util.Map)

end  class org.springframework.beans.factory.support.BeanDefinitionValueResolver
 -- (NullPointerException) null
null
java.lang.NullPointerException
	at org.aspectj.weaver.UnresolvedType.forSignature(UnresolvedType.java:384)
	at org.aspectj.weaver.bcel.BcelObjectType.getDeclaredInterfaces(BcelObjectType.java:275)
	at org.aspectj.weaver.ReferenceType.getDeclaredInterfaces(ReferenceType.java:626)
	at org.aspectj.weaver.ResolvedType.getDirectSupertypes(ResolvedType.java:82)
	at org.aspectj.weaver.patterns.TypePattern.matchesSubtypes(TypePattern.java:178)
	at org.aspectj.weaver.patterns.ExactTypePattern.matchesSubtypes(ExactTypePattern.java:74)
	at org.aspectj.weaver.patterns.TypePattern.matchesStatically(TypePattern.java:130)
	at org.aspectj.weaver.patterns.OrTypePattern.matchesStatically(OrTypePattern.java:76)
	at org.aspectj.weaver.patterns.SignaturePattern.matchesExactlyMethod(SignaturePattern.java:505)
	at org.aspectj.weaver.patterns.SignaturePattern.matchesExactly(SignaturePattern.java:360)
	at org.aspectj.weaver.patterns.SignaturePattern.matches(SignaturePattern.java:320)
	at org.aspectj.weaver.patterns.KindedPointcut.matchInternal(KindedPointcut.java:202)
	at org.aspectj.weaver.patterns.Pointcut.match(Pointcut.java:137)
	at org.aspectj.weaver.patterns.AndPointcut.matchInternal(AndPointcut.java:51)
	at org.aspectj.weaver.patterns.Pointcut.match(Pointcut.java:137)
	at org.aspectj.weaver.patterns.OrPointcut.matchInternal(OrPointcut.java:54)
	at org.aspectj.weaver.patterns.Pointcut.match(Pointcut.java:137)
	at org.aspectj.weaver.ShadowMunger.match(ShadowMunger.java:113)
	at org.aspectj.weaver.Advice.match(Advice.java:109)
	at org.aspectj.weaver.bcel.BcelAdvice.match(BcelAdvice.java:149)
	at org.aspectj.weaver.bcel.BcelClassWeaver.match(BcelClassWeaver.java:3173)
	at org.aspectj.weaver.bcel.BcelClassWeaver.match(BcelClassWeaver.java:2565)
	at org.aspectj.weaver.bcel.BcelClassWeaver.weave(BcelClassWeaver.java:480)
	at org.aspectj.weaver.bcel.BcelClassWeaver.weave(BcelClassWeaver.java:99)
	at org.aspectj.weaver.bcel.BcelWeaver.weave(BcelWeaver.java:1694)
	at org.aspectj.weaver.bcel.BcelWeaver.weaveWithoutDump(BcelWeaver.java:1638)
	at org.aspectj.weaver.bcel.BcelWeaver.weaveAndNotify(BcelWeaver.java:1401)
	at org.aspectj.weaver.bcel.BcelWeaver.weave(BcelWeaver.java:1187)
	at org.aspectj.weaver.tools.WeavingAdaptor.getWovenBytes(WeavingAdaptor.java:472)
	at org.aspectj.weaver.tools.WeavingAdaptor.weaveClass(WeavingAdaptor.java:323)
	at org.aspectj.weaver.loadtime.Aj.preProcess(Aj.java:99)
	at org.aspectj.weaver.loadtime.ClassPreProcessorAgentAdapter.transform(ClassPreProcessorAgentAdapter.java:54)
	at org.springframework.context.weaving.AspectJWeavingEnabler$AspectJClassBypassingClassFileTransformer.transform(AspectJWeavingEnabler.java:108)
	at org.springframework.instrument.classloading.InstrumentationLoadTimeWeaver$FilteringClassFileTransformer.transform(InstrumentationLoadTimeWeaver.java:184)
	at sun.instrument.TransformerManager.transform(Unknown Source)
	at sun.instrument.InstrumentationImpl.transform(Unknown Source)
	at java.lang.ClassLoader.defineClass1(Native Method)
	at java.lang.ClassLoader.defineClass(Unknown Source)
	at java.security.SecureClassLoader.defineClass(Unknown Source)
	at java.net.URLClassLoader.defineClass(Unknown Source)
	at java.net.URLClassLoader.access$100(Unknown Source)
	at java.net.URLClassLoader$1.run(Unknown Source)
	at java.net.URLClassLoader$1.run(Unknown Source)
	at java.security.AccessController.doPrivileged(Native Method)
	at java.net.URLClassLoader.findClass(Unknown Source)
	at java.lang.ClassLoader.loadClass(Unknown Source)
	at sun.misc.Launcher$AppClassLoader.loadClass(Unknown Source)
	at java.lang.ClassLoader.loadClass(Unknown Source)
	at org.springframework.beans.factory.support.ConstructorResolver.resolveConstructorArguments(ConstructorResolver.java:614)
	at org.springframework.beans.factory.support.ConstructorResolver.instantiateUsingFactoryMethod(ConstructorResolver.java:444)
	at org.springframework.beans.factory.support.AbstractAutowireCapableBeanFactory.instantiateUsingFactoryMethod(AbstractAutowireCapableBeanFactory.java:1119)
	at org.springframework.beans.factory.support.AbstractAutowireCapableBeanFactory.createBeanInstance(AbstractAutowireCapableBeanFactory.java:1014)
	at org.springframework.beans.factory.support.AbstractAutowireCapableBeanFactory.doCreateBean(AbstractAutowireCapableBeanFactory.java:504)
	at org.springframework.beans.factory.support.AbstractAutowireCapableBeanFactory.createBean(AbstractAutowireCapableBeanFactory.java:476)
	at org.springframework.beans.factory.support.AbstractBeanFactory$1.getObject(AbstractBeanFactory.java:303)
	at org.springframework.beans.factory.support.DefaultSingletonBeanRegistry.getSingleton(DefaultSingletonBeanRegistry.java:230)
	at org.springframework.beans.factory.support.AbstractBeanFactory.doGetBean(AbstractBeanFactory.java:299)
	at org.springframework.beans.factory.support.AbstractBeanFactory.getBean(AbstractBeanFactory.java:194)
	at org.springframework.beans.factory.support.DefaultListableBeanFactory.preInstantiateSingletons(DefaultListableBeanFactory.java:755)
	at org.springframework.context.support.AbstractApplicationContext.finishBeanFactoryInitialization(AbstractApplicationContext.java:757)
	at org.springframework.context.support.AbstractApplicationContext.refresh(AbstractApplicationContext.java:480)
	at org.springframework.context.support.ClassPathXmlApplicationContext.<init>(ClassPathXmlApplicationContext.java:139)
	at org.springframework.context.support.ClassPathXmlApplicationContext.<init>(ClassPathXmlApplicationContext.java:93)
	at com.springExemple.presentation.Presentation2.main(Presentation2.java:13)

error can't determine annotations of missing type org.springframework.transaction.annotation.Transactional
when weaving type org.springframework.beans.factory.support.ConstructorResolver$ArgumentsHolder
when weaving classes 
when weaving 
 [Xlint:cantFindType]
